Workbook

Sheet BBDD
A1: Fecha Ingreso | B1: Marca | C1: Modelo | D1: Versión | E1: Estado Dealer | F1: Año | G1: Placa Patente | H1: Días Stock | I1: Kilometraje | J1: Estado AutoPro | K1: Suma de Precio Compra Neto | L1: Suma de Precio Lista | M1: Precio Venta Real
A2: 01-02-2023 11:21:43 | B2: RENAULT | C2: RENAULT | D2: DUSTER ZEN 1.6 | E2: DISPONIBLE | F2: 2019 | G2: LBVX44 | H2: 7 | I2: 46987 | J2: Facturado | K2: 13000000 | L2: 15980000 | M2: =IFERROR(VLOOKUP(G2,Hoja3!A:B,2,0),0) -> 8170390
A3: 01-02-2023 11:25:45 | B3: VOLKSWAGEN | C3: TIGUAN | D3: TIGUAN OTTO 1.4 AUT | E3: DISPONIBLE | F3: 2020 | G3: LPXH47 | H3: 7 | I3: 43395 | J3: Facturado | K3: 30000000 | L3: 35980000 | M3: =IFERROR(VLOOKUP(G3,Hoja3!A:B,2,0),0) -> 18320390
A4: 01-03-2023 10:57:53 | B4: NISSAN | C4: QASHQAI | D4: QASHQAI J11 2.0 | E4: DISPONIBLE | F4: 2021 | G4: PPVC34 | H4: 30 | I4: 5928 | J4: Facturado | K4: 24000000 | L4: 28580000 | M4: =IFERROR(VLOOKUP(G4,Hoja3!A:B,2,0),0) -> 18044836
A5: 01-03-2023 11:00:59 | B5: MAZDA | C5: MAZDA | D5: ALL NEW CX30 2.0 | E5: DISPONIBLE | F5: 2020 | G5: LYSR94 | H5: 47 | I5: 35000 | J5: Facturado | K5: 28000000 | L5: 33980000 | M5: =IFERROR(VLOOKUP(G5,Hoja3!A:B,2,0),0) -> 17017540
A6: 01-03-2023 8:27:22 | B6: MG | C6: MG3 | D6: NEW 3 1.5 | E6: DISPONIBLE | F6: 2019 | G6: LBVW84 | H6: 48 | I6: 40350 | J6: Facturado | K6: 10600000 | L6: 13180000 | M6: =IFERROR(VLOOKUP(G6,Hoja3!A:B,2,0),0) -> 6749390
A7: 01-03-2023 8:29:51 | B7: FORD | C7: ESCAPE | D7: ESCAPE 2.0 AUT | E7: DISPONIBLE | F7: 2019 | G7: LBVV62 | H7: 58 | I7: 36000 | J7: Facturado | K7: 26000000 | L7: 29980000 | M7: =IFERROR(VLOOKUP(G7,Hoja3!A:B,2,0),0) -> 14870890
A8: 01-03-2024 9:01:07 | B8: PEUGEOT | C8: 5008 | D8: 5008 BLUEHDI 130 1.5 AUT | E8: DISPONIBLE | F8: 2022 | G8: RLSG73 | H8: 6 | I8: 71000 | J8: Facturado | K8: 36000000 | L8: 41980000 | M8: =IFERROR(VLOOKUP(G8,Hoja3!A:B,2,0),0) -> 21026030
A9: 01-03-2024 9:04:24 | B9: MAXUS | C9: MAXUS | D9: T90 4WD 2.0 AUT | E9: DISPONIBLE | F9: 2024 | G9: TBZL63 | H9: 25 | I9: 2200 | J9: Facturado | K9: 48000000 | L9: 55380000 | M9: =IFERROR(VLOOKUP(G9,Hoja3!A:B,2,0),0) -> 27733729
A10: 01-03-2024 9:08:00 | B10: PEUGEOT | C10: 3008 | D10: 3008 ALLURE BLUEHDI 1.5 AT | E10: DISPONIBLE | F10: 2019 | G10: LHCW17 | H10: 700 | I10: 103000 | J10: Facturado | K10: 22600000 | L10: 24980000 | M10: =IFERROR(VLOOKUP(G10,Hoja3!A:B,2,0),0) -> 12753377
A11: 01-03-2024 9:11:14 | B11: CHERY | C11: TIGGO 2 PRO | D11: TIGGO 2 GLS CVT PRO 1.5 AUT | E11: DISPONIBLE | F11: 2021 | G11: RDLL62 | H11: 183 | I11: 35000 | J11: Facturado | K11: 13600000 | L11: 16780000 | M11: =IFERROR(VLOOKUP(G11,Hoja3!A:B,2,0),0) -> 8084880
A12: 01-03-2024 9:19:20 | B12: OPEL | C12: MOKKA | D12: MOKKA 1.4 AUT | E12: DISPONIBLE | F12: 2020 | G12: LRWG63 | H12: 14 | I12: 30000 | J12: Facturado | K12: 20000000 | L12: 24180000 | M12: =IFERROR(VLOOKUP(G12,Hoja3!A:B,2,0),0) -> 12090000
A13: 01-03-2024 9:21:58 | B13: NISSAN | C13: KICKS | D13: KICKS 1.6 | E13: DISPONIBLE | F13: 2021 | G13: PPJG76 | H13: 25 | I13: 34479 | J13: Facturado | K13: 19600000 | L13: 23780000 | M13: =IFERROR(VLOOKUP(G13,Hoja3!A:B,2,0),0) -> 11890000
... A1010: 16-09-2025 18:44:05 | B1010: HYUNDAI | C1010: HYUNDAI | D1010: TUCSON NX4 GDI 7DCT 1.6 AUT | E1010: DISPONIBLE | F1010: 2022 | G1010: RSHS21 | H1010: 99 | I1010: 33000 | J1010: Facturado | K1010: 29125790 | L1010: 35580000 | M1010: =IFERROR(VLOOKUP(G1010,Hoja3!A:B,2,0),0) -> 15497319
A1011: 16-10-2024 10:05:22 | B1011: PEUGEOT | D1011: 4008 FELINE 4WD 2.0 AUT | E1011: DISPONIBLE | F1011: 2016 | G1011: HTBJ27 | H1011: 195 | I1011: 92000 | J1011: Facturado | K1011: 16000000 | L1011: 20380000 | M1011: =IFERROR(VLOOKUP(G1011,Hoja3!A:B,2,0),0) -> 9043393
A1012: 16-10-2024 10:38:41 | B1012: KIA MOTORS | C1012: SELTOS | D1012: SELTOS EX 1.6 AUT | E1012: DISPONIBLE | F1012: 2020 | G1012: PFRR40 | H1012: 13 | I1012: 45000 | J1012: Facturado | K1012: 23000000 | L1012: 27180000 | M1012: =IFERROR(VLOOKUP(G1012,Hoja3!A:B,2,0),0) -> 13590000
A1013: 16-10-2024 9:24:20 | B1013: KIA MOTORS | C1013: SELTOS | D1013: SELTOS EX 1.5 | E1013: DISPONIBLE | F1013: 2024 | G1013: TPTZ11 | H1013: 14 | I1013: 1326 | J1013: Facturado | K1013: 30000000 | L1013: 33980000 | M1013: =IFERROR(VLOOKUP(G1013,Hoja3!A:B,2,0),0) -> 17026030
A1014: 16-10-2024 9:40:21 | B1014: KIA MOTORS | C1014: MORNING | D1014: MORNING EX 1.2 | E1014: DISPONIBLE | F1014: 2017 | G1014: JPLT11 | H1014: 13 | I1014: 77390 | J1014: Facturado | K1014: 8600000 | L1014: 11780000 | M1014: =IFERROR(VLOOKUP(G1014,Hoja3!A:B,2,0),0) -> 5926030
A1015: 16-10-2025 17:45:02 | B1015: RENAULT | C1015: RENAULT | D1015: OROCH 2.0 | E1015: DISPONIBLE | F1015: 2018 | G1015: KJWV14 | H1015: 32 | I1015: 41894 | J1015: Facturado | K1015: 12900000 | L1015: 15980000 | M1015: =IFERROR(VLOOKUP(G1015,Hoja3!A:B,2,0),0) -> 10895259
A1016: 16-10-2025 18:22:16 | B1016: KIA MOTORS | C1016: SPORTAGE | D1016: SPORTAGE EX 2.0L | E1016: DISPONIBLE | F1016: 2023 | G1016: SJJG29 | H1016: 44 | I1016: 62929 | J1016: Facturado | K1016: 32000000 | L1016: 37780000 | M1016: =IFERROR(VLOOKUP(G1016,Hoja3!A:B,2,0),0) -> 19149380
A1017: 16-12-2025 17:17:41 | B1017: JAC | C1017: JS | D1017: JS2 HATCHBACK 1.5 | E1017: DISPONIBLE | F1017: 2024 | G1017: TJDF16 | H1017: 35 | I1017: 6147 | J1017: Facturado | K1017: 14000000 | L1017: 16780000 | M1017: =IFERROR(VLOOKUP(G1017,Hoja3!A:B,2,0),0) -> 8528955
A1018: 16-12-2025 17:44:20 | B1018: KIA MOTORS | C1018: SPORTAGE | D1018: SPORTAGE EX 2.0 | E1018: CON PRENDA | F1018: 2023 | G1018: SLZG20 | H1018: 31 | I1018: 68000 | J1018: Facturado | K1018: 31400000 | L1018: 38580000 | M1018: =IFERROR(VLOOKUP(G1018,Hoja3!A:B,2,0),0) -> 19290000
A1019: 16-12-2025 19:06:45 | B1019: CHEVROLET | C1019: ONIX | D1019: ONIX HB RS 1.0T | E1019: DISPONIBLE | F1019: 2023 | G1019: SPSY59 | H1019: 36 | I1019: 62213 | J1019: Facturado | K1019: 16000000 | L1019: 19380000 | M1019: =IFERROR(VLOOKUP(G1019,Hoja3!A:B,2,0),0) -> 9911380
A1020: 17-01-2023 15:07:53 | B1020: JMC | C1020: VIGUS PICK UP | D1020: . | E1020: DISPONIBLE | F1020: 2022 | G1020: RTLV30 | H1020: 252 | I1020: 20300 | J1020: Facturado | K1020: 29600000 | L1020: 28980000 | M1020: =IFERROR(VLOOKUP(G1020,Hoja3!A:B,2,0),0) -> 14531063
A1021: 17-01-2025 11:11:03 | B1021: PEUGEOT | C1021: LANDTREK | D1021: LANDTREK BLUEHDI 4X4 2.2 AUT | E1021: DISPONIBLE | F1021: 2024 | G1021: THRH47 | H1021: 0 | I1021: 6600 | J1021: Facturado | K1021: 43600000 | L1021: 53980000 | M1021: =IFERROR(VLOOKUP(G1021,Hoja3!A:B,2,0),0) -> 26990000
A1022: 17-02-2023 12:51:51 | B1022: SUZUKI | C1022: IGNIS | D1022: IGNIS GL HB 1.2 | E1022: DISPONIBLE | F1022: 2017 | G1022: JLTJ52 | H1022: 0 | I1022: 80200 | J1022: Facturado | K1022: 10200000 | L1022: 11800000 | M1022: =IFERROR(VLOOKUP(G1022,Hoja3!A:B,2,0),0) -> 6049040
A1023: 17-02-2023 12:57:37 | B1023: KIA MOTORS | C1023: SOLUTO | D1023: SOLUTO 1.4 | E1023: DISPONIBLE | F1023: 2022 | G1023: RJCT51 | H1023: 7 | I1023: 15000 | J1023: Facturado | K1023: 13400000 | L1023: 15980000 | M1023: =IFERROR(VLOOKUP(G1023,Hoja3!A:B,2,0),0) -> 8295212
... A2253: 31-12-2025 13:17:08 | B2253: RAM | C2253: RAM 700 | D2253: 700 BIGHORN D CAB 4X2 1.4 | E2253: DISPONIBLE | F2253: 2024 | G2253: SZTK19 | H2253: 0 | I2253: 29000 | J2253: Facturado | K2253: 22600000 | L2253: 24000000 | M2253: =IFERROR(VLOOKUP(G2253,Hoja3!A:B,2,0),0) -> 12256030
A2254: Total general | K2254: 56279491157 | L2254: 67467966401

Sheet Hoja3
A1: Placa Patente | B1: Total Venta
A2: HRWV51 | B2: 26592657
A3: RFVX24 | B3: 18990000
A4: KBCK12 | B4: 7800406
A5: RKRX82 | B5: 17305390
A6: RBCZ59 | B6: 18286390
A7: JXSZ39 | B7: 13078406
A8: JKYG98 | B8: 19335390
A9: PFSC16 | B9: 14071566
A10: PJDD13 | B10: 19650040
A11: LYPB29 | B11: 16302290
A12: JBJW21 | B12: 11450000
A13: PSHY94 | B13: 19944390
... A139: PTDH25 | B139: 39629508
B140: 21017540
B141: 14265181
A142: KZVZ40 | B142: 21974390
A143: GFFR39 | B143: 11517540
A144: FFZW59 | B144: 11225540
A145: SPZB66 | B145: 25055530
A146: PLSP29 | B146: 10822824
A147: JXFZ74 | B147: 7192113
A148: PRBC55 | B148: 16598174
A149: PRSH84 | B149: 12110195
A150: JHSB38 | B150: 22401738
A151: KTCS55 | B151: 13017540
A152: PJLL59 | B152: 15596312
A153: LLBJ17 | B153: 9997390
... A228: PSHX59 | B228: 14853540
B229: 13245390
A230: RBJH90 | B230: 14490000
A231: KCBZ34 | B231: 22026048
A232: RFVG61 | B232: 10001642
A233: LXHV17 | B233: 19061945
A234: JHRZ76 | B234: 7099776
A235: LYLV18 | B235: 11017316
A236: GSDW61 | B236: 6647890
A237: KCBZ60 | B237: 10504890
A238: JPZG71 | B238: 7017540
A239: KTCS69 | B239: 18191715
A240: PKBT29 | B240: 31982949
A241: PFRY34 | B241: 8079040
... A310: PPJG77 | B310: 10128980
B311: 20857890
B312: 9840000
A313: PKVB87 | B313: 22000230
A314: JSWT81 | B314: 13253880
A315: JHSD41 | B315: 6002756
A316: PKVB49 | B316: 11741530
A317: PSJH25 | B317: 10208880
A318: RBJJ77 | B318: 11244514
A319: RKPR88 | B319: 28783380
A320: PCFK99 | B320: 12238880
A321: LDBB65 | B321: 17230742
A322: PFRL39 | B322: 7623850
A323: RTLL28 | B323: 7163880
A324: FZPF54 | B324: 8178880
... A366: SFLX85 | B366: 17340796
B367: 16806380
A368: JZGC33 | B368: 16307350
A369: JZSP13 | B369: 13490000
A370: PFSC43 | B370: 12494926
A371: KZWD62 | B371: 8102756
A372: LHCL63 | B372: 8183806
A373: PHJK18 | B373: 9495033
A374: JXGF43 | B374: 7685210
A375: KZWF50 | B375: 4636530
A376: KCBV49 | B376: 9599880
A377: KZVW63 | B377: 16704940
A378: RSTC90 | B378: 18328880
A379: LRCX10 | B379: 12243913
... A469: SHLV14 | B469: 27981030
B470: 13264030
A471: HXYD45 | B471: 8531063
A472: PFSJ75 | B472: 11216030
A473: LSYF15 | B473: 11766032
A474: LHRW37 | B474: 8990000
A475: JBLY67 | B475: 8183943
A476: PTDZ97 | B476: 14273913
A477: SWTP75 | B477: 11690000
A478: PTSC90 | B478: 21384030
A479: PHFX51 | B479: 12029445
A480: RTVV32 | B480: 28990000
A481: KCBY89 | B481: 12193205
A482: KGLJ55 | B482: 14471880
... A525: PKTY70 | B525: 12249030
B526: 8899530
B527: 13761380
B528: 3990000
A529: PGGS58 | B529: 5100000
A530: HFHY93 | B530: 15791380
A531: RZCK51 | B531: 24990000
A532: SKCG47 | B532: 16537430
A533: SPTC10 | B533: 9498380
A534: LBVV96 | B534: 18026030
A535: RJPJ39 | B535: 25894380
A536: KTCW99 | B536: 11134922
A537: JFFW95 | B537: 19749880
A538: LYSS33 | B538: 7621572
A539: KTCZ97 | B539: 10728922
...

Sheet Hoja1
A1: Empresa | B1: Sucursal | C1: Folio Venta | D1: Venta | E1: Estado Venta | F1: Fecha Venta | G1: Tipo Documento (Folio) | H1: Vendedor | I1: Fecha Ingreso | J1: Fecha Facturación | K1: Numero VIN | L1: Marca | M1: Modelo | N1: Versión | O1: Código Versión | P1: Año | Q1: Kilometraje | R1: Código Interno | S1: Placa Patente | T1: Condición Vehículo | U1: Color Exterior | V1: Color Interior | W1: Precio Venta Total | X1: Estado AutoPro | Y1: Días Stock | Z1: Estado Dealer | AA1: Bodega | AB1: Equipamiento | AC1: Numero Motor | AD1: Numero Chasis | AE1: Proveedor | AF1: Fecha Disponibilidad | AG1: Factura Compra | AH1: Vencimiento Documento | AI1: Fecha Compra | AJ1: Fecha Vencto. Revisión Técnica | AK1: N° Propietarios | AL1: Folio Retoma | AM1: Fecha Retoma | AN1: Días Reservado | AO1: Precio Compra Neto | AP1: Gasto | AQ1: Accesorios | AR1: Total Costo | AS1: Precio Lista | AT1: Margen | AU1: Margen %
A2: IMPORTADORA TRENTO LTDA | B2: LOCAL USADOS | C2: 2296 | D2: 44381 | E2: Facturada | F2: 18-01-2025 12:55:55 | G2: Factura Exenta Electrónica (68870) | H2: VANESSA CASANGA CASTILLO | I2: 19-11-2024 19:08:12 | J2: 30-01-2025 0:00:00 | K2: MALC381CA KM453860 | L2: HYUNDAI | M2: HYUNDAI | N2: CRETA GS PE 1.6 | O2: HYCRRE16MT | P2: 2019 | Q2: 79000 | R2: THYSTWU000528 | S2: KZKC62 | T2: USADO | U2: GRIS OSCURO | V2: POR DEFINIR | W2: 9790000 | X2: Facturado | Y2: 72 | Z2: DISPONIBLE | AA2: BODEGA VEHICULOS | AB2: AE,CC,EE,NB,ABS,LL,4AB,AC,AISO,AAUTO,CRE,ACD,SR,UD | AC2: G4FGJW523548 | AD2: MALC381CA KM453860 | AE2: MARIA MIRNA COVARRUBIAS CARMONA | AF2: 19-11-2024 0:00:00 | AG2: 1 | AH2: 04-12-2024 19:29:00 | AI2: 04-12-2024 19:29:00 | AJ2: 31-05-2025 0:00:00 | AK2: 1 | AL2: 0 | AN2: 2 | AO2: 7400000 | AP2: 237030 | AQ2: 0 | AR2: 7637030 | AS2: 9790000 | AT2: 2152970 | AU2: 2199
A3: IMPORTADORA TRENTO LTDA | B3: LOCAL USADOS | C3: 2296 | D3: 44381 | E3: Facturada | F3: 18-01-2025 12:55:55 | G3: Factura Exenta Electrónica (68870) | H3: VANESSA CASANGA CASTILLO | I3: 19-11-2024 19:08:12 | J3: 30-01-2025 0:00:00 | K3: MALC381CA KM453860 | L3: HYUNDAI | M3: HYUNDAI | N3: CRETA GS PE 1.6 | O3: HYCRRE16MT | P3: 2019 | Q3: 79000 | R3: THYSTWU000528 | S3: KZKC62 | T3: USADO | U3: GRIS OSCURO | V3: POR DEFINIR | W3: 9790000 | X3: Facturado | Y3: 72 | Z3: DISPONIBLE | AA3: BODEGA VEHICULOS | AB3: AE,CC,EE,NB,ABS,LL,4AB,AC,AISO,AAUTO,CRE,ACD,SR,UD | AC3: G4FGJW523548 | AD3: MALC381CA KM453860 | AE3: MARIA MIRNA COVARRUBIAS CARMONA | AF3: 19-11-2024 0:00:00 | AG3: 1 | AH3: 04-12-2024 19:29:00 | AI3: 04-12-2024 19:29:00 | AJ3: 31-05-2025 0:00:00 | AK3: 1 | AL3: 0 | AN3: 2 | AO3: 7400000 | AP3: 237030 | AQ3: 0 | AR3: 7637030 | AS3: 9790000 | AT3: 2152970 | AU3: 2199
A4: IMPORTADORA TRENTO LTDA | B4: LOCAL USADOS | C4: 2077 | D4: 40116 | E4: Facturada | F4: 15-02-2024 9:43:21 | G4: Factura Exenta Electrónica (63553) | H4: FEDERICO ALBERT | I4: 13-02-2024 9:18:39 | J4: 16-02-2024 0:00:00 | K4: KNAB3512AJT021057 | L4: KIA MOTORS | M4: MORNING | N4: MORNING EX 1.2 | O4: 17--1510E4 | P4: 2017 | Q4: 66000 | R4: TKIAUTU002128 | S4: JLHR52 | T4: USADO | U4: AZUL CIELO | V4: POR DEFINIR | W4: 6090000 | X4: Facturado | Y4: 3 | Z4: DISPONIBLE | AA4: BODEGA VEHICULOS | AC4: G4LAHP009994 | AD4: KNAB3512AJT021057 | AE4: LILIAN ANGELICA PARRA GONZALEZ | AF4: 13-02-2024 0:00:00 | AG4: 1 | AH4: 13-02-2024 0:00:00 | AI4: 26-02-2024 15:27:55 | AK4: 0 | AL4: 0 | AN4: 2 | AO4: 4500000 | AP4: 0 | AQ4: 0 | AR4: 4500000 | AS4: 6090000 | AT4: 1590000 | AU4: 2611
A5: IMPORTADORA TRENTO LTDA | B5: LOCAL USADOS | C5: 2077 | D5: 40116 | E5: Facturada | F5: 15-02-2024 9:43:21 | G5: Factura Exenta Electrónica (63553) | H5: FEDERICO ALBERT | I5: 13-02-2024 9:18:39 | J5: 16-02-2024 0:00:00 | K5: KNAB3512AJT021057 | L5: KIA MOTORS | M5: MORNING | N5: MORNING EX 1.2 | O5: 17--1510E4 | P5: 2017 | Q5: 66000 | R5: TKIAUTU002128 | S5: JLHR52 | T5: USADO | U5: AZUL CIELO | V5: POR DEFINIR | W5: 6090000 | X5: Facturado | Y5: 3 | Z5: DISPONIBLE | AA5: BODEGA VEHICULOS | AC5: G4LAHP009994 | AD5: KNAB3512AJT021057 | AE5: LILIAN ANGELICA PARRA GONZALEZ | AF5: 13-02-2024 0:00:00 | AG5: 1 | AH5: 13-02-2024 0:00:00 | AI5: 26-02-2024 15:27:55 | AK5: 0 | AL5: 0 | AN5: 2 | AO5: 4500000 | AP5: 0 | AQ5: 0 | AR5: 4500000 | AS5: 6090000 | AT5: 1590000 | AU5: 2611
A6: IMPORTADORA TRENTO LTDA | B6: LOCAL USADOS | C6: 2349 | D6: 45512 | E6: Facturada | F6: 15-04-2025 16:11:59 | G6: Factura Exenta Electrónica (69703) | H6: FEDERICO ALBERT | I6: 31-01-2025 15:39:03 | J6: 29-04-2025 0:00:00 | K6: WVWZZZ60ZHT137869 | L6: VOLKSWAGEN | M6: POLO | N6: POLO HIGHLINE 1.6 | O6: VWPOLO16MT | P6: 2018 | Q6: 51777 | R6: TVOAUTU000223 | S6: JXGB32 | T6: USADO | U6: BLANCO CANDY | V6: POR DEFINIR | W6: 8990000 | X6: Facturado | Y6: 88 | Z6: DISPONIBLE | AA6: BODEGA VEHICULOS | AB6: AE,CC,EE,2AB,NB,ABS,LL,AC,AAUTO,ACD,SR,UD,GF | AC6: CLS 597900 | AD6: WVWZZZ60ZHT137869 | AE6: CARLOS EDIN TAPIA LEIVA | AF6: 31-01-2025 0:00:00 | AG6: 1 | AH6: 28-04-2025 16:57:00 | AI6: 28-04-2025 16:57:00 | AJ6: 31-05-2025 0:00:00 | AK6: 1 | AL6: 0 | AN6: 0 | AO6: 6500000 | AP6: 223530 | AQ6: 9923 | AR6: 6733453 | AS6: 8990000 | AT6: 2256547 | AU6: 251
A7: IMPORTADORA TRENTO LTDA | B7: LOCAL USADOS | C7: 2349 | D7: 45512 | E7: Facturada | F7: 15-04-2025 16:11:59 | G7: Factura Exenta Electrónica (69703) | H7: FEDERICO ALBERT | I7: 31-01-2025 15:39:03 | J7: 29-04-2025 0:00:00 | K7: WVWZZZ60ZHT137869 | L7: VOLKSWAGEN | M7: POLO | N7: POLO HIGHLINE 1.6 | O7: VWPOLO16MT | P7: 2018 | Q7: 51777 | R7: TVOAUTU000223 | S7: JXGB32 | T7: USADO | U7: BLANCO CANDY | V7: POR DEFINIR | W7: 8990000 | X7: Facturado | Y7: 88 | Z7: DISPONIBLE | AA7: BODEGA VEHICULOS | AB7: AE,CC,EE,2AB,NB,ABS,LL,AC,AAUTO,ACD,SR,UD,GF | AC7: CLS 597900 | AD7: WVWZZZ60ZHT137869 | AE7: CARLOS EDIN TAPIA LEIVA | AF7: 31-01-2025 0:00:00 | AG7: 1 | AH7: 28-04-2025 16:57:00 | AI7: 28-04-2025 16:57:00 | AJ7: 31-05-2025 0:00:00 | AK7: 1 | AL7: 0 | AN7: 0 | AO7: 6500000 | AP7: 223530 | AQ7: 9923 | AR7: 6733453 | AS7: 8990000 | AT7: 2256547 | AU7: 251
A8: IMPORTADORA TRENTO LTDA | B8: LOCAL PREMIUM CAR SALES | C8: 1594 | D8: 37848 | E8: Facturada | F8: 25-07-2023 12:34:31 | G8: Factura Exenta Electrónica (63173) | H8: JORDI AGUSTIN FOITZICK MUÑOZ | I8: 19-07-2023 16:42:47 | J8: 26-07-2023 0:00:00 | K8: 3N8CP5HE1PL462445 | L8: NISSAN | M8: KICKS | N8: KICKS CVT 1.6 AUT | O8: KICKS | P8: 2022 | Q8: 4000 | R8: TNISTWU000494 | S8: RZSK13 | T8: USADO | U8: GRIS METALICO | V8: POR DEFINIR | W8: 14990000 | X8: Facturado | Y8: 7 | Z8: DISPONIBLE | AA8: PREMIUM CAR SALES | AC8: HR16-540239V | AD8: 3N8CP5HE1PL462445 | AE8: JAIME EDUARDO GALLEGUILLOS ARAYA | AF8: 19-07-2023 0:00:00 | AG8: 1 | AH8: 19-07-2023 0:00:00 | AI8: 19-07-2023 16:42:08 | AK8: 0 | AL8: 0 | AN8: 4 | AO8: 12200000 | AP8: 353540 | AQ8: 0 | AR8: 12553540 | AS8: 14990000 | AT8: 2436460 | AU8: 1625
A9: IMPORTADORA TRENTO LTDA | B9: LOCAL PREMIUM CAR SALES | C9: 1594 | D9: 37848 | E9: Facturada | F9: 25-07-2023 12:34:31 | G9: Factura Exenta Electrónica (63173) | H9: JORDI AGUSTIN FOITZICK MUÑOZ | I9: 19-07-2023 16:42:47 | J9: 26-07-2023 0:00:00 | K9: 3N8CP5HE1PL462445 | L9: NISSAN | M9: KICKS | N9: KICKS CVT 1.6 AUT | O9: KICKS | P9: 2022 | Q9: 4000 | R9: TNISTWU000494 | S9: RZSK13 | T9: USADO | U9: GRIS METALICO | V9: POR DEFINIR | W9: 14990000 | X9: Facturado | Y9: 7 | Z9: DISPONIBLE | AA9: PREMIUM CAR SALES | AC9: HR16-540239V | AD9: 3N8CP5HE1PL462445 | AE9: JAIME EDUARDO GALLEGUILLOS ARAYA | AF9: 19-07-2023 0:00:00 | AG9: 1 | AH9: 19-07-2023 0:00:00 | AI9: 19-07-2023 16:42:08 | AK9: 0 | AL9: 0 | AN9: 4 | AO9: 12200000 | AP9: 353540 | AQ9: 0 | AR9: 12553540 | AS9: 14990000 | AT9: 2436460 | AU9: 1625
A10: IMPORTADORA TRENTO LTDA | B10: LOCAL PREMIUM CAR SALES | C10: 1881 | D10: 44331 | E10: Facturada | F10: 14-01-2025 15:46:54 | G10: Factura Exenta Electrónica (68850) | H10: DANIEL ALEJANDRO AGUILERA CORTES | I10: 13-12-2024 14:03:40 | J10: 15-01-2025 0:00:00 | K10: VF3MCYHZU SS000521 | L10: PEUGEOT | M10: 5008 | N10: 5008 BLUEHDI 130 1.5 AUT | O10: 5008BH130 | P10: 2024 | Q10: 3361 | R10: TPESTWU000383 | S10: TRTY36 | T10: USADO | U10: GRIS ARTENSE | V10: POR DEFINIR | W10: 26490000 | X10: Facturado | Y10: 33 | Z10: DISPONIBLE | AA10: PREMIUM CAR SALES | AB10: AE,CC,EE,AAC,ABS,LL,ESP,AISO,AAUTO,CRE,ACD,SR,UD,D | AC10: 10Q3EJ1887283 | AD10: VF3MCYHZU SS000521 | AE10: TITO DANILO LEIVA RIQUELME | AF10: 13-12-2024 0:00:00 | AG10: 1 | AH10: 13-12-2024 0:00:00 | AI10: 13-12-2024 13:57:07 | AK10: 1 | AL10: 0 | AN10: 5 | AO10: 22800000 | AP10: 468030 | AQ10: 0 | AR10: 23268030 | AS10: 26490000 | AT10: 3221970 | AU10: 1216
A11: IMPORTADORA TRENTO LTDA | B11: LOCAL PREMIUM CAR SALES | C11: 1881 | D11: 44331 | E11: Facturada | F11: 14-01-2025 15:46:54 | G11: Factura Exenta Electrónica (68850) | H11: DANIEL ALEJANDRO AGUILERA CORTES | I11: 13-12-2024 14:03:40 | J11: 15-01-2025 0:00:00 | K11: VF3MCYHZU SS000521 | L11: PEUGEOT | M11: 5008 | N11: 5008 BLUEHDI 130 1.5 AUT | O11: 5008BH130 | P11: 2024 | Q11: 3361 | R11: TPESTWU000383 | S11: TRTY36 | T11: USADO | U11: GRIS ARTENSE | V11: POR DEFINIR | W11: 26490000 | X11: Facturado | Y11: 33 | Z11: DISPONIBLE | AA11: PREMIUM CAR SALES | AB11: AE,CC,EE,AAC,ABS,LL,ESP,AISO,AAUTO,CRE,ACD,SR,UD,D | AC11: 10Q3EJ1887283 | AD11: VF3MCYHZU SS000521 | AE11: TITO DANILO LEIVA RIQUELME | AF11: 13-12-2024 0:00:00 | AG11: 1 | AH11: 13-12-2024 0:00:00 | AI11: 13-12-2024 13:57:07 | AK11: 1 | AL11: 0 | AN11: 5 | AO11: 22800000 | AP11: 468030 | AQ11: 0 | AR11: 23268030 | AS11: 26490000 | AT11: 3221970 | AU11: 1216
A12: IMPORTADORA TRENTO LTDA | B12: MEGACENTRO OVALLE | C12: 391 | D12: 42945 | E12: Facturada | F12: 04-10-2024 17:30:37 | G12: Factura Exenta Electrónica (64020) | H12: JOSE GREGORIO TORRES | I12: 03-09-2024 15:21:33 | J12: 10-10-2024 0:00:00 | K12: *----....../***// | L12: HYUNDAI | M12: HYUNDAI | N12: CRETA GRAND MPI 2.0 | O12: HYUNCRET2.0 | P12: 2024 | Q12: 1665 | R12: THYSTWU000524 | S12: TLRP41 | T12: USADO | U12: GRIS GRAFITO | V12: POR DEFINIR | W12: 16490000 | X12: Facturado | Y12: 37 | Z12: DISPONIBLE | AA12: BODEGA OVALLEveih | AB12: AE,CC,EE,NB,ABS,LL,4AB,AC,AISO,CRE,MAV,ACD,SR,UD,D | AC12: G4NLPW632552 | AD12: MALPC815ARM865510 | AE12: TITO DANILO LEIVA RIQUELME | AF12: 03-09-2024 0:00:00 | AG12: 1 | AH12: 17-10-2024 18:59:00 | AI12: 17-10-2024 18:59:00 | AK12: 0 | AL12: 0 | AN12: 24 | AO12: 14000000 | AP12: 476280 | AQ12: 9211 | AR12: 14485491 | AS12: 16490000 | AT12: 2004509 | AU12: 1216
A13: IMPORTADORA TRENTO LTDA | B13: MEGACENTRO OVALLE | C13: 391 | D13: 42945 | E13: Facturada | F13: 04-10-2024 17:30:37 | G13: Factura Exenta Electrónica (64020) | H13: JOSE GREGORIO TORRES | I13: 03-09-2024 15:21:33 | J13: 10-10-2024 0:00:00 | K13: *----....../***// | L13: HYUNDAI | M13: HYUNDAI | N13: CRETA GRAND MPI 2.0 | O13: HYUNCRET2.0 | P13: 2024 | Q13: 1665 | R13: THYSTWU000524 | S13: TLRP41 | T13: USADO | U13: GRIS GRAFITO | V13: POR DEFINIR | W13: 16490000 | X13: Facturado | Y13: 37 | Z13: DISPONIBLE | AA13: BODEGA OVALLEveih | AB13: AE,CC,EE,NB,ABS,LL,4AB,AC,AISO,CRE,MAV,ACD,SR,UD,D | AC13: G4NLPW632552 | AD13: MALPC815ARM865510 | AE13: TITO DANILO LEIVA RIQUELME | AF13: 03-09-2024 0:00:00 | AG13: 1 | AH13: 17-10-2024 18:59:00 | AI13: 17-10-2024 18:59:00 | AK13: 0 | AL13: 0 | AN13: 24 | AO13: 14000000 | AP13: 476280 | AQ13: 9211 | AR13: 14485491 | AS13: 16490000 | AT13: 2004509 | AU13: 1216
A14: IMPORTADORA TRENTO LTDA | B14: LOCAL USADOS | C14: 1911 | D14: 36761 | E14: Facturada | F14: 28-03-2023 10:27:22 | G14: Factura Exenta Electrónica (63012) | H14: Rodrigo Andres Toro Orostegui | I14: 27-03-2023 15:11:30 | J14: 28-03-2023 0:00:00 | K14: MZBFC814APN166309 | L14: KIA MOTORS | M14: SONET | N14: SONET EX 1.5 | O14: SOU1 | P14: 2022 | Q14: 6300 | R14: TKISTWU001224 | S14: SBKC22 | T14: USADO | U14: BLANCO INVIERNO | V14: POR DEFINIR | W14: 13990000 | X14: Facturado | Y14: 1 | Z14: DISPONIBLE | AA14: BODEGA VEHICULOS | AC14: G4FLNV303090 | AD14: MZBFC814APN166309 | AE14: JUAN GABRIEL CORTES GAJARDO | AF14: 27-03-2023 0:00:00 | AG14: 1 | AH14: 27-03-2023 0:00:00 | AI14: 27-03-2023 15:11:09 | AK14: 0 | AL14: 0 | AN14: 1 | AO14: 12000000 | AP14: 340540 | AQ14: 10844 | AR14: 12351384 | AS14: 13990000 | AT14: 1638616 | AU14: 1171
A15: IMPORTADORA TRENTO LTDA | B15: LOCAL USADOS | C15: 1911 | D15: 36761 | E15: Facturada | F15: 28-03-2023 10:27:22 | G15: Factura Exenta Electrónica (63012) | H15: Rodrigo Andres Toro Orostegui | I15: 27-03-2023 15:11:30 | J15: 28-03-2023 0:00:00 | K15: MZBFC814APN166309 | L15: KIA MOTORS | M15: SONET | N15: SONET EX 1.5 | O15: SOU1 | P15: 2022 | Q15: 6300 | R15: TKISTWU001224 | S15: SBKC22 | T15: USADO | U15: BLANCO INVIERNO | V15: POR DEFINIR | W15: 13990000 | X15: Facturado | Y15: 1 | Z15: DISPONIBLE | AA15: BODEGA VEHICULOS | AC15: G4FLNV303090 | AD15: MZBFC814APN166309 | AE15: JUAN GABRIEL CORTES GAJARDO | AF15: 27-03-2023 0:00:00 | AG15: 1 | AH15: 27-03-2023 0:00:00 | AI15: 27-03-2023 15:11:09 | AK15: 0 | AL15: 0 | AN15: 1 | AO15: 12000000 | AP15: 340540 | AQ15: 10844 | AR15: 12351384 | AS15: 13990000 | AT15: 1638616 | AU15: 1171
A16: IMPORTADORA TRENTO LTDA | B16: LOCAL PREMIUM CAR SALES | C16: 1819 | D16: 43094 | E16: Facturada | F16: 18-10-2024 15:31:01 | G16: Factura Exenta Electrónica (64041) | H16: DANIEL ALEJANDRO AGUILERA CORTES | I16: 10-10-2024 17:46:14 | J16: 21-10-2024 0:00:00 | K16: LJXCU2BB6MTP06598 | L16: FORD | M16: TERRITORY | N16: TERRITORY 1.5 AUT | O16: FTU1 | P16: 2021 | Q16: 26500 | R16: TFOSTWU001321 | S16: PSHX11 | T16: USADO | U16: BLANCO METALICO | V16: POR DEFINIR | W16: 13290000 | X16: Facturado | Y16: 11 | Z16: DISPONIBLE | AA16: PREMIUM CAR SALES | AB16: AE,CC,EE,NB,AAC,ABS,LL,VC,4AB,AISO,AAUTO,CRE,MAV,A | AC16: LCG061349 | AD16: LJXCU2BB6MTP06598 | AE16: FABIAN RENATO COLLAO CUBILLOS | AF16: 10-10-2024 0:00:00 | AG16: 1 | AH16: 10-10-2024 0:00:00 | AI16: 10-10-2024 17:42:08 | AK16: 0 | AL16: 0 | AN16: 7 | AO16: 11000000 | AP16: 341030 | AQ16: 0 | AR16: 11341030 | AS16: 13290000 | AT16: 1948970 | AU16: 1466
A17: IMPORTADORA TRENTO LTDA | B17: LOCAL PREMIUM CAR SALES | C17: 1819 | D17: 43094 | E17: Facturada | F17: 18-10-2024 15:31:01 | G17: Factura Exenta Electrónica (64041) | H17: DANIEL ALEJANDRO AGUILERA CORTES | I17: 10-10-2024 17:46:14 | J17: 21-10-2024 0:00:00 | K17: LJXCU2BB6MTP06598 | L17: FORD | M17: TERRITORY | N17: TERRITORY 1.5 AUT | O17: FTU1 | P17: 2021 | Q17: 26500 | R17: TFOSTWU001321 | S17: PSHX11 | T17: USADO | U17: BLANCO METALICO | V17: POR DEFINIR | W17: 13290000 | X17: Facturado | Y17: 11 | Z17: DISPONIBLE | AA17: PREMIUM CAR SALES | AB17: AE,CC,EE,NB,AAC,ABS,LL,VC,4AB,AISO,AAUTO,CRE,MAV,A | AC17: LCG061349 | AD17: LJXCU2BB6MTP06598 | AE17: FABIAN RENATO COLLAO CUBILLOS | AF17: 10-10-2024 0:00:00 | AG17: 1 | AH17: 10-10-2024 0:00:00 | AI17: 10-10-2024 17:42:08 | AK17: 0 | AL17: 0 | AN17: 7 | AO17: 11000000 | AP17: 341030 | AQ17: 0 | AR17: 11341030 | AS17: 13290000 | AT17: 1948970 | AU17: 1466
A18: IMPORTADORA TRENTO LTDA | B18: LOCAL USADOS | C18: 2342 | D18: 45388 | E18: Facturada | F18: 04-04-2025 16:20:47 | G18: Factura Exenta Electrónica (69024) | H18: VANESSA CASANGA CASTILLO | I18: 21-03-2025 17:16:00 | J18: 09-04-2025 0:00:00 | K18: 9BFZB55U7J8687464 | L18: FORD | M18: ECOSPORT | N18: ECOSPORT TITANIUM 1.5 | O18: EC3333 | P18: 2018 | Q18: 52119 | R18: TFOSTWU001356 | S18: KDTL69 | T18: USADO | U18: BLANCO | V18: POR DEFINIR | W18: 8990000 | X18: Facturado | Y18: 19 | Z18: CON PRENDA | AA18: BODEGA VEHICULOS | AB18: AE,CC,EE,2AB,NB,ABS,LL,TC,AC,AISO,AAUTO,CRE,MAV,TE | AC18: XZJAJ8687464 | AD18: 9BFZB55U7J8687464 | AE18: SERGIO FLORENCIO GAMBOA | AF18: 21-03-2025 0:00:00 | AG18: 1 | AH18: 21-03-2025 0:00:00 | AI18: 21-03-2025 17:09:36 | AJ18: 31-01-2026 0:00:00 | AK18: 3 | AL18: 0 | AN18: 11 | AO18: 7000000 | AP18: 381608 | AQ18: 2893 | AR18: 7384501 | AS18: 8990000 | AT18: 1605499 | AU18: 1786
A19: IMPORTADORA TRENTO LTDA | B19: LOCAL USADOS | C19: 2342 | D19: 45388 | E19: Facturada | F19: 04-04-2025 16:20:47 | G19: Factura Exenta Electrónica (69024) | H19: VANESSA CASANGA CASTILLO | I19: 21-03-2025 17:16:00 | J19: 09-04-2025 0:00:00 | K19: 9BFZB55U7J8687464 | L19: FORD | M19: ECOSPORT | N19: ECOSPORT TITANIUM 1.5 | O19: EC3333 | P19: 2018 | Q19: 52119 | R19: TFOSTWU001356 | S19: KDTL69 | T19: USADO | U19: BLANCO | V19: POR DEFINIR | W19: 8990000 | X19: Facturado | Y19: 19 | Z19: CON PRENDA | AA19: BODEGA VEHICULOS | AB19: AE,CC,EE,2AB,NB,ABS,LL,TC,AC,AISO,AAUTO,CRE,MAV,TE | AC19: XZJAJ8687464 | AD19: 9BFZB55U7J8687464 | AE19: SERGIO FLORENCIO GAMBOA | AF19: 21-03-2025 0:00:00 | AG19: 1 | AH19: 21-03-2025 0:00:00 | AI19: 21-03-2025 17:09:36 | AJ19: 31-01-2026 0:00:00 | AK19: 3 | AL19: 0 | AN19: 11 | AO19: 7000000 | AP19: 381608 | AQ19: 2893 | AR19: 7384501 | AS19: 8990000 | AT19: 1605499 | AU19: 1786
A20: IMPORTADORA TRENTO LTDA | B20: LOCAL PREMIUM CAR SALES | C20: 1643 | D20: 39079 | E20: Facturada | F20: 16-11-2023 13:48:51 | G20: Factura Exenta Electrónica (63403) | H20: JORDI AGUSTIN FOITZICK MUÑOZ | I20: 19-07-2023 17:01:59 | J20: 20-11-2023 0:00:00 | K20: 9BGEP69K0NG166056 | L20: CHEVROLET | M20: ONIX | N20: ONIX NB PREMIER 1.0T AUT | O20: AG12 | P20: 2022 | Q20: 5200 | R20: TCHAUTU000883 | S20: RVPZ64 | T20: USADO | U20: BLANCO | V20: POR DEFINIR | W20: 11490000 | X20: Facturado | Y20: 124 | Z20: DISPONIBLE | AA20: PREMIUM CAR SALES | AC20: L4F 213434039 | AD20: 9BGEP69K0NG166056 | AE20: NASIB MAJMUT AMPUERO | AF20: 19-07-2023 0:00:00 | AG20: 1 | AH20: 19-07-2023 0:00:00 | AI20: 19-07-2023 17:01:25 | AK20: 0 | AL20: 0 | AN20: 0 | AO20: 10300000 | AP20: 325040 | AQ20: 0 | AR20: 10625040 | AS20: 11490000 | AT20: 864960 | AU20: 753
A21: IMPORTADORA TRENTO LTDA | B21: LOCAL PREMIUM CAR SALES | C21: 1643 | D21: 39079 | E21: Facturada | F21: 16-11-2023 13:48:51 | G21: Factura Exenta Electrónica (63403) | H21: JORDI AGUSTIN FOITZICK MUÑOZ | I21: 19-07-2023 17:01:59 | J21: 20-11-2023 0:00:00 | K21: 9BGEP69K0NG166056 | L21: CHEVROLET | M21: ONIX | N21: ONIX NB PREMIER 1.0T AUT | O21: AG12 | P21: 2022 | Q21: 5200 | R21: TCHAUTU000883 | S21: RVPZ64 | T21: USADO | U21: BLANCO | V21: POR DEFINIR | W21: 11490000 | X21: Facturado | Y21: 124 | Z21: DISPONIBLE | AA21: PREMIUM CAR SALES | AC21: L4F 213434039 | AD21: 9BGEP69K0NG166056 | AE21: NASIB MAJMUT AMPUERO | AF21: 19-07-2023 0:00:00 | AG21: 1 | AH21: 19-07-2023 0:00:00 | AI21: 19-07-2023 17:01:25 | AK21: 0 | AL21: 0 | AN21: 0 | AO21: 10300000 | AP21: 325040 | AQ21: 0 | AR21: 10625040 | AS21: 11490000 | AT21: 864960 | AU21: 753
A22: IMPORTADORA TRENTO LTDA | B22: LOCAL PREMIUM CAR SALES | C22: 1824 | D22: 43176 | E22: Facturada | F22: 24-10-2024 14:20:56 | G22: Factura Exenta Electrónica (68703) | H22: JORDI AGUSTIN FOITZICK MUÑOZ | I22: 18-10-2024 13:25:37 | J22: 28-10-2024 0:00:00 | K22: JMBXNGA1W NU000433 | L22: MITSUBISHI | M22: ASX | N22: ASX 1.6 | O22: ASX 1.6 | P22: 2022 | Q22: 20000 | R22: TMISTWU000344 | S22: RJCW25 | T22: USADO | U22: BLANCO | V22: POR DEFINIR | W22: 14390000 | X22: Facturado | Y22: 10 | Z22: DISPONIBLE | AA22: PREMIUM CAR SALES | AB22: AE,CC,EE,2AB,NB,ABS,LL,AC,AAUTO,CRE,MAV,ACD,SR,UD, | AC22: 4A92 JK8535 | AD22: JMBXNGA1W NU000433 | AE22: HECTOR DIMAS HURIAZ CACERES | AF22: 18-10-2024 0:00:00 | AG22: 1 | AH22: 18-10-2024 0:00:00 | AI22: 18-10-2024 13:21:09 | AK22: 0 | AL22: 0 | AN22: 1 | AO22: 12000000 | AP22: 356030 | AQ22: 0 | AR22: 12356030 | AS22: 14390000 | AT22: 2033970 | AU22: 1413
A23: IMPORTADORA TRENTO LTDA | B23: LOCAL PREMIUM CAR SALES | C23: 1824 | D23: 43176 | E23: Facturada | F23: 24-10-2024 14:20:56 | G23: Factura Exenta Electrónica (68703) | H23: JORDI AGUSTIN FOITZICK MUÑOZ | I23: 18-10-2024 13:25:37 | J23: 28-10-2024 0:00:00 | K23: JMBXNGA1W NU000433 | L23: MITSUBISHI | M23: ASX | N23: ASX 1.6 | O23: ASX 1.6 | P23: 2022 | Q23: 20000 | R23: TMISTWU000344 | S23: RJCW25 | T23: USADO | U23: BLANCO | V23: POR DEFINIR | W23: 14390000 | X23: Facturado | Y23: 10 | Z23: DISPONIBLE | AA23: PREMIUM CAR SALES | AB23: AE,CC,EE,2AB,NB,ABS,LL,AC,AAUTO,CRE,MAV,ACD,SR,UD, | AC23: 4A92 JK8535 | AD23: JMBXNGA1W NU000433 | AE23: HECTOR DIMAS HURIAZ CACERES | AF23: 18-10-2024 0:00:00 | AG23: 1 | AH23: 18-10-2024 0:00:00 | AI23: 18-10-2024 13:21:09 | AK23: 0 | AL23: 0 | AN23: 1 | AO23: 12000000 | AP23: 356030 | AQ23: 0 | AR23: 12356030 | AS23: 14390000 | AT23: 2033970 | AU23: 1413
A24: IMPORTADORA TRENTO LTDA | B24: LOCAL PREMIUM CAR SALES | C24: 0 | D24: 0 | I24: 06-05-2026 18:05:59 | K24: //.//+*+///++*... | L24: MITSUBISHI | M24: OUTLANDER | N24: OUTLANDER GLS 4X4 2.5 AT | O24: NOI09 | P24: 2025 | Q24: 13500 | R24: TMISTWU000373 | S24: VDFP78 | T24: USADO | U24: GRIS GRAFITO | V24: POR DEFINIR | W24: 31590000 | X24: Disponible | Y24: 35 | Z24: EN PREPARACION | AA24: PREMIUM CAR SALES | AB24: AE,CC,EE,NB,AAC,ABS,LL,VC,AISO,AAUTO,CRE,MAV,ACD,S | AC24: PR25 573855F | AD24: JMYXTGM4WSZ002020 | AE24: LUIS GASTÓN ALCAYAGA NUÑEZ | AF24: 06-05-2026 0:00:00 | AG24: 1 | AH24: 06-05-2026 0:00:00 | AI24: 06-05-2026 18:05:30 | AK24: 1 | AL24: 0 | AN24: 0 | AO24: 26300000 | AP24: 523740 | AQ24: 0 | AR24: 26823740 | AS24: 31590000 | AT24: 4766260 | AU24: 1509
A25: IMPORTADORA TRENTO LTDA | B25: LOCAL PREMIUM CAR SALES | C25: 0 | D25: 0 | I25: 06-05-2026 18:05:59 | K25: //.//+*+///++*... | L25: MITSUBISHI | M25: OUTLANDER | N25: OUTLANDER GLS 4X4 2.5 AT | O25: NOI09 | P25: 2025 | Q25: 13500 | R25: TMISTWU000373 | S25: VDFP78 | T25: USADO | U25: GRIS GRAFITO | V25: POR DEFINIR | W25: 31590000 | X25: Disponible | Y25: 35 | Z25: EN PREPARACION | AA25: PREMIUM CAR SALES | AB25: AE,CC,EE,NB,AAC,ABS,LL,VC,AISO,AAUTO,CRE,MAV,ACD,S | AC25: PR25 573855F | AD25: JMYXTGM4WSZ002020 | AE25: LUIS GASTÓN ALCAYAGA NUÑEZ | AF25: 06-05-2026 0:00:00 | AG25: 1 | AH25: 06-05-2026 0:00:00 | AI25: 06-05-2026 18:05:30 | AK25: 1 | AL25: 0 | AN25: 0 | AO25: 26300000 | AP25: 523740 | AQ25: 0 | AR25: 26823740 | AS25: 31590000 | AT25: 4766260 | AU25: 1509
A26: IMPORTADORA TRENTO LTDA | B26: LOCAL PREMIUM CAR SALES | C26: 2012 | D26: 46789 | E26: Facturada | F26: 23-07-2025 12:04:43 | G26: Factura Exenta Electrónica (69867) | H26: JORDI AGUSTIN FOITZICK MUÑOZ | I26: 22-07-2025 18:54:34 | J26: 25-07-2025 0:00:00 | K26: /////////....+++* | L26: CITROEN | M26: C4 | N26: C4 1.2 AT | O26: CIC412AT | P26: 2025 | Q26: 2858 | R26: TCIAUTU000123 | S26: VBHL43 | T26: USADO | U26: GRIS ARTENSE | V26: POR DEFINIR | W26: 18990000 | X26: Facturado | Y26: 3 | Z26: DISPONIBLE | AA26: PREMIUM CAR SALES | AB26: AE,CC,EE,AAC,ABS,LL,VC,AISO,AAUTO,CRE,MAV,ACD,SR,D | AC26: 10XVBB2277247 | AD26: VR7BAHNSBSE000591 | AE26: NELSON JOSE ALEJANDRO GAETE GONZALEZ | AF26: 22-07-2025 0:00:00 | AG26: 1 | AH26: 22-07-2025 0:00:00 | AI26: 22-07-2025 18:51:05 | AK26: 2 | AL26: 0 | AN26: 0 | AO26: 16500000 | AP26: 373530 | AQ26: 0 | AR26: 16873530 | AS26: 18990000 | AT26: 2116470 | AU26: 1115
A27: IMPORTADORA TRENTO LTDA | B27: LOCAL PREMIUM CAR SALES | C27: 2012 | D27: 46789 | E27: Facturada | F27: 23-07-2025 12:04:43 | G27: Factura Exenta Electrónica (69867) | H27: JORDI AGUSTIN FOITZICK MUÑOZ | I27: 22-07-2025 18:54:34 | J27: 25-07-2025 0:00:00 | K27: /////////....+++* | L27: CITROEN | M27: C4 | N27: C4 1.2 AT | O27: CIC412AT | P27: 2025 | Q27: 2858 | R27: TCIAUTU000123 | S27: VBHL43 | T27: USADO | U27: GRIS ARTENSE | V27: POR DEFINIR | W27: 18990000 | X27: Facturado | Y27: 3 | Z27: DISPONIBLE | AA27: PREMIUM CAR SALES | AB27: AE,CC,EE,AAC,ABS,LL,VC,AISO,AAUTO,CRE,MAV,ACD,SR,D | AC27: 10XVBB2277247 | AD27: VR7BAHNSBSE000591 | AE27: NELSON JOSE ALEJANDRO GAETE GONZALEZ | AF27: 22-07-2025 0:00:00 | AG27: 1 | AH27: 22-07-2025 0:00:00 | AI27: 22-07-2025 18:51:05 | AK27: 2 | AL27: 0 | AN27: 0 | AO27: 16500000 | AP27: 373530 | AQ27: 0 | AR27: 16873530 | AS27: 18990000 | AT27: 2116470 | AU27: 1115
A28: IMPORTADORA TRENTO LTDA | B28: LOCAL USADOS COPIAPO | C28: 1069 | D28: 42166 | E28: Facturada | F28: 07-08-2024 12:17:53 | G28: Factura Exenta Electrónica (63901) | H28: LUCILA ANTONIA ARREDONDO CASTRO | I28: 29-07-2024 12:30:11 | J28: 23-08-2024 0:00:00 | K28: LVTDB11B5ND048433 | L28: CHERY | M28: TIGGO 8 | N28: TIGGO 8 1.5 | O28: TIIII8 | P28: 2022 | Q28: 42500 | R28: TCYSTWU000259 | S28: RTWY58 | T28: USADO | U28: AZUL METALIZADO | V28: POR DEFINIR | W28: 12090000 | X28: Facturado | Y28: 25 | Z28: DISPONIBLE | AA28: BODEGA LOS CARRERA COPIAPO | AB28: AE,CC,EE,AAC,ABS,LL,TC,VC,ESP,AISO,AAUTO,CRE,MAV,A | AC28: SQRE4T15BALMM00605 | AD28: LVTDB11B5ND048433 | AE28: TELMO FRANCISCO GALLEGUILLOS QUIROGA | AF28: 29-07-2024 0:00:00 | AG28: 1 | AH28: 29-07-2024 0:00:00 | AI28: 29-07-2024 12:27:27 | AK28: 0 | AL28: 0 | AN28: 6 | AO28: 10200000 | AP28: 329030 | AQ28: 1178 | AR28: 10530208 | AS28: 12090000 | AT28: 1559792 | AU28: 129
A29: IMPORTADORA TRENTO LTDA | B29: LOCAL USADOS COPIAPO | C29: 1069 | D29: 42166 | E29: Facturada | F29: 07-08-2024 12:17:53 | G29: Factura Exenta Electrónica (63901) | H29: LUCILA ANTONIA ARREDONDO CASTRO | I29: 29-07-2024 12:30:11 | J29: 23-08-2024 0:00:00 | K29: LVTDB11B5ND048433 | L29: CHERY | M29: TIGGO 8 | N29: TIGGO 8 1.5 | O29: TIIII8 | P29: 2022 | Q29: 42500 | R29: TCYSTWU000259 | S29: RTWY58 | T29: USADO | U29: AZUL METALIZADO | V29: POR DEFINIR | W29: 12090000 | X29: Facturado | Y29: 25 | Z29: DISPONIBLE | AA29: BODEGA LOS CARRERA COPIAPO | AB29: AE,CC,EE,AAC,ABS,LL,TC,VC,ESP,AISO,AAUTO,CRE,MAV,A | AC29: SQRE4T15BALMM00605 | AD29: LVTDB11B5ND048433 | AE29: TELMO FRANCISCO GALLEGUILLOS QUIROGA | AF29: 29-07-2024 0:00:00 | AG29: 1 | AH29: 29-07-2024 0:00:00 | AI29: 29-07-2024 12:27:27 | AK29: 0 | AL29: 0 | AN29: 6 | AO29: 10200000 | AP29: 329030 | AQ29: 1178 | AR29: 10530208 | AS29: 12090000 | AT29: 1559792 | AU29: 129
A30: IMPORTADORA TRENTO LTDA | B30: LOCAL PREMIUM CAR SALES | C30: 0 | D30: 0 | I30: 28-04-2026 11:16:31 | K30: /////++***/++*... | L30: ZX AUTO | M30: TERRALORD | N30: TERRALORD DCAB DLX 2.5 | O30: ZXTERRDCDLX25MT | P30: 2022 | Q30: 58000 | R30: TZXCMTU000004 | S30: RDWB83 | T30: USADO | U30: PLATEADO PLATA | V30: POR DEFINIR | W30: 11290000 | X30: Disponible | Y30: 43 | Z30: DISPONIBLE | AA30: PREMIUM CAR SALES | AB30: AE,CC,EE,NB,ABS,LL,VC,4AB,AC,AISO,AAUTO,MAV,ACD,UD | AC30: 20-36100283 | AD30: LTA1222U2N9101636 | AE30: ALFONSO SEGUNDO CARVAJAL ROJAS | AF30: 28-04-2026 0:00:00 | AG30: 1 | AH30: 28-04-2026 0:00:00 | AI30: 28-04-2026 11:16:03 | AK30: 1 | AL30: 0 | AN30: 0 | AO30: 8900000 | AP30: 262740 | AQ30: 0 | AR30: 9162740 | AS30: 11290000 | AT30: 2127260 | AU30: 1884
A31: IMPORTADORA TRENTO LTDA | B31: LOCAL PREMIUM CAR SALES | C31: 0 | D31: 0 | I31: 28-04-2026 11:16:31 | K31: /////++***/++*... | L31: ZX AUTO | M31: TERRALORD | N31: TERRALORD DCAB DLX 2.5 | O31: ZXTERRDCDLX25MT | P31: 2022 | Q31: 58000 | R31: TZXCMTU000004 | S31: RDWB83 | T31: USADO | U31: PLATEADO PLATA | V31: POR DEFINIR | W31: 11290000 | X31: Disponible | Y31: 43 | Z31: DISPONIBLE | AA31: PREMIUM CAR SALES | AB31: AE,CC,EE,NB,ABS,LL,VC,4AB,AC,AISO,AAUTO,MAV,ACD,UD | AC31: 20-36100283 | AD31: LTA1222U2N9101636 | AE31: ALFONSO SEGUNDO CARVAJAL ROJAS | AF31: 28-04-2026 0:00:00 | AG31: 1 | AH31: 28-04-2026 0:00:00 | AI31: 28-04-2026 11:16:03 | AK31: 1 | AL31: 0 | AN31: 0 | AO31: 8900000 | AP31: 262740 | AQ31: 0 | AR31: 9162740 | AS31: 11290000 | AT31: 2127260 | AU31: 1884
A32: IMPORTADORA TRENTO LTDA | B32: MEGACENTRO OVALLE | C32: 317 | D32: 36199 | E32: Facturada | F32: 07-02-2023 15:44:29 | G32: Factura Exenta Electrónica (62073) | H32: Armando Canihuante . | I32: 27-01-2023 10:23:12 | J32: 07-02-2023 0:00:00 | K32: LVZA53P91JCB00949 | L32: DFSK | M32: 580 | N32: 580 1.8 | O32: HJ70 | P32: 2018 | Q32: 63900 | R32: TDFSTWU000016 | S32: KGKZ84 | T32: USADO | U32: BLANCO | V32: POR DEFINIR | W32: 7990000 | X32: Facturado | Y32: 11 | Z32: DISPONIBLE | AA32: BODEGA OVALLEveih | AC32: SFG1817552648 | AD32: LVZA53P91JCB00949 | AE32: HERNAN HUMBERTO JIMENEZ RAMOS | AF32: 27-01-2023 0:00:00 | AG32: 1 | AH32: 27-02-2023 17:55:00 | AI32: 27-02-2023 17:55:00 | AK32: 0 | AL32: 0 | AN32: 8 | AO32: 6000000 | AP32: 388323 | AQ32: 21270 | AR32: 6409593 | AS32: 7990000 | AT32: 1580407 | AU32: 1978
A33: IMPORTADORA TRENTO LTDA | B33: MEGACENTRO OVALLE | C33: 317 | D33: 36199 | E33: Facturada | F33: 07-02-2023 15:44:29 | G33: Factura Exenta Electrónica (62073) | H33: Armando Canihuante . | I33: 27-01-2023 10:23:12 | J33: 07-02-2023 0:00:00 | K33: LVZA53P91JCB00949 | L33: DFSK | M33: 580 | N33: 580 1.8 | O33: HJ70 | P33: 2018 | Q33: 63900 | R33: TDFSTWU000016 | S33: KGKZ84 | T33: USADO | U33: BLANCO | V33: POR DEFINIR | W33: 7990000 | X33: Facturado | Y33: 11 | Z33: DISPONIBLE | AA33: BODEGA OVALLEveih | AC33: SFG1817552648 | AD33: LVZA53P91JCB00949 | AE33: HERNAN HUMBERTO JIMENEZ RAMOS | AF33: 27-01-2023 0:00:00 | AG33: 1 | AH33: 27-02-2023 17:55:00 | AI33: 27-02-2023 17:55:00 | AK33: 0 | AL33: 0 | AN33: 8 | AO33: 6000000 | AP33: 388323 | AQ33: 21270 | AR33: 6409593 | AS33: 7990000 | AT33: 1580407 | AU33: 1978
A34: IMPORTADORA TRENTO LTDA | B34: LOCAL USADOS | C34: 2023 | D34: 39101 | E34: Facturada | F34: 17-11-2023 19:12:57 | G34: Factura Exenta Electrónica (63412) | H34: VANESSA CASANGA CASTILLO | I34: 14-11-2023 8:50:02 | J34: 23-11-2023 0:00:00 | K34: LSJW74U98LZ035051 | L34: MG | M34: MGZS | N34: ZS 1.5 AUT | O34: Z87W | P34: 2020 | Q34: 15000 | R34: TMGSTWU000037 | S34: PCDX27 | T34: USADO | U34: BLANCO | V34: POR DEFINIR | W34: 9290000 | X34: Facturado | Y34: 9 | Z34: DISPONIBLE | AA34: BODEGA VEHICULOS | AC34: 15S4C8FGKB011199 | AD34: LSJW74U98LZ035051 | AE34: SERGIO EDUARDO MATURANA ESPINOZA | AF34: 14-11-2023 0:00:00 | AG34: 1 | AH34: 14-11-2023 0:00:00 | AI34: 14-11-2023 8:49:31 | AK34: 0 | AL34: 0 | AN34: 1 | AO34: 7500000 | AP34: 273040 | AQ34: 3946 | AR34: 7776986 | AS34: 9290000 | AT34: 1513014 | AU34: 1629
A35: IMPORTADORA TRENTO LTDA | B35: LOCAL USADOS | C35: 2023 | D35: 39101 | E35: Facturada | F35: 17-11-2023 19:12:57 | G35: Factura Exenta Electrónica (63412) | H35: VANESSA CASANGA CASTILLO | I35: 14-11-2023 8:50:02 | J35: 23-11-2023 0:00:00 | K35: LSJW74U98LZ035051 | L35: MG | M35: MGZS | N35: ZS 1.5 AUT | O35: Z87W | P35: 2020 | Q35: 15000 | R35: TMGSTWU000037 | S35: PCDX27 | T35: USADO | U35: BLANCO | V35: POR DEFINIR | W35: 9290000 | X35: Facturado | Y35: 9 | Z35: DISPONIBLE | AA35: BODEGA VEHICULOS | AC35: 15S4C8FGKB011199 | AD35: LSJW74U98LZ035051 | AE35: SERGIO EDUARDO MATURANA ESPINOZA | AF35: 14-11-2023 0:00:00 | AG35: 1 | AH35: 14-11-2023 0:00:00 | AI35: 14-11-2023 8:49:31 | AK35: 0 | AL35: 0 | AN35: 1 | AO35: 7500000 | AP35: 273040 | AQ35: 3946 | AR35: 7776986 | AS35: 9290000 | AT35: 1513014 | AU35: 1629
A36: IMPORTADORA TRENTO LTDA | B36: LOCAL USADOS | C36: 1892 | D36: 36216 | E36: Facturada | F36: 09-02-2023 12:41:03 | G36: Factura Exenta Electrónica (62086) | H36: VANESSA CASANGA CASTILLO | I36: 03-02-2023 17:48:30 | J36: 13-02-2023 0:00:00 | K36: ...+-*+/*-....... | L36: PEUGEOT | M36: 2008 | N36: 2008 ALLURE BLUEHDI 1.6 | O36: pmu1 | P36: 2017 | Q36: 89000 | R36: TPESTWU000311 | S36: JCDG98 | T36: USADO | U36: ROJO ULTIMATE | V36: POR DEFINIR | W36: 10590000 | X36: Facturado | Y36: 10 | Z36: DISPONIBLE | AA36: BODEGA VEHICULOS | AC36: 10JBHA0187931 | AD36: VF3CUBHY6HY002129 | AE36: GUILLERMO SANCHEZ MUÑOZ | AF36: 03-02-2023 0:00:00 | AG36: 1 | AH36: 03-02-2023 0:00:00 | AI36: 03-02-2023 17:48:04 | AK36: 0 | AL36: 0 | AN36: 0 | AO36: 8500000 | AP36: 288040 | AQ36: 3652 | AR36: 8791692 | AS36: 10590000 | AT36: 1798308 | AU36: 1698
A37: IMPORTADORA TRENTO LTDA | B37: LOCAL USADOS | C37: 1892 | D37: 36216 | E37: Facturada | F37: 09-02-2023 12:41:03 | G37: Factura Exenta Electrónica (62086) | H37: VANESSA CASANGA CASTILLO | I37: 03-02-2023 17:48:30 | J37: 13-02-2023 0:00:00 | K37: ...+-*+/*-....... | L37: PEUGEOT | M37: 2008 | N37: 2008 ALLURE BLUEHDI 1.6 | O37: pmu1 | P37: 2017 | Q37: 89000 | R37: TPESTWU000311 | S37: JCDG98 | T37: USADO | U37: ROJO ULTIMATE | V37: POR DEFINIR | W37: 10590000 | X37: Facturado | Y37: 10 | Z37: DISPONIBLE | AA37: BODEGA VEHICULOS | AC37: 10JBHA0187931 | AD37: VF3CUBHY6HY002129 | AE37: GUILLERMO SANCHEZ MUÑOZ | AF37: 03-02-2023 0:00:00 | AG37: 1 | AH37: 03-02-2023 0:00:00 | AI37: 03-02-2023 17:48:04 | AK37: 0 | AL37: 0 | AN37: 0 | AO37: 8500000 | AP37: 288040 | AQ37: 3652 | AR37: 8791692 | AS37: 10590000 | AT37: 1798308 | AU37: 1698
A38: IMPORTADORA TRENTO LTDA | B38: LOCAL USADOS | C38: 2006 | D38: 38964 | E38: Facturada | F38: 31-10-2023 18:55:41 | G38: Factura Exenta Electrónica (63378) | H38: FEDERICO ALBERT | I38: 31-10-2023 16:43:42 | J38: 31-10-2023 0:00:00 | K38: JN1JBAT32JW013654 | L38: NISSAN | M38: XTRAIL | N38: X TRAIL SENSE 2.5 AUT | O38: XUSADO | P38: 2018 | Q38: 0 | R38: TNISTWU000510 | S38: JXGD53 | T38: USADO | U38: GRIS METALICO | V38: POR DEFINIR | W38: 11690000 | X38: Facturado | Y38: 0 | Z38: DISPONIBLE | AA38: BODEGA VEHICULOS | AC38: QR25006200M | AD38: JN1JBAT32JW013654 | AE38: JORGE EDUARDO CONTRERAS ROBLES | AF38: 31-10-2023 0:00:00 | AG38: 1 | AH38: 31-10-2023 0:00:00 | AI38: 31-10-2023 16:43:18 | AK38: 0 | AL38: 0 | AN38: 0 | AO38: 9000000 | AP38: 295540 | AQ38: 3999 | AR38: 9299539 | AS38: 11690000 | AT38: 2390461 | AU38: 2045
A39: IMPORTADORA TRENTO LTDA | B39: LOCAL USADOS | C39: 2006 | D39: 38964 | E39: Facturada | F39: 31-10-2023 18:55:41 | G39: Factura Exenta Electrónica (63378) | H39: FEDERICO ALBERT | I39: 31-10-2023 16:43:42 | J39: 31-10-2023 0:00:00 | K39: JN1JBAT32JW013654 | L39: NISSAN | M39: XTRAIL | N39: X TRAIL SENSE 2.5 AUT | O39: XUSADO | P39: 2018 | Q39: 0 | R39: TNISTWU000510 | S39: JXGD53 | T39: USADO | U39: GRIS METALICO | V39: POR DEFINIR | W39: 11690000 | X39: Facturado | Y39: 0 | Z39: DISPONIBLE | AA39: BODEGA VEHICULOS | AC39: QR25006200M | AD39: JN1JBAT32JW013654 | AE39: JORGE EDUARDO CONTRERAS ROBLES | AF39: 31-10-2023 0:00:00 | AG39: 1 | AH39: 31-10-2023 0:00:00 | AI39: 31-10-2023 16:43:18 | AK39: 0 | AL39: 0 | AN39: 0 | AO39: 9000000 | AP39: 295540 | AQ39: 3999 | AR39: 9299539 | AS39: 11690000 | AT39: 2390461 | AU39: 2045
A40: IMPORTADORA TRENTO LTDA | B40: LOCAL USADOS | C40: 0 | D40: 0 | I40: 02-09-2025 10:22:59 | K40: ////////..**/++++ | L40: SUZUKI | M40: BALENO | N40: BALENO 4X2 1.5 | O40: SZBAL4X215 | P40: 2024 | Q40: 15000 | R40: TSZAUTU000454 | S40: TJSK21 | T40: USADO | U40: BLANCO PERLA | V40: POR DEFINIR | W40: 11290000 | X40: Retirado Stock | Y40: 0 | Z40: NO DISPONIBLE | AA40: BODEGA VEHICULOS | AB40: AE,CC,EE,2AB,NB,ABS,LL,AC,AISO,AAUTO,CRE,MAV,ACD,S | AC40: K15BN1460866 | AD40: MBHWBA3S1SG665159 | AE40: HECTOR ARMANDO MOYA ROMERO | AF40: 02-09-2025 0:00:00 | AG40: 0 | AK40: 1 | AL40: 0 | AN40: 0 | AO40: 0 | AP40: 0 | AQ40: 0 | AR40: 0 | AS40: 11290000 | AT40: 11290000 | AU40: 100
A41: IMPORTADORA TRENTO LTDA | B41: LOCAL USADOS | C41: 0 | D41: 0 | I41: 02-09-2025 10:22:59 | K41: ////////..**/++++ | L41: SUZUKI | M41: BALENO | N41: BALENO 4X2 1.5 | O41: SZBAL4X215 | P41: 2024 | Q41: 15000 | R41: TSZAUTU000454 | S41: TJSK21 | T41: USADO | U41: BLANCO PERLA | V41: POR DEFINIR | W41: 11290000 | X41: Retirado Stock | Y41: 0 | Z41: NO DISPONIBLE | AA41: BODEGA VEHICULOS | AB41: AE,CC,EE,2AB,NB,ABS,LL,AC,AISO,AAUTO,CRE,MAV,ACD,S | AC41: K15BN1460866 | AD41: MBHWBA3S1SG665159 | AE41: HECTOR ARMANDO MOYA ROMERO | AF41: 02-09-2025 0:00:00 | AG41: 0 | AK41: 1 | AL41: 0 | AN41: 0 | AO41: 0 | AP41: 0 | AQ41: 0 | AR41: 0 | AS41: 11290000 | AT41: 11290000 | AU41: 100
A42: IMPORTADORA TRENTO LTDA | B42: MEGACENTRO OVALLE | C42: 338 | D42: 38696 | E42: Facturada | F42: 12-10-2023 10:02:37 | G42: Factura Exenta Electrónica (63345) | H42: Armando Canihuante . | I42: 03-10-2023 9:16:48 | J42: 13-10-2023 0:00:00 | K42: 3N8CP5HE0NL461123 | L42: NISSAN | M42: KICKS | N42: KICKS 1.6 | O42: KLP0 | P42: 2021 | Q42: 22500 | R42: TNISTWU000506 | S42: PRHK53 | T42: USADO | U42: PLATEADO PLATA | V42: POR DEFINIR | W42: 12590000 | X42: Facturado | Y42: 10 | Z42: DISPONIBLE | AA42: BODEGA OVALLEveih | AC42: HR16-253800V | AD42: 3N8CP5HE0NL461123 | AE42: HECTOR ROSARIO TORO BERENGUELA | AF42: 03-10-2023 0:00:00 | AG42: 1 | AH42: 03-10-2023 0:00:00 | AI42: 03-10-2023 9:16:24 | AK42: 0 | AL42: 0 | AN42: 9 | AO42: 10000000 | AP42: 400790 | AQ42: 15364 | AR42: 10416154 | AS42: 12590000 | AT42: 2173846 | AU42: 1727
A43: IMPORTADORA TRENTO LTDA | B43: MEGACENTRO OVALLE | C43: 338 | D43: 38696 | E43: Facturada | F43: 12-10-2023 10:02:37 | G43: Factura Exenta Electrónica (63345) | H43: Armando Canihuante . | I43: 03-10-2023 9:16:48 | J43: 13-10-2023 0:00:00 | K43: 3N8CP5HE0NL461123 | L43: NISSAN | M43: KICKS | N43: KICKS 1.6 | O43: KLP0 | P43: 2021 | Q43: 22500 | R43: TNISTWU000506 | S43: PRHK53 | T43: USADO | U43: PLATEADO PLATA | V43: POR DEFINIR | W43: 12590000 | X43: Facturado | Y43: 10 | Z43: DISPONIBLE | AA43: BODEGA OVALLEveih | AC43: HR16-253800V | AD43: 3N8CP5HE0NL461123 | AE43: HECTOR ROSARIO TORO BERENGUELA | AF43: 03-10-2023 0:00:00 | AG43: 1 | AH43: 03-10-2023 0:00:00 | AI43: 03-10-2023 9:16:24 | AK43: 0 | AL43: 0 | AN43: 9 | AO43: 10000000 | AP43: 400790 | AQ43: 15364 | AR43: 10416154 | AS43: 12590000 | AT43: 2173846 | AU43: 1727
A44: IMPORTADORA TRENTO LTDA | B44: LOCAL USADOS | C44: 2360 | D44: 45833 | E44: Facturada | F44: 13-05-2025 19:04:22 | H44: VANESSA CASANGA CASTILLO | I44: 13-05-2025 18:58:05 | K44: VF3MCYHZU NS003554 | L44: PEUGEOT | M44: 3008 | N44: 3008 BLUE HDI 130 EAT8 1.5 AUT | O44: 3008 BH4 | P44: 2022 | Q44: 67000 | R44: TPESTWU000401 | S44: RFFT62 | T44: CONSIGNACION USADO | U44: GRIS ARTENSE | V44: POR DEFINIR | W44: 22990000 | X44: Facturado | Y44: 18 | Z44: DISPONIBLE | AA44: BODEGA VEHICULOS | AC44: 10Q4EP0018555 | AD44: VF3MCYHZU NS003554 | AE44: GIOVANNA ELIGIA CALLEGARI PANIZZA | AF44: 13-05-2025 0:00:00 | AG44: 1 | AH44: 13-05-2025 0:00:00 | AI44: 02-09-2025 11:22:14 | AK44: 1 | AL44: 0 | AN44: 0 | AO44: 22930500 | AP44: 0 | AQ44: 0 | AR44: 22930500 | AS44: 22990000 | AT44: 59500 | AU44: 26
A45: IMPORTADORA TRENTO LTDA | B45: LOCAL PREMIUM CAR SALES | C45: 1615 | D45: 38408 | E45: Facturada | F45: 08-09-2023 17:08:18 | G45: Factura Exenta Electrónica (63250) | H45: JORDI AGUSTIN FOITZICK MUÑOZ | I45: 25-05-2023 12:48:42 | J45: 13-09-2023 0:00:00 | K45: VR3FDAHDL N3005080 | L45: PEUGEOT | M45: LANDTREK | N45: LANDTREK 4X4 1.9 | O45: LTR90 | P45: 2022 | Q45: 32000 | R45: TPECMTU000003 | S45: RSTC90 | T45: USADO | U45: VERDE OLEA | V45: POR DEFINIR | W45: 17990000 | X45: Facturado | Y45: 111 | Z45: DISPONIBLE | AA45: PREMIUM CAR SALES | AC45: A5D21006112 | AD45: VR3FDAHDL N3005080 | AE45: TOMAS ERNESTO GONZALEZ GONZALEZ | AF45: 25-05-2023 0:00:00 | AG45: 1 | AH45: 04-09-2023 18:33:00 | AI45: 04-09-2023 18:33:00 | AK45: 0 | AL45: 0 | AN45: 1 | AO45: 17000000 | AP45: 415540 | AQ45: 0 | AR45: 17415540 | AS45: 17990000 | AT45: 574460 | AU45: 319
A46: IMPORTADORA TRENTO LTDA | B46: LOCAL PREMIUM CAR SALES | C46: 1615 | D46: 38408 | E46: Facturada | F46: 08-09-2023 17:08:18 | G46: Factura Exenta Electrónica (63250) | H46: JORDI AGUSTIN FOITZICK MUÑOZ | I46: 25-05-2023 12:48:42 | J46: 13-09-2023 0:00:00 | K46: VR3FDAHDL N3005080 | L46: PEUGEOT | M46: LANDTREK | N46: LANDTREK 4X4 1.9 | O46: LTR90 | P46: 2022 | Q46: 32000 | R46: TPECMTU000003 | S46: RSTC90 | T46: USADO | U46: VERDE OLEA | V46: POR DEFINIR | W46: 17990000 | X46: Facturado | Y46: 111 | Z46: DISPONIBLE | AA46: PREMIUM CAR SALES | AC46: A5D21006112 | AD46: VR3FDAHDL N3005080 | AE46: TOMAS ERNESTO GONZALEZ GONZALEZ | AF46: 25-05-2023 0:00:00 | AG46: 1 | AH46: 04-09-2023 18:33:00 | AI46: 04-09-2023 18:33:00 | AK46: 0 | AL46: 0 | AN46: 1 | AO46: 17000000 | AP46: 415540 | AQ46: 0 | AR46: 17415540 | AS46: 17990000 | AT46: 574460 | AU46: 319
A47: IMPORTADORA TRENTO LTDA | B47: LOCAL USADOS | C47: 2058 | D47: 39722 | E47: Facturada | F47: 10-01-2024 17:00:01 | G47: Factura Exenta Electrónica (63493) | H47: VANESSA CASANGA CASTILLO | I47: 03-10-2023 9:21:24 | J47: 16-01-2024 0:00:00 | K47: *-*/**-*/.+-***** | L47: JEEP | M47: RENEGADE | N47: RENEGADE LX SPORT 1.7 | O47: REL | P47: 2017 | Q47: 86000 | R47: TJESTWU000418 | S47: JPSK79 | T47: USADO | U47: GRIS PLATA | V47: POR DEFINIR | W47: 8990000 | X47: Facturado | Y47: 105 | Z47: DISPONIBLE | AA47: BODEGA VEHICULOS | AC47: 3130476 | AD47: 988611457JK118043 | AE47: LEONARDO ENRIQUE PEREZ CASTRO | AF47: 03-10-2023 0:00:00 | AG47: 1 | AH47: 31-10-2023 12:33:00 | AI47: 31-10-2023 12:33:00 | AK47: 0 | AL47: 0 | AN47: 1 | AO47: 7700000 | AP47: 38050 | AQ47: 10882 | AR47: 7748932 | AS47: 8990000 | AT47: 1241068 | AU47: 138
A48: IMPORTADORA TRENTO LTDA | B48: LOCAL USADOS | C48: 2058 | D48: 39722 | E48: Facturada | F48: 10-01-2024 17:00:01 | G48: Factura Exenta Electrónica (63493) | H48: VANESSA CASANGA CASTILLO | I48: 03-10-2023 9:21:24 | J48: 16-01-2024 0:00:00 | K48: *-*/**-*/.+-***** | L48: JEEP | M48: RENEGADE | N48: RENEGADE LX SPORT 1.7 | O48: REL | P48: 2017 | Q48: 86000 | R48: TJESTWU000418 | S48: JPSK79 | T48: USADO | U48: GRIS PLATA | V48: POR DEFINIR | W48: 8990000 | X48: Facturado | Y48: 105 | Z48: DISPONIBLE | AA48: BODEGA VEHICULOS | AC48: 3130476 | AD48: 988611457JK118043 | AE48: LEONARDO ENRIQUE PEREZ CASTRO | AF48: 03-10-2023 0:00:00 | AG48: 1 | AH48: 31-10-2023 12:33:00 | AI48: 31-10-2023 12:33:00 | AK48: 0 | AL48: 0 | AN48: 1 | AO48: 7700000 | AP48: 38050 | AQ48: 10882 | AR48: 7748932 | AS48: 8990000 | AT48: 1241068 | AU48: 138
A49: IMPORTADORA TRENTO LTDA | B49: LOCAL PREMIUM CAR SALES | C49: 1732 | D49: 41272 | E49: Facturada | F49: 24-05-2024 13:00:12 | G49: Factura Exenta Electrónica (63742) | H49: VENTAS OFICINA . | I49: 29-04-2024 9:44:45 | J49: 28-05-2024 0:00:00 | K49: 3KPF341AB NE441987 | L49: KIA MOTORS | M49: CERATO | N49: CERATO EX 4X2 1.6 AUT | O49: KCE01 | P49: 2022 | Q49: 40000 | R49: TKIAUTU002138 | S49: RWWC29 | T49: USADO | U49: ROJO BENGALA | V49: POR DEFINIR | W49: 15890000 | X49: Facturado | Y49: 29 | Z49: DISPONIBLE | AA49: PREMIUM CAR SALES | AB49: AE,CC,EE,ABS,LL,AC,AISO,AAUTO,CRE,MAV,ACD,SR,UD,DL | AC49: G4FGME049967 | AD49: 3KPF341AB NE441987 | AE49: MIGUEL ANGEL REYES CORNEJO | AF49: 29-04-2024 0:00:00 | AG49: 1 | AH49: 29-04-2024 0:00:00 | AI49: 28-05-2024 13:42:27 | AK49: 0 | AL49: 0 | AN49: 0 | AO49: 12800000 | AP49: 367030 | AQ49: 0 | AR49: 13167030 | AS49: 15890000 | AT49: 2722970 | AU49: 1714
A50: IMPORTADORA TRENTO LTDA | B50: LOCAL PREMIUM CAR SALES | C50: 1732 | D50: 41272 | E50: Facturada | F50: 24-05-2024 13:00:12 | G50: Factura Exenta Electrónica (63742) | H50: VENTAS OFICINA . | I50: 29-04-2024 9:44:45 | J50: 28-05-2024 0:00:00 | K50: 3KPF341AB NE441987 | L50: KIA MOTORS | M50: CERATO | N50: CERATO EX 4X2 1.6 AUT | O50: KCE01 | P50: 2022 | Q50: 40000 | R50: TKIAUTU002138 | S50: RWWC29 | T50: USADO | U50: ROJO BENGALA | V50: POR DEFINIR | W50: 15890000 | X50: Facturado | Y50: 29 | Z50: DISPONIBLE | AA50: PREMIUM CAR SALES | AB50: AE,CC,EE,ABS,LL,AC,AISO,AAUTO,CRE,MAV,ACD,SR,UD,DL | AC50: G4FGME049967 | AD50: 3KPF341AB NE441987 | AE50: MIGUEL ANGEL REYES CORNEJO | AF50: 29-04-2024 0:00:00 | AG50: 1 | AH50: 29-04-2024 0:00:00 | AI50: 28-05-2024 13:42:27 | AK50: 0 | AL50: 0 | AN50: 0 | AO50: 12800000 | AP50: 367030 | AQ50: 0 | AR50: 13167030 | AS50: 15890000 | AT50: 2722970 | AU50: 1714
A51: IMPORTADORA TRENTO LTDA | B51: MEGACENTRO OVALLE | C51: 408 | D51: 44618 | E51: Facturada | F51: 04-02-2025 16:05:23 | G51: Factura Exenta Electrónica (68908) | H51: JOSE GREGORIO TORRES | I51: 29-01-2025 13:51:02 | J51: 07-02-2025 0:00:00 | K51: *++*-....../*.... | L51: SUZUKI | M51: SPRESSO | N51: SPRESSO 1.0 | O51: SZSPRESSO10MT | P51: 2023 | Q51: 1010 | R51: TSZAUTU000442 | S51: SYXS13 | T51: USADO | U51: GRIS GRANITO | V51: POR DEFINIR | W51: 7290000 | X51: Facturado | Y51: 9 | Z51: DISPONIBLE | AA51: BODEGA OVALLEveih | AB51: AE,2AB,LL,AC,ACD,SR,UD,PKM | AC51: K10CNC272167 | AD51: MA3FL61S6RA433220 | AE51: JUAN RAMON RIVERA GALLARDO | AF51: 29-01-2025 0:00:00 | AG51: 1 | AH51: 29-01-2025 0:00:00 | AI51: 29-01-2025 13:47:12 | AK51: 1 | AL51: 0 | AN51: 1 | AO51: 6000000 | AP51: 216030 | AQ51: 8107 | AR51: 6224137 | AS51: 7290000 | AT51: 1065863 | AU51: 1462
A52: IMPORTADORA TRENTO LTDA | B52: MEGACENTRO OVALLE | C52: 408 | D52: 44618 | E52: Facturada | F52: 04-02-2025 16:05:23 | G52: Factura Exenta Electrónica (68908) | H52: JOSE GREGORIO TORRES | I52: 29-01-2025 13:51:02 | J52: 07-02-2025 0:00:00 | K52: *++*-....../*.... | L52: SUZUKI | M52: SPRESSO | N52: SPRESSO 1.0 | O52: SZSPRESSO10MT | P52: 2023 | Q52: 1010 | R52: TSZAUTU000442 | S52: SYXS13 | T52: USADO | U52: GRIS GRANITO | V52: POR DEFINIR | W52: 7290000 | X52: Facturado | Y52: 9 | Z52: DISPONIBLE | AA52: BODEGA OVALLEveih | AB52: AE,2AB,LL,AC,ACD,SR,UD,PKM | AC52: K10CNC272167 | AD52: MA3FL61S6RA433220 | AE52: JUAN RAMON RIVERA GALLARDO | AF52: 29-01-2025 0:00:00 | AG52: 1 | AH52: 29-01-2025 0:00:00 | AI52: 29-01-2025 13:47:12 | AK52: 1 | AL52: 0 | AN52: 1 | AO52: 6000000 | AP52: 216030 | AQ52: 8107 | AR52: 6224137 | AS52: 7290000 | AT52: 1065863 | AU52: 1462
A53: IMPORTADORA TRENTO LTDA | B53: LOCAL PREMIUM CAR SALES | C53: 1505 | D53: 36096 | E53: Facturada | F53: 27-01-2023 18:59:03 | G53: Factura Exenta Electrónica (62056) | H53: JORDI AGUSTIN FOITZICK MUÑOZ | I53: 27-01-2023 9:29:27 | J53: 30-01-2023 0:00:00 | K53: WBATX3105 KLF53205 | L53: BMW | M53: BMW | N53: X3 XDRIVE 20D 4X4 2.0 AT | O53: X3 | P53: 2019 | Q53: 44000 | R53: TBMSTWU000006 | S53: KZKC93 | T53: USADO | U53: BLANCO | V53: POR DEFINIR | W53: 26990000 | X53: Facturado | Y53: 3 | Z53: DISPONIBLE | AA53: PREMIUM CAR SALES | AC53: 51915469 | AD53: WBATX3105 KLF53205 | AE53: MINERVA INES GONZALEZ ZEPEDA | AF53: 27-01-2023 0:00:00 | AG53: 1 | AH53: 13-03-2023 10:49:00 | AI53: 13-03-2023 10:49:00 | AK53: 0 | AL53: 0 | AN53: 0 | AO53: 19500000 | AP53: 453040 | AQ53: 0 | AR53: 19953040 | AS53: 26990000 | AT53: 7036960 | AU53: 2607
A54: IMPORTADORA TRENTO LTDA | B54: LOCAL PREMIUM CAR SALES | C54: 1505 | D54: 36096 | E54: Facturada | F54: 27-01-2023 18:59:03 | G54: Factura Exenta Electrónica (62056) | H54: JORDI AGUSTIN FOITZICK MUÑOZ | I54: 27-01-2023 9:29:27 | J54: 30-01-2023 0:00:00 | K54: WBATX3105 KLF53205 | L54: BMW | M54: BMW | N54: X3 XDRIVE 20D 4X4 2.0 AT | O54: X3 | P54: 2019 | Q54: 44000 | R54: TBMSTWU000006 | S54: KZKC93 | T54: USADO | U54: BLANCO | V54: POR DEFINIR | W54: 26990000 | X54: Facturado | Y54: 3 | Z54: DISPONIBLE | AA54: PREMIUM CAR SALES | AC54: 51915469 | AD54: WBATX3105 KLF53205 | AE54: MINERVA INES GONZALEZ ZEPEDA | AF54: 27-01-2023 0:00:00 | AG54: 1 | AH54: 13-03-2023 10:49:00 | AI54: 13-03-2023 10:49:00 | AK54: 0 | AL54: 0 | AN54: 0 | AO54: 19500000 | AP54: 453040 | AQ54: 0 | AR54: 19953040 | AS54: 26990000 | AT54: 7036960 | AU54: 2607
A55: IMPORTADORA TRENTO LTDA | B55: LOCAL PREMIUM CAR SALES | C55: 1953 | D55: 45495 | E55: Facturada | F55: 15-04-2025 9:58:01 | G55: Factura Exenta Electrónica (69035) | H55: JORDI AGUSTIN FOITZICK MUÑOZ | I55: 18-10-2024 15:58:27 | J55: 25-04-2025 0:00:00 | K55: JF1BS9LC2KG178372 | L55: SUBARU | M55: OUTBACK | N55: ALL NEW OUTBACK 4X4 2.5I AUT | O55: 24--ASASA | P55: 2020 | Q55: 36000 | R55: TSUSTWU000378 | S55: LYPC50 | T55: USADO | U55: GRIS OSCURO | V55: POR DEFINIR | W55: 22190000 | X55: Facturado | Y55: 189 | Z55: DISPONIBLE | AA55: PREMIUM CAR SALES | AB55: AE,CC,EE,NB,AAC,ABS,LL,VC,ESP,AISO,AAUTO,CRE,MAV,A | AC55: YJ17214 | AD55: JF1BS9LC2KG178372 | AE55: FELIX ROBERTO MUÑOZ LILLO | AF55: 18-10-2024 0:00:00 | AG55: 1 | AH55: 14-04-2025 18:54:00 | AI55: 14-04-2025 18:54:00 | AK55: 0 | AL55: 0 | AN55: 3 | AO55: 19000000 | AP55: 484130 | AQ55: 0 | AR55: 19484130 | AS55: 22190000 | AT55: 2705870 | AU55: 1219
A56: IMPORTADORA TRENTO LTDA | B56: LOCAL PREMIUM CAR SALES | C56: 1953 | D56: 45495 | E56: Facturada | F56: 15-04-2025 9:58:01 | G56: Factura Exenta Electrónica (69035) | H56: JORDI AGUSTIN FOITZICK MUÑOZ | I56: 18-10-2024 15:58:27 | J56: 25-04-2025 0:00:00 | K56: JF1BS9LC2KG178372 | L56: SUBARU | M56: OUTBACK | N56: ALL NEW OUTBACK 4X4 2.5I AUT | O56: 24--ASASA | P56: 2020 | Q56: 36000 | R56: TSUSTWU000378 | S56: LYPC50 | T56: USADO | U56: GRIS OSCURO | V56: POR DEFINIR | W56: 22190000 | X56: Facturado | Y56: 189 | Z56: DISPONIBLE | AA56: PREMIUM CAR SALES | AB56: AE,CC,EE,NB,AAC,ABS,LL,VC,ESP,AISO,AAUTO,CRE,MAV,A | AC56: YJ17214 | AD56: JF1BS9LC2KG178372 | AE56: FELIX ROBERTO MUÑOZ LILLO | AF56: 18-10-2024 0:00:00 | AG56: 1 | AH56: 14-04-2025 18:54:00 | AI56: 14-04-2025 18:54:00 | AK56: 0 | AL56: 0 | AN56: 3 | AO56: 19000000 | AP56: 484130 | AQ56: 0 | AR56: 19484130 | AS56: 22190000 | AT56: 2705870 | AU56: 1219
A57: IMPORTADORA TRENTO LTDA | B57: LOCAL USADOS | C57: 2200 | D57: 42371 | E57: Facturada | F57: 24-08-2024 13:16:51 | G57: Factura Exenta Electrónica (63937) | H57: VANESSA CASANGA CASTILLO | I57: 02-08-2024 12:12:53 | J57: 31-08-2024 0:00:00 | K57: JF1GT7LL5KG070881 | L57: SUBARU | M57: XV | N57: NEW XV AWD 2.0I AUT | O57: XV 5665 | P57: 2020 | Q57: 84000 | R57: TSUSTWN000001 | S57: LVLR40 | T57: USADO | U57: GRIS OSCURO METALICO | V57: POR DEFINIR | W57: 15890000 | X57: Facturado | Y57: 29 | Z57: DISPONIBLE | AA57: BODEGA VEHICULOS | AB57: AE,CC,EE,AAC,ABS,LL,VC,ESP,AISO,AAUTO,CRE,MAV,ACD, | AC57: CE04257 | AD57: JF1GT7LL5KG070881 | AE57: CARLOS LADISLAO ISAIAS QUIROZ ESCOBAR | AF57: 02-08-2024 0:00:00 | AG57: 1 | AH57: 02-08-2024 0:00:00 | AI57: 02-08-2024 12:07:26 | AJ57: 28-02-2025 0:00:00 | AK57: 0 | AL57: 0 | AN57: 7 | AO57: 13500000 | AP57: 378530 | AQ57: 0 | AR57: 13878530 | AS57: 15890000 | AT57: 2011470 | AU57: 1266
A58: IMPORTADORA TRENTO LTDA | B58: LOCAL USADOS | C58: 2200 | D58: 42371 | E58: Facturada | F58: 24-08-2024 13:16:51 | G58: Factura Exenta Electrónica (63937) | H58: VANESSA CASANGA CASTILLO | I58: 02-08-2024 12:12:53 | J58: 31-08-2024 0:00:00 | K58: JF1GT7LL5KG070881 | L58: SUBARU | M58: XV | N58: NEW XV AWD 2.0I AUT | O58: XV 5665 | P58: 2020 | Q58: 84000 | R58: TSUSTWN000001 | S58: LVLR40 | T58: USADO | U58: GRIS OSCURO METALICO | V58: POR DEFINIR | W58: 15890000 | X58: Facturado | Y58: 29 | Z58: DISPONIBLE | AA58: BODEGA VEHICULOS | AB58: AE,CC,EE,AAC,ABS,LL,VC,ESP,AISO,AAUTO,CRE,MAV,ACD, | AC58: CE04257 | AD58: JF1GT7LL5KG070881 | AE58: CARLOS LADISLAO ISAIAS QUIROZ ESCOBAR | AF58: 02-08-2024 0:00:00 | AG58: 1 | AH58: 02-08-2024 0:00:00 | AI58: 02-08-2024 12:07:26 | AJ58: 28-02-2025 0:00:00 | AK58: 0 | AL58: 0 | AN58: 7 | AO58: 13500000 | AP58: 378530 | AQ58: 0 | AR58: 13878530 | AS58: 15890000 | AT58: 2011470 | AU58: 1266
A59: IMPORTADORA TRENTO LTDA | B59: LOCAL USADOS | C59: 2440 | D59: 47558 | E59: Facturada | F59: 10-09-2025 16:34:24 | G59: Factura Exenta Electrónica (69972) | H59: VANESSA CASANGA CASTILLO | I59: 17-06-2025 12:41:54 | J59: 11-09-2025 0:00:00 | K59: *----.**/../*.... | L59: HYUNDAI | M59: HYUNDAI | N59: CRETA SU2I 1.5 | O59: HYCRE01 | P59: 2023 | Q59: 35000 | R59: THYSTWU000537 | S59: SWWP61 | T59: USADO | U59: GRIS GRAFITO | V59: POR DEFINIR | W59: 13990000 | X59: Facturado | Y59: 86 | Z59: DISPONIBLE | AA59: BODEGA VEHICULOS | AB59: AE,CC,EE,ABS,LL,AC,AISO,AAUTO,CRE,MAV,ACD,SR,UD,DL | AC59: G4FLNV455376 | AD59: MALPB812A PM455542 | AE59: MARIO ALFONSO MUÑOZ VALLEJOS | AF59: 17-06-2025 0:00:00 | AG59: 1 | AH59: 11-07-2025 14:28:00 | AI59: 11-07-2025 14:28:00 | AJ59: 30-04-2026 0:00:00 | AK59: 1 | AL59: 0 | AN59: 0 | AO59: 12000000 | AP59: 306030 | AQ59: 3506 | AR59: 12309536 | AS59: 13990000 | AT59: 1680464 | AU59: 1201
A60: IMPORTADORA TRENTO LTDA | B60: LOCAL USADOS | C60: 2440 | D60: 47558 | E60: Facturada | F60: 10-09-2025 16:34:24 | G60: Factura Exenta Electrónica (69972) | H60: VANESSA CASANGA CASTILLO | I60: 17-06-2025 12:41:54 | J60: 11-09-2025 0:00:00 | K60: *----.**/../*.... | L60: HYUNDAI | M60: HYUNDAI | N60: CRETA SU2I 1.5 | O60: HYCRE01 | P60: 2023 | Q60: 35000 | R60: THYSTWU000537 | S60: SWWP61 | T60: USADO | U60: GRIS GRAFITO | V60: POR DEFINIR | W60: 13990000 | X60: Facturado | Y60: 86 | Z60: DISPONIBLE | AA60: BODEGA VEHICULOS | AB60: AE,CC,EE,ABS,LL,AC,AISO,AAUTO,CRE,MAV,ACD,SR,UD,DL | AC60: G4FLNV455376 | AD60: MALPB812A PM455542 | AE60: MARIO ALFONSO MUÑOZ VALLEJOS | AF60: 17-06-2025 0:00:00 | AG60: 1 | AH60: 11-07-2025 14:28:00 | AI60: 11-07-2025 14:28:00 | AJ60: 30-04-2026 0:00:00 | AK60: 1 | AL60: 0 | AN60: 0 | AO60: 12000000 | AP60: 306030 | AQ60: 3506 | AR60: 12309536 | AS60: 13990000 | AT60: 1680464 | AU60: 1201
A61: IMPORTADORA TRENTO LTDA | B61: LOCAL USADOS | C61: 2446 | D61: 47824 | E61: Facturada | F61: 26-09-2025 13:50:54 | G61: Factura Exenta Electrónica (70003) | H61: FEDERICO ALBERT | I61: 22-09-2025 10:03:05 | J61: 30-09-2025 0:00:00 | K61: LJD0AA29A N0164890 | L61: KIA MOTORS | M61: SOLUTO | N61: SOLUTO 1.4 | O61: SOLUTO | P61: 2022 | Q61: 16000 | R61: TKIAUTU002189 | S61: RLSG74 | T61: USADO | U61: AZUL EGIPCIO | V61: POR DEFINIR | W61: 8390000 | X61: Facturado | Y61: 8 | Z61: DISPONIBLE | AA61: BODEGA VEHICULOS | AC61: G4LCM1042397 | AD61: LJD0AA29A N0164890 | AE61: SALOMON ALBERTO CASTRO GODOY | AF61: 22-09-2025 0:00:00 | AG61: 1 | AH61: 22-09-2025 0:00:00 | AI61: 22-09-2025 9:59:22 | AJ61: 31-07-2026 0:00:00 | AK61: 1 | AL61: 0 | AN61: 1 | AO61: 7000000 | AP61: 231030 | AQ61: 3506 | AR61: 7234536 | AS61: 8390000 | AT61: 1155464 | AU61: 1377
A62: IMPORTADORA TRENTO LTDA | B62: LOCAL USADOS | C62: 2446 | D62: 47824 | E62: Facturada | F62: 26-09-2025 13:50:54 | G62: Factura Exenta Electrónica (70003) | H62: FEDERICO ALBERT | I62: 22-09-2025 10:03:05 | J62: 30-09-2025 0:00:00 | K62: LJD0AA29A N0164890 | L62: KIA MOTORS | M62: SOLUTO | N62: SOLUTO 1.4 | O62: SOLUTO | P62: 2022 | Q62: 16000 | R62: TKIAUTU002189 | S62: RLSG74 | T62: USADO | U62: AZUL EGIPCIO | V62: POR DEFINIR | W62: 8390000 | X62: Facturado | Y62: 8 | Z62: DISPONIBLE | AA62: BODEGA VEHICULOS | AC62: G4LCM1042397 | AD62: LJD0AA29A N0164890 | AE62: SALOMON ALBERTO CASTRO GODOY | AF62: 22-09-2025 0:00:00 | AG62: 1 | AH62: 22-09-2025 0:00:00 | AI62: 22-09-2025 9:59:22 | AJ62: 31-07-2026 0:00:00 | AK62: 1 | AL62: 0 | AN62: 1 | AO62: 7000000 | AP62: 231030 | AQ62: 3506 | AR62: 7234536 | AS62: 8390000 | AT62: 1155464 | AU62: 1377
A63: IMPORTADORA TRENTO LTDA | B63: LOCAL USADOS | C63: 2269 | D63: 43844 | E63: Facturada | F63: 10-12-2024 18:22:20 | G63: Factura Exenta Electrónica (68795) | H63: FEDERICO ALBERT | I63: 09-12-2024 18:44:59 | J63: 20-12-2024 0:00:00 | K63: VR3USHNSKLJ653041 | L63: PEUGEOT | M63: 2008 | N63: 2008 ACTIVE 1.2 | O63: KI8 | P63: 2020 | Q63: 75000 | R63: TPESTWU000382 | S63: PFRX97 | T63: USADO | U63: BLANCO NACARADO | V63: POR DEFINIR | W63: 11690000 | X63: Facturado | Y63: 11 | Z63: DISPONIBLE | AA63: BODEGA VEHICULOS | AB63: AE,CC,EE,AAC,ABS,LL,AISO,AAUTO,CRE,MAV,ACD,SR,DLL, | AC63: 10XVAP0033611 | AD63: VR3USHNSKLJ653041 | AE63: CARLOS ALEJANDRO RETAMAL CASTILLO | AF63: 09-12-2024 0:00:00 | AG63: 1 | AH63: 09-12-2024 0:00:00 | AI63: 09-12-2024 18:38:57 | AJ63: 31-10-2025 0:00:00 | AK63: 4 | AL63: 0 | AN63: 0 | AO63: 9300000 | AP63: 265530 | AQ63: 1194 | AR63: 9566724 | AS63: 11690000 | AT63: 2123276 | AU63: 1816
A64: IMPORTADORA TRENTO LTDA | B64: LOCAL USADOS | C64: 2269 | D64: 43844 | E64: Facturada | F64: 10-12-2024 18:22:20 | G64: Factura Exenta Electrónica (68795) | H64: FEDERICO ALBERT | I64: 09-12-2024 18:44:59 | J64: 20-12-2024 0:00:00 | K64: VR3USHNSKLJ653041 | L64: PEUGEOT | M64: 2008 | N64: 2008 ACTIVE 1.2 | O64: KI8 | P64: 2020 | Q64: 75000 | R64: TPESTWU000382 | S64: PFRX97 | T64: USADO | U64: BLANCO NACARADO | V64: POR DEFINIR | W64: 11690000 | X64: Facturado | Y64: 11 | Z64: DISPONIBLE | AA64: BODEGA VEHICULOS | AB64: AE,CC,EE,AAC,ABS,LL,AISO,AAUTO,CRE,MAV,ACD,SR,DLL, | AC64: 10XVAP0033611 | AD64: VR3USHNSKLJ653041 | AE64: CARLOS ALEJANDRO RETAMAL CASTILLO | AF64: 09-12-2024 0:00:00 | AG64: 1 | AH64: 09-12-2024 0:00:00 | AI64: 09-12-2024 18:38:57 | AJ64: 31-10-2025 0:00:00 | AK64: 4 | AL64: 0 | AN64: 0 | AO64: 9300000 | AP64: 265530 | AQ64: 1194 | AR64: 9566724 | AS64: 11690000 | AT64: 2123276 | AU64: 1816
A65: IMPORTADORA TRENTO LTDA | B65: LOCAL CAMIONES | C65: 18 | D65: 37288 | E65: Facturada | F65: 24-05-2023 16:01:18 | G65: Factura Exenta Electrónica (63088) | H65: JUAN CARLOS GONZALEZ ARAYA | I65: 26-04-2023 18:09:56 | J65: 25-05-2023 0:00:00 | K65: 988611457HK079688 | L65: JEEP | M65: RENEGADE | N65: RENEGADE SPORT 1.8 | O65: RT8888 | P65: 2017 | Q65: 67000 | R65: TJESTWU000408 | S65: JDKX55 | T65: USADO | U65: BLANCO | V65: POR DEFINIR | W65: 10990000 | X65: Facturado | Y65: 29 | Z65: DISPONIBLE | AA65: BODEGA LOCAL CAMIONES | AC65: 2978476 | AD65: 988611457HK079688 | AE65: GLORIA EVELYN MARTELL MUÑOZ | AF65: 26-04-2023 0:00:00 | AG65: 1 | AH65: 26-04-2023 0:00:00 | AI65: 26-04-2023 18:09:28 | AK65: 0 | AL65: 0 | AN65: 0 | AO65: 9000000 | AP65: 295540 | AQ65: 0 | AR65: 9295540 | AS65: 10990000 | AT65: 1694460 | AU65: 1542
A66: IMPORTADORA TRENTO LTDA | B66: LOCAL CAMIONES | C66: 18 | D66: 37288 | E66: Facturada | F66: 24-05-2023 16:01:18 | G66: Factura Exenta Electrónica (63088) | H66: JUAN CARLOS GONZALEZ ARAYA | I66: 26-04-2023 18:09:56 | J66: 25-05-2023 0:00:00 | K66: 988611457HK079688 | L66: JEEP | M66: RENEGADE | N66: RENEGADE SPORT 1.8 | O66: RT8888 | P66: 2017 | Q66: 67000 | R66: TJESTWU000408 | S66: JDKX55 | T66: USADO | U66: BLANCO | V66: POR DEFINIR | W66: 10990000 | X66: Facturado | Y66: 29 | Z66: DISPONIBLE | AA66: BODEGA LOCAL CAMIONES | AC66: 2978476 | AD66: 988611457HK079688 | AE66: GLORIA EVELYN MARTELL MUÑOZ | AF66: 26-04-2023 0:00:00 | AG66: 1 | AH66: 26-04-2023 0:00:00 | AI66: 26-04-2023 18:09:28 | AK66: 0 | AL66: 0 | AN66: 0 | AO66: 9000000 | AP66: 295540 | AQ66: 0 | AR66: 9295540 | AS66: 10990000 | AT66: 1694460 | AU66: 1542
A67: IMPORTADORA TRENTO LTDA | B67: LOCAL USADOS COPIAPO | C67: 1046 | D67: 41036 | E67: Facturada | F67: 30-04-2024 12:13:22 | G67: Factura Exenta Electrónica (63703) | H67: LUCILA ANTONIA ARREDONDO CASTRO | I67: 07-02-2024 15:09:55 | J67: 30-04-2024 0:00:00 | K67: 8AFAR23W7KJ143636 | L67: FORD | M67: RANGER | N67: RANGER LTD 4X4 3.2 | O67: RLT0 | P67: 2019 | Q67: 92200 | R67: TFOCMTU001087 | S67: LFXL70 | T67: USADO | U67: BLANCO | V67: POR DEFINIR | W67: 13990000 | X67: Facturado | Y67: 83 | Z67: DISPONIBLE | AA67: BODEGA LOS CARRERA COPIAPO | AB67: AE,CC,EE,2AB,NB,ABS,LL,VC,AC,AISO,MAV,UD,DLL,6AB | AC67: SA2S KJ143636 | AD67: 8AFAR23W7KJ143636 | AE67: JUAN ADRIAN BENAVIDES VARGAS | AF67: 07-02-2024 0:00:00 | AG67: 1 | AH67: 07-02-2024 0:00:00 | AI67: 07-02-2024 15:09:25 | AK67: 0 | AL67: 0 | AN67: 4 | AO67: 12200000 | AP67: 343540 | AQ67: 1178 | AR67: 12544718 | AS67: 13990000 | AT67: 1445282 | AU67: 1033
A68: IMPORTADORA TRENTO LTDA | B68: LOCAL USADOS COPIAPO | C68: 1046 | D68: 41036 | E68: Facturada | F68: 30-04-2024 12:13:22 | G68: Factura Exenta Electrónica (63703) | H68: LUCILA ANTONIA ARREDONDO CASTRO | I68: 07-02-2024 15:09:55 | J68: 30-04-2024 0:00:00 | K68: 8AFAR23W7KJ143636 | L68: FORD | M68: RANGER | N68: RANGER LTD 4X4 3.2 | O68: RLT0 | P68: 2019 | Q68: 92200 | R68: TFOCMTU001087 | S68: LFXL70 | T68: USADO | U68: BLANCO | V68: POR DEFINIR | W68: 13990000 | X68: Facturado | Y68: 83 | Z68: DISPONIBLE | AA68: BODEGA LOS CARRERA COPIAPO | AB68: AE,CC,EE,2AB,NB,ABS,LL,VC,AC,AISO,MAV,UD,DLL,6AB | AC68: SA2S KJ143636 | AD68: 8AFAR23W7KJ143636 | AE68: JUAN ADRIAN BENAVIDES VARGAS | AF68: 07-02-2024 0:00:00 | AG68: 1 | AH68: 07-02-2024 0:00:00 | AI68: 07-02-2024 15:09:25 | AK68: 0 | AL68: 0 | AN68: 4 | AO68: 12200000 | AP68: 343540 | AQ68: 1178 | AR68: 12544718 | AS68: 13990000 | AT68: 1445282 | AU68: 1033
A69: IMPORTADORA TRENTO LTDA | B69: LOCAL USADOS COPIAPO | C69: 1232 | D69: 48387 | E69: Facturada | F69: 10-11-2025 12:50:14 | G69: Factura Exenta Electrónica (70114) | H69: JOSE MAURICIO IBAÑEZ LOYOLA | I69: 30-10-2025 15:50:45 | J69: 29-11-2025 0:00:00 | K69: JTMZ43FV1LD510208 | L69: TOYOTA | M69: RAV | N69: RAV4 OTTO 2.0 AUT | O69: TORAV4OT | P69: 2020 | Q69: 83600 | R69: TTOSTWU000254 | S69: PDWX41 | T69: USADO | U69: PLATEADO SILVER METALICO | V69: POR DEFINIR | W69: 16690000 | X69: Facturado | Y69: 30 | Z69: DISPONIBLE | AA69: BODEGA LOS CARRERA COPIAPO | AB69: AE,CC,EE,ABS,LL,VC,4AB,AC,AISO,AAUTO,MAV,ACD,SR,UD | AC69: M20AV123816 | AD69: JTMZ43FV1LD510208 | AE69: PABLO ATILIO SOTO VILLEGAS | AF69: 30-10-2025 0:00:00 | AG69: 1 | AH69: 30-10-2025 0:00:00 | AI69: 30-10-2025 15:50:12 | AJ69: 30-04-2026 0:00:00 | AK69: 1 | AL69: 0 | AN69: 2 | AO69: 13800000 | AP69: 333030 | AQ69: 0 | AR69: 14133030 | AS69: 16690000 | AT69: 2556970 | AU69: 1532
A70: IMPORTADORA TRENTO LTDA | B70: LOCAL USADOS COPIAPO | C70: 1232 | D70: 48387 | E70: Facturada | F70: 10-11-2025 12:50:14 | G70: Factura Exenta Electrónica (70114) | H70: JOSE MAURICIO IBAÑEZ LOYOLA | I70: 30-10-2025 15:50:45 | J70: 29-11-2025 0:00:00 | K70: JTMZ43FV1LD510208 | L70: TOYOTA | M70: RAV | N70: RAV4 OTTO 2.0 AUT | O70: TORAV4OT | P70: 2020 | Q70: 83600 | R70: TTOSTWU000254 | S70: PDWX41 | T70: USADO | U70: PLATEADO SILVER METALICO | V70: POR DEFINIR | W70: 16690000 | X70: Facturado | Y70: 30 | Z70: DISPONIBLE | AA70: BODEGA LOS CARRERA COPIAPO | AB70: AE,CC,EE,ABS,LL,VC,4AB,AC,AISO,AAUTO,MAV,ACD,SR,UD | AC70: M20AV123816 | AD70: JTMZ43FV1LD510208 | AE70: PABLO ATILIO SOTO VILLEGAS | AF70: 30-10-2025 0:00:00 | AG70: 1 | AH70: 30-10-2025 0:00:00 | AI70: 30-10-2025 15:50:12 | AJ70: 30-04-2026 0:00:00 | AK70: 1 | AL70: 0 | AN70: 2 | AO70: 13800000 | AP70: 333030 | AQ70: 0 | AR70: 14133030 | AS70: 16690000 | AT70: 2556970 | AU70: 1532
A71: IMPORTADORA TRENTO LTDA | B71: LOCAL PREMIUM CAR SALES | C71: 1767 | D71: 41966 | E71: Facturada | F71: 24-07-2024 18:16:40 | G71: Factura Exenta Electrónica (63880) | H71: DANIEL ALEJANDRO AGUILERA CORTES | I71: 22-03-2024 19:15:42 | J71: 31-07-2024 0:00:00 | K71: *----.+..../*.... | L71: FORD | M71: EXPLORER | N71: EXPLORER 2.3 | O71: UN7000 | P71: 2023 | Q71: 30000 | R71: TFOSTWU001288 | S71: SLRC28 | T71: USADO | U71: GRIS CARBONIZADO | W71: 42490000 | X71: Facturado | Y71: 131 | Z71: DISPONIBLE | AA71: PREMIUM CAR SALES | AB71: AE,CC,EE,NB,AAC,ABS,LL,VC,ESP,CT,SS,AISO,ACP,AAUTO | AC71: NGC27127 | AD71: 1FMSK8FH5NGC27127 | AE71: ALBERTO FRANCISCO OLIVIER ESCUDERO GABILANES | AF71: 22-03-2024 0:00:00 | AG71: 1 | AH71: 22-03-2024 0:00:00 | AI71: 22-03-2024 19:07:12 | AK71: 0 | AL71: 0 | AN71: 2 | AO71: 36500000 | AP71: 322530 | AQ71: 8346 | AR71: 36830876 | AS71: 42490000 | AT71: 5659124 | AU71: 1332
A72: IMPORTADORA TRENTO LTDA | B72: LOCAL PREMIUM CAR SALES | C72: 1767 | D72: 41966 | E72: Facturada | F72: 24-07-2024 18:16:40 | G72: Factura Exenta Electrónica (63880) | H72: DANIEL ALEJANDRO AGUILERA CORTES | I72: 22-03-2024 19:15:42 | J72: 31-07-2024 0:00:00 | K72: *----.+..../*.... | L72: FORD | M72: EXPLORER | N72: EXPLORER 2.3 | O72: UN7000 | P72: 2023 | Q72: 30000 | R72: TFOSTWU001288 | S72: SLRC28 | T72: USADO | U72: GRIS CARBONIZADO | W72: 42490000 | X72: Facturado | Y72: 131 | Z72: DISPONIBLE | AA72: PREMIUM CAR SALES | AB72: AE,CC,EE,NB,AAC,ABS,LL,VC,ESP,CT,SS,AISO,ACP,AAUTO | AC72: NGC27127 | AD72: 1FMSK8FH5NGC27127 | AE72: ALBERTO FRANCISCO OLIVIER ESCUDERO GABILANES | AF72: 22-03-2024 0:00:00 | AG72: 1 | AH72: 22-03-2024 0:00:00 | AI72: 22-03-2024 19:07:12 | AK72: 0 | AL72: 0 | AN72: 2 | AO72: 36500000 | AP72: 322530 | AQ72: 8346 | AR72: 36830876 | AS72: 42490000 | AT72: 5659124 | AU72: 1332
A73: IMPORTADORA TRENTO LTDA | B73: LOCAL PREMIUM CAR SALES | C73: 2173 | D73: 50588 | E73: Facturada | F73: 20-04-2026 15:46:48 | G73: Factura Exenta Electrónica (70391) | H73: JORDI AGUSTIN FOITZICK MUÑOZ | I73: 16-09-2025 13:19:10 | J73: 27-04-2026 0:00:00 | K73: 1FTFW1E88 PFC68301 | L73: FORD | M73: F-150 | N73: F150 PLATINIUM 4X4 3.5 AT | O73: F150 | P73: 2024 | Q73: 21000 | R73: TFOCMTU001135 | S73: TJDB78 | T73: USADO | U73: GRIS CARBONIZADO | V73: POR DEFINIR | W73: 47990000 | X73: Facturado | Y73: 223 | Z73: DISPONIBLE | AA73: PREMIUM CAR SALES | AC73: PFC68301 | AD73: 1FTFW1E88 PFC68301 | AE73: ALBERTO FRANCISCO OLIVIER ESCUDERO GABILANES | AF73: 16-09-2025 0:00:00 | AG73: 1 | AH73: 16-09-2025 0:00:00 | AI73: 16-09-2025 13:17:59 | AK73: 1 | AL73: 0 | AN73: 3 | AO73: 45000000 | AP73: 1554760 | AQ73: 0 | AR73: 46554760 | AS73: 47990000 | AT73: 1435240 | AU73: 299
A74: IMPORTADORA TRENTO LTDA | B74: LOCAL PREMIUM CAR SALES | C74: 2173 | D74: 50588 | E74: Facturada | F74: 20-04-2026 15:46:48 | G74: Factura Exenta Electrónica (70391) | H74: JORDI AGUSTIN FOITZICK MUÑOZ | I74: 16-09-2025 13:19:10 | J74: 27-04-2026 0:00:00 | K74: 1FTFW1E88 PFC68301 | L74: FORD | M74: F-150 | N74: F150 PLATINIUM 4X4 3.5 AT | O74: F150 | P74: 2024 | Q74: 21000 | R74: TFOCMTU001135 | S74: TJDB78 | T74: USADO | U74: GRIS CARBONIZADO | V74: POR DEFINIR | W74: 47990000 | X74: Facturado | Y74: 223 | Z74: DISPONIBLE | AA74: PREMIUM CAR SALES | AC74: PFC68301 | AD74: 1FTFW1E88 PFC68301 | AE74: ALBERTO FRANCISCO OLIVIER ESCUDERO GABILANES | AF74: 16-09-2025 0:00:00 | AG74: 1 | AH74: 16-09-2025 0:00:00 | AI74: 16-09-2025 13:17:59 | AK74: 1 | AL74: 0 | AN74: 3 | AO74: 45000000 | AP74: 1554760 | AQ74: 0 | AR74: 46554760 | AS74: 47990000 | AT74: 1435240 | AU74: 299
A75: IMPORTADORA TRENTO LTDA | B75: LOCAL USADOS COPIAPO | C75: 976 | D75: 37683 | E75: Facturada | F75: 04-07-2023 9:59:44 | G75: Factura Exenta Electrónica (63149) | H75: LUCILA ANTONIA ARREDONDO CASTRO | I75: 29-06-2023 15:07:22 | J75: 04-07-2023 0:00:00 | K75: JM7GL4S36J1118303 | L75: MAZDA | M75: MAZDA | N75: NEW 6 2.5 AUT | O75: MA2D | P75: 2017 | Q75: 99500 | R75: TMAAUTU000229 | S75: JPLT99 | T75: USADO | U75: BLANCO | V75: POR DEFINIR | W75: 9990000 | X75: Facturado | Y75: 5 | Z75: DISPONIBLE | AA75: BODEGA LOS CARRERA COPIAPO | AC75: PY20933755 | AD75: JM7GL4S36J1118303 | AE75: OMAR LUIS ANDRES LUZ HIDALGO | AF75: 29-06-2023 0:00:00 | AG75: 1 | AH75: 30-06-2023 17:52:00 | AI75: 30-06-2023 17:52:00 | AK75: 0 | AL75: 0 | AN75: 0 | AO75: 8300000 | AP75: 413025 | AQ75: 0 | AR75: 8713025 | AS75: 9990000 | AT75: 1276975 | AU75: 1278
A76: IMPORTADORA TRENTO LTDA | B76: LOCAL USADOS COPIAPO | C76: 976 | D76: 37683 | E76: Facturada | F76: 04-07-2023 9:59:44 | G76: Factura Exenta Electrónica (63149) | H76: LUCILA ANTONIA ARREDONDO CASTRO | I76: 29-06-2023 15:07:22 | J76: 04-07-2023 0:00:00 | K76: JM7GL4S36J1118303 | L76: MAZDA | M76: MAZDA | N76: NEW 6 2.5 AUT | O76: MA2D | P76: 2017 | Q76: 99500 | R76: TMAAUTU000229 | S76: JPLT99 | T76: USADO | U76: BLANCO | V76: POR DEFINIR | W76: 9990000 | X76: Facturado | Y76: 5 | Z76: DISPONIBLE | AA76: BODEGA LOS CARRERA COPIAPO | AC76: PY20933755 | AD76: JM7GL4S36J1118303 | AE76: OMAR LUIS ANDRES LUZ HIDALGO | AF76: 29-06-2023 0:00:00 | AG76: 1 | AH76: 30-06-2023 17:52:00 | AI76: 30-06-2023 17:52:00 | AK76: 0 | AL76: 0 | AN76: 0 | AO76: 8300000 | AP76: 413025 | AQ76: 0 | AR76: 8713025 | AS76: 9990000 | AT76: 1276975 | AU76: 1278
A77: IMPORTADORA TRENTO LTDA | B77: LOCAL USADOS COPIAPO | C77: 956 | D77: 36890 | E77: Facturada | F77: 12-04-2023 12:56:32 | G77: Factura Exenta Electrónica (63030) | H77: LUCILA ANTONIA ARREDONDO CASTRO | I77: 10-03-2023 11:57:20 | J77: 12-04-2023 0:00:00 | K77: KNABX512AET704379 | L77: KIA MOTORS | M77: MORNING | N77: MORNING EX 1.2 | O77: 17--1510E4 | P77: 2014 | Q77: 13000 | R77: TKIAUTU002094 | S77: GGJW34 | T77: USADO | U77: ROJO SIGNAL | V77: POR DEFINIR | W77: 5290000 | X77: Facturado | Y77: 33 | Z77: DISPONIBLE | AA77: BODEGA LOS CARRERA COPIAPO | AC77: G4LADP126312 | AD77: KNABX512AET704379 | AE77: ENEDIS DEL CARMEN YENIZA CARRASCO PAEZ | AF77: 10-03-2023 0:00:00 | AG77: 1 | AH77: 18-04-2023 19:11:00 | AI77: 18-04-2023 19:11:00 | AK77: 0 | AL77: 0 | AN77: 0 | AO77: 4200000 | AP77: 30000 | AQ77: 0 | AR77: 4230000 | AS77: 5290000 | AT77: 1060000 | AU77: 2004
A78: IMPORTADORA TRENTO LTDA | B78: LOCAL USADOS COPIAPO | C78: 956 | D78: 36890 | E78: Facturada | F78: 12-04-2023 12:56:32 | G78: Factura Exenta Electrónica (63030) | H78: LUCILA ANTONIA ARREDONDO CASTRO | I78: 10-03-2023 11:57:20 | J78: 12-04-2023 0:00:00 | K78: KNABX512AET704379 | L78: KIA MOTORS | M78: MORNING | N78: MORNING EX 1.2 | O78: 17--1510E4 | P78: 2014 | Q78: 13000 | R78: TKIAUTU002094 | S78: GGJW34 | T78: USADO | U78: ROJO SIGNAL | V78: POR DEFINIR | W78: 5290000 | X78: Facturado | Y78: 33 | Z78: DISPONIBLE | AA78: BODEGA LOS CARRERA COPIAPO | AC78: G4LADP126312 | AD78: KNABX512AET704379 | AE78: ENEDIS DEL CARMEN YENIZA CARRASCO PAEZ | AF78: 10-03-2023 0:00:00 | AG78: 1 | AH78: 18-04-2023 19:11:00 | AI78: 18-04-2023 19:11:00 | AK78: 0 | AL78: 0 | AN78: 0 | AO78: 4200000 | AP78: 30000 | AQ78: 0 | AR78: 4230000 | AS78: 5290000 | AT78: 1060000 | AU78: 2004
A79: IMPORTADORA TRENTO LTDA | B79: MEGACENTRO OVALLE | C79: 337 | D79: 38596 | E79: Facturada | F79: 29-09-2023 18:06:36 | G79: Factura Exenta Electrónica (63323) | H79: Armando Canihuante . | I79: 28-09-2023 9:05:28 | J79: 30-09-2023 0:00:00 | K79: VR3ECBHYBLJ517276 | L79: PEUGEOT | M79: RIFTER | N79: RIFTER BLUE HDI 100 1.6 | O79: RBH1 | P79: 2020 | Q79: 28316 | R79: TPESTWU000332 | S79: LYLW59 | T79: USADO | U79: GRIS ARTENSE | V79: POR DEFINIR | W79: 13990000 | X79: Facturado | Y79: 2 | Z79: DISPONIBLE | AA79: BODEGA OVALLEveih | AC79: 10JCAV0114165 | AD79: VR3ECBHYBLJ517276 | AE79: DANTE CARRERA LAGOS | AF79: 28-09-2023 0:00:00 | AG79: 1 | AH79: 30-09-2023 0:00:00 | AI79: 30-09-2023 12:45:06 | AK79: 0 | AL79: 0 | AN79: 0 | AO79: 11500000 | AP79: 333040 | AQ79: 26321 | AR79: 11859361 | AS79: 13990000 | AT79: 2130639 | AU79: 1523
A80: IMPORTADORA TRENTO LTDA | B80: MEGACENTRO OVALLE | C80: 337 | D80: 38596 | E80: Facturada | F80: 29-09-2023 18:06:36 | G80: Factura Exenta Electrónica (63323) | H80: Armando Canihuante . | I80: 28-09-2023 9:05:28 | J80: 30-09-2023 0:00:00 | K80: VR3ECBHYBLJ517276 | L80: PEUGEOT | M80: RIFTER | N80: RIFTER BLUE HDI 100 1.6 | O80: RBH1 | P80: 2020 | Q80: 28316 | R80: TPESTWU000332 | S80: LYLW59 | T80: USADO | U80: GRIS ARTENSE | V80: POR DEFINIR | W80: 13990000 | X80: Facturado | Y80: 2 | Z80: DISPONIBLE | AA80: BODEGA OVALLEveih | AC80: 10JCAV0114165 | AD80: VR3ECBHYBLJ517276 | AE80: DANTE CARRERA LAGOS | AF80: 28-09-2023 0:00:00 | AG80: 1 | AH80: 30-09-2023 0:00:00 | AI80: 30-09-2023 12:45:06 | AK80: 0 | AL80: 0 | AN80: 0 | AO80: 11500000 | AP80: 333040 | AQ80: 26321 | AR80: 11859361 | AS80: 13990000 | AT80: 2130639 | AU80: 1523
A81: IMPORTADORA TRENTO LTDA | B81: LOCAL USADOS | C81: 2146 | D81: 41449 | E81: Facturada | F81: 04-06-2024 17:54:09 | G81: Factura Exenta Electrónica (63767) | H81: VANESSA CASANGA CASTILLO | I81: 30-05-2024 11:29:46 | J81: 07-06-2024 0:00:00 | K81: KL1JJ7C52LB066826 | L81: CHEVROLET | M81: TRACKER | N81: TRACKER II FWD 1,8 | O81: CHTR01 | P81: 2020 | Q81: 37000 | R81: TCHSTWU000278 | S81: LZHZ29 | T81: USADO | U81: GRIS METALICO | V81: POR DEFINIR | W81: 9590000 | X81: Facturado | Y81: 8 | Z81: DISPONIBLE | AA81: BODEGA VEHICULOS | AB81: AE,CC,EE,NB,AAC,ABS,LL,VC,ESP,AISO,AAUTO,CRE,MAV,A | AC81: F18D4193160272 | AD81: KL1JJ7C52LB066826 | AE81: IRIS ANTONIETA AGUILAR DE LA VEGA | AF81: 30-05-2024 0:00:00 | AG81: 1 | AH81: 30-05-2024 0:00:00 | AI81: 30-05-2024 11:23:04 | AJ81: 31-01-2025 0:00:00 | AK81: 0 | AL81: 0 | AN81: 1 | AO81: 8000000 | AP81: 295030 | AQ81: 2593 | AR81: 8297623 | AS81: 9590000 | AT81: 1292377 | AU81: 1348
A82: IMPORTADORA TRENTO LTDA | B82: LOCAL USADOS | C82: 2146 | D82: 41449 | E82: Facturada | F82: 04-06-2024 17:54:09 | G82: Factura Exenta Electrónica (63767) | H82: VANESSA CASANGA CASTILLO | I82: 30-05-2024 11:29:46 | J82: 07-06-2024 0:00:00 | K82: KL1JJ7C52LB066826 | L82: CHEVROLET | M82: TRACKER | N82: TRACKER II FWD 1,8 | O82: CHTR01 | P82: 2020 | Q82: 37000 | R82: TCHSTWU000278 | S82: LZHZ29 | T82: USADO | U82: GRIS METALICO | V82: POR DEFINIR | W82: 9590000 | X82: Facturado | Y82: 8 | Z82: DISPONIBLE | AA82: BODEGA VEHICULOS | AB82: AE,CC,EE,NB,AAC,ABS,LL,VC,ESP,AISO,AAUTO,CRE,MAV,A | AC82: F18D4193160272 | AD82: KL1JJ7C52LB066826 | AE82: IRIS ANTONIETA AGUILAR DE LA VEGA | AF82: 30-05-2024 0:00:00 | AG82: 1 | AH82: 30-05-2024 0:00:00 | AI82: 30-05-2024 11:23:04 | AJ82: 31-01-2025 0:00:00 | AK82: 0 | AL82: 0 | AN82: 1 | AO82: 8000000 | AP82: 295030 | AQ82: 2593 | AR82: 8297623 | AS82: 9590000 | AT82: 1292377 | AU82: 1348
A83: IMPORTADORA TRENTO LTDA | B83: MEGACENTRO OVALLE | C83: 370 | D83: 41181 | E83: Facturada | F83: 16-05-2024 16:24:55 | G83: Factura Exenta Electrónica (63727) | H83: JOSE GREGORIO TORRES | I83: 19-04-2024 13:10:19 | J83: 20-05-2024 0:00:00 | K83: KMHJB81BGNU101948 | L83: HYUNDAI | M83: HYUNDAI | N83: TUCSON NX4 1.6 AUT | O83: HTC01 | P83: 2022 | Q83: 22000 | R83: THYSTWU000511 | S83: RRZF71 | T83: USADO | U83: BLANCO PERLA | V83: POR DEFINIR | W83: 18190000 | X83: Facturado | Y83: 31 | Z83: DISPONIBLE | AA83: BODEGA OVALLEveih | AB83: AE,CC,EE,NB,AAC,ABS,LL,VC,ESP,SS,AISO,AAUTO,CRE,MA | AC83: G4FPMU463621 | AD83: KMHJB81BGNU101948 | AE83: LUCIANO SHANDOR CAMACHO CAÑAS | AF83: 19-04-2024 0:00:00 | AG83: 1 | AH83: 19-04-2024 0:00:00 | AI83: 19-04-2024 12:54:28 | AJ83: 30-04-2026 0:00:00 | AK83: 0 | AL83: 0 | AN83: 7 | AO83: 15200000 | AP83: 563280 | AQ83: 36643 | AR83: 15799923 | AS83: 18190000 | AT83: 2390077 | AU83: 1314
A84: IMPORTADORA TRENTO LTDA | B84: MEGACENTRO OVALLE | C84: 370 | D84: 41181 | E84: Facturada | F84: 16-05-2024 16:24:55 | G84: Factura Exenta Electrónica (63727) | H84: JOSE GREGORIO TORRES | I84: 19-04-2024 13:10:19 | J84: 20-05-2024 0:00:00 | K84: KMHJB81BGNU101948 | L84: HYUNDAI | M84: HYUNDAI | N84: TUCSON NX4 1.6 AUT | O84: HTC01 | P84: 2022 | Q84: 22000 | R84: THYSTWU000511 | S84: RRZF71 | T84: USADO | U84: BLANCO PERLA | V84: POR DEFINIR | W84: 18190000 | X84: Facturado | Y84: 31 | Z84: DISPONIBLE | AA84: BODEGA OVALLEveih | AB84: AE,CC,EE,NB,AAC,ABS,LL,VC,ESP,SS,AISO,AAUTO,CRE,MA | AC84: G4FPMU463621 | AD84: KMHJB81BGNU101948 | AE84: LUCIANO SHANDOR CAMACHO CAÑAS | AF84: 19-04-2024 0:00:00 | AG84: 1 | AH84: 19-04-2024 0:00:00 | AI84: 19-04-2024 12:54:28 | AJ84: 30-04-2026 0:00:00 | AK84: 0 | AL84: 0 | AN84: 7 | AO84: 15200000 | AP84: 563280 | AQ84: 36643 | AR84: 15799923 | AS84: 18190000 | AT84: 2390077 | AU84: 1314
A85: IMPORTADORA TRENTO LTDA | B85: LOCAL PREMIUM CAR SALES | C85: 1761 | D85: 41836 | E85: Facturada | F85: 12-07-2024 10:43:05 | G85: Factura Exenta Electrónica (63837) | H85: JORDI AGUSTIN FOITZICK MUÑOZ | I85: 30-05-2024 10:36:36 | J85: 15-07-2024 0:00:00 | K85: VXKUSHNSS RW001557 | L85: OPEL | M85: MOKKA | N85: MOKKA 1.2T AUT | O85: OMK01 | P85: 2024 | Q85: 1702 | R85: TOPSTWU000006 | S85: TJLF41 | T85: USADO | U85: GRIS ARTENSE | V85: POR DEFINIR | W85: 19190000 | X85: Facturado | Y85: 46 | Z85: DISPONIBLE | AA85: PREMIUM CAR SALES | AB85: AE,CC,EE,AAC,ABS,LL,VC,4AB,AISO,AAUTO,CRE,MAV,ACD, | AC85: 10XVDW2143131 | AD85: VXKUSHNSS RW001557 | AE85: LUCIANO SHANDOR CAMACHO CAÑAS | AF85: 30-05-2024 0:00:00 | AG85: 1 | AH85: 30-05-2024 0:00:00 | AI85: 30-05-2024 10:33:30 | AK85: 0 | AL85: 0 | AN85: 1 | AO85: 16800000 | AP85: 427030 | AQ85: 0 | AR85: 17227030 | AS85: 19190000 | AT85: 1962970 | AU85: 1023
A86: IMPORTADORA TRENTO LTDA | B86: LOCAL PREMIUM CAR SALES | C86: 1761 | D86: 41836 | E86: Facturada | F86: 12-07-2024 10:43:05 | G86: Factura Exenta Electrónica (63837) | H86: JORDI AGUSTIN FOITZICK MUÑOZ | I86: 30-05-2024 10:36:36 | J86: 15-07-2024 0:00:00 | K86: VXKUSHNSS RW001557 | L86: OPEL | M86: MOKKA | N86: MOKKA 1.2T AUT | O86: OMK01 | P86: 2024 | Q86: 1702 | R86: TOPSTWU000006 | S86: TJLF41 | T86: USADO | U86: GRIS ARTENSE | V86: POR DEFINIR | W86: 19190000 | X86: Facturado | Y86: 46 | Z86: DISPONIBLE | AA86: PREMIUM CAR SALES | AB86: AE,CC,EE,AAC,ABS,LL,VC,4AB,AISO,AAUTO,CRE,MAV,ACD, | AC86: 10XVDW2143131 | AD86: VXKUSHNSS RW001557 | AE86: LUCIANO SHANDOR CAMACHO CAÑAS | AF86: 30-05-2024 0:00:00 | AG86: 1 | AH86: 30-05-2024 0:00:00 | AI86: 30-05-2024 10:33:30 | AK86: 0 | AL86: 0 | AN86: 1 | AO86: 16800000 | AP86: 427030 | AQ86: 0 | AR86: 17227030 | AS86: 19190000 | AT86: 1962970 | AU86: 1023
A87: IMPORTADORA TRENTO LTDA | B87: LOCAL USADOS | C87: 1972 | D87: 38280 | E87: Facturada | F87: 29-08-2023 17:50:26 | G87: Factura Exenta Electrónica (63242) | H87: VANESSA CASANGA CASTILLO | I87: 23-08-2023 15:36:25 | J87: 31-08-2023 0:00:00 | K87: ---/*-+*-./*----- | L87: MITSUBISHI | M87: OUTLANDER | N87: OUTLANDER 2.0 AUT | O87: 101FG | P87: 2019 | Q87: 37270 | R87: TMISTWU000332 | S87: KWVR43 | T87: USADO | U87: BLANCO | V87: POR DEFINIR | W87: 12490000 | X87: Facturado | Y87: 8 | Z87: DISPONIBLE | AA87: BODEGA VEHICULOS | AC87: 4J11 YP7028 | AD87: JMYXTGF7WJZ800385 | AE87: ELIZABETH DEL CARMEN MORENO OYARCE | AF87: 23-08-2023 0:00:00 | AG87: 1 | AH87: 23-08-2023 0:00:00 | AI87: 23-08-2023 15:35:54 | AK87: 0 | AL87: 0 | AN87: 3 | AO87: 10000000 | AP87: 320540 | AQ87: 11049 | AR87: 10331589 | AS87: 12490000 | AT87: 2158411 | AU87: 1728
A88: IMPORTADORA TRENTO LTDA | B88: LOCAL USADOS | C88: 1972 | D88: 38280 | E88: Facturada | F88: 29-08-2023 17:50:26 | G88: Factura Exenta Electrónica (63242) | H88: VANESSA CASANGA CASTILLO | I88: 23-08-2023 15:36:25 | J88: 31-08-2023 0:00:00 | K88: ---/*-+*-./*----- | L88: MITSUBISHI | M88: OUTLANDER | N88: OUTLANDER 2.0 AUT | O88: 101FG | P88: 2019 | Q88: 37270 | R88: TMISTWU000332 | S88: KWVR43 | T88: USADO | U88: BLANCO | V88: POR DEFINIR | W88: 12490000 | X88: Facturado | Y88: 8 | Z88: DISPONIBLE | AA88: BODEGA VEHICULOS | AC88: 4J11 YP7028 | AD88: JMYXTGF7WJZ800385 | AE88: ELIZABETH DEL CARMEN MORENO OYARCE | AF88: 23-08-2023 0:00:00 | AG88: 1 | AH88: 23-08-2023 0:00:00 | AI88: 23-08-2023 15:35:54 | AK88: 0 | AL88: 0 | AN88: 3 | AO88: 10000000 | AP88: 320540 | AQ88: 11049 | AR88: 10331589 | AS88: 12490000 | AT88: 2158411 | AU88: 1728
A89: IMPORTADORA TRENTO LTDA | B89: LOCAL PREMIUM COPIAPO | C89: 653 | D89: 42964 | E89: Facturada | F89: 07-10-2024 18:52:04 | G89: Factura Exenta Electrónica (64012) | H89: OMAR ANDRES ROJAS ACOSTA | I89: 09-09-2024 17:25:29 | J89: 08-10-2024 0:00:00 | K89: MBHZF63SX PG297599 | L89: SUZUKI | M89: DZIRE | N89: DZIRE SEDAN 1.2 | O89: SUDZIMT12 | P89: 2023 | Q89: 27034 | R89: TSZAUTU000436 | S89: SLLW76 | T89: USADO | U89: ROJO PERLADO | V89: POR DEFINIR | W89: 8490000 | X89: Facturado | Y89: 29 | Z89: DISPONIBLE | AA89: IMPORTADORA TRENTO LTDA | AB89: AE,CC,EE,2AB,NB,ABS,LL,AC,AISO,AAUTO,ACD,UD,DLL,PK | AC89: K12MP4336798 | AD89: MBHZF63SX PG297599 | AE89: HUMBERTO JESUS ABARCIA ARNES | AF89: 09-09-2024 0:00:00 | AG89: 1 | AH89: 04-10-2024 17:36:00 | AI89: 04-10-2024 17:36:00 | AK89: 0 | AL89: 0 | AN89: 13 | AO89: 7000000 | AP89: 391099 | AQ89: 0 | AR89: 7391099 | AS89: 8490000 | AT89: 1098901 | AU89: 1294
A90: IMPORTADORA TRENTO LTDA | B90: LOCAL PREMIUM COPIAPO | C90: 653 | D90: 42964 | E90: Facturada | F90: 07-10-2024 18:52:04 | G90: Factura Exenta Electrónica (64012) | H90: OMAR ANDRES ROJAS ACOSTA | I90: 09-09-2024 17:25:29 | J90: 08-10-2024 0:00:00 | K90: MBHZF63SX PG297599 | L90: SUZUKI | M90: DZIRE | N90: DZIRE SEDAN 1.2 | O90: SUDZIMT12 | P90: 2023 | Q90: 27034 | R90: TSZAUTU000436 | S90: SLLW76 | T90: USADO | U90: ROJO PERLADO | V90: POR DEFINIR | W90: 8490000 | X90: Facturado | Y90: 29 | Z90: DISPONIBLE | AA90: IMPORTADORA TRENTO LTDA | AB90: AE,CC,EE,2AB,NB,ABS,LL,AC,AISO,AAUTO,ACD,UD,DLL,PK | AC90: K12MP4336798 | AD90: MBHZF63SX PG297599 | AE90: HUMBERTO JESUS ABARCIA ARNES | AF90: 09-09-2024 0:00:00 | AG90: 1 | AH90: 04-10-2024 17:36:00 | AI90: 04-10-2024 17:36:00 | AK90: 0 | AL90: 0 | AN90: 13 | AO90: 7000000 | AP90: 391099 | AQ90: 0 | AR90: 7391099 | AS90: 8490000 | AT90: 1098901 | AU90: 1294
A91: IMPORTADORA TRENTO LTDA | B91: LOCAL USADOS COPIAPO | C91: 1213 | D91: 47934 | E91: Facturada | F91: 02-10-2025 18:02:43 | G91: Factura Exenta Electrónica (70031) | H91: SEBASTIAN NICOLAS CABRERA GONZALEZ | I91: 06-05-2025 19:29:56 | J91: 13-10-2025 0:00:00 | K91: KPTE0A1YSRP036201 | L91: SSANGYONG | M91: TORRES | N91: TORRES GLX 1.5 AUT | O91: SSTOGLX15AT | P91: 2024 | Q91: 10991 | R91: TSYSTWU000333 | S91: TKTY27 | T91: USADO | U91: AZUL METALICO | V91: POR DEFINIR | W91: 21190000 | X91: Facturado | Y91: 160 | Z91: DISPONIBLE | AA91: BODEGA LOS CARRERA COPIAPO | AB91: AE,CC,EE,NB,AAC,ABS,LL,TC,VC,AISO,AAUTO,CRE,MAV,AC | AC91: 17595002165458 | AD91: KPTE0A1YSRP036201 | AE91: LUIS EUGENIO RIVERA ANGEL | AF91: 06-05-2025 0:00:00 | AG91: 1 | AH91: 06-05-2025 0:00:00 | AI91: 06-05-2025 19:26:31 | AK91: 1 | AL91: 0 | AN91: 9 | AO91: 19000000 | AP91: 563743 | AQ91: 0 | AR91: 19563743 | AS91: 21190000 | AT91: 1626257 | AU91: 767
A92: IMPORTADORA TRENTO LTDA | B92: LOCAL USADOS COPIAPO | C92: 1213 | D92: 47934 | E92: Facturada | F92: 02-10-2025 18:02:43 | G92: Factura Exenta Electrónica (70031) | H92: SEBASTIAN NICOLAS CABRERA GONZALEZ | I92: 06-05-2025 19:29:56 | J92: 13-10-2025 0:00:00 | K92: KPTE0A1YSRP036201 | L92: SSANGYONG | M92: TORRES | N92: TORRES GLX 1.5 AUT | O92: SSTOGLX15AT | P92: 2024 | Q92: 10991 | R92: TSYSTWU000333 | S92: TKTY27 | T92: USADO | U92: AZUL METALICO | V92: POR DEFINIR | W92: 21190000 | X92: Facturado | Y92: 160 | Z92: DISPONIBLE | AA92: BODEGA LOS CARRERA COPIAPO | AB92: AE,CC,EE,NB,AAC,ABS,LL,TC,VC,AISO,AAUTO,CRE,MAV,AC | AC92: 17595002165458 | AD92: KPTE0A1YSRP036201 | AE92: LUIS EUGENIO RIVERA ANGEL | AF92: 06-05-2025 0:00:00 | AG92: 1 | AH92: 06-05-2025 0:00:00 | AI92: 06-05-2025 19:26:31 | AK92: 1 | AL92: 0 | AN92: 9 | AO92: 19000000 | AP92: 563743 | AQ92: 0 | AR92: 19563743 | AS92: 21190000 | AT92: 1626257 | AU92: 767
A93: IMPORTADORA TRENTO LTDA | B93: MEGACENTRO OVALLE | C93: 372 | D93: 41457 | E93: Facturada | F93: 05-06-2024 12:04:32 | G93: Factura Exenta Electrónica (63773) | H93: JOSE GREGORIO TORRES | I93: 28-05-2024 16:43:33 | J93: 11-06-2024 0:00:00 | K93: *----....../*.+*+ | L93: PEUGEOT | M93: 3008 | N93: 3008 BLUE HDI HP 1.5 AUT | O93: PCM10 | P93: 2019 | Q93: 64500 | R93: TPESTWU000360 | S93: LRWC74 | T93: USADO | U93: BLANCO NACARADO | V93: POR DEFINIR | W93: 14190000 | X93: Facturado | Y93: 14 | Z93: DISPONIBLE | AA93: BODEGA OVALLEveih | AB93: AE,CC,EE,ABS,LL,AC,AISO,AAUTO,CRE,MAV,ACD,SR,UD,DL | AC93: 10Q3AR0090426 | AD93: VF3MCYHZRLS003325 | AE93: LUIS EUGENIO RIVERA ANGEL | AF93: 28-05-2024 0:00:00 | AG93: 1 | AH93: 28-05-2024 0:00:00 | AI93: 28-05-2024 16:39:23 | AK93: 0 | AL93: 0 | AN93: 0 | AO93: 12000000 | AP93: 355030 | AQ93: 22992 | AR93: 12378022 | AS93: 14190000 | AT93: 1811978 | AU93: 1277
A94: IMPORTADORA TRENTO LTDA | B94: MEGACENTRO OVALLE | C94: 372 | D94: 41457 | E94: Facturada | F94: 05-06-2024 12:04:32 | G94: Factura Exenta Electrónica (63773) | H94: JOSE GREGORIO TORRES | I94: 28-05-2024 16:43:33 | J94: 11-06-2024 0:00:00 | K94: *----....../*.+*+ | L94: PEUGEOT | M94: 3008 | N94: 3008 BLUE HDI HP 1.5 AUT | O94: PCM10 | P94: 2019 | Q94: 64500 | R94: TPESTWU000360 | S94: LRWC74 | T94: USADO | U94: BLANCO NACARADO | V94: POR DEFINIR | W94: 14190000 | X94: Facturado | Y94: 14 | Z94: DISPONIBLE | AA94: BODEGA OVALLEveih | AB94: AE,CC,EE,ABS,LL,AC,AISO,AAUTO,CRE,MAV,ACD,SR,UD,DL | AC94: 10Q3AR0090426 | AD94: VF3MCYHZRLS003325 | AE94: LUIS EUGENIO RIVERA ANGEL | AF94: 28-05-2024 0:00:00 | AG94: 1 | AH94: 28-05-2024 0:00:00 | AI94: 28-05-2024 16:39:23 | AK94: 0 | AL94: 0 | AN94: 0 | AO94: 12000000 | AP94: 355030 | AQ94: 22992 | AR94: 12378022 | AS94: 14190000 | AT94: 1811978 | AU94: 1277
A95: IMPORTADORA TRENTO LTDA | B95: MEGACENTRO OVALLE | C95: 321 | D95: 36769 | E95: Facturada | F95: 28-03-2023 15:40:43 | G95: Factura Exenta Electrónica (63008) | H95: Armando Canihuante . | I95: 27-01-2023 9:47:38 | J95: 28-03-2023 0:00:00 | K95: 8AFAR23W7KJ103735 | L95: FORD | M95: RANGER | N95: RANGER LTD 4X4 3.2 AUT | O95: LTD3.2AUT | P95: 2019 | Q95: 90000 | R95: TFOCMTU001057 | S95: KWXZ72 | T95: USADO | U95: GRIS PLATA | V95: POR DEFINIR | W95: 21590000 | X95: Facturado | Y95: 60 | Z95: DISPONIBLE | AA95: BODEGA OVALLEveih | AC95: SA2SKJ103735 | AD95: 8AFAR23W7KJ103735 | AE95: BLANCA DEL CARMEN SAAVEDRA LOPEZ | AF95: 27-01-2023 0:00:00 | AG95: 1 | AH95: 27-01-2023 0:00:00 | AI95: 27-01-2023 9:47:24 | AK95: 0 | AL95: 0 | AN95: 0 | AO95: 18000000 | AP95: 861245 | AQ95: 25322 | AR95: 18886567 | AS95: 21590000 | AT95: 2703433 | AU95: 1252
A96: IMPORTADORA TRENTO LTDA | B96: MEGACENTRO OVALLE | C96: 321 | D96: 36769 | E96: Facturada | F96: 28-03-2023 15:40:43 | G96: Factura Exenta Electrónica (63008) | H96: Armando Canihuante . | I96: 27-01-2023 9:47:38 | J96: 28-03-2023 0:00:00 | K96: 8AFAR23W7KJ103735 | L96: FORD | M96: RANGER | N96: RANGER LTD 4X4 3.2 AUT | O96: LTD3.2AUT | P96: 2019 | Q96: 90000 | R96: TFOCMTU001057 | S96: KWXZ72 | T96: USADO | U96: GRIS PLATA | V96: POR DEFINIR | W96: 21590000 | X96: Facturado | Y96: 60 | Z96: DISPONIBLE | AA96: BODEGA OVALLEveih | AC96: SA2SKJ103735 | AD96: 8AFAR23W7KJ103735 | AE96: BLANCA DEL CARMEN SAAVEDRA LOPEZ | AF96: 27-01-2023 0:00:00 | AG96: 1 | AH96: 27-01-2023 0:00:00 | AI96: 27-01-2023 9:47:24 | AK96: 0 | AL96: 0 | AN96: 0 | AO96: 18000000 | AP96: 861245 | AQ96: 25322 | AR96: 18886567 | AS96: 21590000 | AT96: 2703433 | AU96: 1252
A97: IMPORTADORA TRENTO LTDA | B97: LOCAL VALLENAR | C97: 274 | D97: 42440 | E97: Facturada | F97: 28-08-2024 11:51:47 | G97: Factura Exenta Electrónica (63909) | H97: CLAUDIA ALEJANDRA VASQUEZ ALARCON | I97: 20-05-2024 11:21:34 | J97: 29-08-2024 0:00:00 | K97: 1FTMF1CM0EFA88282 | L97: FORD | M97: F-150 | N97: F150 XLT 3.7 | O97: FUSADA9 | P97: 2014 | Q97: 62800 | R97: TFOCMTU001099 | S97: GJJL60 | T97: USADO | U97: BLANCO OXFORD | V97: POR DEFINIR | W97: 13990000 | X97: Facturado | Y97: 101 | Z97: DISPONIBLE | AA97: LOCAL VALLENAR | AB97: AE,CC,EE,AAC,ABS,LL,VC,ESP,AISO,AAUTO,AELE,CRE,MAV | AC97: EFA88282 | AD97: 1FTMF1CM0EFA88282 | AE97: TIERNA DAFNE KENDALL VASQUEZ | AF97: 20-05-2024 0:00:00 | AG97: 1 | AH97: 20-05-2024 0:00:00 | AI97: 20-05-2024 11:05:07 | AJ97: 28-02-2025 0:00:00 | AK97: 0 | AL97: 0 | AN97: 7 | AO97: 12000000 | AP97: 452884 | AQ97: 0 | AR97: 12452884 | AS97: 13990000 | AT97: 1537116 | AU97: 1099
A98: IMPORTADORA TRENTO LTDA | B98: LOCAL VALLENAR | C98: 274 | D98: 42440 | E98: Facturada | F98: 28-08-2024 11:51:47 | G98: Factura Exenta Electrónica (63909) | H98: CLAUDIA ALEJANDRA VASQUEZ ALARCON | I98: 20-05-2024 11:21:34 | J98: 29-08-2024 0:00:00 | K98: 1FTMF1CM0EFA88282 | L98: FORD | M98: F-150 | N98: F150 XLT 3.7 | O98: FUSADA9 | P98: 2014 | Q98: 62800 | R98: TFOCMTU001099 | S98: GJJL60 | T98: USADO | U98: BLANCO OXFORD | V98: POR DEFINIR | W98: 13990000 | X98: Facturado | Y98: 101 | Z98: DISPONIBLE | AA98: LOCAL VALLENAR | AB98: AE,CC,EE,AAC,ABS,LL,VC,ESP,AISO,AAUTO,AELE,CRE,MAV | AC98: EFA88282 | AD98: 1FTMF1CM0EFA88282 | AE98: TIERNA DAFNE KENDALL VASQUEZ | AF98: 20-05-2024 0:00:00 | AG98: 1 | AH98: 20-05-2024 0:00:00 | AI98: 20-05-2024 11:05:07 | AJ98: 28-02-2025 0:00:00 | AK98: 0 | AL98: 0 | AN98: 7 | AO98: 12000000 | AP98: 452884 | AQ98: 0 | AR98: 12452884 | AS98: 13990000 | AT98: 1537116 | AU98: 1099
A99: IMPORTADORA TRENTO LTDA | B99: LOCAL PREMIUM CAR SALES | C99: 0 | D99: 0 | I99: 06-04-2026 18:13:21 | K99: 1FTFW1E52 PFB48046 | L99: FORD | M99: F-150 | N99: F150 XLT 4X4 5.0L AUT | O99: F11111 | P99: 2024 | Q99: 13800 | R99: TFOCMTU001160 | S99: TKHS25 | T99: USADO | U99: BLANCO OXFORD | V99: POR DEFINIR | W99: 36490000 | X99: Disponible | Y99: 65 | Z99: DISPONIBLE | AA99: PREMIUM CAR SALES | AB99: AE,CC,EE,NB,AAC,ABS,LL,TC,VC,SS,AISO,ACP,AAUTO,CRE | AC99: PFB48046 | AD99: 1FTFW1E52 PFB48046 | AE99: TIERNA DAFNE KENDALL VASQUEZ | AF99: 06-04-2026 0:00:00 | AG99: 1 | AH99: 06-04-2026 0:00:00 | AI99: 06-04-2026 18:11:36 | AK99: 1 | AL99: 0 | AN99: 0 | AO99: 31300000 | AP99: 598740 | AQ99: 0 | AR99: 31898740 | AS99: 36490000 | AT99: 4591260 | AU99: 1258
A100: IMPORTADORA TRENTO LTDA | B100: LOCAL PREMIUM CAR SALES | C100: 0 | D100: 0 | I100: 06-04-2026 18:13:21 | K100: 1FTFW1E52 PFB48046 | L100: FORD | M100: F-150 | N100: F150 XLT 4X4 5.0L AUT | O100: F11111 | P100: 2024 | Q100: 13800 | R100: TFOCMTU001160 | S100: TKHS25 | T100: USADO | U100: BLANCO OXFORD | V100: POR DEFINIR | W100: 36490000 | X100: Disponible | Y100: 65 | Z100: DISPONIBLE | AA100: PREMIUM CAR SALES | AB100: AE,CC,EE,NB,AAC,ABS,LL,TC,VC,SS,AISO,ACP,AAUTO,CRE | AC100: PFB48046 | AD100: 1FTFW1E52 PFB48046 | AE100: TIERNA DAFNE KENDALL VASQUEZ | AF100: 06-04-2026 0:00:00 | AG100: 1 | AH100: 06-04-2026 0:00:00 | AI100: 06-04-2026 18:11:36 | AK100: 1 | AL100: 0 | AN100: 0 | AO100: 31300000 | AP100: 598740 | AQ100: 0 | AR100: 31898740 | AS100: 36490000 | AT100: 4591260 | AU100: 1258
...
