Workbook

Sheet BBDD2
A1: Marca | B1: Modelo | C1: Versión | D1: Estado Dealer | E1: Año | F1: Placa Patente | G1: Suma de Días Stock | H1: Modelo-versión-año | I1: Precio toma historico | J1: Precio toma historico autored | K1: Precio unidad venta | L1: Precio Lista informe stock | M1: Precio Mercado | N1: Precio Compra Neto Informe Stock | O1: Total Costo Informe Stock
A2: BYD | B2: SHARK DMO | C2: SHARK 1.5 AUT | D2: CON PRENDA | E2: 2025 | F2: TGVF52 | G2: 57 | H2: =CONCATENATE(B2,C2,E2) -> SHARK DMOSHARK 1.5 AUT2025 | J2: =VLOOKUP(F2,'PRECIO TOMA HISTORICO '!A:B,2,0) -> 31627180 | L2: =_xlfn.XLOOKUP(F2,BBDD!$S:$S,BBDD!$AS:$AS) -> 36990000 | M2: =IFERROR(VLOOKUP(F2,'PRECIO MERCADO'!D:E,2,0),"0") -> 40300000 | N2: =_xlfn.XLOOKUP(F2,BBDD!$S:$S,BBDD!$AO:$AO) -> 31627180 | O2: =_xlfn.XLOOKUP(F2,BBDD!$S:$S,BBDD!$AR:$AR) -> 32230828
A3: BYD | B3: SONG PLUS DM-i | C3: SONG PLUS 4X2 1.5 AUT | D3: DISPONIBLE | E3: 2024 | F3: TJDC55 | G3: 145 | H3: =CONCATENATE(B3,C3,E3) -> SONG PLUS DM-iSONG PLUS 4X2 1.5 AUT2024 | J3: =VLOOKUP(F3,'PRECIO TOMA HISTORICO '!A:B,2,0) -> 20000000 | L3: =_xlfn.XLOOKUP(F3,BBDD!$S:$S,BBDD!$AS:$AS) -> 20990000 | M3: =IFERROR(VLOOKUP(F3,'PRECIO MERCADO'!D:E,2,0),"0") -> 22100000 | N3: =_xlfn.XLOOKUP(F3,BBDD!$S:$S,BBDD!$AO:$AO) -> 20000000 | O3: =_xlfn.XLOOKUP(F3,BBDD!$S:$S,BBDD!$AR:$AR) -> 20524003
A4: CHANGAN | B4: CHANGAN | C4: CX70 T 1.5 AUT | D4: EN PREPARACION | E4: 2022 | F4: RXCG78 | G4: 1 | H4: =CONCATENATE(B4,C4,E4) -> CHANGANCX70 T 1.5 AUT2022 | J4: =VLOOKUP(F4,'PRECIO TOMA HISTORICO '!A:B,2,0) -> #N/A | L4: =_xlfn.XLOOKUP(F4,BBDD!$S:$S,BBDD!$AS:$AS) -> 9490000 | M4: =IFERROR(VLOOKUP(F4,'PRECIO MERCADO'!D:E,2,0),"0") -> 9400000 | N4: =_xlfn.XLOOKUP(F4,BBDD!$S:$S,BBDD!$AO:$AO) -> 7100000 | O4: =_xlfn.XLOOKUP(F4,BBDD!$S:$S,BBDD!$AR:$AR) -> 7100000
A5: CHERY | B5: ARRIZO 3 | C5: NEW ARRIZO 3 GLS 1.5 | D5: DISPONIBLE | E5: 2021 | F5: PKHC89 | G5: 27 | H5: =CONCATENATE(B5,C5,E5) -> ARRIZO 3NEW ARRIZO 3 GLS 1.52021 | J5: =VLOOKUP(F5,'PRECIO TOMA HISTORICO '!A:B,2,0) -> 4800000 | L5: =_xlfn.XLOOKUP(F5,BBDD!$S:$S,BBDD!$AS:$AS) -> 6190000 | M5: =IFERROR(VLOOKUP(F5,'PRECIO MERCADO'!D:E,2,0),"0") -> 5990000 | N5: =_xlfn.XLOOKUP(F5,BBDD!$S:$S,BBDD!$AO:$AO) -> 4800000 | O5: =_xlfn.XLOOKUP(F5,BBDD!$S:$S,BBDD!$AR:$AR) -> 5001240
A6: CHERY | B6: TIGGO 2 | C6: TIGGO 2 GLS CVT 1.5 AUT | D6: EN PREPARACION | E6: 2023 | F6: SJVT25 | G6: 3 | H6: =CONCATENATE(B6,C6,E6) -> TIGGO 2TIGGO 2 GLS CVT 1.5 AUT2023 | J6: =VLOOKUP(F6,'PRECIO TOMA HISTORICO '!A:B,2,0) -> 7100000 | L6: =_xlfn.XLOOKUP(F6,BBDD!$S:$S,BBDD!$AS:$AS) -> 8490000 | M6: =IFERROR(VLOOKUP(F6,'PRECIO MERCADO'!D:E,2,0),"0") -> 8300000 | N6: =_xlfn.XLOOKUP(F6,BBDD!$S:$S,BBDD!$AO:$AO) -> 7100000 | O6: =_xlfn.XLOOKUP(F6,BBDD!$S:$S,BBDD!$AR:$AR) -> 7100000
A7: CHERY | B7: TIGGO 3 | C7: TIGGO 3 1.5 | D7: EN PREPARACION | E7: 2022 | F7: RPZK49 | G7: 3 | H7: =CONCATENATE(B7,C7,E7) -> TIGGO 3TIGGO 3 1.52022 | J7: =VLOOKUP(F7,'PRECIO TOMA HISTORICO '!A:B,2,0) -> 6450000 | L7: =_xlfn.XLOOKUP(F7,BBDD!$S:$S,BBDD!$AS:$AS) -> 7990000 | M7: =IFERROR(VLOOKUP(F7,'PRECIO MERCADO'!D:E,2,0),"0") -> 7930000 | N7: =_xlfn.XLOOKUP(F7,BBDD!$S:$S,BBDD!$AO:$AO) -> 6450000 | O7: =_xlfn.XLOOKUP(F7,BBDD!$S:$S,BBDD!$AR:$AR) -> 6450000
A8: CHERY | B8: TIGGO 3 | C8: TIGGO 3 1.5 | D8: EN RESCILIACION | E8: 2021 | F8: RBZD91 | G8: 223 | H8: =CONCATENATE(B8,C8,E8) -> TIGGO 3TIGGO 3 1.52021 | J8: =VLOOKUP(F8,'PRECIO TOMA HISTORICO '!A:B,2,0) -> 6200000 | L8: =_xlfn.XLOOKUP(F8,BBDD!$S:$S,BBDD!$AS:$AS) -> 8190000 | M8: =IFERROR(VLOOKUP(F8,'PRECIO MERCADO'!D:E,2,0),"0") -> 8400000 | N8: =_xlfn.XLOOKUP(F8,BBDD!$S:$S,BBDD!$AO:$AO) -> 6200000 | O8: =_xlfn.XLOOKUP(F8,BBDD!$S:$S,BBDD!$AR:$AR) -> 6419030
A9: CHERY | B9: TIGGO 3 PRO | C9: TIGGO 3 PRO GLS 1.5 AUT | D9: DISPONIBLE | E9: 2026 | F9: VKCY97 | G9: 33 | H9: =CONCATENATE(B9,C9,E9) -> TIGGO 3 PROTIGGO 3 PRO GLS 1.5 AUT2026 | J9: =VLOOKUP(F9,'PRECIO TOMA HISTORICO '!A:B,2,0) -> 10000000 | L9: =_xlfn.XLOOKUP(F9,BBDD!$S:$S,BBDD!$AS:$AS) -> 11690000 | M9: =IFERROR(VLOOKUP(F9,'PRECIO MERCADO'!D:E,2,0),"0") -> 11300000 | N9: =_xlfn.XLOOKUP(F9,BBDD!$S:$S,BBDD!$AO:$AO) -> 10000000 | O9: =_xlfn.XLOOKUP(F9,BBDD!$S:$S,BBDD!$AR:$AR) -> 10279240
A10: CHERY | B10: TIGGO 7 PRO | C10: TIGGO 7 GLX CVT PRO 1.5 AUT | D10: EN TALLER | E10: 2022 | F10: RVRD47 | G10: 118 | H10: =CONCATENATE(B10,C10,E10) -> TIGGO 7 PROTIGGO 7 GLX CVT PRO 1.5 AUT2022 | J10: =VLOOKUP(F10,'PRECIO TOMA HISTORICO '!A:B,2,0) -> 10000000 | L10: =_xlfn.XLOOKUP(F10,BBDD!$S:$S,BBDD!$AS:$AS) -> 11990000 | M10: =IFERROR(VLOOKUP(F10,'PRECIO MERCADO'!D:E,2,0),"0") -> 11900000 | N10: =_xlfn.XLOOKUP(F10,BBDD!$S:$S,BBDD!$AO:$AO) -> 10000000 | O10: =_xlfn.XLOOKUP(F10,BBDD!$S:$S,BBDD!$AR:$AR) -> 10276030
A11: CHERY | B11: TIGGO 8 | C11: TIGGO 8 1.5 | D11: EN PREPARACION | E11: 2022 | F11: RSJD48 | G11: 26 | H11: =CONCATENATE(B11,C11,E11) -> TIGGO 8TIGGO 8 1.52022 | J11: =VLOOKUP(F11,'PRECIO TOMA HISTORICO '!A:B,2,0) -> 9500000 | L11: =_xlfn.XLOOKUP(F11,BBDD!$S:$S,BBDD!$AS:$AS) -> 11490000 | M11: =IFERROR(VLOOKUP(F11,'PRECIO MERCADO'!D:E,2,0),"0") -> 11600000 | N11: =_xlfn.XLOOKUP(F11,BBDD!$S:$S,BBDD!$AO:$AO) -> 9500000 | O11: =_xlfn.XLOOKUP(F11,BBDD!$S:$S,BBDD!$AR:$AR) -> 9771740
A12: CHERY | B12: TIGGO 8 | C12: TIGGO 8 1.5 AUT | D12: EN PREPARACION | E12: 2022 | F12: RTWH37 | G12: 1 | H12: =CONCATENATE(B12,C12,E12) -> TIGGO 8TIGGO 8 1.5 AUT2022 | J12: =VLOOKUP(F12,'PRECIO TOMA HISTORICO '!A:B,2,0) -> #N/A | L12: =_xlfn.XLOOKUP(F12,BBDD!$S:$S,BBDD!$AS:$AS) -> 11390000 | M12: =IFERROR(VLOOKUP(F12,'PRECIO MERCADO'!D:E,2,0),"0") -> 11400000 | N12: =_xlfn.XLOOKUP(F12,BBDD!$S:$S,BBDD!$AO:$AO) -> 8800000 | O12: =_xlfn.XLOOKUP(F12,BBDD!$S:$S,BBDD!$AR:$AR) -> 8800000
A13: CHEVROLET | B13: CAPTIVA | C13: CAPTIVA LS 2.4 AT | D13: EN TALLER | E13: 2017 | F13: JHSK67 | G13: 279 | H13: =CONCATENATE(B13,C13,E13) -> CAPTIVACAPTIVA LS 2.4 AT2017 | J13: =VLOOKUP(F13,'PRECIO TOMA HISTORICO '!A:B,2,0) -> 7300000 | L13: =_xlfn.XLOOKUP(F13,BBDD!$S:$S,BBDD!$AS:$AS) -> 9590000 | M13: =IFERROR(VLOOKUP(F13,'PRECIO MERCADO'!D:E,2,0),"0") -> 9300000 | N13: =_xlfn.XLOOKUP(F13,BBDD!$S:$S,BBDD!$AO:$AO) -> 7300000 | O13: =_xlfn.XLOOKUP(F13,BBDD!$S:$S,BBDD!$AR:$AR) -> 7535530
... A134: ZX AUTO | B134: TERRALORD | C134: TERRALORD DCAB DLX 2.5 | D134: DISPONIBLE | E134: 2022 | F134: RDWB83 | G134: 35 | H134: =CONCATENATE(B134,C134,E134) -> TERRALORDTERRALORD DCAB DLX 2.52022 | J134: =VLOOKUP(F134,'PRECIO TOMA HISTORICO '!A:B,2,0) -> 8900000 | L134: =_xlfn.XLOOKUP(F134,BBDD!$S:$S,BBDD!$AS:$AS) -> 11290000 | M134: =IFERROR(VLOOKUP(F134,'PRECIO MERCADO'!D:E,2,0),"0") -> 11100000 | N134: =_xlfn.XLOOKUP(F134,BBDD!$S:$S,BBDD!$AO:$AO) -> 8900000 | O134: =_xlfn.XLOOKUP(F134,BBDD!$S:$S,BBDD!$AR:$AR) -> 9162740

Sheet PRECIO TOMA HISTORICO 
A1: Patente | B1: Precio toma autored
A2: DTBC89 | B2: 5000000
A3: DYZJ57 | B3: 7700000
A4: FCBT93 | B4: 7000000
A5: FKKK46 | B5: 1
A6: FSRC30 | B6: 4000000
A7: GGJW34 | B7: 4200000
A8: GGWC79 | B8: 7000000
A9: GHBF56 | B9: 14000000
A10: GJJL60 | B10: 12000000
A11: GKCY72 | B11: 4350000
A12: GLHV84 | B12: 8500000
A13: GPBL74 | B13: 9500000
... A2731: VPGG34 | B2731: 13000000

Sheet PRECIO MERCADO
A1: FECHA CONSULTA | B1: MARCA | C1: MODELO | D1: PATENTE | E1: VALOR AUTOPRESS
A2: 45827.41 | B2: HONDA | C2: HR-V | D2: PKTY15 | E2: 13100000
A3: 46014.258 | B3: FORD | C3: F-150 NEW | D3: TCTV39 | E3: 43400000
A4: 46014.285 | B4: FORD | C4: BRONCO | D4: No informado | E4: 48700000
A5: 46014.314 | B5: PEUGEOT | C5: NUEVO 308 | D5: SLRJ93 | E5: 16500000
A6: 46014.327 | B6: HYUNDAI | C6: ACCENT | D6: RDJS62 | E6: 10500000
A7: 46014.334 | B7: CHEVROLET | C7: ALL NEW TRACKER | D7: SBWS64 | E7: 11000000
A8: 46014.335 | B8: PEUGEOT | C8: 3008 | D8: LVCS57 | E8: 15000000
A9: 46014.347 | B9: MITSUBISHI | C9: MONTERO SPORT NEW | D9: LBVX49 | E9: 20200000
A10: 46014.352 | B10: FORD | C10: F-150 NEW | D10: TCTV39 | E10: 43400000
A11: 46014.38 | B11: JEEP | C11: GRAND CHEROKEE | D11: THRJ80 | E11: 43000000
A12: 46014.39 | B12: RENAULT | C12: KWID | D12: SJHZ88 | E12: 6780000
A13: 46014.397 | B13: PEUGEOT | C13: NUEVO 2008 | D13: RJCW76 | E13: 12400000
A14: 46014.401 | B14: PEUGEOT | C14: NUEVO 208 | D14: VBBD69 | E14: 19000000
A15: 46014.407 | B15: DFSK | C15: 560 | D15: RCBJ98 | E15: 8200000
A16: 46014.41 | B16: PEUGEOT | C16: NUEVO 3008 | D16: PRVP72 | E16: 15200000
A17: 46014.415 | B17: FORD | C17: NUEVO MUSTANG | D17: VDBS14 | E17: 45800000
A18: 46014.421 | B18: CHERY | C18: TIGGO 8 | D18: PSGB54 | E18: 11500000
A19: 46014.428 | B19: CHERY | C19: TIGGO 8 PRO | D19: SPPY18 | E19: 14700000
A20: 46014.438 | B20: TOYOTA | C20: COROLLA CROSS | D20: RVKL20 | E20: 23300000
A21: 46014.475 | B21: RAM | C21: 1500 | D21: SHLW33 | E21: 31400000
A22: 46014.479 | B22: NISSAN | C22: NUEVA X-TRAIL | D22: SHDG89 | E22: 20100000
A23: 46014.496 | B23: EXEED | C23: LX | D23: TRJC45 | E23: 14700000
A24: 46014.51 | B24: CHANGAN | C24: CS15 | D24: KTCV74 | E24: 5850000
A25: 46014.516 | B25: PEUGEOT | C25: 3008 | D25: TLRT68 | E25: 25800000
A26: 46014.553 | B26: CHERY | C26: TIGGO 2 | D26: RYDL24 | E26: 7600000
A27: 46015.296 | B27: KIA | C27: SOLUTO | D27: SYPS56 | E27: 8600000
A28: 46015.317 | B28: NISSAN | C28: QASHQAI | D28: RBXV26 | E28: 13000000
A29: 46015.323 | B29: PEUGEOT | C29: NUEVO 5008 | D29: SKSZ62 | E29: 23700000
A30: 46015.34 | B30: PEUGEOT | C30: LANDTREK | D30: RSYF47 | E30: 17200000
A31: 46015.349 | B31: CHERY | C31: TIGGO 3 | D31: RBZD91 | E31: 8400000
A32: 46015.35 | B32: FORD | C32: NEW F-150 RAPTOR | D32: LYPC19 | E32: 45300000
A33: 46015.352 | B33: PEUGEOT | C33: NEW 3008 | D33: TZTC96 | E33: 23900000
A34: 46015.356 | B34: PEUGEOT | C34: NUEVO 2008 | D34: SWBX38 | E34: 16900000
A35: 46015.357 | B35: FORD | C35: NUEVA EXPLORER | D35: TXYY85 | E35: 49700000
A36: 46015.361 | B36: FORD | C36: NUEVA RANGER | D36: SYPL90 | E36: 26400000
A37: 46015.363 | B37: BAIC | C37: X55 | D37: TRTW63 | E37: 12000000
... A43: 46015.376 | B43: FORD | C43: EDGE | D43: TFFD89 | E43: 26100000
A44: 46015.379 | B44: DFSK | C44: 580 | D44: SJJH10 | E44: 10300000
A45: 46015.38 | B45: NISSAN | C45: NUEVO SENTRA | D45: SJRW76 | E45: 15600000
A46: 46015.385 | B46: PEUGEOT | C46: NEW RIFTER | D46: TZHX32 | E46: 20500000
A47: 46015.385 | B47: PEUGEOT | C47: 2008 | D47: LXLT74 | E47: 12900000
A48: 46015.389 | B48: FORD | C48: TERRITORY | D48: RRWP38 | E48: 12800000
A49: 46015.391 | B49: HAVAL | C49: NEW JOLION | D49: TFRF61 | E49: 12300000
A50: 46015.393 | B50: PEUGEOT | C50: NUEVO 308 | D50: TJSJ77 | E50: 17900000
A51: 46015.394 | B51: BRILLIANCE | C51: X30 | D51: RJRF51 | E51: 5270000
A52: 46015.394 | B52: CITROEN | C52: C5 AIRCROSS | D52: LVWV64 | E52: 13500000
A53: 46015.425 | B53: JMC | C53: GRAND AVENUE | D53: TRTB48 | E53: 21500000
A54: 46015.432 | B54: KIA | C54: RIO 4 | D54: TBZP32 | E54: 12300000
A55: 46017.284 | B55: CHEVROLET | C55: NEW COLORADO | D55: SJRV42 | E55: 23200000
A56: 46017.285 | B56: PEUGEOT | C56: NEW RIFTER | D56: VBBC94 | E56: 20600000
A57: 46017.288 | B57: DFSK | C57: 580 | D57: SJJH94 | E57: 10000000
A58: 46017.292 | B58: PEUGEOT | C58: NUEVO 5008 | D58: SRWC14 | E58: 24900000
A59: 46017.293 | B59: PEUGEOT | C59: LANDTREK | D59: SLJL53 | E59: 18400000
A60: 46017.293 | B60: FIAT | C60: ARGO | D60: RXCG22 | E60: 8800000
A61: 46017.295 | B61: FORD | C61: F-150 NEW | D61: TJDB78 | E61: 49800000
A62: 46017.296 | B62: PEUGEOT | C62: NUEVO 3008 | D62: RSJF58 | E62: 20700000
A63: 46017.297 | B63: HAVAL | C63: H6 GT | D63: THRJ85 | E63: 19400000
A64: 46017.298 | B64: OMODA | C64: C5 | D64: TSSG86 | E64: 12800000
A65: 46017.299 | B65: PEUGEOT | C65: LANDTREK | D65: SLWF83 | E65: 17700000
A66: 46017.301 | B66: NISSAN | C66: VERSA | D66: RBJH77 | E66: 9800000
A67: 46017.302 | B67: JAC | C67: JS2 | D67: TJDF16 | E67: 9000000
A68: 46017.302 | B68: RAM | C68: NEW 1500 | D68: SCZP26 | E68: 34300000
A69: 46017.303 | B69: CHANGAN | C69: CX70 | D69: PYXJ35 | E69: 9500000
... A81: 46017.334 | B81: FORD | C81: F-150 | D81: PKTZ57 | E81: 29800000
A82: 46017.334 | B82: PEUGEOT | C82: 3008 | D82: TDYK32 | E82: 17100000
A83: 46017.336 | B83: FORD | C83: TERRITORY | D83: SSBR38 | E83: 13100000
A84: 46017.336 | B84: PEUGEOT | C84: NUEVO 2008 | D84: SVGL43 | E84: 18800000
A85: 46017.349 | B85: KIA | C85: NIRO | D85: TFGR11 | E85: 30400000
A86: 46017.352 | B86: SSANGYONG | C86: NEW KORANDO | D86: PKBJ31 | E86: 12100000
A87: 46017.353 | B87: PEUGEOT | C87: NUEVO 3008 | D87: SPSZ45 | E87: 19200000
A88: 46017.358 | B88: HYUNDAI | C88: ALL NEW SANTA FE | D88: TTVD23 | E88: 32100000
A89: 46017.359 | B89: PEUGEOT | C89: NUEVO 5008 | D89: SDGD26 | E89: 22000000
A90: 46017.363 | B90: FORD | C90: RANGER | D90: SWTR81 | E90: 18700000
A91: 46017.367 | B91: CHEVROLET | C91: ONIX | D91: SPSY59 | E91: 9900000
A92: 46017.368 | B92: FORD | C92: NUEVA RANGER | D92: TJSK30 | E92: 36200000
A93: 46017.369 | B93: SUZUKI | C93: NUEVO SWIFT | D93: SZHT24 | E93: 9800000
A94: 46017.371 | B94: JMC | C94: VIGUS | D94: SKSZ63 | E94: 11500000
... A99: 46017.388 | B99: OPEL | C99: NEW GRANDLAND | D99: TFGL44 | E99: 17400000
A100: 46017.39 | B100: DFSK | C100: 560 | D100: SSTS80 | E100: 8900000
A101: 46017.392 | B101: NISSAN | C101: QASHQAI | D101: SXTX58 | E101: 17300000
A102: 46017.394 | B102: NISSAN | C102: QASHQAI | D102: SFLX53 | E102: 17400000
A103: 46017.397 | B103: JEEP | C103: COMPASS | D103: TSYZ42 | E103: 24400000
A104: 46017.399 | B104: FORD | C104: NUEVA RANGER | D104: TSSB95 | E104: 49500000
A105: 46017.406 | B105: NISSAN | C105: QASHQAI | D105: TFGP60 | E105: 22700000
A106: 46017.411 | B106: NISSAN | C106: NUEVA X-TRAIL | D106: SSTS34 | E106: 27600000
A107: 46017.412 | B107: FORD | C107: TERRITORY | D107: RPSZ19 | E107: 12400000
A108: 46017.419 | B108: TOYOTA | C108: C-HR | D108: PXVL80 | E108: 19000000
A109: 46017.428 | B109: TOYOTA | C109: COROLLA CROSS | D109: TJDD28 | E109: 21900000
A110: 46017.456 | B110: PEUGEOT | C110: NUEVO 2008 | D110: SLRJ69 | E110: 13400000
A111: 46017.462 | B111: PEUGEOT | C111: NUEVO 208 | D111: SYPP39 | E111: 12400000
A112: 46017.518 | B112: CHEVROLET | C112: TRAVERSE | D112: RFYC31 | E112: 24600000
A113: 46017.527 | B113: PEUGEOT | C113: NUEVO 208 | D113: SYPP39 | E113: 11800000
A114: 46017.538 | B114: PEUGEOT | C114: 3008 | D114: LHCW17 | E114: 13200000
A115: 46017.54 | B115: FORD | C115: EDGE NEW | D115: PCDV84 | E115: 19200000
A116: 46017.543 | B116: FORD | C116: TERRITORY | D116: PJDC98 | E116: 13200000
A117: 46017.544 | B117: FORD | C117: EXPEDITION | D117: JGFD64 | E117: 16300000
A118: 46017.544 | B118: RENAULT | C118: ALL NEW DUSTER | D118: RBLB70 | E118: 8600000
A119: 46017.546 | B119: SSANGYONG | C119: REXTON | D119: GLRH21 | E119: 8300000
A120: 46017.548 | B120: CITROEN | C120: C3 AIRCROSS NEW | D120: LPXJ44 | E120: 10700000
...

Sheet INFORME VENTAS
A1: Marca | B1: Modelo | C1: Versión | D1: Año | E1: Modelo-version-año | F1: Placa Patente | G1: Suma de Unidad Venta | H1: Suma de Unidad Costo
G2: 0 | H2: 0
A3: AUDI | B3: A3 | C3: A3 HB 1.4 AUT | D3: 2019 | E3: =CONCATENATE(B3,C3,D3) -> A3A3 HB 1.4 AUT2019 | F3: KZRK80 | G3: 14582000 | H3: 15000000
A4: AUDI | B4: A3 | C4: A3 SEDAN 35 TFSI 1.4 AUT | D4: 2022 | E4: =CONCATENATE(B4,C4,D4) -> A3A3 SEDAN 35 TFSI 1.4 AUT2022 | F4: RTLW29 | G4: 22990000 | H4: 23800000
A5: AUDI | B5: Q2 | C5: Q2 35 TFSI 1.4 AUT | D5: 2023 | E5: =CONCATENATE(B5,C5,D5) -> Q2Q2 35 TFSI 1.4 AUT2023 | F5: SPZD69 | G5: 26190000 | H5: 22500000
A6: AUDI | B6: Q3 | C6: Q3 35 TFSI 1.4 AUT | D6: 2023 | E6: =CONCATENATE(B6,C6,D6) -> Q3Q3 35 TFSI 1.4 AUT2023 | F6: SRZH16 | G6: 25990000 | H6: 23200000
A7: AUDI | B7: Q3 | C7: Q3 35 TFSI SPORTBACK 1.4 AUT | D7: 2023 | E7: =CONCATENATE(B7,C7,D7) -> Q3Q3 35 TFSI SPORTBACK 1.4 AUT2023 | F7: SLYZ27 | G7: 33990000 | H7: 29000000
A8: AUDI | B8: Q5 | C8: Q5 TDI 2.0 | D8: 2012 | E8: =CONCATENATE(B8,C8,D8) -> Q5Q5 TDI 2.02012 | F8: DTLC56 | G8: 11000000 | H8: 15000000
A9: AUDI | B9: Q5 | C9: Q5 TFSI 4X4 2.0 AUT | D9: 2020 | E9: =CONCATENATE(B9,C9,D9) -> Q5Q5 TFSI 4X4 2.0 AUT2020 | F9: LPXH29 | G9: 25390000 | H9: 31300000
A10: AUDI | B10: Q5 | C10: Q5 TFSI 4X4 2.0 AUT | D10: 2020 | E10: =CONCATENATE(B10,C10,D10) -> Q5Q5 TFSI 4X4 2.0 AUT2020 | F10: PFRP23 | G10: 23490000 | H10: 32000000
A11: AUDI | B11: Q7 | C11: Q7 TDI 4X4 3.0 AUT | D11: 2019 | E11: =CONCATENATE(B11,C11,D11) -> Q7Q7 TDI 4X4 3.0 AUT2019 | F11: KWYD58 | G11: 33490000 | H11: 29000000
A12: BAIC | B12: BAIC | C12: X35 1.5 | D12: 2019 | E12: =CONCATENATE(B12,C12,D12) -> BAICX35 1.52019 | F12: LGXV34 | G12: 7990000 | H12: 8800000
A13: BAIC | B13: BAIC | C13: X35 1.5 | D13: 2023 | E13: =CONCATENATE(B13,C13,D13) -> BAICX35 1.52023 | F13: SBLF15 | G13: 7890000 | H13: 6500000
A14: BAIC | B14: BAIC | C14: X55 1.5T | D14: 2023 | E14: =CONCATENATE(B14,C14,D14) -> BAICX55 1.5T2023 | F14: SSRS44 | G14: 8690000 | H14: 6800000
... A326: CITROEN | B326: C4 | C326: C4 1.2 AT | D326: 2025 | E326: =CONCATENATE(B326,C326,D326) -> C4C4 1.2 AT2025 | F326: VBHL43 | G326: 18990000 | H326: 16500000
A327: CITROEN | B327: C4 | C327: C4 1.5 AUT | D327: 2025 | E327: =CONCATENATE(B327,C327,D327) -> C4C4 1.5 AUT2025 | G327: 17990000 | H327: 0
A328: CITROEN | B328: C4 | C328: C4 1.5 AUT | D328: 2025 | E328: =CONCATENATE(B328,C328,D328) -> C4C4 1.5 AUT2025 | F328: TXZB72 | G328: 17990000 | H328: 14500000
A329: CITROEN | B329: C4 | C329: C4 1.6 | D329: 2010 | E329: =CONCATENATE(B329,C329,D329) -> C4C4 1.62010 | F329: CJZV22 | G329: 2000000 | H329: 3600000
A330: CITROEN | B330: C4 | C330: C4 CACTUS HDI 1.6 | D330: 2016 | E330: =CONCATENATE(B330,C330,D330) -> C4C4 CACTUS HDI 1.62016 | F330: HRWS66 | G330: 9690000 | H330: 8000000
A331: CITROEN | B331: C4 | C331: C4 HDI 1.6 | D331: 2016 | E331: =CONCATENATE(B331,C331,D331) -> C4C4 HDI 1.62016 | F331: HJSY32 | G331: 8490000 | H331: 7000000
A332: CITROEN | B332: C5 | C332: C5 AIRCROSS 1.5 AUT | D332: 2019 | E332: =CONCATENATE(B332,C332,D332) -> C5C5 AIRCROSS 1.5 AUT2019 | G332: 16490000 | H332: 0
A333: CITROEN | B333: C5 | C333: C5 AIRCROSS 1.5 AUT | D333: 2019 | E333: =CONCATENATE(B333,C333,D333) -> C5C5 AIRCROSS 1.5 AUT2019 | F333: LFXV54 | G333: 27980000 | H333: 29800000
A334: CITROEN | B334: C5 | C334: C5 AIRCROSS 1.5 AUT | D334: 2020 | E334: =CONCATENATE(B334,C334,D334) -> C5C5 AIRCROSS 1.5 AUT2020 | F334: LVWV64 | G334: 14190000 | H334: 12000000
A335: CITROEN | B335: C5 | C335: C5 AIRCROSS BHDI 1.5 AUT | D335: 2020 | E335: =CONCATENATE(B335,C335,D335) -> C5C5 AIRCROSS BHDI 1.5 AUT2020 | F335: LVWY70 | G335: 21990000 | H335: 21330300
A336: CITROEN | B336: C5 | C336: C5 AIRCROSS BLUEHDI 1.5 AUT | D336: 2022 | E336: =CONCATENATE(B336,C336,D336) -> C5C5 AIRCROSS BLUEHDI 1.5 AUT2022 | F336: PCFG80 | G336: 18090000 | H336: 15500000
A337: CITROEN | B337: C5 | C337: C5 AIRCROSS CVA8 STT 1.5 AUT | D337: 2024 | E337: =CONCATENATE(B337,C337,D337) -> C5C5 AIRCROSS CVA8 STT 1.5 AUT2024 | F337: TCTS12 | G337: 19150000 | H337: 16750000
A338: CITROEN | B338: C-ELYSEE | C338: C ELYSEE 1.2 | D338: 2018 | E338: =CONCATENATE(B338,C338,D338) -> C-ELYSEEC ELYSEE 1.22018 | F338: KGLK41 | G338: 6100000 | H338: 4900000
A339: CITROEN | B339: C-ELYSEE | C339: C ELYSEE 1.6 | D339: 2017 | E339: =CONCATENATE(B339,C339,D339) -> C-ELYSEEC ELYSEE 1.62017 | F339: JGCC12 | G339: 5590000 | H339: 5000000
A340: CITROEN | B340: SPACETOURER | C340: BUSINEES HDI 2.0 | D340: 2022 | E340: =CONCATENATE(B340,C340,D340) -> SPACETOURERBUSINEES HDI 2.02022 | F340: PCFG40 | G340: 20390000 | H340: 17500000
A341: DFLM | B341: JOYEAR | C341: JOYEAR SX5 1.6 | D341: 2021 | E341: =CONCATENATE(B341,C341,D341) -> JOYEARJOYEAR SX5 1.62021 | F341: RFHP74 | G341: 7746004 | H341: 6500000
A342: DFM | B342: AX4 | C342: AX4 LUXURY 1.6 AUT | D342: 2021 | E342: =CONCATENATE(B342,C342,D342) -> AX4AX4 LUXURY 1.6 AUT2021 | F342: PSPC17 | G342: 7990000 | H342: 5700000
A343: DFM | B343: JOYEAR | C343: JOYEAR SX5 1.6 | D343: 2022 | E343: =CONCATENATE(B343,C343,D343) -> JOYEARJOYEAR SX5 1.62022 | F343: RXSL88 | G343: 7850000 | H343: 6500000
A344: DFM | B344: T5L | C344: T5L LUX 1.8 | D344: 2025 | E344: =CONCATENATE(B344,C344,D344) -> T5LT5L LUX 1.82025 | F344: TSRG98 | G344: 11990000 | H344: 10700000
... A380: DFSK | B380: CARGO | C380: CARGO VAN C35 1.5 | D380: 2022 | E380: =CONCATENATE(B380,C380,D380) -> CARGOCARGO VAN C35 1.52022 | F380: SCGS46 | G380: 10265960 | H380: 12000000
A381: DFSK | B381: DFSK | C381: CARGO BOX XL 1.3 | D381: 2014 | E381: =CONCATENATE(B381,C381,D381) -> DFSKCARGO BOX XL 1.32014 | G381: 3990000 | H381: 0
A382: DFSK | B382: DFSK | C382: CARGO BOX XL 1.3 | D382: 2014 | E382: =CONCATENATE(B382,C382,D382) -> DFSKCARGO BOX XL 1.32014 | F382: GBDZ39 | G382: 3990000 | H382: 4331719
A383: DFSK | B383: PICK UP D1 | C383: D1 COMFORT 2.3 | D383: 2024 | E383: =CONCATENATE(B383,C383,D383) -> PICK UP D1D1 COMFORT 2.32024 | F383: TCHY13 | G383: 13990000 | H383: 14500000
A384: DFSK | B384: PICK UP D1 | C384: D1 LUXURY 4X4 2.3 | D384: 2024 | E384: =CONCATENATE(B384,C384,D384) -> PICK UP D1D1 LUXURY 4X4 2.32024 | F384: TLRR98 | G384: 16490000 | H384: 13750000
A385: DFSK | B385: TRUCK | C385: TRUCK CS C21 1.3 | D385: 2026 | E385: =CONCATENATE(B385,C385,D385) -> TRUCKTRUCK CS C21 1.32026 | F385: VJTT72 | G385: 7690000 | H385: 6500000
A386: DFSK | B386: TRUCK | C386: TRUCK DC 1.0 | D386: 2025 | E386: =CONCATENATE(B386,C386,D386) -> TRUCKTRUCK DC 1.02025 | F386: VCRP11 | G386: 6990000 | H386: 0
A387: DFSK | B387: TRUCK | C387: TRUCK DC 1.3 | D387: 2024 | E387: =CONCATENATE(B387,C387,D387) -> TRUCKTRUCK DC 1.32024 | F387: TFCC55 | G387: 6810000 | H387: 5500000
A388: DFSK | B388: TRUCK | C388: TRUCK SERIE C DCAB 1.5 | D388: 2023 | E388: =CONCATENATE(B388,C388,D388) -> TRUCKTRUCK SERIE C DCAB 1.52023 | F388: SHLV24 | G388: 6490000 | H388: 5000000
A389: DODGE | B389: DODGE | C389: NEW RAM1500 SLT SPORT 4X4 5.7 AUT | D389: 2016 | E389: =CONCATENATE(B389,C389,D389) -> DODGENEW RAM1500 SLT SPORT 4X4 5.7 AUT2016 | F389: HYSL74 | G389: 17000000 | H389: 20400000
A390: DODGE | B390: DODGE | C390: RAM1500 LARAMIE 4X4 5.7 | D390: 2017 | E390: =CONCATENATE(B390,C390,D390) -> DODGERAM1500 LARAMIE 4X4 5.72017 | F390: JLXP52 | G390: 26490000 | H390: 24700000
A391: DODGE | B391: DURANGO | C391: NEW DURANGO CITADEL AWD 5.7 | D391: 2011 | E391: =CONCATENATE(B391,C391,D391) -> DURANGONEW DURANGO CITADEL AWD 5.72011 | F391: DBXP41 | G391: 4750000 | H391: 11000000
A392: DODGE | B392: JOURNEY | C392: JOURNEY 2.4 AUT | D392: 2016 | E392: =CONCATENATE(B392,C392,D392) -> JOURNEYJOURNEY 2.4 AUT2016 | F392: HLBT63 | G392: 11090000 | H392: 10000000
A393: DODGE | B393: RAM | C393: RAM1500 LARAMIE 4X4 5.7 | D393: 2018 | E393: =CONCATENATE(B393,C393,D393) -> RAMRAM1500 LARAMIE 4X4 5.72018 | F393: JXBR60 | G393: 29290000 | H393: 26000000
... A407: FIAT | B407: PULSE | C407: PULSE HB MT 1.3 | D407: 2025 | E407: =CONCATENATE(B407,C407,D407) -> PULSEPULSE HB MT 1.32025 | F407: VBRX43 | G407: 12590000 | H407: 10800000
A408: FIAT | B408: PULSE | C408: PULSE IMPETUS TF200 1.0 AUT | D408: 2022 | E408: =CONCATENATE(B408,C408,D408) -> PULSEPULSE IMPETUS TF200 1.0 AUT2022 | G408: 13490000 | H408: 0
A409: FIAT | B409: PULSE | C409: PULSE IMPETUS TF200 1.0 AUT | D409: 2022 | E409: =CONCATENATE(B409,C409,D409) -> PULSEPULSE IMPETUS TF200 1.0 AUT2022 | F409: RYDR17 | G409: 12990000 | H409: 19900000
A410: FIAT | B410: QUBO | C410: QUBO DYNAMIC 1.4 | D410: 2020 | E410: =CONCATENATE(B410,C410,D410) -> QUBOQUBO DYNAMIC 1.42020 | F410: PFRP57 | G410: 8490000 | H410: 8000000
A411: FIAT | B411: UNO WAY | C411: UNO WAY 1.4 | D411: 2016 | E411: =CONCATENATE(B411,C411,D411) -> UNO WAYUNO WAY 1.42016 | F411: HXRF54 | G411: 4990000 | H411: 3800000
A412: FIAT | B412: UNO WAY | C412: UNO WAY 1.4 | D412: 2017 | E412: =CONCATENATE(B412,C412,D412) -> UNO WAYUNO WAY 1.42017 | F412: JBJC25 | G412: 5990000 | H412: 5100000
A413: FIAT | B413: UNO WAY | C413: UNO WAY EVO 1.3 | D413: 2018 | E413: =CONCATENATE(B413,C413,D413) -> UNO WAYUNO WAY EVO 1.32018 | F413: KJYF93 | G413: 6790000 | H413: 5500000
A414: FIAT | B414: UNO WAY | C414: UNO WAY EVO 1.4 | D414: 2017 | E414: =CONCATENATE(B414,C414,D414) -> UNO WAYUNO WAY EVO 1.42017 | F414: JGBX93 | G414: 7090000 | H414: 5000000
A415: FIAT | B415: UNO WAY | C415: UNO WAY EVO 1.4 | D415: 2020 | E415: =CONCATENATE(B415,C415,D415) -> UNO WAYUNO WAY EVO 1.42020 | F415: LVXF83 | G415: 5990000 | H415: 4850000
A416: FIAT | B416: UNO WAY | C416: UNO WAY EVO FL 1.3 | D416: 2018 | E416: =CONCATENATE(B416,C416,D416) -> UNO WAYUNO WAY EVO FL 1.32018 | F416: KGLL79 | G416: 4990000 | H416: 4000000
A417: FORD | B417: BRONCO | C417: BRONCO SPORT 4X4 1.5 AUT | D417: 2023 | E417: =CONCATENATE(B417,C417,D417) -> BRONCOBRONCO SPORT 4X4 1.5 AUT2023 | F417: SYXT32 | G417: 20990000 | H417: 18300000
A418: FORD | B418: BRONCO | C418: BRONCO SPORT 4X4 1.5 AUT | D418: 2023 | E418: =CONCATENATE(B418,C418,D418) -> BRONCOBRONCO SPORT 4X4 1.5 AUT2023 | F418: SYXT50 | G418: 21690000 | H418: 18500000
A419: FORD | B419: BRONCO | C419: BRONCO SPORT 4X4 1.5 AUT | D419: 2024 | E419: =CONCATENATE(B419,C419,D419) -> BRONCOBRONCO SPORT 4X4 1.5 AUT2024 | F419: SYPZ14 | G419: 23990000 | H419: 21000000
A420: FORD | B420: BRONCO | C420: BRONCO SPORT WILDTRAK 4X4 2.0 AUT | D420: 2022 | E420: =CONCATENATE(B420,C420,D420) -> BRONCOBRONCO SPORT WILDTRAK 4X4 2.0 AUT2022 | F420: RTJJ48 | G420: 31790000 | H420: 28000000
... A443: FORD | B443: ECOSPORT | C443: ECOSPORT 2.0 AUT | D443: 2019 | E443: =CONCATENATE(B443,C443,D443) -> ECOSPORTECOSPORT 2.0 AUT2019 | F443: KWVP39 | G443: 11990000 | H443: 13000000
A444: FORD | B444: ECOSPORT | C444: ECOSPORT FREESTYLE 1.5 | D444: 2018 | E444: =CONCATENATE(B444,C444,D444) -> ECOSPORTECOSPORT FREESTYLE 1.52018 | G444: 7890000 | H444: 0
A445: FORD | B445: ECOSPORT | C445: ECOSPORT FREESTYLE 1.5 | D445: 2018 | E445: =CONCATENATE(B445,C445,D445) -> ECOSPORTECOSPORT FREESTYLE 1.52018 | F445: KGPD80 | G445: 6950000 | H445: 5800000
A446: FORD | B446: ECOSPORT | C446: ECOSPORT FREESTYLE 1.5 | D446: 2019 | E446: =CONCATENATE(B446,C446,D446) -> ECOSPORTECOSPORT FREESTYLE 1.52019 | F446: LBVT23 | G446: 8490000 | H446: 6000000
A447: FORD | B447: ECOSPORT | C447: ECOSPORT FREESTYLE 1.5 | D447: 2019 | E447: =CONCATENATE(B447,C447,D447) -> ECOSPORTECOSPORT FREESTYLE 1.52019 | F447: LHCL79 | G447: 9290000 | H447: 7983193
A448: FORD | B448: ECOSPORT | C448: ECOSPORT FREESTYLE 1.5 | D448: 2020 | E448: =CONCATENATE(B448,C448,D448) -> ECOSPORTECOSPORT FREESTYLE 1.52020 | F448: LVXD95 | G448: 10790000 | H448: 8900000
A449: FORD | B449: ECOSPORT | C449: ECOSPORT FREESTYLE 1.5 | D449: 2020 | E449: =CONCATENATE(B449,C449,D449) -> ECOSPORTECOSPORT FREESTYLE 1.52020 | F449: PFRR32 | G449: 9990000 | H449: 10500000
A450: FORD | B450: ECOSPORT | C450: ECOSPORT S 1.5 | D450: 2019 | E450: =CONCATENATE(B450,C450,D450) -> ECOSPORTECOSPORT S 1.52019 | F450: RGHD32 | G450: 11290000 | H450: 9500000
A451: FORD | B451: ECOSPORT | C451: ECOSPORT S 1.5 | D451: 2020 | E451: =CONCATENATE(B451,C451,D451) -> ECOSPORTECOSPORT S 1.52020 | F451: LYPC86 | G451: 8490000 | H451: 7074790
A452: FORD | B452: ECOSPORT | C452: ECOSPORT S 1.5 | D452: 2021 | E452: =CONCATENATE(B452,C452,D452) -> ECOSPORTECOSPORT S 1.52021 | F452: PFRZ91 | G452: 7990000 | H452: 6000000
A453: FORD | B453: ECOSPORT | C453: ECOSPORT S 1.5 | D453: 2021 | E453: =CONCATENATE(B453,C453,D453) -> ECOSPORTECOSPORT S 1.52021 | F453: PKJP78 | G453: 10790000 | H453: 8800000
A454: FORD | B454: ECOSPORT | C454: ECOSPORT TITANIUM 1.5 | D454: 2018 | E454: =CONCATENATE(B454,C454,D454) -> ECOSPORTECOSPORT TITANIUM 1.52018 | F454: KDTL69 | G454: 8990000 | H454: 7000000
A455: FORD | B455: ECOSPORT | C455: ECOSPORT TITANIUM 1.5 | D455: 2019 | E455: =CONCATENATE(B455,C455,D455) -> ECOSPORTECOSPORT TITANIUM 1.52019 | F455: KTCZ97 | G455: 10490000 | H455: 8483193
A456: FORD | B456: ECOSPORT | C456: ECOSPORT TITANIUM 1.5 | D456: 2019 | E456: =CONCATENATE(B456,C456,D456) -> ECOSPORTECOSPORT TITANIUM 1.52019 | F456: LBGV62 | G456: 8390000 | H456: 7300000
... A477: FORD | B477: EDGE | C477: EDGE SEL 2.0 AUT | D477: 2019 | E477: =CONCATENATE(B477,C477,D477) -> EDGEEDGE SEL 2.0 AUT2019 | F477: KTCZ34 | G477: 16990000 | H477: 16000000
A478: FORD | B478: EDGE | C478: EDGE SEL 4X4 2.0 AUT | D478: 2020 | E478: =CONCATENATE(B478,C478,D478) -> EDGEEDGE SEL 4X4 2.0 AUT2020 | G478: 20990000 | H478: 0
A479: FORD | B479: EDGE | C479: EDGE SEL 4X4 3.5 AUT | D479: 2019 | E479: =CONCATENATE(B479,C479,D479) -> EDGEEDGE SEL 4X4 3.5 AUT2019 | F479: LYPD12 | G479: 15990000 | H479: 15000000
A480: FORD | B480: ESCAPE | C480: ESCAPE 2.0 AUT | D480: 2018 | E480: =CONCATENATE(B480,C480,D480) -> ESCAPEESCAPE 2.0 AUT2018 | F480: JZGK45 | G480: 10290000 | H480: 8200000
A481: FORD | B481: ESCAPE | C481: ESCAPE 2.0 AUT | D481: 2019 | E481: =CONCATENATE(B481,C481,D481) -> ESCAPEESCAPE 2.0 AUT2019 | F481: LBVV62 | G481: 14690000 | H481: 13000000
A482: FORD | B482: ESCAPE | C482: ESCAPE 2.5 AT | D482: 2020 | E482: =CONCATENATE(B482,C482,D482) -> ESCAPEESCAPE 2.5 AT2020 | F482: LKZY27 | G482: 12575800 | H482: 12100000
A483: FORD | B483: ESCAPE | C483: ESCAPE 2.5 AUT | D483: 2017 | E483: =CONCATENATE(B483,C483,D483) -> ESCAPEESCAPE 2.5 AUT2017 | F483: JDKT68 | G483: 8189030 | H483: 8000000
A484: FORD | B484: ESCAPE | C484: ESCAPE 2.5 AUT | D484: 2020 | E484: =CONCATENATE(B484,C484,D484) -> ESCAPEESCAPE 2.5 AUT2020 | F484: LTZP19 | G484: 12416174 | H484: 11000000
A485: FORD | B485: ESCAPE | C485: ESCAPE 4X4 2.0 | D485: 2020 | E485: =CONCATENATE(B485,C485,D485) -> ESCAPEESCAPE 4X4 2.02020 | F485: LTZH55 | G485: 13690000 | H485: 10500000
A486: FORD | B486: ESCAPE | C486: ESCAPE 4X4 2.0 AUT | D486: 2018 | E486: =CONCATENATE(B486,C486,D486) -> ESCAPEESCAPE 4X4 2.0 AUT2018 | F486: JZGL35 | G486: 11590000 | H486: 9200000
A487: FORD | B487: ESCAPE | C487: ESCAPE 4X4 2.0 AUT | D487: 2018 | E487: =CONCATENATE(B487,C487,D487) -> ESCAPEESCAPE 4X4 2.0 AUT2018 | F487: KRWJ90 | G487: 9590000 | H487: 7700000
A488: FORD | B488: ESCAPE | C488: ESCAPE 4X4 2.0 AUT | D488: 2019 | E488: =CONCATENATE(B488,C488,D488) -> ESCAPEESCAPE 4X4 2.0 AUT2019 | F488: LHPY35 | G488: 13990000 | H488: 11500000
A489: FORD | B489: ESCAPE | C489: ESCAPE 4X4 2.0L AUT | D489: 2021 | E489: =CONCATENATE(B489,C489,D489) -> ESCAPEESCAPE 4X4 2.0L AUT2021 | F489: PRVR51 | G489: 16990000 | H489: 13000000
A490: FORD | B490: ESCAPE | C490: ESCAPE AWD 2.0 AUT | D490: 2023 | E490: =CONCATENATE(B490,C490,D490) -> ESCAPEESCAPE AWD 2.0 AUT2023 | F490: TRJC24 | G490: 20990000 | H490: 23870000
... A492: FORD | B492: ESCAPE | C492: ESCAPE FHEV 2.5 AUT | D492: 2023 | E492: =CONCATENATE(B492,C492,D492) -> ESCAPEESCAPE FHEV 2.5 AUT2023 | F492: SFLZ50 | G492: 21782120 | H492: 19000000
A493: FORD | B493: ESCAPE | C493: ESCAPE FHEV 2.5 AUT | D493: 2024 | E493: =CONCATENATE(B493,C493,D493) -> ESCAPEESCAPE FHEV 2.5 AUT2024 | G493: 26490000 | H493: 0
A494: FORD | B494: ESCAPE | C494: ESCAPE FHEV 2.5 AUT | D494: 2024 | E494: =CONCATENATE(B494,C494,D494) -> ESCAPEESCAPE FHEV 2.5 AUT2024 | F494: TKVB34 | G494: 26510000 | H494: 24000000
A495: FORD | B495: ESCAPE | C495: ESCAPE FHEV 2.5 AUT | D495: 2024 | E495: =CONCATENATE(B495,C495,D495) -> ESCAPEESCAPE FHEV 2.5 AUT2024 | F495: TPTZ45 | G495: 26990000 | H495: 24000000
A496: FORD | B496: ESCAPE | C496: ESCAPE TITANIUM 4X4 2.0 AUT | D496: 2020 | E496: =CONCATENATE(B496,C496,D496) -> ESCAPEESCAPE TITANIUM 4X4 2.0 AUT2020 | F496: LSYF35 | G496: 17990000 | H496: 14500000
A497: FORD | B497: EXPEDITION | C497: EXPEDITION LIMITED 4X4 3.5 AUT | D497: 2022 | E497: =CONCATENATE(B497,C497,D497) -> EXPEDITIONEXPEDITION LIMITED 4X4 3.5 AUT2022 | F497: RGTR45 | G497: 41990000 | H497: 38000000
A498: FORD | B498: EXPEDITION | C498: EXPEDITION LTD 4X4 3.5 AUT | D498: 2018 | E498: =CONCATENATE(B498,C498,D498) -> EXPEDITIONEXPEDITION LTD 4X4 3.5 AUT2018 | F498: KRPW91 | G498: 21990000 | H498: 19500000
A499: FORD | B499: EXPEDITION | C499: EXPEDITION LTD 4X4 3.5 AUT | D499: 2020 | E499: =CONCATENATE(B499,C499,D499) -> EXPEDITIONEXPEDITION LTD 4X4 3.5 AUT2020 | F499: PFSB87 | G499: 35990000 | H499: 31000000
A500: FORD | B500: EXPEDITION | C500: EXPEDITION XLT 3.5 AUT | D500: 2017 | E500: =CONCATENATE(B500,C500,D500) -> EXPEDITIONEXPEDITION XLT 3.5 AUT2017 | F500: JHSD53 | G500: 18000000 | H500: 15500000
A501: FORD | B501: EXPEDITION | C501: EXPEDITION XLT 3.5 AUT | D501: 2017 | E501: =CONCATENATE(B501,C501,D501) -> EXPEDITIONEXPEDITION XLT 3.5 AUT2017 | F501: JPZR22 | G501: 18990000 | H501: 16000000
A502: FORD | B502: EXPLORER | C502: EXPLORER 2.3 | D502: 2018 | E502: =CONCATENATE(B502,C502,D502) -> EXPLOREREXPLORER 2.32018 | F502: JXWF79 | G502: 13990000 | H502: 11500000
...

Sheet BBDD
A1: Empresa | B1: Sucursal | C1: Folio Venta | D1: Venta | E1: Estado Venta | F1: Fecha Venta | G1: Tipo Documento (Folio) | H1: Vendedor | I1: Fecha Ingreso | J1: Fecha Facturación | K1: Numero VIN | L1: Marca | M1: Modelo | N1: Versión | O1: Código Versión | P1: Año | Q1: Kilometraje | R1: Código Interno | S1: Placa Patente | T1: Condición Vehículo | U1: Color Exterior | V1: Color Interior | W1: Precio Venta Total | X1: Estado AutoPro | Y1: Días Stock | Z1: Estado Dealer | AA1: Bodega | AB1: Equipamiento | AC1: Numero Motor | AD1: Numero Chasis | AE1: Proveedor | AF1: Fecha Disponibilidad | AG1: Factura Compra | AH1: Vencimiento Documento | AI1: Fecha Compra | AJ1: Fecha Vencto. Revisión Técnica | AK1: N° Propietarios | AL1: Folio Retoma | AM1: Fecha Retoma | AN1: Días Reservado | AO1: Precio Compra Neto | AP1: Gasto | AQ1: Accesorios | AR1: Total Costo | AS1: Precio Lista | AT1: Margen | AU1: Margen %
A2: IMPORTADORA TRENTO LTDA | B2: LOCAL USADOS COPIAPO | C2: 0 | D2: 0 | I2: 13-11-2025 16:08:09 | K2: VF3MCYHZU PS006748 | L2: PEUGEOT | M2: 5008 | N2: 5008 BLUEHDI 130 1.5 AUT | O2: 5008BH130 | P2: 2023 | Q2: 66999 | R2: TPESTWU000433 | S2: SFLW13 | T2: USADO | U2: BLANCO NACARADO | V2: POR DEFINIR | W2: 22690000 | X2: Disponible | Y2: 201 | Z2: DISPONIBLE | AA2: BODEGA LOS CARRERA COPIAPO | AB2: AE,CC,EE,AAC,ABS,LL,VC,AISO,AAUTO,CRE,MAV,ACD,SR,U | AC2: 10Q4EP0125437 | AD2: VF3MCYHZU PS006748 | AE2: YOANA ELENA ROJAS HENRIQUEZ | AF2: 13-11-2025 0:00:00 | AG2: 1 | AH2: 13-11-2025 0:00:00 | AI2: 13-11-2025 16:00:05 | AJ2: 30-06-2027 0:00:00 | AK2: 1 | AL2: 0 | AN2: 0 | AO2: 19800000 | AP2: 423030 | AQ2: 0 | AR2: 20223030 | AS2: 22690000 | AT2: 2466970 | AU2: 1087
A3: IMPORTADORA TRENTO LTDA | B3: LOCAL USADOS | C3: 0 | D3: 0 | I3: 05-02-2026 13:04:12 | K3: VF3M45GFUPS010582 | L3: PEUGEOT | M3: 5008 | N3: 5008 PURETECH 180 EAT8 1.6 AUT | O3: PE5008PT16AT | P3: 2023 | Q3: 76000 | R3: TPESTWU000446 | S3: SJKL16 | T3: USADO | U3: GRIS ARTENSE | V3: POR DEFINIR | W3: 19290000 | X3: Disponible | Y3: 117 | Z3: CON PRENDA | AA3: BODEGA VEHICULOS | AB3: AE,CC,EE,AAC,ABS,LL,VC,AISO,AAUTO,CRE,MAV,ACD,SR,U | AC3: 10FKBL3003916 | AD3: VF3M45GFUPS010582 | AE3: JOHNNY SEBASTIAN DIAZ ZAMORANO | AF3: 05-02-2026 0:00:00 | AG3: 1 | AH3: 05-02-2026 0:00:00 | AI3: 05-02-2026 13:00:32 | AJ3: 30-09-2027 0:00:00 | AK3: 1 | AL3: 0 | AN3: 0 | AO3: 16500000 | AP3: 373530 | AQ3: 0 | AR3: 16873530 | AS3: 19290000 | AT3: 2416470 | AU3: 1253
A4: IMPORTADORA TRENTO LTDA | B4: LOCAL USADOS | C4: 0 | D4: 0 | I4: 03-01-2017 1:36:33 | K4: LGHT12173E9700288 | L4: DFSK | M4: DFSK | N4: CARGO BOX XL 1.3 | O4: 2012--CARGOBOX1 | P4: 2014 | Q4: 0 | R4: TDFCMTU000001 | S4: GBDZ38 | T4: USADO | U4: BLANCO | V4: NO DEFINIDO | W4: 3490000 | X4: Disponible | Y4: 4381 | Z4: VEHICULO USO DE SERVICIO | AA4: BODEGA VEHICULOS | AC4: EQ474I-3013074700 | AD4: LGHT12173E9700288 | AE4: SOCIEDAD HERMANAS CALLEGARI LTDA | AF4: 04-06-2014 0:00:00 | AG4: 0 | AJ4: 04-06-2014 0:00:00 | AK4: 0 | AL4: 0 | AN4: 0 | AO4: 82597 | AP4: 4016851 | AQ4: 0 | AR4: 4099448 | AS4: 3490000 | AT4: -609448 | AU4: -1746
A5: IMPORTADORA TRENTO LTDA | B5: LOCAL PREMIUM CAR SALES | C5: 0 | D5: 0 | I5: 06-04-2026 18:46:12 | K5: LGWEE4A40LH899522 | L5: HAVAL | M5: H2 | N5: H2 ELITE 1.5 | O5: HL1 | P5: 2019 | Q5: 88000 | R5: THASTWU000022 | S5: LHCV19 | T5: USADO | U5: AZUL | V5: POR DEFINIR | W5: 8290000 | X5: Disponible | Y5: 57 | Z5: DISPONIBLE | AA5: PREMIUM CAR SALES | AB5: AE,CC,EE,NB,ABS,LL,VC,AC,AISO,AAUTO,CRE,MAV,ACD,SR | AC5: GW4G15B1805110609 | AD5: LGWEE4A40LH899522 | AE5: YORMAN JOSE HERNANDEZ USECHE | AF5: 06-04-2026 0:00:00 | AG5: 1 | AH5: 06-04-2026 0:00:00 | AI5: 06-04-2026 18:45:47 | AJ5: 31-01-2027 0:00:00 | AK5: 1 | AL5: 0 | AN5: 0 | AO5: 6800000 | AP5: 231240 | AQ5: 0 | AR5: 7031240 | AS5: 8290000 | AT5: 1258760 | AU5: 1518
A6: IMPORTADORA TRENTO LTDA | B6: LOCAL USADOS | C6: 0 | D6: 0 | I6: 29-04-2025 19:05:19 | K6: LJXCU2BB5 NTF05473 | L6: FORD | M6: TERRITORY | N6: TERRITORY 1.5 AUT | O6: FTU1 | P6: 2022 | Q6: 25200 | R6: TFOSTWU001363 | S6: RRWP38 | T6: USADO | U6: NEGRO PANTERA | V6: POR DEFINIR | W6: 10490000 | X6: Disponible | Y6: 399 | Z6: EN TALLER | AA6: BODEGA VEHICULOS | AB6: AE,CC,EE,NB,AAC,ABS,LL,VC,AISO,AAUTO,CRE,MAV,ACD,S | AC6: M9G068199 | AD6: LJXCU2BB5 NTF05473 | AE6: JAIME NICOLAS MUÑOZ RODRIGUEZ | AF6: 29-04-2025 0:00:00 | AG6: 1 | AH6: 29-04-2025 0:00:00 | AI6: 29-04-2025 18:59:46 | AJ6: 30-11-2026 0:00:00 | AK6: 1 | AL6: 0 | AN6: 1 | AO6: 10300000 | AP6: 280530 | AQ6: 0 | AR6: 10580530 | AS6: 10490000 | AT6: -90530 | AU6: -86
A7: IMPORTADORA TRENTO LTDA | B7: LOCAL PREMIUM CAR SALES | C7: 0 | D7: 0 | I7: 02-09-2025 15:11:09 | K7: KMFYFX71AMU043854 | L7: HYUNDAI | M7: STARIA | N7: US4 CRDI 6MT 2.2 | O7: HYSTAMTDSL | P7: 2022 | Q7: 28000 | R7: THYFRGU000001 | S7: RXXW40 | T7: USADO | U7: BLANCO | V7: POR DEFINIR | W7: 21500000 | X7: Disponible | Y7: 273 | Z7: DISPONIBLE | AA7: PREMIUM CAR SALES | AB7: AE,CC,EE,2AB,ABS,AC,AISO,AAUTO,MAV,ACD,UD,DLL | AC7: D4HBNU232537 | AD7: KMFYFX71AMU043854 | AE7: ELISEO SERGIO GAJARDO VALDERRAMA | AF7: 02-09-2025 0:00:00 | AG7: 1 | AH7: 02-09-2025 0:00:00 | AI7: 02-09-2025 15:10:43 | AJ7: 28-02-2027 0:00:00 | AK7: 1 | AL7: 0 | AN7: 0 | AO7: 20000000 | AP7: 426030 | AQ7: 0 | AR7: 20426030 | AS7: 21500000 | AT7: 1073970 | AU7: 5
A8: IMPORTADORA TRENTO LTDA | B8: LOCAL USADOS COPIAPO | C8: 0 | D8: 0 | I8: 01-06-2026 18:21:00 | K8: //+**+++///++*... | L8: CHERY | M8: TIGGO 8 | N8: TIGGO 8 1.5 AUT | O8: TY8US | P8: 2022 | Q8: 93000 | R8: TCYSTWU000356 | S8: RTWH37 | T8: USADO | U8: BLANCO METALIZADO | V8: POR DEFINIR | W8: 11390000 | X8: Disponible | Y8: 1 | Z8: EN PREPARACION | AA8: BODEGA LOS CARRERA COPIAPO | AB8: AE,CC,EE,ABS,LL,AC,AISO,AAUTO,CRE,MAV,ACD,SR,DLL,6 | AC8: SQRE4T15BAVMJ00643 | AD8: LVTDB21B8ND032457 | AE8: FÉLIX RODRIGO TIFFI ARAVENA | AF8: 01-06-2026 0:00:00 | AG8: 1 | AH8: 01-06-2026 0:00:00 | AI8: 01-06-2026 18:18:33 | AK8: 2 | AL8: 0 | AN8: 0 | AO8: 8800000 | AP8: 0 | AQ8: 0 | AR8: 8800000 | AS8: 11390000 | AT8: 2590000 | AU8: 2274
A9: IMPORTADORA TRENTO LTDA | B9: LOCAL USADOS COPIAPO | C9: 0 | D9: 0 | I9: 12-09-2025 18:26:55 | K9: *---****.../*.... | L9: JAC | M9: T8 | N9: T8 PRO TM 4X4 2.0 | O9: JAT8PRO4X420MT | P9: 2023 | Q9: 40695 | R9: TJACMTU000006 | S9: SSVL57 | T9: USADO | U9: GRIS | V9: POR DEFINIR | W9: 12790000 | X9: Disponible | Y9: 263 | Z9: EN TALLER | AA9: BODEGA LOS CARRERA COPIAPO | AC9: N4127324 | AD9: LJ11PABD8 PC091786 | AE9: CARLOS GABRIEL ROMERO PINO | AF9: 12-09-2025 0:00:00 | AG9: 1 | AH9: 12-09-2025 0:00:00 | AI9: 12-09-2025 18:26:22 | AK9: 3 | AL9: 0 | AN9: 0 | AO9: 10600000 | AP9: 285030 | AQ9: 0 | AR9: 10885030 | AS9: 12790000 | AT9: 1904970 | AU9: 1489
A10: IMPORTADORA TRENTO LTDA | B10: LOCAL PREMIUM CAR SALES | C10: 0 | D10: 0 | I10: 25-05-2026 10:35:24 | K10: 3FTTW8H92RRA99365 | L10: FORD | M10: MAVERICK | N10: MAVERICK XLT 2.0 AUT | O10: FOMAVXLT204X2AT | P10: 2025 | Q10: 24000 | R10: TFOCMTU001161 | S10: TTVV23 | T10: USADO | U10: NEGRO PROFUNDO | V10: POR DEFINIR | W10: 22990000 | X10: Disponible | Y10: 8 | Z10: EN PREPARACION | AA10: PREMIUM CAR SALES | AC10: RRA99365 | AD10: 3FTTW8H92RRA99365 | AE10: INSIGHTGROUP SPA | AF10: 25-05-2026 0:00:00 | AG10: 1 | AH10: 25-05-2026 0:00:00 | AI10: 25-05-2026 10:34:53 | AK10: 3 | AL10: 0 | AN10: 0 | AO10: 20000000 | AP10: 0 | AQ10: 0 | AR10: 20000000 | AS10: 22990000 | AT10: 2990000 | AU10: 1301
A11: IMPORTADORA TRENTO LTDA | B11: LOCAL PREMIUM CAR SALES | C11: 0 | D11: 0 | I11: 29-04-2026 14:31:23 | K11: LVZA53P91 NA129835 | L11: DFSK | M11: 560 | N11: SUV 560 OTTO 1.8 | O11: S560 | P11: 2023 | Q11: 75442 | R11: TDFSTWU000054 | S11: SSTB40 | T11: USADO | U11: BLANCO | V11: POR DEFINIR | W11: 8890000 | X11: Disponible | Y11: 34 | Z11: CON PRENDA | AA11: PREMIUM CAR SALES | AB11: AE,CC,EE,2AB,ABS,LL,AC,AISO,AAUTO,MAV,ACD,SR,UD,DL | AC11: SFG18-22348600 | AD11: LVZA53P91 NA129835 | AE11: MELISSA VALESKA SAEZ FUENTES | AF11: 29-04-2026 0:00:00 | AG11: 1 | AH11: 29-04-2026 0:00:00 | AI11: 29-04-2026 14:30:57 | AK11: 1 | AL11: 0 | AN11: 0 | AO11: 6900000 | AP11: 232740 | AQ11: 0 | AR11: 7132740 | AS11: 8890000 | AT11: 1757260 | AU11: 1977
A12: IMPORTADORA TRENTO LTDA | B12: LOCAL PREMIUM CAR SALES | C12: 0 | D12: 0 | I12: 07-01-2026 16:22:02 | K12: /**//+.+///++*... | L12: HYUNDAI | M12: HYUNDAI | N12: SANTA FE MX5 GDI 2.5 AUT | O12: HYSTFMX525AT | P12: 2024 | Q12: 58500 | R12: THYSTWU000548 | S12: THXK86 | T12: USADO | U12: PLATEADO PLATA | V12: POR DEFINIR | W12: 26390000 | X12: Disponible | Y12: 146 | Z12: DISPONIBLE | AA12: PREMIUM CAR SALES | AB12: AE,CC,EE,ABS,LL,TC,VC,AC,AISO,ACP,AAUTO,CRE,MAV,AC | AC12: G4KNRA734924 | AD12: KMHP281JBRU017462 | AE12: MARIA PAZ GONZALEZ ARAYA | AF12: 07-01-2026 0:00:00 | AG12: 1 | AH12: 07-01-2026 0:00:00 | AI12: 07-01-2026 16:21:28 | AK12: 1 | AL12: 0 | AN12: 0 | AO12: 23500000 | AP12: 903834 | AQ12: 0 | AR12: 24403834 | AS12: 26390000 | AT12: 1986166 | AU12: 753
A13: IMPORTADORA TRENTO LTDA | B13: LOCAL PREMIUM CAR SALES | C13: 0 | D13: 0 | I13: 23-12-2025 18:40:06 | K13: 1C6RR7LG8 NS154084 | L13: RAM | M13: RAM 1500 | N13: 1500 CREW CAB SPORT DCAB 4X4 3.6 AT | O13: RA1500CRSPDC4X436AT | P13: 2023 | Q13: 33892 | R13: TRACMTU000047 | S13: SHLW33 | T13: USADO | U13: BLANCO | V13: POR DEFINIR | W13: 29490000 | X13: Disponible | Y13: 161 | Z13: DISPONIBLE | AA13: PREMIUM CAR SALES | AB13: AE,CC,EE,NB,AAC,ABS,LL,VC,AISO,AAUTO,CRE,MAV,ACD,S | AC13: NS154084 | AD13: 1C6RR7LG8 NS154084 | AE13: MIXY GRACIELA CORNEJO BASTIAS SOCIEDAD GASTRONOMICA E.I.R.L | AF13: 23-12-2025 0:00:00 | AG13: 1 | AH13: 23-12-2025 0:00:00 | AI13: 23-12-2025 18:39:16 | AJ13: 30-06-2027 0:00:00 | AK13: 1 | AL13: 0 | AN13: 0 | AO13: 26200000 | AP13: 519030 | AQ13: 0 | AR13: 26719030 | AS13: 29490000 | AT13: 2770970 | AU13: 94
A14: IMPORTADORA TRENTO LTDA | B14: LOCAL PREMIUM CAR SALES | C14: 0 | D14: 0 | I14: 30-05-2026 13:15:09 | K14: LVPC52898 TCB00699 | L14: DFSK | M14: 600 | N14: 600 PHEV 4X2 1.5 AUT | O14: DF600PHEV4X215AT | P14: 2026 | Q14: 598 | R14: TDFSTWU000056 | S14: VRHP15 | T14: USADO | U14: GRIS CLARO | V14: POR DEFINIR | W14: 18990000 | X14: Disponible | Y14: 3 | Z14: EN PREPARACION | AA14: PREMIUM CAR SALES | AB14: AE,CC,EE,AAC,ABS,LL,VC,AISO,AAUTO,CRE,MAV,ACD,SR,U | AC14: F31A 125003402 | AD14: LVPC52898 TCB00699 | AE14: EMILIO ANDRES ORDENES ROJAS | AF14: 30-05-2026 0:00:00 | AG14: 1 | AH14: 30-05-2026 0:00:00 | AI14: 30-05-2026 13:12:38 | AK14: 1 | AL14: 0 | AN14: 0 | AO14: 16500000 | AP14: 0 | AQ14: 0 | AR14: 16500000 | AS14: 18990000 | AT14: 2490000 | AU14: 1311
A15: IMPORTADORA TRENTO LTDA | B15: LOCAL USADOS COPIAPO | C15: 0 | D15: 0 | I15: 30-05-2026 11:28:44 | K15: WF0AXXWPMHGY88472 | L15: FORD | M15: ESCAPE | N15: ESCAPE 4X4 2.0 AUT | O15: 01--ESCAUT1 | P15: 2018 | Q15: 66252 | R15: TFOSTWU001411 | S15: JXDK27 | T15: USADO | U15: NEGRO ABSOLUTO | V15: POR DEFINIR | W15: 10490000 | X15: Disponible | Y15: 3 | Z15: EN PREPARACION | AA15: BODEGA LOS CARRERA COPIAPO | AB15: AE,CC,EE,AAC,ABS,LL,VC,AISO,AAUTO,CRE,MAV,ACD,SR,U | AC15: HGY88472 | AD15: WF0AXXWPMHGY88472 | AE15: SUSAN CARMEN GLORIA HENRY HENRY | AF15: 30-05-2026 0:00:00 | AG15: 1 | AH15: 30-05-2026 0:00:00 | AI15: 30-05-2026 11:28:08 | AJ15: 31-10-2027 0:00:00 | AK15: 1 | AL15: 0 | AN15: 0 | AO15: 8600000 | AP15: 0 | AQ15: 0 | AR15: 8600000 | AS15: 10490000 | AT15: 1890000 | AU15: 1802
A16: IMPORTADORA TRENTO LTDA | B16: LOCAL PREMIUM CAR SALES | C16: 0 | D16: 0 | I16: 30-05-2026 11:49:56 | K16: 98867545CKKH86607 | L16: JEEP | M16: COMPASS | N16: ALL NEW COMPASS SPORT LX 2.4 | O16: CVN | P16: 2018 | Q16: 105000 | R16: TJESTWU000441 | S16: KSRT45 | T16: USADO | U16: PLATEADO | V16: POR DEFINIR | W16: 8990000 | X16: Disponible | Y16: 3 | Z16: EN PREPARACION | AA16: PREMIUM CAR SALES | AB16: AE,CC,EE,ABS,LL,AC,AISO,AAUTO,CRE,MAV,ACD,SR,DLL,6 | AC16: 0255313 | AD16: 98867545CKKH86607 | AE16: LAURA CECILIA FLORES ROJAS | AF16: 30-05-2026 0:00:00 | AG16: 1 | AH16: 30-05-2026 0:00:00 | AI16: 30-05-2026 11:48:50 | AJ16: 31-08-2026 0:00:00 | AK16: 3 | AL16: 0 | AN16: 0 | AO16: 7600000 | AP16: 0 | AQ16: 0 | AR16: 7600000 | AS16: 8990000 | AT16: 1390000 | AU16: 1546
A17: IMPORTADORA TRENTO LTDA | B17: LOCAL PREMIUM CAR SALES | C17: 0 | D17: 0 | I17: 18-02-2026 9:46:22 | K17: KNACP81EG P5055975 | L17: KIA MOTORS | M17: NIRO | N17: NIRO HEV DCT GDI 1.6 AUT | O17: KINIRO16AT | P17: 2024 | Q17: 43000 | R17: TKISTWU001335 | S17: THXP99 | T17: USADO | U17: BLANCO INVIERNO | V17: POR DEFINIR | W17: 19990000 | X17: Disponible | Y17: 104 | Z17: DISPONIBLE | AA17: PREMIUM CAR SALES | AB17: AE,CC,EE,AAC,ABS,LL,AISO,AAUTO,CRE,MAV,SR,DLL,6AB | AC17: G4LLNS082877 | AD17: KNACP81EG P5055975 | AE17: MARY CARMEN ALFARO AHUMADA | AF17: 18-02-2026 0:00:00 | AG17: 1 | AH17: 18-02-2026 0:00:00 | AI17: 18-02-2026 9:45:23 | AK17: 0 | AL17: 0 | AN17: 0 | AO17: 17750000 | AP17: 392280 | AQ17: 0 | AR17: 18142280 | AS17: 19990000 | AT17: 1847720 | AU17: 924
A18: IMPORTADORA TRENTO LTDA | B18: LOCAL USADOS COPIAPO | C18: 0 | D18: 0 | I18: 01-06-2026 17:30:09 | K18: MMBGJKR10NH010717 | L18: MITSUBISHI | M18: MONTERO | N18: MONTERO SPORT 2.4 | O18: KM7000 | P18: 2023 | Q18: 67096 | R18: TMISTWU000374 | S18: SDKF65 | T18: USADO | U18: BLANCO DIAMANTE | V18: POR DEFINIR | W18: 22990000 | X18: Disponible | Y18: 1 | Z18: EN PREPARACION | AA18: BODEGA LOS CARRERA COPIAPO | AB18: AE,CC,EE,ABS,LL,VC,AC,AISO,AAUTO,CRE,MAV,ACD,SR,UD | AC18: 4N15 UJD6131 | AD18: MMBGJKR10NH010717 | AE18: IBAR RODRIGO MANZANO REQUENA | AF18: 01-06-2026 0:00:00 | AG18: 1 | AH18: 01-06-2026 0:00:00 | AI18: 01-06-2026 17:29:47 | AK18: 1 | AL18: 0 | AN18: 0 | AO18: 18300000 | AP18: 0 | AQ18: 0 | AR18: 18300000 | AS18: 22990000 | AT18: 4690000 | AU18: 204
A19: IMPORTADORA TRENTO LTDA | B19: LOCAL PREMIUM CAR SALES | C19: 0 | D19: 0 | I19: 28-04-2026 10:56:17 | K19: ///***++///++*... | L19: VOLKSWAGEN | M19: SAVEIRO | N19: SAVEIRO CD 4X2 1.6 | O19: VOSAVECD16 | P19: 2024 | Q19: 31107 | R19: TVOCMTU000041 | S19: TFGS79 | T19: USADO | U19: BLANCO CANDY | V19: POR DEFINIR | W19: 11590000 | X19: Disponible | Y19: 35 | Z19: CON PRENDA | AA19: PREMIUM CAR SALES | AB19: AE,CC,EE,2AB,NB,ABS,LL,AC,AISO,AAUTO,ACD,UD,DLL | AC19: CWS 588198 | AD19: 9BWJL45U9 PP056766 | AE19: BARBARA ANDREINA CASTILLO MAVARES | AF19: 28-04-2026 0:00:00 | AG19: 1 | AH19: 28-04-2026 0:00:00 | AI19: 28-04-2026 10:53:19 | AK19: 1 | AL19: 0 | AN19: 0 | AO19: 9600000 | AP19: 273240 | AQ19: 0 | AR19: 9873240 | AS19: 11590000 | AT19: 1716760 | AU19: 1481
A20: IMPORTADORA TRENTO LTDA | B20: LOCAL PREMIUM CAR SALES | C20: 0 | D20: 0 | I20: 30-04-2026 17:13:00 | K20: 9BGJK7560LB180490 | L20: CHEVROLET | M20: SPIN | N20: SPIN 1.8 | O20: CHSPI18MT | P20: 2021 | Q20: 83079 | R20: TCHSTWU000321 | S20: PKZB80 | T20: USADO | U20: AZUL ATLANTICO | V20: POR DEFINIR | W20: 8990000 | X20: Disponible | Y20: 33 | Z20: DISPONIBLE | AA20: PREMIUM CAR SALES | AC20: JWJ001279 | AD20: 9BGJK7560LB180490 | AE20: ROBERTO EMILIO VILLABLANCA VERA | AF20: 30-04-2026 0:00:00 | AG20: 1 | AH20: 30-04-2026 0:00:00 | AI20: 30-04-2026 17:12:42 | AJ20: 28-02-2027 0:00:00 | AK20: 1 | AL20: 0 | AN20: 0 | AO20: 7100000 | AP20: 0 | AQ20: 0 | AR20: 7100000 | AS20: 8990000 | AT20: 1890000 | AU20: 2102
A21: IMPORTADORA TRENTO LTDA | B21: LOCAL PREMIUM CAR SALES | C21: 0 | D21: 0 | I21: 06-05-2026 18:05:59 | K21: //.//+*+///++*... | L21: MITSUBISHI | M21: OUTLANDER | N21: OUTLANDER GLS 4X4 2.5 AT | O21: NOI09 | P21: 2025 | Q21: 13500 | R21: TMISTWU000373 | S21: VDFP78 | T21: USADO | U21: GRIS GRAFITO | V21: POR DEFINIR | W21: 31590000 | X21: Disponible | Y21: 27 | Z21: EN PREPARACION | AA21: PREMIUM CAR SALES | AB21: AE,CC,EE,NB,AAC,ABS,LL,VC,AISO,AAUTO,CRE,MAV,ACD,S | AC21: PR25 573855F | AD21: JMYXTGM4WSZ002020 | AE21: LUIS GASTÓN ALCAYAGA NUÑEZ | AF21: 06-05-2026 0:00:00 | AG21: 1 | AH21: 06-05-2026 0:00:00 | AI21: 06-05-2026 18:05:30 | AK21: 1 | AL21: 0 | AN21: 0 | AO21: 26300000 | AP21: 523740 | AQ21: 0 | AR21: 26823740 | AS21: 31590000 | AT21: 4766260 | AU21: 1509
A22: IMPORTADORA TRENTO LTDA | B22: MEGACENTRO OVALLE | C22: 0 | D22: 0 | I22: 28-02-2026 16:17:28 | K22: 8AFBR01C4RJ372982 | L22: FORD | M22: RANGER | N22: RANGER XLT 4X4 2.0 | O22: FORANXLT4X420MT | P22: 2024 | Q22: 40100 | R22: TFOCMTU001156 | S22: THRJ79 | T22: USADO | U22: GRIS MERCURIO | V22: POR DEFINIR | W22: 28490000 | X22: Disponible | Y22: 94 | Z22: DISPONIBLE | AA22: BODEGA OVALLEveih | AC22: YN2X RJ372982 | AD22: 8AFBR01C4RJ372982 | AE22: HECTOR LIAZ CAYULEF HUICHICOY | AF22: 28-02-2026 0:00:00 | AG22: 1 | AH22: 28-02-2026 0:00:00 | AI22: 28-02-2026 16:16:52 | AK22: 0 | AL22: 0 | AN22: 0 | AO22: 24000000 | AP22: 877705 | AQ22: 0 | AR22: 24877705 | AS22: 28490000 | AT22: 3612295 | AU22: 1268
A23: IMPORTADORA TRENTO LTDA | B23: LOCAL USADOS | C23: 0 | D23: 0 | I23: 28-02-2026 11:42:29 | K23: 1FM5K8FH7KGA98168 | L23: FORD | M23: EXPLORER | N23: EXPLORER LTD 4X4 2.3 AUT | O23: EXPUS1 | P23: 2020 | Q23: 84600 | R23: TFOSTWU001401 | S23: LSZV62 | T23: USADO | U23: BLANCO METAL | V23: POR DEFINIR | W23: 22990000 | X23: Disponible | Y23: 94 | Z23: EN TALLER | AA23: BODEGA VEHICULOS | AC23: KGA98168 | AD23: 1FM5K8FH7KGA98168 | AE23: CLAUDIO VALENZUELA CELIS | AF23: 28-02-2026 0:00:00 | AG23: 1 | AH23: 28-02-2026 0:00:00 | AI23: 28-02-2026 11:42:08 | AK23: 0 | AL23: 0 | AN23: 0 | AO23: 17000000 | AP23: 381030 | AQ23: 0 | AR23: 17381030 | AS23: 22990000 | AT23: 5608970 | AU23: 244
A24: IMPORTADORA TRENTO LTDA | B24: MEGACENTRO OVALLE | C24: 0 | D24: 0 | I24: 07-05-2026 12:16:55 | K24: VF3MRHNSM RS002587 | L24: PEUGEOT | M24: 3008 | N24: 3008 PURETECH 1.2L | O24: 3P1L | P24: 2023 | Q24: 18500 | R24: TPESTWU000455 | S24: SVGL34 | T24: USADO | U24: BLANCO NACARADO | V24: POR DEFINIR | W24: 13690000 | X24: Disponible | Y24: 26 | Z24: EN PREPARACION | AA24: BODEGA OVALLEveih | AB24: AE,CC,EE,AAC,ABS,LL,VC,AISO,AAUTO,CRE,MAV,SR,DLL,6 | AC24: 10Z1AJ0024780 | AD24: VF3MRHNSM RS002587 | AE24: PABLO ALEJANDRO IGNACIO FIGUEROA TELLO | AF24: 07-05-2026 0:00:00 | AG24: 1 | AH24: 07-05-2026 0:00:00 | AI24: 07-05-2026 12:16:07 | AJ24: 31-07-2027 0:00:00 | AK24: 2 | AL24: 0 | AN24: 0 | AO24: 11200000 | AP24: 297240 | AQ24: 0 | AR24: 11497240 | AS24: 13690000 | AT24: 2192760 | AU24: 1602
A25: IMPORTADORA TRENTO LTDA | B25: LOCAL USADOS COPIAPO | C25: 0 | D25: 0 | I25: 30-04-2026 16:45:15 | K25: 9FBHSRA95LM023521 | L25: RENAULT | M25: RENAULT | N25: DUSTER ZEN 1.6 | O25: 124FG | P25: 2019 | Q25: 95000 | R25: TRESTWU000047 | S25: LPXF73 | T25: USADO | U25: GRIS ESTRELLA | V25: POR DEFINIR | W25: 7690000 | X25: Disponible | Y25: 33 | Z25: EN TALLER | AA25: BODEGA LOS CARRERA COPIAPO | AB25: AE,CC,EE,2AB,NB,ABS,LL,AC,AISO,MAV,SR,UD,DLL | AC25: K4M2842Q234165 | AD25: 9FBHSRA95LM023521 | AE25: MIRIAM ELIANA ROJAS PAEZ | AF25: 30-04-2026 0:00:00 | AG25: 1 | AH25: 30-04-2026 0:00:00 | AI25: 30-04-2026 16:43:05 | AJ25: 30-06-2026 0:00:00 | AK25: 1 | AL25: 0 | AN25: 0 | AO25: 5800000 | AP25: 0 | AQ25: 0 | AR25: 5800000 | AS25: 7690000 | AT25: 1890000 | AU25: 2458
A26: IMPORTADORA TRENTO LTDA | B26: LOCAL USADOS COPIAPO | C26: 0 | D26: 0 | I26: 28-01-2026 17:28:07 | K26: 1FMCU0BZ6NUB03562 | L26: FORD | M26: ESCAPE | N26: ESCAPE FHEV 2.5 AUT | O26: FOESFEHV20AT | P26: 2023 | Q26: 45000 | R26: TFOSTWU001396 | S26: SBLD74 | T26: USADO | U26: BLANCO METALICO | V26: POR DEFINIR | W26: 19990000 | X26: Disponible | Y26: 125 | Z26: DISPONIBLE | AA26: BODEGA LOS CARRERA COPIAPO | AB26: AE,CC,EE,AAC,ABS,LL,AISO,AAUTO,CRE,MAV,ACD,SR,UD,D | AC26: NUB03562 | AD26: 1FMCU0BZ6NUB03562 | AE26: SOCIEDAD COMERCIAL HERMANOS GODOY ARAYA SPA | AF26: 28-01-2026 0:00:00 | AG26: 1 | AH26: 28-01-2026 0:00:00 | AI26: 28-01-2026 17:22:31 | AK26: 1 | AL26: 0 | AN26: 0 | AO26: 17500000 | AP26: 388530 | AQ26: 0 | AR26: 17888530 | AS26: 19990000 | AT26: 2101470 | AU26: 1051
A27: IMPORTADORA TRENTO LTDA | B27: LOCAL USADOS COPIAPO | C27: 0 | D27: 0 | I27: 06-02-2026 23:32:37 | K27: 98859125B TKS03533 | L27: RAM | M27: RAM 1500 | N27: RAMPAGE DS LARAMIE 4X4 2.0 AUT | O27: RARAMCSLA4X420AT | P27: 2025 | Q27: 16869 | R27: TRACMTU000050 | S27: VFSF65 | T27: USADO | U27: PLATEADO PLATA BILLET | V27: POR DEFINIR | W27: 31590000 | X27: Disponible | Y27: 116 | Z27: DISPONIBLE | AA27: BODEGA LOS CARRERA COPIAPO | AB27: AE,CC,EE,AAC,ABS,LL,VC,AC,AISO,AAUTO,CRE,MAV,ACD,S | AC27: 463495081880130 | AD27: 98859125B TKS03533 | AE27: BERNARDO MAURICIO CORTES AVALOS | AF27: 06-02-2026 0:00:00 | AG27: 60226 | AH27: 06-02-2026 0:00:00 | AI27: 06-02-2026 23:31:06 | AK27: 0 | AL27: 0 | AN27: 0 | AO27: 29000000 | AP27: 561030 | AQ27: 0 | AR27: 29561030 | AS27: 31590000 | AT27: 2028970 | AU27: 642
A28: IMPORTADORA TRENTO LTDA | B28: LOCAL PREMIUM CAR SALES | C28: 0 | D28: 0 | I28: 28-02-2026 15:52:31 | K28: LVVDB21B7 SC004108 | L28: JAECOO | M28: 7 | N28: 7 DCT FWD 1.6 AUT | O28: JE7AWD16AT | P28: 2025 | Q28: 7500 | R28: TJAESTWU000003 | S28: VDWK12 | T28: USADO | U28: PLATEADO NEGRO | V28: POR DEFINIR | W28: 17490000 | X28: Disponible | Y28: 94 | Z28: DISPONIBLE | AA28: PREMIUM CAR SALES | AB28: AE,CC,EE,AAC,ABS,LL,AISO,ACP,AAUTO,CRE,MAV,ACD,SR, | AC28: SQRF4J16CAHRE00209 | AD28: LVVDB21B7 SC004108 | AE28: WILSON ELOY PIZARRO GERALDO | AF28: 28-02-2026 0:00:00 | AG28: 1 | AH28: 28-02-2026 0:00:00 | AI28: 28-02-2026 15:51:53 | AK28: 0 | AL28: 0 | AN28: 0 | AO28: 15500000 | AP28: 358530 | AQ28: 0 | AR28: 15858530 | AS28: 17490000 | AT28: 1631470 | AU28: 933
A29: IMPORTADORA TRENTO LTDA | B29: LOCAL PREMIUM CAR SALES | C29: 0 | D29: 0 | I29: 08-01-2026 15:20:40 | K29: LGXC74C40R0005634 | L29: BYD | M29: SONG PLUS DM-i | N29: SONG PLUS 4X2 1.5 AUT | O29: BYSONP15AT | P29: 2024 | Q29: 30000 | R29: TBYSTWU000006 | S29: TJDC55 | T29: USADO | U29: ROJO | V29: POR DEFINIR | W29: 20990000 | X29: Disponible | Y29: 145 | Z29: DISPONIBLE | AA29: PREMIUM CAR SALES | AB29: AE,CC,EE,AAC,ABS,LL,AISO,AAUTO,CRE,MAV,SR,UD,DLL,6 | AC29: BYD472QA S23333377 | AD29: LGXC74C40R0005634 | AE29: EMILIO ANDRES ORDENES ROJAS | AF29: 08-01-2026 0:00:00 | AG29: 1 | AH29: 08-01-2026 0:00:00 | AI29: 08-01-2026 15:16:26 | AK29: 1 | AL29: 0 | AN29: 0 | AO29: 20000000 | AP29: 524003 | AQ29: 0 | AR29: 20524003 | AS29: 20990000 | AT29: 465997 | AU29: 222
A30: IMPORTADORA TRENTO LTDA | B30: LOCAL USADOS | C30: 0 | D30: 0 | I30: 17-02-2022 15:53:19 | K30: VF3M45GZWJS004469 | L30: PEUGEOT | M30: 3008 | N30: 3008 ALLURE 1.6 AT | O30: PALL7 | P30: 2018 | Q30: 120000 | R30: TPESTWU000279 | S30: JXGC32 | T30: USADO | U30: GRIS HURRICANE | V30: POR DEFINIR | W30: 14390000 | X30: Disponible | Y30: 1566 | Z30: EN TALLER | AA30: BODEGA VEHICULOS | AB30: AE,CC,EE,2AB,NB,AAC,ABS,LL,TC,VC,4AB,ESP,CT,SS,AIS | AC30: 10FJCC2346652 | AD30: VF3M45GZWJS004469 | AE30: OSCAR ARMANDO PIZARRO BEMBOW | AF30: 17-02-2022 0:00:00 | AG30: 1 | AH30: 29-04-2022 19:24:00 | AI30: 29-04-2022 19:24:00 | AK30: 0 | AL30: 0 | AN30: 0 | AO30: 17650000 | AP30: 753678 | AQ30: 0 | AR30: 18403678 | AS30: 14390000 | AT30: -4013678 | AU30: -2789
A31: IMPORTADORA TRENTO LTDA | B31: LOCAL PREMIUM CAR SALES | C31: 0 | D31: 0 | I31: 14-03-2023 10:52:12 | K31: 2FMPK4J94KBB16022 | L31: FORD | M31: EDGE | N31: EDGE SEL 4X4 2.0 AUT | O31: EDD900 | P31: 2020 | Q31: 55000 | R31: TFOSTWU001240 | S31: PCDV84 | T31: USADO | U31: GRIS METALICO | V31: POR DEFINIR | W31: 18490000 | X31: Disponible | Y31: 1176 | Z31: EN TALLER | AA31: PREMIUM CAR SALES | AB31: AE,CC,EE,NB,AAC,ABS,LL,TC,VC,ESP,CT,SS,AISO,ACP,AA | AC31: KBB16022 | AD31: 2FMPK4J94KBB16022 | AE31: BARBARA YEIME CEA URRIAGA | AF31: 14-03-2023 0:00:00 | AG31: 1 | AH31: 14-03-2023 0:00:00 | AI31: 14-03-2023 10:51:51 | AK31: 0 | AL31: 0 | AN31: 0 | AO31: 18000000 | AP31: 673380 | AQ31: 0 | AR31: 18673380 | AS31: 18490000 | AT31: -183380 | AU31: -99
A32: IMPORTADORA TRENTO LTDA | B32: LOCAL USADOS COPIAPO | C32: 0 | D32: 0 | I32: 22-01-2026 12:55:07 | K32: KNARH81BHR5259144 | L32: KIA MOTORS | M32: SORENTO | N32: SORENTO 8DCT 4WD 2.2 AUT | O32: KISO4WD2.2AT | P32: 2024 | Q32: 37000 | R32: TKISTWU001330 | S32: TRBJ23 | T32: USADO | U32: GRIS ACERO | V32: POR DEFINIR | W32: 33490000 | X32: Disponible | Y32: 131 | Z32: DISPONIBLE | AA32: BODEGA LOS CARRERA COPIAPO | AB32: AE,CC,EE,AAC,ABS,LL,TC,VC,AISO,AAUTO,CRE,MAV,ACD,S | AC32: D4HEPH357028 | AD32: KNARH81BHR5259144 | AE32: OPERACIONES JORGE ALEJANDRO VARAS VARAS E.I.R.L | AF32: 22-01-2026 0:00:00 | AG32: 1 | AH32: 22-01-2026 0:00:00 | AI32: 22-01-2026 12:54:40 | AK32: 1 | AL32: 0 | AN32: 0 | AO32: 28000000 | AP32: 1142194 | AQ32: 0 | AR32: 29142194 | AS32: 33490000 | AT32: 4347806 | AU32: 1298
A33: IMPORTADORA TRENTO LTDA | B33: LOCAL PREMIUM CAR SALES | C33: 0 | D33: 0 | I33: 06-04-2026 15:27:31 | K33: LPE19W2A6TF007924 | L33: BYD | M33: SHARK DMO | N33: SHARK 1.5 AUT | O33: BYDSHA15AT | P33: 2025 | Q33: 20000 | R33: TBYCMTU000001 | S33: TGVF52 | T33: USADO | U33: BLANCO | V33: POR DEFINIR | W33: 36990000 | X33: Disponible | Y33: 57 | Z33: CON PRENDA | AA33: PREMIUM CAR SALES | AB33: AE,CC,EE,NB,AAC,ABS,LL,TC,AISO,AAUTO,CRE,ACD,SR,UD | AC33: BYD476ZQFT25007008 | AD33: LPE19W2A6TF007924 | AE33: SEGURIDAD PRIVADA Y ASEO INDUSTRIAL GUILLERMO DE JESUS NEIRA ARAYA SPA . . | AF33: 06-04-2026 0:00:00 | AG33: 1 | AH33: 06-04-2026 0:00:00 | AI33: 06-04-2026 15:26:56 | AK33: 1 | AL33: 0 | AN33: 0 | AO33: 31627180 | AP33: 603648 | AQ33: 0 | AR33: 32230828 | AS33: 36990000 | AT33: 4759172 | AU33: 1287
A34: IMPORTADORA TRENTO LTDA | B34: LOCAL USADOS COPIAPO | C34: 0 | D34: 0 | I34: 30-04-2026 10:10:05 | K34: MALGT41DASM115787 | L34: HYUNDAI | M34: HYUNDAI | N34: ACCENT 1.5 | O34: 20--ACC90 | P34: 2025 | Q34: 7193 | R34: THYAUTU000585 | S34: TTXB96 | T34: USADO | U34: GRIS GRAFITO | V34: POR DEFINIR | W34: 12890000 | X34: Disponible | Y34: 33 | Z34: CON PRENDA | AA34: BODEGA LOS CARRERA COPIAPO | AB34: AE,CC,EE,AAC,ABS,LL,VC,AISO,AAUTO,CRE,MAV,ACD,SR,U | AC34: G4FLRQ356179 | AD34: MALGT41DASM115787 | AE34: JESSICA DEL CARMEN CHILLA CAMPILLAY | AF34: 30-04-2026 0:00:00 | AG34: 1 | AH34: 30-04-2026 0:00:00 | AI34: 30-04-2026 10:07:04 | AK34: 1 | AL34: 0 | AN34: 0 | AO34: 10350000 | AP34: 284490 | AQ34: 0 | AR34: 10634490 | AS34: 12890000 | AT34: 2255510 | AU34: 175
A35: IMPORTADORA TRENTO LTDA | B35: LOCAL PREMIUM CAR SALES | C35: 0 | D35: 0 | I35: 06-04-2026 11:44:19 | K35: 1FTFW1E50 MFA34669 | L35: FORD | M35: F-150 | N35: F150 LARIAT LUXURY 4X4 5.0L AUT | O35: F150AUT | P35: 2021 | Q35: 47500 | R35: TFOCMTU001159 | S35: PSTV42 | T35: USADO | U35: ROJO METALICO | V35: POR DEFINIR | W35: 31990000 | X35: Disponible | Y35: 57 | Z35: EN TALLER | AA35: PREMIUM CAR SALES | AB35: AE,CC,EE,NB,AAC,ABS,LL,TC,VC,AISO,ACP,AAUTO,CRE,MA | AC35: MFA34669 | AD35: 1FTFW1E50 MFA34669 | AE35: FREDDY ORLANDO ARIAS CHOQUE | AF35: 06-04-2026 0:00:00 | AG35: 1 | AH35: 06-04-2026 0:00:00 | AI35: 06-04-2026 11:43:26 | AJ35: 31-05-2026 0:00:00 | AK35: 1 | AL35: 0 | AN35: 0 | AO35: 20000000 | AP35: 429240 | AQ35: 0 | AR35: 20429240 | AS35: 31990000 | AT35: 11560760 | AU35: 3614
A36: IMPORTADORA TRENTO LTDA | B36: LOCAL PREMIUM CAR SALES | C36: 0 | D36: 0 | I36: 24-09-2025 17:50:46 | K36: 8AFBR01K1 RJ394381 | L36: FORD | M36: RANGER | N36: RANGER LTD 4X4 3.0 AUT | O36: RANGERDEV | P36: 2024 | Q36: 69690 | R36: TFOCMTU001136 | S36: TJSK30 | T36: USADO | U36: GRIS MERCURIO | V36: POR DEFINIR | W36: 34990000 | X36: Disponible | Y36: 251 | Z36: DISPONIBLE | AA36: PREMIUM CAR SALES | AB36: AE,CC,EE,AAC,ABS,LL,VC,AISO,AAUTO,CRE,MAV,ACD,SR,U | AC36: BF2X RJ394381 | AD36: 8AFBR01K1 RJ394381 | AE36: DRILLING SERVICES AND SOLUTIONS SPA | AF36: 24-09-2025 0:00:00 | AG36: 1 | AH36: 24-09-2025 0:00:00 | AI36: 24-09-2025 17:50:08 | AK36: 1 | AL36: 0 | AN36: 0 | AO36: 34000000 | AP36: 1178778 | AQ36: 0 | AR36: 35178778 | AS36: 34990000 | AT36: -188778 | AU36: -54
A37: IMPORTADORA TRENTO LTDA | B37: MEGACENTRO OVALLE | C37: 0 | D37: 0 | I37: 02-01-2026 15:09:11 | K37: VF3M45GZWJS004343 | L37: PEUGEOT | M37: 3008 | N37: 3008 ACTIVE 1.6 | O37: P7R9 | P37: 2018 | Q37: 95984 | R37: TPESTWU000443 | S37: JYBF33 | T37: USADO | U37: ROJO ULTIMATE | V37: POR DEFINIR | W37: 10490000 | X37: Disponible | Y37: 151 | Z37: EN TALLER | AA37: BODEGA OVALLEveih | AB37: AE,CC,EE,ABS,LL,VC,AC,AISO,AAUTO,CRE,MAV,ACD,SR,UD | AC37: 10FJCC2344377 | AD37: VF3M45GZWJS004343 | AE37: mario lagunas | AF37: 02-01-2026 0:00:00 | AG37: 1 | AH37: 10-03-2026 22:23:00 | AI37: 10-03-2026 22:23:00 | AJ37: 30-06-2026 0:00:00 | AK37: 1 | AL37: 0 | AN37: 0 | AO37: 8800000 | AP37: 258030 | AQ37: 0 | AR37: 9058030 | AS37: 10490000 | AT37: 1431970 | AU37: 1365
A38: IMPORTADORA TRENTO LTDA | B38: LOCAL USADOS COPIAPO | C38: 0 | D38: 0 | I38: 22-10-2025 9:20:00 | K38: LVVDB11B7 MD082945 | L38: CHERY | M38: TIGGO 3 | N38: TIGGO 3 1.5 | O38: T315 | P38: 2021 | Q38: 40095 | R38: TCYSTWU000320 | S38: RBZD91 | T38: USADO | U38: AZUL METALIZADO | V38: POR DEFINIR | W38: 8190000 | X38: Disponible | Y38: 223 | Z38: EN RESCILIACION | AA38: BODEGA LOS CARRERA COPIAPO | AB38: AE,CC,EE,ABS,LL,4AB,AC,AISO,AAUTO,CRE,ACD,SR,UD,DL | AC38: SQRE4G15BATMC00062 | AD38: LVVDB11B7 MD082945 | AE38: MILENKA SUSANA NEGRON CABALLERO | AF38: 22-10-2025 0:00:00 | AG38: 1 | AH38: 22-10-2025 0:00:00 | AI38: 22-10-2025 9:19:18 | AJ38: 30-04-2026 0:00:00 | AK38: 1 | AL38: 0 | AN38: 0 | AO38: 6200000 | AP38: 219030 | AQ38: 0 | AR38: 6419030 | AS38: 8190000 | AT38: 1770970 | AU38: 2162
A39: IMPORTADORA TRENTO LTDA | B39: LOCAL PREMIUM CAR SALES | C39: 0 | D39: 0 | I39: 02-05-2022 18:10:07 | K39: VF3MCYHZRLS003227 | L39: PEUGEOT | M39: 3008 | N39: 3008 BLUE HDI HP 1.5 AUT | O39: PCM10 | P39: 2020 | Q39: 31000 | R39: TPESTWU000283 | S39: LVCS57 | T39: USADO | U39: BLANCO NACARADO | V39: POR DEFINIR | W39: 14990000 | X39: Disponible | Y39: 1492 | Z39: EN TALLER | AA39: PREMIUM CAR SALES | AB39: AE,CC,EE,NB,ABS,LL,AC,AISO,AAUTO,CRE,ACD,SR,DLL,6A | AC39: 10Q3BC0371833 | AD39: VF3MCYHZRLS003227 | AE39: PRUDENCIA LEONELLY VALDIVIA PLAZA | AF39: 02-05-2022 0:00:00 | AG39: 1 | AH39: 26-02-2025 17:20:00 | AI39: 26-02-2025 17:20:00 | AK39: 0 | AL39: 0 | AN39: 7 | AO39: 20000000 | AP39: 1051072 | AQ39: 0 | AR39: 21051072 | AS39: 14990000 | AT39: -6061072 | AU39: -4043
A40: IMPORTADORA TRENTO LTDA | B40: LOCAL PDI | C40: 0 | D40: 0 | I40: 14-08-2018 18:36:12 | K40: KNABE511AET622431 | L40: KIA MOTORS | M40: MORNING | N40: MORNING LX 1.0 | O40: 17--1416E4 | P40: 2014 | Q40: 50000 | R40: TKIAUTU001659 | S40: FZPL81 | T40: USADO | U40: ROJO SIGNAL | V40: POR DEFINIR | W40: 4390000 | X40: Disponible | Y40: 2849 | Z40: VEHICULO EMPRESA | AA40: BODEGA PDI | AC40: G3LADP101529 | AD40: KNABE511AET622431 | AE40: JUAN CARLOS MORALES GODOY | AF40: 14-08-2018 0:00:00 | AG40: 0 | AK40: 0 | AL40: 0 | AN40: 1 | AO40: 0 | AP40: 1812732 | AQ40: 0 | AR40: 1812732 | AS40: 4390000 | AT40: 2577268 | AU40: 5871
A41: IMPORTADORA TRENTO LTDA | B41: LOCAL PREMIUM CAR SALES | C41: 0 | D41: 0 | I41: 07-11-2023 9:03:21 | K41: 1FMJK1HT4GEF47400 | L41: FORD | M41: EXPEDITION | N41: EXPEDITION XLT 3.5 AUT | O41: RT7777 | P41: 2017 | Q41: 107300 | R41: TFOSTWU001266 | S41: JGFD64 | T41: USADO | U41: NEGRO PROFUNDO | V41: POR DEFINIR | W41: 15290000 | X41: Disponible | Y41: 938 | Z41: DISPONIBLE | AA41: PREMIUM CAR SALES | AB41: AE,CC,EE,2AB,NB,ABS,LL,VC,4AB,ESP,AC,AISO,AAUTO,CR | AC41: GEF47400 | AD41: 1FMJK1HT4GEF47400 | AE41: JEAN PAUL GALLEGOS ARRAÑO | AF41: 07-11-2023 0:00:00 | AG41: 1 | AH41: 29-12-2023 18:16:00 | AI41: 29-12-2023 18:16:00 | AK41: 0 | AL41: 0 | AN41: 0 | AO41: 18000000 | AP41: 961786 | AQ41: 0 | AR41: 18961786 | AS41: 15290000 | AT41: -3671786 | AU41: -2401
A42: IMPORTADORA TRENTO LTDA | B42: LOCAL PREMIUM CAR SALES | C42: 0 | D42: 0 | I42: 23-10-2025 13:59:01 | K42: /////+*+///++*... | L42: CHEVROLET | M42: SILVERADO | N42: SILVERADO CC LTZ 4X4 3.0 AUT | O42: SIL4X4 | P42: 2023 | Q42: 44495 | R42: TCHCMTU000483 | S42: SJDW14 | T42: USADO | U42: NEGRO | V42: POR DEFINIR | W42: 49990000 | X42: Disponible | Y42: 222 | Z42: DISPONIBLE | AA42: PREMIUM CAR SALES | AC42: LM2 TNG625504 | AD42: 3GCUD9ET6 NG625504 | AE42: IMPORTADORA TRENTO LTDA | AF42: 23-10-2025 0:00:00 | AG42: 1 | AH42: 20-11-2025 0:00:00 | AI42: 20-11-2025 19:37:03 | AK42: 4 | AL42: 0 | AN42: 0 | AO42: 48000000 | AP42: 846030 | AQ42: 0 | AR42: 48846030 | AS42: 49990000 | AT42: 1143970 | AU42: 229
A43: IMPORTADORA TRENTO LTDA | B43: MEGACENTRO OVALLE | C43: 0 | D43: 0 | I43: 22-04-2026 17:42:39 | K43: KMHJB81DB RU268314 | L43: HYUNDAI | M43: HYUNDAI | N43: TUCSON NX4 2.0 AUT | O43: HT01 | P43: 2024 | Q43: 25840 | R43: THYSTWU000553 | S43: SZTF51 | T43: USADO | U43: NEGRO | V43: POR DEFINIR | W43: 19990000 | X43: Disponible | Y43: 41 | Z43: DISPONIBLE | AA43: BODEGA OVALLEveih | AB43: AE,CC,EE,AAC,ABS,LL,AISO,AAUTO,CRE,MAV,ACD,SR,UD,D | AC43: G4NLPU935907 | AD43: KMHJB81DB RU268314 | AE43: SAMUEL ALEJANDRO PULGAR LOPEZ | AF43: 22-04-2026 0:00:00 | AG43: 1 | AH43: 22-04-2026 0:00:00 | AI43: 22-04-2026 17:42:12 | AK43: 1 | AL43: 0 | AN43: 0 | AO43: 17200000 | AP43: 387240 | AQ43: 0 | AR43: 17587240 | AS43: 19990000 | AT43: 2402760 | AU43: 1202
A44: IMPORTADORA TRENTO LTDA | B44: LOCAL PREMIUM CAR SALES | C44: 0 | D44: 0 | I44: 06-05-2026 18:11:52 | K44: 1FMCU9JZ4PUA50384 | L44: FORD | M44: ESCAPE | N44: ESCAPE FHEV 2.5 AUT | O44: FOESFEHV20AT | P44: 2024 | Q44: 52000 | R44: TFOSTWU001410 | S44: TJSK11 | T44: USADO | U44: AZUL ATLAS | V44: POR DEFINIR | W44: 23590000 | X44: Disponible | Y44: 27 | Z44: EN TALLER | AA44: PREMIUM CAR SALES | AB44: AE,CC,EE,AAC,ABS,LL,VC,SS,AISO,ACP,AAUTO,CRE,MAV,A | AC44: PUA50384 | AD44: 1FMCU9JZ4PUA50384 | AE44: RAUL LUIS ARQUEROS ARANCIBIA | AF44: 06-05-2026 0:00:00 | AG44: 1 | AH44: 06-05-2026 0:00:00 | AI44: 06-05-2026 18:11:32 | AK44: 1 | AL44: 0 | AN44: 0 | AO44: 18900000 | AP44: 412740 | AQ44: 0 | AR44: 19312740 | AS44: 23590000 | AT44: 4277260 | AU44: 1813
A45: IMPORTADORA TRENTO LTDA | B45: LOCAL USADOS COPIAPO | C45: 0 | D45: 0 | I45: 06-04-2026 11:01:03 | K45: JS3TD04V3K4101439 | L45: SUZUKI | M45: GRAND NOMADE | N45: GRAND NOMADE GLX 2.4 AUT | O45: SZGRANNOGLX24AT | P45: 2019 | Q45: 63000 | R45: TSZSTWU000469 | S45: LBVT54 | T45: USADO | U45: NEGRO | V45: POR DEFINIR | W45: 11990000 | X45: Disponible | Y45: 57 | Z45: DISPONIBLE | AA45: BODEGA LOS CARRERA COPIAPO | AB45: AE,CC,EE,ABS,LL,AC,AISO,AAUTO,CRE,MAV,ACD,UD,DLL | AC45: J24B-1339542 | AD45: JS3TD04V3K4101439 | AE45: JENNIFER JOHANNA TAPIA AGUILERA | AF45: 06-04-2026 0:00:00 | AG45: 1 | AH45: 06-04-2026 0:00:00 | AI45: 06-04-2026 11:00:30 | AK45: 1 | AL45: 0 | AN45: 0 | AO45: 9100000 | AP45: 265740 | AQ45: 0 | AR45: 9365740 | AS45: 11990000 | AT45: 2624260 | AU45: 2189
A46: IMPORTADORA TRENTO LTDA | B46: LOCAL USADOS COPIAPO | C46: 0 | D46: 0 | I46: 01-06-2026 17:51:47 | K46: LS4ASJ2E2NA986230 | L46: CHANGAN | M46: CHANGAN | N46: CX70 T 1.5 AUT | P46: 2022 | Q46: 75000 | R46: TCGSTWU000033 | S46: RXCG78 | T46: USADO | U46: BLANCO | V46: POR DEFINIR | W46: 9490000 | X46: Disponible | Y46: 1 | Z46: EN PREPARACION | AA46: BODEGA LOS CARRERA COPIAPO | AB46: AE,CC,EE,NB,ABS,LL,4AB,AC,AISO,AAUTO,CRE,MAV,ACD,S | AC46: JL476ZQCCMCRB001989 | AD46: LS4ASJ2E2NA986230 | AE46: ISMAEL ENRIQUE OLIVARES RAMOS | AF46: 01-06-2026 0:00:00 | AG46: 1 | AH46: 01-06-2026 0:00:00 | AI46: 01-06-2026 17:36:46 | AK46: 1 | AL46: 0 | AN46: 0 | AO46: 7100000 | AP46: 0 | AQ46: 0 | AR46: 7100000 | AS46: 9490000 | AT46: 2390000 | AU46: 2518
A47: IMPORTADORA TRENTO LTDA | B47: LOCAL PREMIUM CAR SALES | C47: 0 | D47: 0 | I47: 06-04-2026 18:13:21 | K47: 1FTFW1E52 PFB48046 | L47: FORD | M47: F-150 | N47: F150 XLT 4X4 5.0L AUT | O47: F11111 | P47: 2024 | Q47: 13800 | R47: TFOCMTU001160 | S47: TKHS25 | T47: USADO | U47: BLANCO OXFORD | V47: POR DEFINIR | W47: 36490000 | X47: Disponible | Y47: 57 | Z47: DISPONIBLE | AA47: PREMIUM CAR SALES | AB47: AE,CC,EE,NB,AAC,ABS,LL,TC,VC,SS,AISO,ACP,AAUTO,CRE | AC47: PFB48046 | AD47: 1FTFW1E52 PFB48046 | AE47: TIERNA DAFNE KENDALL VASQUEZ | AF47: 06-04-2026 0:00:00 | AG47: 1 | AH47: 06-04-2026 0:00:00 | AI47: 06-04-2026 18:11:36 | AK47: 1 | AL47: 0 | AN47: 0 | AO47: 31300000 | AP47: 598740 | AQ47: 0 | AR47: 31898740 | AS47: 36490000 | AT47: 4591260 | AU47: 1258
A48: IMPORTADORA TRENTO LTDA | B48: LOCAL SALAMANCA | C48: 0 | D48: 0 | I48: 16-05-2026 13:31:20 | K48: /////+/+///++*.*. | L48: JAC | M48: JS4 | N48: JS4 LUXURY HB 1.5 | O48: JAJS4LUX15MT | P48: 2024 | Q48: 8249 | R48: TJASTWU000025 | S48: TDKL17 | T48: USADO | U48: ROJO | V48: POR DEFINIR | W48: 10490000 | X48: Disponible | Y48: 17 | Z48: DISPONIBLE | AA48: BODEGA VEHICULOS | AB48: AE,CC,EE,AAC,ABS,LL,AISO,AAUTO,CRE,MAV,SR,UD,DLL,6 | AC48: R3305832 | AD48: LJ12EKS31S4700355 | AE48: ANDREA CAROLINA VILCHES ABARCA | AF48: 16-05-2026 0:00:00 | AG48: 1 | AH48: 16-05-2026 0:00:00 | AI48: 16-05-2026 13:29:04 | AK48: 1 | AL48: 0 | AN48: 0 | AO48: 8500000 | AP48: 0 | AQ48: 0 | AR48: 8500000 | AS48: 10490000 | AT48: 1990000 | AU48: 1897
A49: IMPORTADORA TRENTO LTDA | B49: LOCAL PREMIUM CAR SALES | C49: 0 | D49: 0 | I49: 30-05-2025 23:11:48 | K49: /////+++++****... | L49: NISSAN | M49: QASHQAI | N49: QASHQAI TURBO 1.3 | O49: ASTR77 | P49: 2023 | Q49: 45836 | R49: TNISTWU000581 | S49: SXTX58 | T49: USADO | U49: GRIS METALICO | V49: POR DEFINIR | W49: 17290000 | X49: Disponible | Y49: 368 | Z49: DISPONIBLE | AA49: PREMIUM CAR SALES | AB49: AE,CC,EE,2AB,ABS,LL,VC,AC,AISO,AAUTO,CRE,SR,UD,DLL | AC49: HR13510927A | AD49: SJNTAAJ12PA169942 | AE49: RODRIGO ANDRES LEDESMA RITCHIE | AF49: 30-05-2025 0:00:00 | AG49: 1 | AH49: 30-05-2025 0:00:00 | AI49: 30-05-2025 23:10:29 | AK49: 1 | AL49: 0 | AN49: 0 | AO49: 17500000 | AP49: 598467 | AQ49: 0 | AR49: 18098467 | AS49: 17290000 | AT49: -808467 | AU49: -468
A50: IMPORTADORA TRENTO LTDA | B50: LOCAL PREMIUM CAR SALES | C50: 0 | D50: 0 | I50: 07-01-2026 10:30:07 | K50: MPBAR2F18 PX515886 | L50: FORD | M50: RANGER | N50: RANGER RAPTOR 4X4 3.0 AT | O50: FORNGRP30AT | P50: 2024 | Q50: 30900 | R50: TFOCMTU001149 | S50: TFDC75 | T50: USADO | U50: NARANJO NARANJA TIERRA | V50: POR DEFINIR | W50: 43990000 | X50: Disponible | Y50: 146 | Z50: DISPONIBLE | AA50: PREMIUM CAR SALES | AB50: AE,CC,EE,NB,AAC,ABS,LL,VC,AISO,AAUTO,CRE,MAV,ACD,S | AC50: DD2XPX515886 | AD50: MPBAR2F18 PX515886 | AE50: SERVICIOS ASEO AMC SPA | AF50: 07-01-2026 0:00:00 | AG50: 1 | AH50: 07-01-2026 0:00:00 | AI50: 09-04-2026 10:27:26 | AK50: 1 | AL50: 0 | AN50: 0 | AO50: 39300000 | AP50: 718740 | AQ50: 0 | AR50: 40018740 | AS50: 43990000 | AT50: 3971260 | AU50: 903
A51: IMPORTADORA TRENTO LTDA | B51: LOCAL USADOS COPIAPO | C51: 0 | D51: 0 | I51: 02-01-2026 16:34:09 | K51: KPTE0A1YS PP010412 | L51: SSANGYONG | M51: TORRES | N51: TORRES 4X2 1.5 | O51: SSTO4X215MT | P51: 2024 | Q51: 35150 | R51: TSYSTWU000339 | S51: TLRS70 | T51: USADO | U51: AZUL METALICO | V51: POR DEFINIR | W51: 18690000 | X51: Disponible | Y51: 151 | Z51: DISPONIBLE | AA51: BODEGA LOS CARRERA COPIAPO | AB51: AE,CC,EE,NB,AAC,ABS,LL,VC,AISO,AAUTO,CRE,MAV,ACD,S | AC51: 17595000015783 | AD51: KPTE0A1YS PP010412 | AE51: GONZALO ANTONIO DELGADO COFRÉ | AF51: 02-01-2026 0:00:00 | AG51: 1 | AH51: 02-01-2026 0:00:00 | AI51: 02-01-2026 16:33:28 | AK51: 1 | AL51: 0 | AN51: 0 | AO51: 16400000 | AP51: 372030 | AQ51: 0 | AR51: 16772030 | AS51: 18690000 | AT51: 1917970 | AU51: 1026
A52: IMPORTADORA TRENTO LTDA | B52: LOCAL USADOS COPIAPO | C52: 0 | D52: 0 | I52: 24-04-2026 18:17:03 | K52: KNAPV81DB P7090666 | L52: KIA MOTORS | M52: SPORTAGE | N52: SPORTAGE EX 2.0 AUT | O52: TY100 | P52: 2023 | Q52: 43000 | R52: TKISTWU001339 | S52: SDKG61 | T52: USADO | U52: GRIS ACERO | V52: POR DEFINIR | W52: 19990000 | X52: Disponible | Y52: 39 | Z52: CON PRENDA | AA52: BODEGA LOS CARRERA COPIAPO | AB52: AE,CC,EE,AAC,ABS,LL,VC,AISO,AAUTO,CRE,MAV,ACD,SR,U | AC52: G4NLMH010969 | AD52: KNAPV81DB P7090666 | AE52: ATALIA NAZARET QUINTEROS CORTES | AF52: 24-04-2026 0:00:00 | AG52: 1 | AH52: 24-04-2026 0:00:00 | AI52: 24-04-2026 18:16:25 | AJ52: 30-04-2028 0:00:00 | AK52: 1 | AL52: 0 | AN52: 0 | AO52: 17000000 | AP52: 384240 | AQ52: 0 | AR52: 17384240 | AS52: 19990000 | AT52: 2605760 | AU52: 1304
A53: IMPORTADORA TRENTO LTDA | B53: LOCAL PREMIUM CAR SALES | C53: 0 | D53: 0 | I53: 18-02-2026 10:03:09 | K53: ///-*/*-.+-*/.+// | L53: RAM | M53: RAM 1500 | N53: 1500 REBEL CREW DCAB 4X4 5.7 AUT | O53: RA1500REBDC4X457AT | P53: 2022 | Q53: 72237 | R53: TRACMTU000051 | S53: RXYT46 | T53: USADO | U53: NEGRO METALICO | V53: POR DEFINIR | W53: 35990000 | X53: Disponible | Y53: 104 | Z53: DISPONIBLE | AA53: PREMIUM CAR SALES | AC53: NN224561 | AD53: 1C6SRFLT6NN224561 | AE53: SERVICIOS A LA MINERIA OMINT SPA | AF53: 18-02-2026 0:00:00 | AG53: 1 | AH53: 18-02-2026 0:00:00 | AI53: 18-02-2026 10:02:46 | AK53: 0 | AL53: 0 | AN53: 0 | AO53: 30400000 | AP53: 582030 | AQ53: 0 | AR53: 30982030 | AS53: 35990000 | AT53: 5007970 | AU53: 1391
A54: IMPORTADORA TRENTO LTDA | B54: LOCAL PREMIUM CAR SALES | C54: 0 | D54: 0 | I54: 07-05-2026 12:06:20 | K54: LVTDB11B9ND037466 | L54: CHERY | M54: TIGGO 8 | N54: TIGGO 8 1.5 | O54: TIIII8 | P54: 2022 | Q54: 30000 | R54: TCYSTWU000353 | S54: RSJD48 | T54: USADO | U54: AZUL OSCURO | V54: POR DEFINIR | W54: 11490000 | X54: Disponible | Y54: 26 | Z54: EN PREPARACION | AA54: PREMIUM CAR SALES | AB54: AE,CC,EE,ABS,LL,4AB,AC,AISO,AAUTO,CRE,MAV,ACD,SR,U | AC54: SQRE4T15BALML00187 | AD54: LVTDB11B9ND037466 | AE54: ANGEL ANTONIO YEPEZ RASSE | AF54: 07-05-2026 0:00:00 | AG54: 1 | AH54: 07-05-2026 0:00:00 | AI54: 07-05-2026 12:02:35 | AK54: 1 | AL54: 0 | AN54: 0 | AO54: 9500000 | AP54: 271740 | AQ54: 0 | AR54: 9771740 | AS54: 11490000 | AT54: 1718260 | AU54: 1495
A55: IMPORTADORA TRENTO LTDA | B55: LOCAL USADOS COPIAPO | C55: 0 | D55: 0 | I55: 15-07-2025 13:46:05 | K55: KPT60A1USMP040811 | L55: SSANGYONG | M55: KORANDO | N55: NEW KORANDO 1.6 | O55: NK80 | P55: 2021 | Q55: 75000 | R55: TSYSTWU000337 | S55: PKBJ31 | T55: USADO | U55: BLANCO | V55: POR DEFINIR | W55: 12990000 | X55: Disponible | Y55: 322 | Z55: EN TALLER | AA55: BODEGA LOS CARRERA COPIAPO | AB55: AE,CC,EE,ABS,LL,VC,4AB,AC,AISO,AAUTO,CRE,SR,DLL | AC55: 67391002105133 | AD55: KPT60A1USMP040811 | AE55: CAROLINA MARICELA PIZARRO CASTRO | AF55: 15-07-2025 0:00:00 | AG55: 1 | AH55: 15-07-2025 0:00:00 | AI55: 15-07-2025 13:45:17 | AJ55: 30-04-2026 0:00:00 | AK55: 2 | AL55: 0 | AN55: 0 | AO55: 11000000 | AP55: 443877 | AQ55: 0 | AR55: 11443877 | AS55: 12990000 | AT55: 1546123 | AU55: 119
A56: IMPORTADORA TRENTO LTDA | B56: LOCAL PREMIUM CAR SALES | C56: 0 | D56: 0 | I56: 18-03-2026 18:56:36 | K56: 8AFAR22Z9PJ320092 | L56: FORD | M56: RANGER | N56: RANGER XLT 2.5 | O56: 01--TFOCMTU216 | P56: 2023 | Q56: 70000 | R56: TFOCMTU001157 | S56: RVKK81 | T56: USADO | U56: BLANCO | V56: POR DEFINIR | W56: 17990000 | X56: Disponible | Y56: 76 | Z56: DISPONIBLE | AA56: PREMIUM CAR SALES | AB56: AE,CC,EE,AAC,ABS,LL,VC,AISO,AAUTO,CRE,MAV,ACD,SR,D | AC56: EV2S PJ320092 | AD56: 8AFAR22Z9PJ320092 | AE56: EVENTOS GUAYACAN SPA | AF56: 18-03-2026 0:00:00 | AG56: 1 | AH56: 18-03-2026 0:00:00 | AI56: 18-03-2026 18:56:05 | AJ56: 30-04-2026 0:00:00 | AK56: 1 | AL56: 0 | AN56: 0 | AO56: 14500000 | AP56: 343530 | AQ56: 0 | AR56: 14843530 | AS56: 17990000 | AT56: 3146470 | AU56: 1749
A57: IMPORTADORA TRENTO LTDA | B57: LOCAL USADOS COPIAPO | C57: 0 | D57: 0 | I57: 30-04-2026 16:15:08 | K57: LGWEE4A59PK600630 | L57: HAVAL | M57: JOLION | N57: JOLION TURBO DCT 1.5 AUT | O57: HAJOL15AT | P57: 2022 | Q57: 58239 | R57: THASTWU000023 | S57: RSTC22 | T57: USADO | U57: ROJO | V57: POR DEFINIR | W57: 12490000 | X57: Disponible | Y57: 33 | Z57: DISPONIBLE | AA57: BODEGA LOS CARRERA COPIAPO | AB57: AE,CC,EE,AAC,ABS,LL,VC,AISO,AAUTO,CRE,MAV,ACD,SR,U | AC57: GW4G15K21499027556 | AD57: LGWEE4A59PK600630 | AE57: MARIA JOSE CASTILLO ARAYA | AF57: 30-04-2026 0:00:00 | AG57: 1 | AH57: 30-04-2026 0:00:00 | AI57: 30-04-2026 16:09:10 | AK57: 1 | AL57: 0 | AN57: 0 | AO57: 10100000 | AP57: 280740 | AQ57: 0 | AR57: 10380740 | AS57: 12490000 | AT57: 2109260 | AU57: 1689
A58: IMPORTADORA TRENTO LTDA | B58: LOCAL PREMIUM CAR SALES | C58: 0 | D58: 0 | I58: 06-04-2026 12:02:41 | K58: LVVDB21B5SC004219 | L58: JAECOO | M58: 7 | N58: 7 DCT FWD 1.6 AUT | O58: JE7AWD16AT | P58: 2026 | Q58: 6400 | R58: TJAESTWU000004 | S58: VJTS35 | T58: USADO | U58: GRIS ARTEMIS | V58: POR DEFINIR | W58: 16490000 | X58: Disponible | Y58: 57 | Z58: DISPONIBLE | AA58: PREMIUM CAR SALES | AB58: AE,CC,EE,AAC,ABS,LL,TC,AISO,AAUTO,CRE,MAV,ACD,SR,U | AC58: SQRF4J16CAHRE00160 | AD58: LVVDB21B5 SC004219 | AE58: JOSE LUIS ALE DAIRE CALLEGARI | AF58: 06-04-2026 0:00:00 | AG58: 1 | AH58: 06-04-2026 0:00:00 | AI58: 06-04-2026 12:01:30 | AK58: 1 | AL58: 0 | AN58: 0 | AO58: 14500000 | AP58: 346740 | AQ58: 0 | AR58: 14846740 | AS58: 16490000 | AT58: 1643260 | AU58: 997
A59: IMPORTADORA TRENTO LTDA | B59: LOCAL PDI | C59: 0 | D59: 0 | I59: 03-01-2017 1:36:33 | K59: KNCSJX76AF7939699 | L59: KIA MOTORS | M59: FRONTIER | N59: FRONTIER C/C 2.5 6MT | O59: 17--1336 | P59: 2016 | Q59: 0 | R59: TKICMTN000002 | S59: HKVZ15 | T59: USADO | U59: BLANCO INVIERNO | V59: NO DEFINIDO | W59: 14800000 | X59: Disponible | Y59: 3858 | Z59: VEHICULO EMPRESA | AA59: BODEGA PDI | AC59: D4CBF677399 | AD59: KNCSJX76AF7939699 | AE59: SERVICIOS DE INGENIERIA Y MINERIA SPA | AF59: 09-11-2015 0:00:00 | AG59: 23832 | AH59: 10-11-2015 0:00:00 | AI59: 12-11-2020 15:42:13 | AJ59: 09-11-2015 0:00:00 | AK59: 0 | AL59: 0 | AN59: 0 | AO59: 323597 | AP59: 3165631 | AQ59: 0 | AR59: 3489228 | AS59: 14800000 | AT59: 11310772 | AU59: 7642
A60: IMPORTADORA TRENTO LTDA | B60: LOCAL SALAMANCA | C60: 0 | D60: 0 | I60: 30-04-2026 15:19:16 | K60: LVVDB21B4 SC023313 | L60: CHERY | M60: TIGGO 3 PRO | N60: TIGGO 3 PRO GLS 1.5 AUT | O60: CHTIG3PRGLS15AT | P60: 2026 | Q60: 22255 | R60: TCYSTWU000352 | S60: VKCY97 | T60: USADO | U60: GRIS PLATA | V60: POR DEFINIR | W60: 11690000 | X60: Disponible | Y60: 33 | Z60: DISPONIBLE | AA60: BODEGA VEHICULOS | AC60: SQRE4G15CBDRL00035 | AD60: LVVDB21B4 SC023313 | AE60: RUTH ESTER OSSANDON NARBONA | AF60: 30-04-2026 0:00:00 | AG60: 1 | AH60: 30-04-2026 0:00:00 | AI60: 30-04-2026 15:17:56 | AK60: 1 | AL60: 0 | AN60: 0 | AO60: 10000000 | AP60: 279240 | AQ60: 0 | AR60: 10279240 | AS60: 11690000 | AT60: 1410760 | AU60: 1207
A61: IMPORTADORA TRENTO LTDA | B61: LOCAL PREMIUM CAR SALES | C61: 0 | D61: 0 | I61: 01-04-2026 18:18:58 | K61: VF3MCYHZUSL001353 | L61: PEUGEOT | M61: 5008 | N61: 5008 BLUEHDI 130 1.5 AUT | O61: 5008BH130 | P61: 2025 | Q61: 20000 | R61: TPESTWU000451 | S61: TSZC89 | T61: USADO | U61: BLANCO NACARADO | V61: POR DEFINIR | W61: 26990000 | X61: Disponible | Y61: 62 | Z61: DISPONIBLE | AA61: PREMIUM CAR SALES | AB61: AE,CC,EE,AAC,ABS,LL,VC,AISO,ACP,AAUTO,CRE,MAV,ACD, | AC61: 10Q3EJ1989595 | AD61: VF3MCYHZUSL001353 | AE61: CAMILA MONSERRAT COLLAO CASTILLO | AF61: 01-04-2026 0:00:00 | AG61: 1 | AH61: 01-04-2026 0:00:00 | AI61: 01-04-2026 18:18:30 | AK61: 1 | AL61: 0 | AN61: 0 | AO61: 23500000 | AP61: 481740 | AQ61: 0 | AR61: 23981740 | AS61: 26990000 | AT61: 3008260 | AU61: 1115
A62: IMPORTADORA TRENTO LTDA | B62: LOCAL PREMIUM CAR SALES | C62: 0 | D62: 0 | I62: 13-05-2026 12:22:14 | K62: LVTDB21B7PD021629 | L62: EXEED BORN FOR MORE | M62: LX | N62: LX ADVANCED 1.5 AUT | O62: EXLXADV15AT | P62: 2024 | Q62: 43000 | R62: TEXESTWU000005 | S62: SZTL17 | T62: USADO | U62: GRIS PHANTOM | V62: POR DEFINIR | W62: 13790000 | X62: Disponible | Y62: 20 | Z62: EN PREPARACION | AA62: PREMIUM CAR SALES | AC62: SQRE4T15CAPNE00204 | AD62: LVTDB21B7PD021629 | AE62: ELIANA DEL CARMEN GONZÁLEZ ARAYA | AF62: 13-05-2026 0:00:00 | AG62: 1 | AH62: 13-05-2026 0:00:00 | AI62: 13-05-2026 12:21:23 | AK62: 1 | AL62: 0 | AN62: 0 | AO62: 11300000 | AP62: 0 | AQ62: 0 | AR62: 11300000 | AS62: 13790000 | AT62: 2490000 | AU62: 1806
A63: IMPORTADORA TRENTO LTDA | B63: LOCAL PREMIUM CAR SALES | C63: 0 | D63: 0 | I63: 03-10-2025 18:06:52 | K63: ////////******++. | L63: HYUNDAI | M63: HYUNDAI | N63: SANTA FE MX5 GDI 4X4 2.5 AUT | O63: HYSTF4X425AT | P63: 2025 | Q63: 17000 | R63: THYSTWU000544 | S63: TTVD23 | T63: USADO | U63: PLATEADO PLATA | V63: POR DEFINIR | W63: 32990000 | X63: Disponible | Y63: 242 | Z63: DISPONIBLE | AA63: PREMIUM CAR SALES | AB63: AE,CC,EE,ABS,LL,VC,AC,AISO,CRE,MAV,ACD,SR,DLL,6AB, | AC63: G4KNRA851884 | AD63: KMHP281JD RU030971 | AE63: RODOLFO ANDRES SALGADO MARILEO | AF63: 03-10-2025 0:00:00 | AG63: 1 | AH63: 03-10-2025 0:00:00 | AI63: 03-10-2025 18:06:12 | AK63: 2 | AL63: 0 | AN63: 0 | AO63: 28700000 | AP63: 1053703 | AQ63: 0 | AR63: 29753703 | AS63: 32990000 | AT63: 3236297 | AU63: 981
A64: IMPORTADORA TRENTO LTDA | B64: MEGACENTRO OVALLE | C64: 0 | D64: 0 | I64: 22-05-2026 18:40:31 | K64: /////+++**+++*... | L64: SUZUKI | M64: BALENO | N64: BALENO 4X2 1.5 AUT | O64: SZBAL4X215AT | P64: 2024 | Q64: 22000 | R64: TSZAUTU000460 | S64: TJYK56 | T64: USADO | U64: AZUL MARINO | V64: POR DEFINIR | W64: 12490000 | X64: Disponible | Y64: 11 | Z64: EN PREPARACION | AA64: BODEGA OVALLEveih | AB64: AE,CC,EE,2AB,NB,ABS,LL,AC,AISO,AAUTO,MAV,ACD,SR,UD | AC64: K15BN1459791 | AD64: MBHWBA3S3SG662957 | AE64: MAURICIO ARIEL OSSANDON ARAYA | AF64: 22-05-2026 0:00:00 | AG64: 1 | AH64: 22-05-2026 0:00:00 | AI64: 22-05-2026 18:40:05 | AK64: 1 | AL64: 0 | AN64: 0 | AO64: 10300000 | AP64: 0 | AQ64: 0 | AR64: 10300000 | AS64: 12490000 | AT64: 2190000 | AU64: 1753
A65: IMPORTADORA TRENTO LTDA | B65: LOCAL USADOS COPIAPO | C65: 0 | D65: 0 | I65: 15-03-2022 11:58:49 | K65: KPTG0B1TSFP339581 | L65: SSANGYONG | M65: REXTON | N65: REXTON 2.0 | O65: 05--12345678 | P65: 2015 | Q65: 169000 | R65: TSYSTWU000306 | S65: GLRH21 | T65: USADO | U65: NEGRO | V65: POR DEFINIR | W65: 8490000 | X65: Disponible | Y65: 1540 | Z65: NO DISPONIBLE | AA65: BODEGA LOS CARRERA COPIAPO | AB65: AE,CC,2AB,NB,ABS,AC,AISO,CRE,MAV | AC65: 67196010530787 | AD65: KPTG0B1TSFP339581 | AE65: ALEJANDRA DEL CARMEN URTUBIA MENDIETA | AF65: 15-03-2022 0:00:00 | AG65: 1 | AH65: 15-03-2022 0:00:00 | AI65: 15-03-2022 11:58:28 | AK65: 0 | AL65: 0 | AN65: 0 | AO65: 10500000 | AP65: 461694 | AQ65: 0 | AR65: 10961694 | AS65: 8490000 | AT65: -2471694 | AU65: -2911
A66: IMPORTADORA TRENTO LTDA | B66: MEGACENTRO OVALLE | C66: 0 | D66: 0 | I66: 30-04-2026 10:49:34 | K66: LVZA53P93 PAA16703 | L66: DFSK | M66: 560 | N66: SUV 560 4X2 1.8 | O66: DF56018MT | P66: 2023 | Q66: 31487 | R66: TDFSTWU000055 | S66: STBT82 | T66: USADO | U66: GRIS CLARO | V66: POR DEFINIR | W66: 8990000 | X66: Disponible | Y66: 33 | Z66: CON PRENDA | AA66: BODEGA OVALLEveih | AC66: SFG18-22372086 | AD66: LVZA53P93 PAA16703 | AE66: MARIA JOSE SOLEDAD MOROSO NAVEA | AF66: 30-04-2026 0:00:00 | AG66: 1 | AH66: 30-04-2026 0:00:00 | AI66: 30-04-2026 10:41:13 | AK66: 3 | AL66: 0 | AN66: 0 | AO66: 7300000 | AP66: 0 | AQ66: 0 | AR66: 7300000 | AS66: 8990000 | AT66: 1690000 | AU66: 188
A67: IMPORTADORA TRENTO LTDA | B67: LOCAL PREMIUM CAR SALES | C67: 0 | D67: 0 | I67: 01-04-2026 12:48:10 | K67: 1GNSK7KC8 KR384750 | L67: CHEVROLET | M67: TAHOE | N67: TAHOE 4X4 5.3 AUT | O67: CHTAH4X453AT | P67: 2020 | Q67: 85300 | R67: TCHSTWU000319 | S67: PDBT76 | T67: USADO | U67: GRIS METALICO | V67: POR DEFINIR | W67: 28990000 | X67: Disponible | Y67: 62 | Z67: DISPONIBLE | AA67: PREMIUM CAR SALES | AB67: AE,CC,EE,AAC,ABS,LL,TC,VC,AISO,AAUTO,CRE,MAV,ACD,S | AC67: CKR384750 | AD67: 1GNSK7KC8 KR384750 | AE67: RAUL EDUARDO HUERTA DIAZ | AF67: 01-04-2026 0:00:00 | AG67: 1 | AH67: 01-04-2026 0:00:00 | AI67: 01-04-2026 12:45:35 | AJ67: 30-09-2026 0:00:00 | AK67: 3 | AL67: 0 | AN67: 0 | AO67: 24500000 | AP67: 496740 | AQ67: 0 | AR67: 24996740 | AS67: 28990000 | AT67: 3993260 | AU67: 1377
A68: IMPORTADORA TRENTO LTDA | B68: LOCAL SALAMANCA | C68: 0 | D68: 0 | I68: 02-10-2025 17:10:39 | K68: 9V8FF4HY1RA800991 | L68: PEUGEOT | M68: LANDTREK | N68: LANDTREK BLUEHDI 4X4 2.2 AUT | O68: PELANHDI4X422AT | P68: 2025 | Q68: 5800 | R68: TPECMTU000016 | S68: TSSB38 | T68: USADO | U68: GRIS ALUMINIUM | V68: POR DEFINIR | W68: 20990000 | X68: Disponible | Y68: 243 | Z68: DISPONIBLE | AA68: BODEGA VEHICULOS | AB68: AE,CC,EE,AAC,ABS,LL,VC,AISO,AAUTO,CRE,MAV,ACD,SR,U | AC68: 10VRAC4002861 | AD68: 9V8FF4HY1RA800991 | AE68: JONATHAN JAVIER LARA BARRAZA | AF68: 02-10-2025 0:00:00 | AG68: 1 | AH68: 02-10-2025 0:00:00 | AI68: 02-10-2025 17:09:54 | AK68: 1 | AL68: 0 | AN68: 0 | AO68: 27929100 | AP68: 918614 | AQ68: 0 | AR68: 28847714 | AS68: 20990000 | AT68: -7857714 | AU68: -3744
A69: IMPORTADORA TRENTO LTDA | B69: LOCAL USADOS COPIAPO | C69: 0 | D69: 0 | I69: 05-02-2026 13:13:22 | K69: JN1JAAT33PW000133 | L69: NISSAN | M69: XTRAIL | N69: X TRAIL 4X2 7P CVT 2.5 | O69: XXTT22 | P69: 2024 | Q69: 19000 | R69: TNISTWU000607 | S69: SXHW25 | T69: USADO | U69: BLANCO PERLA | V69: POR DEFINIR | W69: 21490000 | X69: Disponible | Y69: 117 | Z69: DISPONIBLE | AA69: BODEGA LOS CARRERA COPIAPO | AB69: AE,CC,EE,AAC,ABS,LL,VC,AISO,AAUTO,CRE,MAV,ACD,SR,U | AC69: PR25206464F | AD69: JN1JAAT33PW000133 | AE69: ROXANA DE LOURDES VALLE GALLEGUILLOS | AF69: 05-02-2026 0:00:00 | AG69: 1 | AH69: 05-02-2026 0:00:00 | AI69: 05-02-2026 13:12:44 | AK69: 1 | AL69: 0 | AN69: 0 | AO69: 18500000 | AP69: 689954 | AQ69: 0 | AR69: 19189954 | AS69: 21490000 | AT69: 2300046 | AU69: 107
A70: IMPORTADORA TRENTO LTDA | B70: LOCAL PREMIUM CAR SALES | C70: 0 | D70: 0 | I70: 22-05-2026 17:42:59 | K70: VR3USHNSK SJ500220 | L70: PEUGEOT | M70: 2008 | N70: 2008 ACTIVE 130 1.2 | O70: PE2008ACT12MT | P70: 2025 | Q70: 22000 | R70: TPESTWU000456 | S70: TSYY69 | T70: USADO | U70: BLANCO OKENITE | V70: POR DEFINIR | W70: 14990000 | X70: Disponible | Y70: 11 | Z70: EN PREPARACION | AA70: PREMIUM CAR SALES | AB70: AE,CC,EE,AAC,ABS,LL,AISO,AAUTO,CRE,MAV,ACD,SR,UD,D | AC70: 10Z1AC0194696 | AD70: VR3USHNSK SJ500220 | AE70: FRANCISCA DANIELA JADRANKA NEIRA VUSKOVIC | AF70: 22-05-2026 0:00:00 | AG70: 1 | AH70: 22-05-2026 0:00:00 | AI70: 22-05-2026 17:42:16 | AK70: 1 | AL70: 0 | AN70: 0 | AO70: 12246151 | AP70: 0 | AQ70: 0 | AR70: 12246151 | AS70: 14990000 | AT70: 2743849 | AU70: 183
A71: IMPORTADORA TRENTO LTDA | B71: LOCAL PREMIUM CAR SALES | C71: 0 | D71: 0 | I71: 13-05-2026 13:08:12 | K71: /////++++//++*... | L71: GREAT WALL | M71: POER | N71: POER 4X2 MT 2.0 | O71: GWPOER4X2MT20 | P71: 2024 | Q71: 19000 | R71: TGWCMTU000019 | S71: TPJF75 | T71: USADO | U71: PLATEADO PLATA | V71: POR DEFINIR | W71: 16490000 | X71: Disponible | Y71: 20 | Z71: EN PREPARACION | AA71: PREMIUM CAR SALES | AB71: AE,CC,EE,AAC,ABS,LL,VC,AISO,AAUTO,CRE,MAV,ACD,SR,U | AC71: GW4D20M23597131983 | AD71: LGWCCF190 RJ615909 | AE71: SERVICIO AUTOMOTRIZ MARIO EDINSON TAPIA RIVEROS EIRL . . | AF71: 13-05-2026 0:00:00 | AG71: 1 | AH71: 13-05-2026 0:00:00 | AI71: 13-05-2026 13:07:32 | AK71: 1 | AL71: 0 | AN71: 0 | AO71: 13500000 | AP71: 0 | AQ71: 0 | AR71: 13500000 | AS71: 16490000 | AT71: 2990000 | AU71: 1813
A72: IMPORTADORA TRENTO LTDA | B72: LOCAL USADOS COPIAPO | C72: 0 | D72: 0 | I72: 03-08-2022 14:52:06 | K72: ***//*.+********* | L72: NISSAN | M72: JUKE | N72: JUKE 1.6 AUT | O72: 22--010 | P72: 2015 | Q72: 96083 | R72: TNISTWU000449 | S72: HHYB74 | T72: USADO | U72: BLANCO PERLA | V72: POR DEFINIR | W72: 9890000 | X72: Disponible | Y72: 71 | Z72: DISPONIBLE | AA72: BODEGA LOS CARRERA COPIAPO | AC72: HR16411356R | AD72: SJNFBAF15GA090279 | AE72: SERGIO H OLIVARES ORTIZ Y CIA LTDA | AF72: 23-03-2026 0:00:00 | AG72: 1 | AH72: 03-08-2022 0:00:00 | AI72: 30-03-2026 8:51:48 | AK72: 0 | AL72: 0 | AN72: 0 | AO72: 9300000 | AP72: 1603570 | AQ72: 0 | AR72: 10903570 | AS72: 9890000 | AT72: -1013570 | AU72: -1025
A73: IMPORTADORA TRENTO LTDA | B73: LOCAL USADOS COPIAPO | C73: 0 | D73: 0 | I73: 28-04-2026 13:25:38 | K73: LVVDD21B9RC025336 | L73: JAECOO | M73: 7 | N73: 7 DCT 1.6 AUT | O73: JA716ATSUMMIT | P73: 2025 | Q73: 12000 | R73: TJAESTWU000006 | S73: VGPT64 | T73: USADO | U73: BLANCO AURA | V73: POR DEFINIR | W73: 20990000 | X73: Disponible | Y73: 35 | Z73: CON PRENDA | AA73: BODEGA LOS CARRERA COPIAPO | AB73: AE,CC,EE,NB,AAC,ABS,LL,VC,AISO,AAUTO,CRE,MAV,ACD,S | AC73: SQRF4J16CAMRA00471 | AD73: LVVDD21B9RC025336 | AE73: TRANSPORTE DOBLE C SPA | AF73: 28-04-2026 0:00:00 | AG73: 1 | AH73: 28-04-2026 0:00:00 | AI73: 28-04-2026 13:24:50 | AK73: 2 | AL73: 0 | AN73: 0 | AO73: 17500000 | AP73: 391740 | AQ73: 0 | AR73: 17891740 | AS73: 20990000 | AT73: 3098260 | AU73: 1476
A74: IMPORTADORA TRENTO LTDA | B74: LOCAL USADOS | C74: 0 | D74: 0 | I74: 10-11-2025 18:59:30 | K74: //.//+++/+/++*... | L74: JAECOO | M74: 7 | N74: 7 DCT FWD 1.6 AUT | O74: JE7AWD16AT | P74: 2025 | Q74: 10200 | R74: TJAESTWU000001 | S74: TYFD45 | T74: USADO | U74: ROJO NEGRO RUBI | V74: POR DEFINIR | W74: 16490000 | X74: Disponible | Y74: 204 | Z74: EN RESCILIACION | AA74: BODEGA VEHICULOS | AB74: AE,CC,EE,AAC,ABS,LL,AISO,AAUTO,CRE,MAV,ACD,SR,UD,D | AC74: SQRF4J16CAMPM02301 | AD74: LVVDB21B5 RC012704 | AE74: LEONARDO JORGE ESTEBAN BOLTON MONTALVA | AF74: 10-11-2025 0:00:00 | AG74: 1 | AH74: 10-11-2025 0:00:00 | AI74: 10-11-2025 18:58:34 | AK74: 1 | AL74: 0 | AN74: 0 | AO74: 15500000 | AP74: 358530 | AQ74: 0 | AR74: 15858530 | AS74: 16490000 | AT74: 631470 | AU74: 383
A75: IMPORTADORA TRENTO LTDA | B75: LOCAL USADOS COPIAPO | C75: 0 | D75: 0 | I75: 18-03-2026 11:24:08 | K75: JMYXTGM4W NZ000993 | L75: MITSUBISHI | M75: OUTLANDER | N75: OUTLANDER GL 2.5 AUT | O75: MIOUTGL25AT | P75: 2023 | Q75: 44000 | R75: TMISTWU000370 | S75: SLWH28 | T75: USADO | U75: AZUL METALICO | V75: POR DEFINIR | W75: 18190000 | X75: Disponible | Y75: 76 | Z75: CON PRENDA | AA75: BODEGA LOS CARRERA COPIAPO | AB75: AE,CC,EE,AAC,ABS,LL,VC,AISO,AAUTO,CRE,MAV,ACD,SR,U | AC75: PR25 251342 | AD75: JMYXTGM4W NZ000993 | AE75: DANIELA ALEJANDRA DONAIRE FREDES | AF75: 18-03-2026 0:00:00 | AG75: 1 | AH75: 18-03-2026 0:00:00 | AI75: 18-03-2026 11:23:40 | AJ75: 30-11-2027 0:00:00 | AK75: 1 | AL75: 0 | AN75: 0 | AO75: 15200000 | AP75: 354030 | AQ75: 0 | AR75: 15554030 | AS75: 18190000 | AT75: 2635970 | AU75: 1449
A76: IMPORTADORA TRENTO LTDA | B76: LOCAL USADOS | C76: 0 | D76: 0 | I76: 20-03-2020 12:53:54 | K76: KNAPB811BE7498300 | L76: KIA MOTORS | M76: SPORTAGE | N76: SPORTAGE LX 4X4 2.0 AUT | O76: 17--0120 | P76: 2014 | Q76: 83000 | R76: TKISTWU001135 | S76: FWLT41 | T76: USADO | U76: ROJO ORANGE | V76: POR DEFINIR | W76: 8490000 | X76: Disponible | Y76: 2265 | Z76: USO GERENCIA | AA76: BODEGA VEHICULOS | AC76: G4KDDH424564 | AD76: KNAPB811BE7498300 | AE76: IMPORTADORA TRENTO LTDA | AF76: 20-03-2020 0:00:00 | AG76: 1 | AH76: 13-04-2020 0:00:00 | AI76: 13-04-2020 10:05:55 | AK76: 0 | AL76: 0 | AN76: 0 | AO76: 0 | AP76: 2523835 | AQ76: 0 | AR76: 2523835 | AS76: 8490000 | AT76: 5966165 | AU76: 7027
A77: IMPORTADORA TRENTO LTDA | B77: LOCAL PREMIUM CAR SALES | C77: 0 | D77: 0 | I77: 29-04-2026 14:50:28 | K77: JM7DM2W7AS0309501 | L77: MAZDA | M77: CX-30 | N77: CX30 4X2 2.0 AUT | O77: MACX3020AT | P77: 2025 | Q77: 39700 | R77: TMASTWU000106 | S77: VBWR52 | T77: USADO | U77: AZUL OSCURO METALIZADO | V77: POR DEFINIR | W77: 21990000 | X77: Disponible | Y77: 34 | Z77: CON PRENDA | AA77: PREMIUM CAR SALES | AB77: AE,CC,EE,AAC,ABS,LL,VC,AISO,ACP,AAUTO,CRE,MAV,ACD, | AC77: PE 22028517 | AD77: JM7DM2W7AS0309501 | AE77: COMPAÑÍA DE ASISTENCIA MEDICA DOMICILIARIA A INSTITUCIONES PÚBL | AF77: 29-04-2026 0:00:00 | AG77: 1 | AH77: 29-04-2026 0:00:00 | AI77: 29-04-2026 14:49:51 | AK77: 1 | AL77: 0 | AN77: 0 | AO77: 18300000 | AP77: 403740 | AQ77: 0 | AR77: 18703740 | AS77: 21990000 | AT77: 3286260 | AU77: 1494
A78: IMPORTADORA TRENTO LTDA | B78: MEGACENTRO OVALLE | C78: 0 | D78: 0 | I78: 30-05-2026 11:41:55 | K78: LVVDB11B9ND032419 | L78: CHERY | M78: TIGGO 3 | N78: TIGGO 3 1.5 | O78: T315 | P78: 2022 | Q78: 94076 | R78: TCYSTWU000355 | S78: RPZK49 | T78: USADO | U78: GRIS PLATA | V78: POR DEFINIR | W78: 7990000 | X78: Disponible | Y78: 3 | Z78: EN PREPARACION | AA78: BODEGA OVALLEveih | AB78: AE,CC,EE,2AB,ABS,LL,AC,AISO,AAUTO,MAV,ACD,SR,UD,DL | AC78: SQRE4G15BATMJ01319 | AD78: LVVDB11B9ND032419 | AE78: MARCELO ALEJANDRO CARVAJAL BUGUEÑO | AF78: 30-05-2026 0:00:00 | AG78: 1 | AH78: 30-05-2026 0:00:00 | AI78: 30-05-2026 11:41:07 | AJ78: 31-01-2027 0:00:00 | AK78: 1 | AL78: 0 | AN78: 0 | AO78: 6450000 | AP78: 0 | AQ78: 0 | AR78: 6450000 | AS78: 7990000 | AT78: 1540000 | AU78: 1927
A79: IMPORTADORA TRENTO LTDA | B79: LOCAL USADOS | C79: 0 | D79: 0 | I79: 04-03-2025 17:16:08 | K79: LVVDB21B8SD022028 | L79: OMODA | M79: C5 | N79: C5 1.5 AUT | O79: OMC515AT | P79: 2025 | Q79: 1905 | R79: TOMOSTWU000003 | S79: TSSG86 | T79: USADO | U79: BLANCO | V79: POR DEFINIR | W79: 11290000 | X79: Disponible | Y79: 455 | Z79: EN TALLER | AA79: BODEGA VEHICULOS | AB79: AE,CC,EE,NB,AAC,ABS,LL,AISO,AAUTO,CRE,MAV,ACD,UD,G | AC79: SQRE4T15CCHRD00089 | AD79: LVVDB21B8SD022028 | AE79: ANDREA ALEJANDRA LIBERON LIBERON | AF79: 04-03-2025 0:00:00 | AG79: 1 | AH79: 04-03-2025 0:00:00 | AI79: 04-03-2025 17:00:37 | AK79: 1 | AL79: 0 | AN79: 0 | AO79: 10300000 | AP79: 280530 | AQ79: 0 | AR79: 10580530 | AS79: 11290000 | AT79: 709470 | AU79: 628
A80: IMPORTADORA TRENTO LTDA | B80: LOCAL USADOS | C80: 0 | D80: 0 | I80: 04-02-2026 12:44:44 | K80: 3N1AB7AE8LY202955 | L80: NISSAN | M80: SENTRA | N80: SENTRA 1.8 AT | O80: NISEN18AT | P80: 2020 | Q80: 96000 | R80: TNIAUTU000649 | S80: PDBJ62 | T80: USADO | U80: BLANCO PERLA | V80: POR DEFINIR | W80: 10990000 | X80: Disponible | Y80: 118 | Z80: DISPONIBLE | AA80: BODEGA VEHICULOS | AB80: AE,CC,EE,NB,ABS,LL,4AB,AC,AISO,AAUTO,ACD,DLL | AC80: MRA8720448J | AD80: 3N1AB7AE8LY202955 | AE80: RUPERTO ALEJANDRO GALLEGOS GUTIERREZ | AF80: 04-02-2026 0:00:00 | AG80: 1 | AH80: 04-02-2026 0:00:00 | AI80: 04-02-2026 12:43:25 | AJ80: 31-05-2026 0:00:00 | AK80: 4 | AL80: 0 | AN80: 0 | AO80: 8500000 | AP80: 253530 | AQ80: 0 | AR80: 8753530 | AS80: 10990000 | AT80: 2236470 | AU80: 2035
A81: IMPORTADORA TRENTO LTDA | B81: LOCAL PREMIUM CAR SALES | C81: 0 | D81: 0 | I81: 30-10-2025 18:48:57 | K81: 1FTFW1RGXKFC93274 | L81: FORD | M81: F-150 | N81: F150 RAPTOR 4X4 3.5 AUT | O81: FRK7 | P81: 2020 | Q81: 80000 | R81: TFOCMTU001138 | S81: LYPC19 | T81: USADO | U81: BLANCO OXFORD | V81: POR DEFINIR | W81: 45990000 | X81: Disponible | Y81: 215 | Z81: DISPONIBLE | AA81: PREMIUM CAR SALES | AB81: AE,CC,EE,AAC,ABS,LL,TC,VC,SS,AISO,AAUTO,CRE,MAV,AC | AC81: KFC93274 | AD81: 1FTFW1RGXKFC93274 | AE81: ARRIAGADA DIAZ MANUEL ANTONIO Y PINTO OÑATE MARIA BELEN LTDA | AF81: 30-10-2025 0:00:00 | AG81: 1 | AH81: 31-03-2026 10:59:00 | AI81: 31-03-2026 10:59:00 | AJ81: 31-01-2026 0:00:00 | AK81: 2 | AL81: 0 | AN81: 0 | AO81: 37200000 | AP81: 684030 | AQ81: 0 | AR81: 37884030 | AS81: 45990000 | AT81: 8105970 | AU81: 1763
A82: IMPORTADORA TRENTO LTDA | B82: LOCAL PREMIUM CAR SALES | C82: 0 | D82: 0 | I82: 18-05-2026 12:54:42 | K82: LVZZU3P96SCB03062 | L82: DFSK | M82: 500 | N82: 500 1.5 CVT | O82: US500 | P82: 2025 | Q82: 6443 | R82: TDFAUTU000002 | S82: VFTG62 | T82: USADO | U82: BLANCO | V82: POR DEFINIR | W82: 11290000 | X82: Disponible | Y82: 15 | Z82: EN TALLER | AA82: PREMIUM CAR SALES | AB82: AE,CC,EE,ABS,LL,AC,AISO,AAUTO,CRE,MAV,ACD,SR,UD,DL | AC82: SFG15A 24402834 | AD82: LVZZU3P96SCB03062 | AE82: JOSE MIGUEL NUÑEZ ALVARADO | AF82: 18-05-2026 0:00:00 | AG82: 1 | AH82: 18-05-2026 0:00:00 | AI82: 18-05-2026 12:54:06 | AK82: 1 | AL82: 0 | AN82: 0 | AO82: 9000000 | AP82: 0 | AQ82: 0 | AR82: 9000000 | AS82: 11290000 | AT82: 2290000 | AU82: 2028
A83: IMPORTADORA TRENTO LTDA | B83: MEGACENTRO OVALLE | C83: 0 | D83: 0 | I83: 23-02-2026 15:52:12 | K83: MPBUR2366NX379509 | L83: FORD | M83: RANGER | N83: RANGER RAPTOR 4X4 2.0 AUT | O83: FRR20 | P83: 2023 | Q83: 114000 | R83: TFOCMTU001154 | S83: SFTZ65 | T83: USADO | U83: NEGRO ABSOLUTO | V83: POR DEFINIR | W83: 30290000 | X83: Disponible | Y83: 99 | Z83: DISPONIBLE | AA83: BODEGA OVALLEveih | AC83: YN2SXM379509 | AD83: MPBUR2366NX379509 | AE83: SOCIEDAD AGRICOLA, GANADERA, FORESTAL Y DE TRANSPORTES SANTO TOMAS LIMITADA | AF83: 23-02-2026 0:00:00 | AG83: 24 | AH83: 29-01-2026 0:00:00 | AI83: 18-03-2026 12:59:05 | AK83: 0 | AL83: 0 | AN83: 0 | AO83: 26500000 | AP83: 523530 | AQ83: 0 | AR83: 27023530 | AS83: 30290000 | AT83: 3266470 | AU83: 1078
A84: IMPORTADORA TRENTO LTDA | B84: LOCAL USADOS | C84: 0 | D84: 0 | I84: 04-05-2026 17:27:55 | K84: /..+/+++///++*... | L84: CITROEN | M84: C3 | N84: C3 AIRCROSS 1.2 AUT | O84: CR566 | P84: 2019 | Q84: 72580 | R84: TCIAUTU000131 | S84: LPXJ44 | T84: USADO | U84: GRIS SATINADO T BLANCO | V84: POR DEFINIR | W84: 9290000 | X84: Disponible | Y84: 29 | Z84: EN TALLER | AA84: BODEGA VEHICULOS | AB84: AE,CC,EE,2AB,ABS,LL,AC,AISO,AAUTO,MAV,ACD,DLL | AC84: 10XK132270863 | AD84: VF72RHNZWJ4344809 | AE84: MYRIAM LORENA ALVAREZ DIAZ | AF84: 04-05-2026 0:00:00 | AG84: 1 | AH84: 04-05-2026 0:00:00 | AI84: 04-05-2026 17:22:16 | AK84: 4 | AL84: 0 | AN84: 0 | AO84: 8300000 | AP84: 253740 | AQ84: 0 | AR84: 8553740 | AS84: 9290000 | AT84: 736260 | AU84: 793
A85: IMPORTADORA TRENTO LTDA | B85: LOCAL USADOS COPIAPO | C85: 0 | D85: 0 | I85: 06-04-2026 14:59:49 | K85: 9V8FF4HY1 RA800320 | L85: PEUGEOT | M85: LANDTREK | N85: LANDTREK BLUEHDI 4X4 2.2 AUT | O85: PELNDDHI4X422AT | P85: 2024 | Q85: 29570 | R85: TPECMTU000018 | S85: TFGP78 | T85: USADO | U85: GRIS ALUMINIUM | V85: POR DEFINIR | W85: 19990000 | X85: Disponible | Y85: 57 | Z85: CON PRENDA | AA85: BODEGA LOS CARRERA COPIAPO | AB85: AE,CC,EE,NB,AAC,ABS,LL,VC,AISO,AAUTO,CRE,ACD,SR,UD | AC85: 10VRAC4001968 | AD85: 9V8FF4HY1 RA800320 | AE85: RODRIGO ALEJANDRO FUENTES ARAYA | AF85: 06-04-2026 0:00:00 | AG85: 1 | AH85: 06-04-2026 0:00:00 | AI85: 06-04-2026 14:59:18 | AK85: 1 | AL85: 0 | AN85: 0 | AO85: 16000000 | AP85: 369240 | AQ85: 0 | AR85: 16369240 | AS85: 19990000 | AT85: 3620760 | AU85: 1811
A86: IMPORTADORA TRENTO LTDA | B86: LOCAL PREMIUM CAR SALES | C86: 0 | D86: 0 | I86: 25-05-2026 16:44:02 | K86: 3KPA251AA PE534052 | L86: KIA MOTORS | M86: RIO | N86: RIO 5 6MT 1.4 | O86: PATAN | P86: 2023 | Q86: 39280 | R86: TKIAUTU002214 | S86: SVRS43 | T86: USADO | U86: BLANCO INVIERNO | V86: POR DEFINIR | W86: 12290000 | X86: Disponible | Y86: 8 | Z86: EN PREPARACION | AA86: PREMIUM CAR SALES | AB86: AE,CC,EE,ABS,LL,AC,AISO,AAUTO,CRE,MAV,ACD,SR,UD,DL | AC86: G4LCNE709367 | AD86: 3KPA251AA PE534052 | AE86: CLAUDIA CECILIA HERRERA MUÑOZ | AF86: 25-05-2026 0:00:00 | AG86: 1 | AH86: 25-05-2026 0:00:00 | AI86: 25-05-2026 16:43:21 | AK86: 1 | AL86: 0 | AN86: 0 | AO86: 9400000 | AP86: 0 | AQ86: 0 | AR86: 9400000 | AS86: 12290000 | AT86: 2890000 | AU86: 2352
A87: IMPORTADORA TRENTO LTDA | B87: LOCAL USADOS COPIAPO | C87: 0 | D87: 0 | I87: 18-05-2026 12:26:28 | K87: 9V8FF4HY1RA801169 | L87: PEUGEOT | M87: LANDTREK | N87: LANDTREK BLUEHDI 4X4 2.2 AUT | O87: PELNDDHI4X422AT | P87: 2024 | Q87: 11557 | R87: TPECMTU000020 | S87: TCTX97 | T87: USADO | U87: GRIS ALUMINIUM | V87: POR DEFINIR | W87: 19990000 | X87: Disponible | Y87: 15 | Z87: CON PRENDA | AA87: BODEGA LOS CARRERA COPIAPO | AB87: AE,CC,EE,NB,AAC,ABS,LL,VC,AISO,AAUTO,CRE,MAV,ACD,S | AC87: 10VRAC4002519 | AD87: 9V8FF4HY1RA801169 | AE87: DAVID RODRIGO ARACENA LOIS | AF87: 18-05-2026 0:00:00 | AG87: 1 | AH87: 18-05-2026 0:00:00 | AI87: 18-05-2026 12:25:24 | AK87: 1 | AL87: 0 | AN87: 0 | AO87: 16000000 | AP87: 0 | AQ87: 0 | AR87: 16000000 | AS87: 19990000 | AT87: 3990000 | AU87: 1996
A88: IMPORTADORA TRENTO LTDA | B88: LOCAL USADOS COPIAPO | C88: 0 | D88: 0 | I88: 05-06-2025 17:27:51 | K88: 9BGEN76C0 PB119398 | L88: CHEVROLET | M88: TRACKER | N88: TRACKER 1.2T | O88: TU8000 | P88: 2022 | Q88: 33420 | R88: TCHSTWU000300 | S88: SBWS64 | T88: USADO | U88: GRIS METALICO | V88: POR DEFINIR | W88: 11690000 | X88: Disponible | Y88: 362 | Z88: DISPONIBLE | AA88: BODEGA LOS CARRERA COPIAPO | AC88: L4H 221104607 | AD88: 9BGEN76C0 PB119398 | AE88: MARITZA XIMENA FLORES NAVARRO | AF88: 05-06-2025 0:00:00 | AG88: 1 | AH88: 14-01-2026 23:58:00 | AI88: 14-01-2026 23:58:00 | AK88: 1 | AL88: 0 | AN88: 0 | AO88: 9300000 | AP88: 436959 | AQ88: 0 | AR88: 9736959 | AS88: 11690000 | AT88: 1953041 | AU88: 1671
A89: IMPORTADORA TRENTO LTDA | B89: LOCAL USADOS COPIAPO | C89: 0 | D89: 0 | I89: 30-12-2025 10:51:56 | K89: MA1VE2RJC M6E84266 | L89: MAHINDRA | M89: MAHINDRA | N89: KUV 100 HATCH BACK 1.2 | O89: MAKUV100HB12MT | P89: 2022 | Q89: 0 | R89: TMHAUTU000006 | S89: RGLK10 | T89: USADO | U89: BLANCO | V89: POR DEFINIR | W89: 6390000 | X89: Disponible | Y89: 154 | Z89: EN TALLER | AA89: BODEGA LOS CARRERA COPIAPO | AB89: AE,CC,AC,AISO,ACD | AC89: RJMZE50719 | AD89: MA1VE2RJC M6E84266 | AE89: FRANK EDWARD ECHANDIA HERNÁNDEZ | AF89: 30-12-2025 0:00:00 | AG89: 1 | AH89: 30-12-2025 0:00:00 | AI89: 30-12-2025 10:51:21 | AK89: 0 | AL89: 0 | AN89: 0 | AO89: 8137896 | AP89: 248098 | AQ89: 0 | AR89: 8385994 | AS89: 6390000 | AT89: -1995994 | AU89: -3124
A90: IMPORTADORA TRENTO LTDA | B90: LOCAL PREMIUM CAR SALES | C90: 0 | D90: 0 | I90: 04-02-2026 18:55:48 | K90: 3FMCR9E91RRF05973 | L90: FORD | M90: BRONCO | N90: BRONCO SPORT WILDTRAK 4X4 2.0 AUT | O90: BRUS7 | P90: 2025 | Q90: 13400 | R90: TFOSTWU001397 | S90: TYWS69 | T90: USADO | U90: GRIS AZULADO | V90: POR DEFINIR | W90: 28290000 | X90: Disponible | Y90: 118 | Z90: DISPONIBLE | AA90: PREMIUM CAR SALES | AB90: AE,CC,EE,AAC,ABS,LL,VC,ESP,AISO,AAUTO,CRE,ACD,SR,U | AC90: RRF05973 | AD90: 3FMCR9E91RRF05973 | AE90: RUTH ESTER OSSANDON NARBONA | AF90: 04-02-2026 0:00:00 | AG90: 1 | AH90: 04-02-2026 0:00:00 | AI90: 04-02-2026 18:50:21 | AK90: 1 | AL90: 0 | AN90: 0 | AO90: 23500000 | AP90: 949179 | AQ90: 0 | AR90: 24449179 | AS90: 28290000 | AT90: 3840821 | AU90: 1358
A91: IMPORTADORA TRENTO LTDA | B91: MEGACENTRO OVALLE | C91: 0 | D91: 0 | I91: 18-04-2026 13:36:35 | K91: MALB241CAPM142324 | L91: HYUNDAI | M91: HYUNDAI | N91: GRAND I10 SDN 1.2 | O91: HYGRDI10SDN12MT | P91: 2023 | Q91: 59200 | R91: THYAUTU000584 | S91: SLDR66 | T91: USADO | U91: ROJO PASION | V91: POR DEFINIR | W91: 9190000 | X91: Disponible | Y91: 45 | Z91: CON PRENDA | AA91: BODEGA OVALLEveih | AB91: AE,CC,EE,NB,ABS,LL,4AB,AC,AISO,AAUTO,CRE,MAV,ACD,U | AC91: G4LANM260060 | AD91: MALB241CAPM142324 | AE91: ROBINSON LORENZO CASTILLO BERRIOS | AF91: 18-04-2026 0:00:00 | AG91: 1 | AH91: 18-04-2026 0:00:00 | AI91: 18-04-2026 13:34:30 | AJ91: 30-09-2027 0:00:00 | AK91: 1 | AL91: 0 | AN91: 0 | AO91: 7000000 | AP91: 234240 | AQ91: 0 | AR91: 7234240 | AS91: 9190000 | AT91: 1955760 | AU91: 2128
A92: IMPORTADORA TRENTO LTDA | B92: LOCAL USADOS COPIAPO | C92: 0 | D92: 0 | I92: 06-05-2026 17:51:31 | K92: /////+++/./++*... | L92: CHERY | M92: ARRIZO 3 | N92: NEW ARRIZO 3 GLS 1.5 | O92: CHNEARRI3GLS15MT | P92: 2021 | Q92: 59576 | R92: TCYAUTU000147 | S92: PKHC89 | T92: USADO | U92: ROJO METALIZADO | V92: POR DEFINIR | W92: 6190000 | X92: Disponible | Y92: 27 | Z92: DISPONIBLE | AA92: BODEGA LOS CARRERA COPIAPO | AB92: AE,CC,EE,2AB,AC,AISO,AAUTO,SR,UD,DLL | AC92: SQRD4G15BBLD00056 | AD92: LVVDC11B1MD013133 | AE92: MAURICIO ANDRÉS VALENZUELA SOLAR | AF92: 06-05-2026 0:00:00 | AG92: 1 | AH92: 06-05-2026 0:00:00 | AI92: 06-05-2026 17:48:56 | AK92: 1 | AL92: 0 | AN92: 0 | AO92: 4800000 | AP92: 201240 | AQ92: 0 | AR92: 5001240 | AS92: 6190000 | AT92: 1188760 | AU92: 192
A93: IMPORTADORA TRENTO LTDA | B93: MEGACENTRO OVALLE | C93: 0 | D93: 0 | I93: 05-12-2025 18:11:39 | K93: 1FTEW1E51LFC25883 | L93: FORD | M93: F-150 | N93: F150 LARIAT 4X4 5.0 AT | O93: FOF150LA4X450AT | P93: 2021 | Q93: 111255 | R93: TFOCMTU001144 | S93: PKTZ57 | T93: USADO | U93: PLATEADO METALICO | V93: POR DEFINIR | W93: 27190000 | X93: Disponible | Y93: 179 | Z93: DISPONIBLE | AA93: BODEGA OVALLEveih | AB93: AE,CC,EE,NB,AAC,ABS,LL,AISO,AAUTO,CRE,MAV,SR,DLL,6 | AC93: LFC25883 | AD93: 1FTEW1E51LFC25883 | AE93: GILBERTO ALEJANDRO PARDO ALCAYAGA | AF93: 05-12-2025 0:00:00 | AG93: 1 | AH93: 05-12-2025 0:00:00 | AI93: 05-12-2025 18:11:02 | AK93: 2 | AL93: 0 | AN93: 0 | AO93: 24000000 | AP93: 486030 | AQ93: 0 | AR93: 24486030 | AS93: 27190000 | AT93: 2703970 | AU93: 994
A94: IMPORTADORA TRENTO LTDA | B94: LOCAL USADOS COPIAPO | C94: 0 | D94: 0 | I94: 30-03-2026 13:25:15 | K94: VF3MCYHZUNL000473 | L94: PEUGEOT | M94: 5008 | N94: 5008 BLUEHDI 130 1.5 AUT | O94: 5008BH130 | P94: 2021 | Q94: 77000 | R94: TPESTWU000450 | S94: PZTS12 | T94: USADO | U94: GRIS PLATINIUM | V94: POR DEFINIR | W94: 16490000 | X94: Disponible | Y94: 64 | Z94: DISPONIBLE | AA94: BODEGA LOS CARRERA COPIAPO | AB94: AE,CC,EE,AAC,ABS,LL,VC,AISO,AAUTO,CRE,MAV,ACD,SR,U | AC94: 10Q3EJ1170226 | AD94: VF3MCYHZUNL000473 | AE94: JESSICA ALEJANDRA MELLA TAPIA | AF94: 30-03-2026 0:00:00 | AG94: 1 | AH94: 30-03-2026 0:00:00 | AI94: 30-03-2026 13:24:46 | AK94: 1 | AL94: 0 | AN94: 0 | AO94: 14600000 | AP94: 348240 | AQ94: 0 | AR94: 14948240 | AS94: 16490000 | AT94: 1541760 | AU94: 935
A95: IMPORTADORA TRENTO LTDA | B95: LOCAL USADOS COPIAPO | C95: 0 | D95: 0 | I95: 28-08-2025 17:50:15 | K95: VR3FDAHDE P3009377 | L95: PEUGEOT | M95: LANDTREK | N95: LANDTREK 1.9 | O95: L666MT | P95: 2023 | Q95: 67000 | R95: TPECMTU000014 | S95: SHDG76 | T95: USADO | U95: BLANCO | V95: POR DEFINIR | W95: 13750000 | X95: Disponible | Y95: 278 | Z95: EN RESCILIACION | AA95: BODEGA LOS CARRERA COPIAPO | AB95: AE,CC,EE,ABS,VC,AC,AISO,AAUTO,CRE,MAV,ACD,SR,UD,DL | AC95: A5D22003815 | AD95: VR3FDAHDE P3009377 | AE95: DANIEL ALEJANDRO RODRIGUEZ LETELIER | AF95: 28-08-2025 0:00:00 | AG95: 1 | AH95: 28-08-2025 0:00:00 | AI95: 28-08-2025 17:49:40 | AK95: 1 | AL95: 0 | AN95: 0 | AO95: 14000000 | AP95: 336030 | AQ95: 0 | AR95: 14336030 | AS95: 13750000 | AT95: -586030 | AU95: -426
A96: IMPORTADORA TRENTO LTDA | B96: LOCAL PREMIUM CAR SALES | C96: 0 | D96: 0 | I96: 17-11-2025 18:40:32 | K96: VF3MCYHZM NS002292 | L96: PEUGEOT | M96: 3008 | N96: 3008 BLUE HDI 130 1.5 | O96: P300815 | P96: 2021 | Q96: 98100 | R96: TPESTWU000435 | S96: PYLP70 | T96: USADO | U96: BLANCO NACARADO | V96: POR DEFINIR | W96: 14890000 | X96: Disponible | Y96: 197 | Z96: EN TALLER | AA96: PREMIUM CAR SALES | AB96: AE,CC,EE,AAC,ABS,LL,AISO,AAUTO,CRE,MAV,SR,DLL,6AB | AC96: 10Q4EL0002967 | AD96: VF3MCYHZM NS002292 | AE96: ADOLFO MARCELO ACUÑA MADRIGAL | AF96: 17-11-2025 0:00:00 | AG96: 1 | AH96: 17-11-2025 0:00:00 | AI96: 17-11-2025 18:38:59 | AK96: 3 | AL96: 0 | AN96: 0 | AO96: 13490000 | AP96: 328380 | AQ96: 0 | AR96: 13818380 | AS96: 14890000 | AT96: 1071620 | AU96: 72
A97: IMPORTADORA TRENTO LTDA | B97: MEGACENTRO OVALLE | C97: 0 | D97: 0 | I97: 30-09-2025 19:19:30 | K97: VF3MRHNSM PS004241 | L97: PEUGEOT | M97: 3008 | N97: 3008 PURETECH 1.2L | O97: 3P1L | P97: 2023 | Q97: 45360 | R97: TPESTWU000424 | S97: SDPF24 | T97: USADO | U97: BLANCO NACARADO | V97: POR DEFINIR | W97: 13990000 | X97: Disponible | Y97: 245 | Z97: DISPONIBLE | AA97: BODEGA OVALLEveih | AB97: AE,CC,EE,AAC,ABS,LL,VC,AISO,AAUTO,CRE,MAV,SR,UD,DL | AC97: 10TMAF0001673 | AD97: VF3MRHNSM PS004241 | AE97: CECILIA BEATRIZ TAPIA CASTRO | AF97: 30-09-2025 0:00:00 | AG97: 1 | AH97: 06-11-2025 11:46:00 | AI97: 06-11-2025 11:46:00 | AJ97: 31-07-2027 0:00:00 | AK97: 1 | AL97: 0 | AN97: 0 | AO97: 12100000 | AP97: 307530 | AQ97: 0 | AR97: 12407530 | AS97: 13990000 | AT97: 1582470 | AU97: 1131
A98: IMPORTADORA TRENTO LTDA | B98: MEGACENTRO OVALLE | C98: 0 | D98: 0 | I98: 27-05-2026 17:54:58 | K98: JF1SK7LL5RG259442 | L98: SUBARU | M98: FORESTER | N98: FORESTER 4X4 2.0 AT | O98: SF99 | P98: 2024 | Q98: 76000 | R98: TSUSTWU000399 | S98: TPCS18 | T98: USADO | U98: PLATEADO HIELO CLARO | V98: POR DEFINIR | W98: 23990000 | X98: Disponible | Y98: 6 | Z98: EN PREPARACION | AA98: BODEGA OVALLEveih | AB98: AE,CC,EE,NB,AAC,ABS,LL,VC,AISO,AAUTO,CRE,MAV,ACD,S | AC98: YX96759 | AD98: JF1SK7LL5RG259442 | AE98: EDUARDO ENRIQUE ANTIQUERA ANTIQUERA | AF98: 27-05-2026 0:00:00 | AG98: 1 | AH98: 27-05-2026 0:00:00 | AI98: 27-05-2026 17:50:26 | AK98: 1 | AL98: 0 | AN98: 0 | AO98: 19000000 | AP98: 0 | AQ98: 0 | AR98: 19000000 | AS98: 23990000 | AT98: 4990000 | AU98: 208
A99: IMPORTADORA TRENTO LTDA | B99: LOCAL USADOS COPIAPO | C99: 0 | D99: 0 | I99: 19-12-2025 10:02:31 | K99: 8AFBR00E1RJ404211 | L99: FORD | M99: RANGER | N99: RANGER XLS 2.0 | O99: FORANXLS20MT | P99: 2025 | Q99: 34500 | R99: TFOCMTU001145 | S99: SYPL90 | T99: USADO | U99: BLANCO | V99: POR DEFINIR | W99: 29490000 | X99: Disponible | Y99: 165 | Z99: DISPONIBLE | AA99: BODEGA LOS CARRERA COPIAPO | AB99: AE,CC,EE,AAC,ABS,LL,VC,ESP,AISO,AAUTO,CRE,MAV,SR,U | AC99: P02X RJ404211 | AD99: 8AFBR00E1RJ404211 | AE99: MATIAS OLAZO SPA | AF99: 19-12-2025 0:00:00 | AG99: 1 | AH99: 19-12-2025 0:00:00 | AI99: 19-12-2025 9:51:58 | AK99: 1 | AL99: 0 | AN99: 0 | AO99: 27000000 | AP99: 531030 | AQ99: 0 | AR99: 27531030 | AS99: 29490000 | AT99: 1958970 | AU99: 664
A100: IMPORTADORA TRENTO LTDA | B100: LOCAL USADOS COPIAPO | C100: 0 | D100: 0 | I100: 02-10-2025 16:52:58 | K100: VR3KAHPY6 SS009601 | L100: PEUGEOT | M100: 3008 | N100: 3008 ALLURE 1.2 AUT | O100: 3008ALLUSA | P100: 2025 | Q100: 4687 | R100: TPESTWU000425 | S100: TZTC96 | T100: USADO | U100: GRIS ARTENSE | V100: POR DEFINIR | W100: 23890000 | X100: Disponible | Y100: 243 | Z100: DISPONIBLE | AA100: BODEGA LOS CARRERA COPIAPO | AB100: AE,CC,EE,AAC,ABS,LL,AISO,AAUTO,CRE,MAV,ACD,SR,UD,D | AC100: 10ZA040090603 | AD100: VR3KAHPY6 SS009601 | AE100: PEDRO ANDRES NARVAEZ FLORES | AF100: 02-10-2025 0:00:00 | AG100: 1 | AH100: 02-10-2025 0:00:00 | AI100: 02-10-2025 16:52:06 | AK100: 1 | AL100: 0 | AN100: 0 | AO100: 28490000 | AP100: 914223 | AQ100: 0 | AR100: 29404223 | AS100: 23890000 | AT100: -5514223 | AU100: -2308
...
