Workbook

Sheet BBDD2
A1: Marca | B1: Modelo | C1: Versión | D1: Estado Dealer | E1: Año | F1: Placa Patente | G1: Días Stock | H1: Kilometraje | I1: Empresa | J1: Modelo-versión-año | K1: Precio toma historico | L1: Precio toma historico autored | M1: Precio unidad venta | N1: Precio Lista informe stock | O1: Precio Mercado | P1: Precio Compra Neto Informe Stock | Q1: Total Costo Informe Stock | R1: Tipo rotación
A2: AUDI | B2: Q2 | C2: Q2 35 TFSI 1.4 AUT | D2: DISPONIBLE | E2: 2023 | F2: SPZD69 | G2: 47 | H2: 58362 | I2: IMPORTADORA TRENTO LTDA | J2: =CONCATENATE(B2,C2,E2) -> Q2Q2 35 TFSI 1.4 AUT2023 | L2: =IFERROR(_xlfn.XLOOKUP(F2,'PRECIO TOMA HISTORICO '!$A:$A,'PRECIO TOMA HISTORICO '!$B:$B,_xlfn.XLOOKUP(F2,BBDD!$S:$S,BBDD!$AO:$AO,"",0,1),0,-1),"") -> 16700000 | N2: =_xlfn.XLOOKUP(F2,BBDD!$S:$S,BBDD!$AS:$AS) -> 20990000 | O2: =IFERROR(VLOOKUP(F2,'PRECIO MERCADO'!D:E,2,0),"0") -> 22400000 | P2: =_xlfn.XLOOKUP(F2,BBDD!$S:$S,BBDD!$AO:$AO) -> 16500000 | Q2: =_xlfn.XLOOKUP(F2,BBDD!$S:$S,BBDD!$AR:$AR) -> 16876740 | R2: =IF(G2<=30,"ROTACION ALTA",IF(G2<30,"ROTACION MEDIA",IF(G2<60,"ROTACION BAJA",IF(G2>60,"LIQUIDAR")))) -> ROTACION BAJA
A3: BAIC | B3: BJ30 | C3: BJ30 LV5 AWD HEV | D3: EN PREPARACION | E3: 2026 | F3: VSWT54 | G3: 228 | H3: 2500 | I3: CALLEGARI E HIJOS LTDA | J3: =CONCATENATE(B3,C3,E3) -> BJ30BJ30 LV5 AWD HEV2026 | L3: =IFERROR(_xlfn.XLOOKUP(F3,'PRECIO TOMA HISTORICO '!$A:$A,'PRECIO TOMA HISTORICO '!$B:$B,_xlfn.XLOOKUP(F3,BBDD!$S:$S,BBDD!$AO:$AO,"",0,1),0,-1),"") -> 21210924 | N3: =_xlfn.XLOOKUP(F3,BBDD!$S:$S,BBDD!$AS:$AS) -> 24900000 | O3: =IFERROR(VLOOKUP(F3,'PRECIO MERCADO'!D:E,2,0),"0") -> 20000000 | P3: =_xlfn.XLOOKUP(F3,BBDD!$S:$S,BBDD!$AO:$AO) -> 21210924 | Q3: =_xlfn.XLOOKUP(F3,BBDD!$S:$S,BBDD!$AR:$AR) -> 22186979 | R3: =IF(G3<=30,"ROTACION ALTA",IF(G3<30,"ROTACION MEDIA",IF(G3<60,"ROTACION BAJA",IF(G3>60,"LIQUIDAR")))) -> LIQUIDAR
A4: BAIC | B4: BJ60 | C4: BJ60 FLAGSHIP 7P MHEV (Mild Hybrid) | D4: EN PREPARACION | E4: 2026 | F4: TGVT33 | G4: 228 | H4: 5200 | I4: CALLEGARI E HIJOS LTDA | J4: =CONCATENATE(B4,C4,E4) -> BJ60BJ60 FLAGSHIP 7P MHEV (Mild Hybrid)2026 | L4: =IFERROR(_xlfn.XLOOKUP(F4,'PRECIO TOMA HISTORICO '!$A:$A,'PRECIO TOMA HISTORICO '!$B:$B,_xlfn.XLOOKUP(F4,BBDD!$S:$S,BBDD!$AO:$AO,"",0,1),0,-1),"") -> 37849580 | N4: =_xlfn.XLOOKUP(F4,BBDD!$S:$S,BBDD!$AS:$AS) -> 44800000 | O4: =IFERROR(VLOOKUP(F4,'PRECIO MERCADO'!D:E,2,0),"0") -> 43800000 | P4: =_xlfn.XLOOKUP(F4,BBDD!$S:$S,BBDD!$AO:$AO) -> 37849580 | Q4: =_xlfn.XLOOKUP(F4,BBDD!$S:$S,BBDD!$AR:$AR) -> 39771286 | R4: =IF(G4<=30,"ROTACION ALTA",IF(G4<30,"ROTACION MEDIA",IF(G4<60,"ROTACION BAJA",IF(G4>60,"LIQUIDAR")))) -> LIQUIDAR
A5: BAIC | B5: X7 | C5: X7 EXCLUSIVE | D5: EN PREPARACION | E5: 2026 | F5: VSWT56 | G5: 228 | H5: 900 | I5: CALLEGARI E HIJOS LTDA | J5: =CONCATENATE(B5,C5,E5) -> X7X7 EXCLUSIVE2026 | L5: =IFERROR(_xlfn.XLOOKUP(F5,'PRECIO TOMA HISTORICO '!$A:$A,'PRECIO TOMA HISTORICO '!$B:$B,_xlfn.XLOOKUP(F5,BBDD!$S:$S,BBDD!$AO:$AO,"",0,1),0,-1),"") -> 19320168 | N5: =_xlfn.XLOOKUP(F5,BBDD!$S:$S,BBDD!$AS:$AS) -> 22490000 | O5: =IFERROR(VLOOKUP(F5,'PRECIO MERCADO'!D:E,2,0),"0") -> 21800000 | P5: =_xlfn.XLOOKUP(F5,BBDD!$S:$S,BBDD!$AO:$AO) -> 19320168 | Q5: =_xlfn.XLOOKUP(F5,BBDD!$S:$S,BBDD!$AR:$AR) -> 20341262 | R5: =IF(G5<=30,"ROTACION ALTA",IF(G5<30,"ROTACION MEDIA",IF(G5<60,"ROTACION BAJA",IF(G5>60,"LIQUIDAR")))) -> LIQUIDAR
A6: BYD | B6: SONG PLUS DM-i | C6: SONG PLUS 4X2 1.5 AUT | D6: DISPONIBLE | E6: 2024 | F6: TJDC55 | G6: 250 | H6: 30000 | I6: IMPORTADORA TRENTO LTDA | J6: =CONCATENATE(B6,C6,E6) -> SONG PLUS DM-iSONG PLUS 4X2 1.5 AUT2024 | L6: =IFERROR(_xlfn.XLOOKUP(F6,'PRECIO TOMA HISTORICO '!$A:$A,'PRECIO TOMA HISTORICO '!$B:$B,_xlfn.XLOOKUP(F6,BBDD!$S:$S,BBDD!$AO:$AO,"",0,1),0,-1),"") -> 20000000 | N6: =_xlfn.XLOOKUP(F6,BBDD!$S:$S,BBDD!$AS:$AS) -> 20990000 | O6: =IFERROR(VLOOKUP(F6,'PRECIO MERCADO'!D:E,2,0),"0") -> 22100000 | P6: =_xlfn.XLOOKUP(F6,BBDD!$S:$S,BBDD!$AO:$AO) -> 20000000 | Q6: =_xlfn.XLOOKUP(F6,BBDD!$S:$S,BBDD!$AR:$AR) -> 20524003 | R6: =IF(G6<=30,"ROTACION ALTA",IF(G6<30,"ROTACION MEDIA",IF(G6<60,"ROTACION BAJA",IF(G6>60,"LIQUIDAR")))) -> LIQUIDAR
A7: BYD | B7: SONG PLUS DM-i | C7: SONG PLUS GS | D7: DEMO/INTERNO | E7: 2024 | F7: TJSJ84 | G7: 403 | H7: 19482 | I7: SOC. HERMANAS CALLEGARI LTDA | J7: =CONCATENATE(B7,C7,E7) -> SONG PLUS DM-iSONG PLUS GS2024 | L7: =IFERROR(_xlfn.XLOOKUP(F7,'PRECIO TOMA HISTORICO '!$A:$A,'PRECIO TOMA HISTORICO '!$B:$B,_xlfn.XLOOKUP(F7,BBDD!$S:$S,BBDD!$AO:$AO,"",0,1),0,-1),"") -> 29403361 | N7: =_xlfn.XLOOKUP(F7,BBDD!$S:$S,BBDD!$AS:$AS) -> 28990000 | O7: =IFERROR(VLOOKUP(F7,'PRECIO MERCADO'!D:E,2,0),"0") -> 24700000 | P7: =_xlfn.XLOOKUP(F7,BBDD!$S:$S,BBDD!$AO:$AO) -> 29403361 | Q7: =_xlfn.XLOOKUP(F7,BBDD!$S:$S,BBDD!$AR:$AR) -> 30640616 | R7: =IF(G7<=30,"ROTACION ALTA",IF(G7<30,"ROTACION MEDIA",IF(G7<60,"ROTACION BAJA",IF(G7>60,"LIQUIDAR")))) -> LIQUIDAR
A8: BYD | B8: YUAN PLUS EV | C8: YUAN PLUS EV GS | D8: DEMO/INTERNO | E8: 2024 | F8: SYPY23 | G8: 960 | H8: 15100 | I8: SOC. HERMANAS CALLEGARI LTDA | J8: =CONCATENATE(B8,C8,E8) -> YUAN PLUS EVYUAN PLUS EV GS2024 | L8: =IFERROR(_xlfn.XLOOKUP(F8,'PRECIO TOMA HISTORICO '!$A:$A,'PRECIO TOMA HISTORICO '!$B:$B,_xlfn.XLOOKUP(F8,BBDD!$S:$S,BBDD!$AO:$AO,"",0,1),0,-1),"") -> 30243697 | N8: =_xlfn.XLOOKUP(F8,BBDD!$S:$S,BBDD!$AS:$AS) -> 19790000 | O8: =IFERROR(VLOOKUP(F8,'PRECIO MERCADO'!D:E,2,0),"0") -> 19700000 | P8: =_xlfn.XLOOKUP(F8,BBDD!$S:$S,BBDD!$AO:$AO) -> 30243697 | Q8: =_xlfn.XLOOKUP(F8,BBDD!$S:$S,BBDD!$AR:$AR) -> 31091577 | R8: =IF(G8<=30,"ROTACION ALTA",IF(G8<30,"ROTACION MEDIA",IF(G8<60,"ROTACION BAJA",IF(G8>60,"LIQUIDAR")))) -> LIQUIDAR
A9: CHANGAN | B9: CS15 | C9: CS15 HB 4X2 1.5 | D9: EN TALLER | E9: 2021 | F9: RJDX35 | G9: 64 | H9: 90000 | I9: IMPORTADORA TRENTO LTDA | J9: =CONCATENATE(B9,C9,E9) -> CS15CS15 HB 4X2 1.52021 | L9: =IFERROR(_xlfn.XLOOKUP(F9,'PRECIO TOMA HISTORICO '!$A:$A,'PRECIO TOMA HISTORICO '!$B:$B,_xlfn.XLOOKUP(F9,BBDD!$S:$S,BBDD!$AO:$AO,"",0,1),0,-1),"") -> 5200000 | N9: =_xlfn.XLOOKUP(F9,BBDD!$S:$S,BBDD!$AS:$AS) -> 7290000 | O9: =IFERROR(VLOOKUP(F9,'PRECIO MERCADO'!D:E,2,0),"0") -> 7290000 | P9: =_xlfn.XLOOKUP(F9,BBDD!$S:$S,BBDD!$AO:$AO) -> 5200000 | Q9: =_xlfn.XLOOKUP(F9,BBDD!$S:$S,BBDD!$AR:$AR) -> 5407240 | R9: =IF(G9<=30,"ROTACION ALTA",IF(G9<30,"ROTACION MEDIA",IF(G9<60,"ROTACION BAJA",IF(G9>60,"LIQUIDAR")))) -> LIQUIDAR
A10: CHANGAN | B10: HUNTER | C10: HUNTER 4X4 2.0 | D10: DISPONIBLE | E10: 2026 | F10: VRHK60 | G10: 14 | H10: 5250 | I10: IMPORTADORA TRENTO LTDA | J10: =CONCATENATE(B10,C10,E10) -> HUNTERHUNTER 4X4 2.02026 | L10: =IFERROR(_xlfn.XLOOKUP(F10,'PRECIO TOMA HISTORICO '!$A:$A,'PRECIO TOMA HISTORICO '!$B:$B,_xlfn.XLOOKUP(F10,BBDD!$S:$S,BBDD!$AO:$AO,"",0,1),0,-1),"") -> 15000000 | N10: =_xlfn.XLOOKUP(F10,BBDD!$S:$S,BBDD!$AS:$AS) -> 17990000 | O10: =IFERROR(VLOOKUP(F10,'PRECIO MERCADO'!D:E,2,0),"0") -> 17100000 | P10: =_xlfn.XLOOKUP(F10,BBDD!$S:$S,BBDD!$AO:$AO) -> 15000000 | Q10: =_xlfn.XLOOKUP(F10,BBDD!$S:$S,BBDD!$AR:$AR) -> 15354240 | R10: =IF(G10<=30,"ROTACION ALTA",IF(G10<30,"ROTACION MEDIA",IF(G10<60,"ROTACION BAJA",IF(G10>60,"LIQUIDAR")))) -> ROTACION ALTA
A11: CHANGAN | B11: MS201 | C11: MS201 DCAB 1.2 | D11: EN PREPARACION | E11: 2023 | F11: SDYB13 | G11: 6 | H11: 34836 | I11: IMPORTADORA TRENTO LTDA | J11: =CONCATENATE(B11,C11,E11) -> MS201MS201 DCAB 1.22023 | L11: =IFERROR(_xlfn.XLOOKUP(F11,'PRECIO TOMA HISTORICO '!$A:$A,'PRECIO TOMA HISTORICO '!$B:$B,_xlfn.XLOOKUP(F11,BBDD!$S:$S,BBDD!$AO:$AO,"",0,1),0,-1),"") -> 5100000 | N11: =_xlfn.XLOOKUP(F11,BBDD!$S:$S,BBDD!$AS:$AS) -> 6290000 | O11: =IFERROR(VLOOKUP(F11,'PRECIO MERCADO'!D:E,2,0),"0") -> 7060000 | P11: =_xlfn.XLOOKUP(F11,BBDD!$S:$S,BBDD!$AO:$AO) -> 5100000 | Q11: =_xlfn.XLOOKUP(F11,BBDD!$S:$S,BBDD!$AR:$AR) -> 5305740 | R11: =IF(G11<=30,"ROTACION ALTA",IF(G11<30,"ROTACION MEDIA",IF(G11<60,"ROTACION BAJA",IF(G11>60,"LIQUIDAR")))) -> ROTACION ALTA
A12: CHANGAN | B12: X7 | C12: X7 PLUS TURBO 1.5 | D12: EN PREPARACION | E12: 2026 | F12: VLYP47 | G12: 21 | H12: 15600 | I12: IMPORTADORA TRENTO LTDA | J12: =CONCATENATE(B12,C12,E12) -> X7X7 PLUS TURBO 1.52026 | L12: =IFERROR(_xlfn.XLOOKUP(F12,'PRECIO TOMA HISTORICO '!$A:$A,'PRECIO TOMA HISTORICO '!$B:$B,_xlfn.XLOOKUP(F12,BBDD!$S:$S,BBDD!$AO:$AO,"",0,1),0,-1),"") -> 11550000 | N12: =_xlfn.XLOOKUP(F12,BBDD!$S:$S,BBDD!$AS:$AS) -> 14200000 | O12: =IFERROR(VLOOKUP(F12,'PRECIO MERCADO'!D:E,2,0),"0") -> 14400000 | P12: =_xlfn.XLOOKUP(F12,BBDD!$S:$S,BBDD!$AO:$AO) -> 11550000 | Q12: =_xlfn.XLOOKUP(F12,BBDD!$S:$S,BBDD!$AR:$AR) -> 11852490 | R12: =IF(G12<=30,"ROTACION ALTA",IF(G12<30,"ROTACION MEDIA",IF(G12<60,"ROTACION BAJA",IF(G12>60,"LIQUIDAR")))) -> ROTACION ALTA
A13: CHERY | B13: TIGGO 2 | C13: TIGGO 2 1.5 | D13: DISPONIBLE | E13: 2021 | F13: PPPB53 | G13: 14 | H13: 30197 | I13: IMPORTADORA TRENTO LTDA | J13: =CONCATENATE(B13,C13,E13) -> TIGGO 2TIGGO 2 1.52021 | L13: =IFERROR(_xlfn.XLOOKUP(F13,'PRECIO TOMA HISTORICO '!$A:$A,'PRECIO TOMA HISTORICO '!$B:$B,_xlfn.XLOOKUP(F13,BBDD!$S:$S,BBDD!$AO:$AO,"",0,1),0,-1),"") -> 6000000 | N13: =_xlfn.XLOOKUP(F13,BBDD!$S:$S,BBDD!$AS:$AS) -> 7290000 | O13: =IFERROR(VLOOKUP(F13,'PRECIO MERCADO'!D:E,2,0),"0") -> 7310000 | P13: =_xlfn.XLOOKUP(F13,BBDD!$S:$S,BBDD!$AO:$AO) -> 6000000 | Q13: =_xlfn.XLOOKUP(F13,BBDD!$S:$S,BBDD!$AR:$AR) -> 6219240 | R13: =IF(G13<=30,"ROTACION ALTA",IF(G13<30,"ROTACION MEDIA",IF(G13<60,"ROTACION BAJA",IF(G13>60,"LIQUIDAR")))) -> ROTACION ALTA
... A262: SSANGYONG | B262: TORRES | C262: TORRES 4X2 1.5 | D262: DISPONIBLE | E262: 2024 | F262: TLRS70 | G262: 256 | H262: 35150 | I262: IMPORTADORA TRENTO LTDA | J262: =CONCATENATE(B262,C262,E262) -> TORRESTORRES 4X2 1.52024 | L262: =IFERROR(_xlfn.XLOOKUP(F262,'PRECIO TOMA HISTORICO '!$A:$A,'PRECIO TOMA HISTORICO '!$B:$B,_xlfn.XLOOKUP(F262,BBDD!$S:$S,BBDD!$AO:$AO,"",0,1),0,-1),"") -> 16400000 | N262: =_xlfn.XLOOKUP(F262,BBDD!$S:$S,BBDD!$AS:$AS) -> 17490000 | O262: =IFERROR(VLOOKUP(F262,'PRECIO MERCADO'!D:E,2,0),"0") -> 19300000 | P262: =_xlfn.XLOOKUP(F262,BBDD!$S:$S,BBDD!$AO:$AO) -> 16400000 | Q262: =_xlfn.XLOOKUP(F262,BBDD!$S:$S,BBDD!$AR:$AR) -> 16772030 | R262: =IF(G262<=30,"ROTACION ALTA",IF(G262<30,"ROTACION MEDIA",IF(G262<60,"ROTACION BAJA",IF(G262>60,"LIQUIDAR")))) -> LIQUIDAR
A263: SUBARU | B263: FORESTER | C263: FORESTER 4X4 2.0 AT | E263: 2023 | F263: SFLW10 | G263: 14 | H263: 60800 | I263: IMPORTADORA TRENTO LTDA | J263: =CONCATENATE(B263,C263,E263) -> FORESTERFORESTER 4X4 2.0 AT2023 | L263: =IFERROR(_xlfn.XLOOKUP(F263,'PRECIO TOMA HISTORICO '!$A:$A,'PRECIO TOMA HISTORICO '!$B:$B,_xlfn.XLOOKUP(F263,BBDD!$S:$S,BBDD!$AO:$AO,"",0,1),0,-1),"") -> 19000000 | N263: =_xlfn.XLOOKUP(F263,BBDD!$S:$S,BBDD!$AS:$AS) -> 22490000 | O263: =IFERROR(VLOOKUP(F263,'PRECIO MERCADO'!D:E,2,0),"0") -> 22500000 | P263: =_xlfn.XLOOKUP(F263,BBDD!$S:$S,BBDD!$AO:$AO) -> 19000000 | Q263: =_xlfn.XLOOKUP(F263,BBDD!$S:$S,BBDD!$AR:$AR) -> 19414240 | R263: =IF(G263<=30,"ROTACION ALTA",IF(G263<30,"ROTACION MEDIA",IF(G263<60,"ROTACION BAJA",IF(G263>60,"LIQUIDAR")))) -> ROTACION ALTA
A264: SUBARU | B264: FORESTER | C264: FORESTER 4X4 2.0 AT | D264: DISPONIBLE | E264: 2024 | F264: TPCS18 | G264: 111 | H264: 76000 | I264: IMPORTADORA TRENTO LTDA | J264: =CONCATENATE(B264,C264,E264) -> FORESTERFORESTER 4X4 2.0 AT2024 | L264: =IFERROR(_xlfn.XLOOKUP(F264,'PRECIO TOMA HISTORICO '!$A:$A,'PRECIO TOMA HISTORICO '!$B:$B,_xlfn.XLOOKUP(F264,BBDD!$S:$S,BBDD!$AO:$AO,"",0,1),0,-1),"") -> 19000000 | N264: =_xlfn.XLOOKUP(F264,BBDD!$S:$S,BBDD!$AS:$AS) -> 20490000 | O264: =IFERROR(VLOOKUP(F264,'PRECIO MERCADO'!D:E,2,0),"0") -> 20900000 | P264: =_xlfn.XLOOKUP(F264,BBDD!$S:$S,BBDD!$AO:$AO) -> 19000000 | Q264: =_xlfn.XLOOKUP(F264,BBDD!$S:$S,BBDD!$AR:$AR) -> 19414240 | R264: =IF(G264<=30,"ROTACION ALTA",IF(G264<30,"ROTACION MEDIA",IF(G264<60,"ROTACION BAJA",IF(G264>60,"LIQUIDAR")))) -> LIQUIDAR
A265: SUBARU | B265: FORESTER | C265: FORESTER 4X4 2.0 AT | D265: EN PREPARACION | E265: 2023 | F265: SGTD48 | G265: 19 | H265: 48000 | I265: IMPORTADORA TRENTO LTDA | J265: =CONCATENATE(B265,C265,E265) -> FORESTERFORESTER 4X4 2.0 AT2023 | L265: =IFERROR(_xlfn.XLOOKUP(F265,'PRECIO TOMA HISTORICO '!$A:$A,'PRECIO TOMA HISTORICO '!$B:$B,_xlfn.XLOOKUP(F265,BBDD!$S:$S,BBDD!$AO:$AO,"",0,1),0,-1),"") -> 17000000 | N265: =_xlfn.XLOOKUP(F265,BBDD!$S:$S,BBDD!$AS:$AS) -> 22490000 | O265: =IFERROR(VLOOKUP(F265,'PRECIO MERCADO'!D:E,2,0),"0") -> 23100000 | P265: =_xlfn.XLOOKUP(F265,BBDD!$S:$S,BBDD!$AO:$AO) -> 17000000 | Q265: =_xlfn.XLOOKUP(F265,BBDD!$S:$S,BBDD!$AR:$AR) -> 17384240 | R265: =IF(G265<=30,"ROTACION ALTA",IF(G265<30,"ROTACION MEDIA",IF(G265<60,"ROTACION BAJA",IF(G265>60,"LIQUIDAR")))) -> ROTACION ALTA
A266: SUBARU | B266: FORESTER | C266: FORESTER CVT 4X4 2.0 AUT | D266: EN PREPARACION | E266: 2020 | F266: PJDF47 | G266: 18 | H266: 47000 | I266: IMPORTADORA TRENTO LTDA | J266: =CONCATENATE(B266,C266,E266) -> FORESTERFORESTER CVT 4X4 2.0 AUT2020 | L266: =IFERROR(_xlfn.XLOOKUP(F266,'PRECIO TOMA HISTORICO '!$A:$A,'PRECIO TOMA HISTORICO '!$B:$B,_xlfn.XLOOKUP(F266,BBDD!$S:$S,BBDD!$AO:$AO,"",0,1),0,-1),"") -> 15700000 | N266: =_xlfn.XLOOKUP(F266,BBDD!$S:$S,BBDD!$AS:$AS) -> 17990000 | O266: =IFERROR(VLOOKUP(F266,'PRECIO MERCADO'!D:E,2,0),"0") -> 18800000 | P266: =_xlfn.XLOOKUP(F266,BBDD!$S:$S,BBDD!$AO:$AO) -> 15700000 | Q266: =_xlfn.XLOOKUP(F266,BBDD!$S:$S,BBDD!$AR:$AR) -> 16064740 | R266: =IF(G266<=30,"ROTACION ALTA",IF(G266<30,"ROTACION MEDIA",IF(G266<60,"ROTACION BAJA",IF(G266>60,"LIQUIDAR")))) -> ROTACION ALTA
A267: SUBARU | B267: XV | C267: NEW XV 2.0I AWD CVT DYNAMIC | D267: NO DISPONIBLE | E267: 2019 | F267: LBGX66 | G267: 1411 | H267: 6400 | I267: CALLEGARI E HIJOS LTDA | J267: =CONCATENATE(B267,C267,E267) -> XVNEW XV 2.0I AWD CVT DYNAMIC2019 | L267: =IFERROR(_xlfn.XLOOKUP(F267,'PRECIO TOMA HISTORICO '!$A:$A,'PRECIO TOMA HISTORICO '!$B:$B,_xlfn.XLOOKUP(F267,BBDD!$S:$S,BBDD!$AO:$AO,"",0,1),0,-1),"") -> 12497480 | N267: =_xlfn.XLOOKUP(F267,BBDD!$S:$S,BBDD!$AS:$AS) -> 15900000 | O267: =IFERROR(VLOOKUP(F267,'PRECIO MERCADO'!D:E,2,0),"0") -> 15500000 | P267: =_xlfn.XLOOKUP(F267,BBDD!$S:$S,BBDD!$AO:$AO) -> 12497480 | Q267: =_xlfn.XLOOKUP(F267,BBDD!$S:$S,BBDD!$AR:$AR) -> 15632904 | R267: =IF(G267<=30,"ROTACION ALTA",IF(G267<30,"ROTACION MEDIA",IF(G267<60,"ROTACION BAJA",IF(G267>60,"LIQUIDAR")))) -> LIQUIDAR
A268: TOYOTA | B268: RAV | C268: RAV4 CVT 2.0 | D268: EN PREPARACION | E268: 2024 | F268: SYRB80 | G268: 76 | H268: 56985 | I268: IMPORTADORA TRENTO LTDA | J268: =CONCATENATE(B268,C268,E268) -> RAVRAV4 CVT 2.02024 | L268: =IFERROR(_xlfn.XLOOKUP(F268,'PRECIO TOMA HISTORICO '!$A:$A,'PRECIO TOMA HISTORICO '!$B:$B,_xlfn.XLOOKUP(F268,BBDD!$S:$S,BBDD!$AO:$AO,"",0,1),0,-1),"") -> 17000000 | N268: =_xlfn.XLOOKUP(F268,BBDD!$S:$S,BBDD!$AS:$AS) -> 20290000 | O268: =IFERROR(VLOOKUP(F268,'PRECIO MERCADO'!D:E,2,0),"0") -> 21800000 | P268: =_xlfn.XLOOKUP(F268,BBDD!$S:$S,BBDD!$AO:$AO) -> 17000000 | Q268: =_xlfn.XLOOKUP(F268,BBDD!$S:$S,BBDD!$AR:$AR) -> 17384240 | R268: =IF(G268<=30,"ROTACION ALTA",IF(G268<30,"ROTACION MEDIA",IF(G268<60,"ROTACION BAJA",IF(G268>60,"LIQUIDAR")))) -> LIQUIDAR
A269: VOLKSWAGEN | B269: AMAROK | C269: AMAROK DCAB TDI DOHC 4X4 2.0 AUT | D269: NO DISPONIBLE | E269: 2023 | F269: SRHZ99 | G269: 868 | H269: 15600 | I269: IMPORTADORA TRENTO LTDA | J269: =CONCATENATE(B269,C269,E269) -> AMAROKAMAROK DCAB TDI DOHC 4X4 2.0 AUT2023 | L269: =IFERROR(_xlfn.XLOOKUP(F269,'PRECIO TOMA HISTORICO '!$A:$A,'PRECIO TOMA HISTORICO '!$B:$B,_xlfn.XLOOKUP(F269,BBDD!$S:$S,BBDD!$AO:$AO,"",0,1),0,-1),"") -> 28500000 | N269: =_xlfn.XLOOKUP(F269,BBDD!$S:$S,BBDD!$AS:$AS) -> 33190000 | O269: =IFERROR(VLOOKUP(F269,'PRECIO MERCADO'!D:E,2,0),"0") -> 31500000 | P269: =_xlfn.XLOOKUP(F269,BBDD!$S:$S,BBDD!$AO:$AO) -> 28500000 | Q269: =_xlfn.XLOOKUP(F269,BBDD!$S:$S,BBDD!$AR:$AR) -> 29597663 | R269: =IF(G269<=30,"ROTACION ALTA",IF(G269<30,"ROTACION MEDIA",IF(G269<60,"ROTACION BAJA",IF(G269>60,"LIQUIDAR")))) -> LIQUIDAR
A270: VOLKSWAGEN | B270: GOLF | C270: GOLF HB 1.4 AUT | D270: NO DISPONIBLE | E270: 2016 | F270: HTSJ81 | G270: 46 | H270: 80000 | I270: IMPORTADORA TRENTO LTDA | J270: =CONCATENATE(B270,C270,E270) -> GOLFGOLF HB 1.4 AUT2016 | L270: =IFERROR(_xlfn.XLOOKUP(F270,'PRECIO TOMA HISTORICO '!$A:$A,'PRECIO TOMA HISTORICO '!$B:$B,_xlfn.XLOOKUP(F270,BBDD!$S:$S,BBDD!$AO:$AO,"",0,1),0,-1),"") -> 6600000 | N270: =_xlfn.XLOOKUP(F270,BBDD!$S:$S,BBDD!$AS:$AS) -> 8990000 | O270: =IFERROR(VLOOKUP(F270,'PRECIO MERCADO'!D:E,2,0),"0") -> 10100000 | P270: =_xlfn.XLOOKUP(F270,BBDD!$S:$S,BBDD!$AO:$AO) -> 6600000 | Q270: =_xlfn.XLOOKUP(F270,BBDD!$S:$S,BBDD!$AR:$AR) -> 6828240 | R270: =IF(G270<=30,"ROTACION ALTA",IF(G270<30,"ROTACION MEDIA",IF(G270<60,"ROTACION BAJA",IF(G270>60,"LIQUIDAR")))) -> ROTACION BAJA
A271: ZX AUTO | B271: TERRALORD | C271: TERRALORD 4X4 2.5 AUT | D271: NO DISPONIBLE | E271: 2022 | F271: RSWX56 | G271: 162 | H271: 65000 | I271: IMPORTADORA TRENTO LTDA | J271: =CONCATENATE(B271,C271,E271) -> TERRALORDTERRALORD 4X4 2.5 AUT2022 | L271: =IFERROR(_xlfn.XLOOKUP(F271,'PRECIO TOMA HISTORICO '!$A:$A,'PRECIO TOMA HISTORICO '!$B:$B,_xlfn.XLOOKUP(F271,BBDD!$S:$S,BBDD!$AO:$AO,"",0,1),0,-1),"") -> 11500000 | N271: =_xlfn.XLOOKUP(F271,BBDD!$S:$S,BBDD!$AS:$AS) -> 13690000 | O271: =IFERROR(VLOOKUP(F271,'PRECIO MERCADO'!D:E,2,0),"0") -> 14100000 | P271: =_xlfn.XLOOKUP(F271,BBDD!$S:$S,BBDD!$AO:$AO) -> 11500000 | Q271: =_xlfn.XLOOKUP(F271,BBDD!$S:$S,BBDD!$AR:$AR) -> 11801740 | R271: =IF(G271<=30,"ROTACION ALTA",IF(G271<30,"ROTACION MEDIA",IF(G271<60,"ROTACION BAJA",IF(G271>60,"LIQUIDAR")))) -> LIQUIDAR

Sheet PRECIO TOMA HISTORICO 
A1: Patente | B1: Precio toma autored
A2: PFRX97 | B2: 14500000
A3: LSYG12 | B3: 15000000
A4: JZGD93 | B4: 17700000
A5: HRWV51 | B5: 20500000
A6: KLHJ78 | B6: 11000000
A7: PFSC16 | B7: 11700000
A8: SCGS82 | B8: 6500000
A9: LVXR90 | B9: 8000000
A10: LYPF74 | B10: 8000000
A11: LDVR65 | B11: 7700000
A12: RFVX24 | B12: 16000000
A13: RTLV30 | B13: 14800000
... A2472: VYCH76 | B2472: 8000000

Sheet PRECIO MERCADO
A1: FECHA CONSULTA | B1: MARCA | C1: MODELO | D1: PATENTE | E1: VALOR AUTOPRESS
A2: 2024-03-01 14:46:22 | B2: NISSAN | C2: QASHQAI | D2: SWTP31 | E2: 21800000
A3: 2024-03-01 14:51:13 | B3: PEUGEOT | C3: 3008 | D3: No informado | E3: 15400000
A4: 2024-03-01 14:53:18 | B4: FORD | C4: F-150 NEW | D4: KLPL67 | E4: 27800000
A5: 2024-03-01 14:54:44 | B5: CHERY | C5: TIGGO 7 | D5: RVPX58 | E5: 14100000
A6: 2024-03-01 14:57:14 | B6: FORD | C6: TERRITORY | D6: SVRR83 | E6: 16400000
A7: 2024-03-01 14:59:00 | B7: DFSK | C7: 500 | D7: SGXX60 | E7: 8800000
A8: 2024-03-01 15:02:52 | B8: DFSK | C8: 580 | D8: SYXS66 | E8: 12700000
A9: 2024-03-02 07:29:35 | B9: SSANGYONG | C9: NEW MUSSO | D9: RFKS23 | E9: 18000000
A10: 2024-03-02 07:31:21 | B10: KIA | C10: OPIRUS | D10: CDLV87 | E10: 5820000
A11: 2024-03-02 07:34:07 | B11: FORD | C11: F-150 NEW | D11: SPTC39 | E11: 43800000
A12: 2024-05-23 12:21:26 | B12: NISSAN | C12: NEW QASHQAI | D12: LLBT84 | E12: 11800000
A13: 2024-05-23 12:29:53 | B13: CHEVROLET | C13: ALL NEW TRACKER | D13: RSDZ65 | E13: 13400000
A14: 2025-06-19 09:51:03 | B14: HONDA | C14: HR-V | D14: PKTY15 | E14: 13100000
A15: 2025-12-23 06:11:20 | B15: FORD | C15: F-150 NEW | D15: TCTV39 | E15: 43400000
A16: 2025-12-23 06:50:57 | B16: FORD | C16: BRONCO | D16: No informado | E16: 48700000
A17: 2025-12-23 07:32:14 | B17: PEUGEOT | C17: NUEVO 308 | D17: SLRJ93 | E17: 16500000
A18: 2025-12-23 07:51:24 | B18: HYUNDAI | C18: ACCENT | D18: RDJS62 | E18: 10500000
A19: 2025-12-23 08:01:01 | B19: CHEVROLET | C19: ALL NEW TRACKER | D19: SBWS64 | E19: 11000000
A20: 2025-12-23 08:02:39 | B20: PEUGEOT | C20: 3008 | D20: LVCS57 | E20: 15000000
A21: 2025-12-23 08:19:28 | B21: MITSUBISHI | C21: MONTERO SPORT NEW | D21: LBVX49 | E21: 20200000
A22: 2025-12-23 08:27:10 | B22: FORD | C22: F-150 NEW | D22: TCTV39 | E22: 43400000
A23: 2025-12-23 09:07:44 | B23: JEEP | C23: GRAND CHEROKEE | D23: THRJ80 | E23: 43000000
A24: 2025-12-23 09:21:47 | B24: RENAULT | C24: KWID | D24: SJHZ88 | E24: 6780000
A25: 2025-12-23 09:31:04 | B25: PEUGEOT | C25: NUEVO 2008 | D25: RJCW76 | E25: 12400000
A26: 2025-12-23 09:37:46 | B26: PEUGEOT | C26: NUEVO 208 | D26: VBBD69 | E26: 19000000
A27: 2025-12-23 09:45:53 | B27: DFSK | C27: 560 | D27: RCBJ98 | E27: 8200000
A28: 2025-12-23 09:50:23 | B28: PEUGEOT | C28: NUEVO 3008 | D28: PRVP72 | E28: 15200000
A29: 2025-12-23 09:58:07 | B29: FORD | C29: NUEVO MUSTANG | D29: VDBS14 | E29: 45800000
A30: 2025-12-23 10:06:57 | B30: CHERY | C30: TIGGO 8 | D30: PSGB54 | E30: 11500000
A31: 2025-12-23 10:16:14 | B31: CHERY | C31: TIGGO 8 PRO | D31: SPPY18 | E31: 14700000
A32: 2025-12-23 10:30:51 | B32: TOYOTA | C32: COROLLA CROSS | D32: RVKL20 | E32: 23300000
A33: 2025-12-23 11:23:38 | B33: RAM | C33: 1500 | D33: SHLW33 | E33: 31400000
A34: 2025-12-23 11:29:51 | B34: NISSAN | C34: NUEVA X-TRAIL | D34: SHDG89 | E34: 20100000
A35: 2025-12-23 11:54:02 | B35: EXEED | C35: LX | D35: TRJC45 | E35: 14700000
A36: 2025-12-23 12:14:38 | B36: CHANGAN | C36: CS15 | D36: KTCV74 | E36: 5850000
A37: 2025-12-23 12:23:10 | B37: PEUGEOT | C37: 3008 | D37: TLRT68 | E37: 25800000
A38: 2025-12-23 13:16:31 | B38: CHERY | C38: TIGGO 2 | D38: RYDL24 | E38: 7600000
A39: 2025-12-24 07:06:40 | B39: KIA | C39: SOLUTO | D39: SYPS56 | E39: 8600000
A40: 2025-12-24 07:36:01 | B40: NISSAN | C40: QASHQAI | D40: RBXV26 | E40: 13000000
A41: 2025-12-24 07:45:06 | B41: PEUGEOT | C41: NUEVO 5008 | D41: SKSZ62 | E41: 23700000
A42: 2025-12-24 08:09:35 | B42: PEUGEOT | C42: LANDTREK | D42: RSYF47 | E42: 17200000
A43: 2025-12-24 08:21:52 | B43: CHERY | C43: TIGGO 3 | D43: RBZD91 | E43: 8400000
A44: 2025-12-24 08:23:58 | B44: FORD | C44: NEW F-150 RAPTOR | D44: LYPC19 | E44: 45300000
A45: 2025-12-24 08:26:35 | B45: PEUGEOT | C45: NEW 3008 | D45: TZTC96 | E45: 23900000
A46: 2025-12-24 08:32:16 | B46: PEUGEOT | C46: NUEVO 2008 | D46: SWBX38 | E46: 16900000
A47: 2025-12-24 08:33:32 | B47: FORD | C47: NUEVA EXPLORER | D47: TXYY85 | E47: 49700000
A48: 2025-12-24 08:39:58 | B48: FORD | C48: NUEVA RANGER | D48: SYPL90 | E48: 26400000
A49: 2025-12-24 08:43:12 | B49: BAIC | C49: X55 | D49: TRTW63 | E49: 12000000
... A55: 2025-12-24 09:01:36 | B55: FORD | C55: EDGE | D55: TFFD89 | E55: 26100000
A56: 2025-12-24 09:05:40 | B56: DFSK | C56: 580 | D56: SJJH10 | E56: 10300000
A57: 2025-12-24 09:07:42 | B57: NISSAN | C57: NUEVO SENTRA | D57: SJRW76 | E57: 15600000
A58: 2025-12-24 09:14:13 | B58: PEUGEOT | C58: NEW RIFTER | D58: TZHX32 | E58: 20500000
A59: 2025-12-24 09:14:33 | B59: PEUGEOT | C59: 2008 | D59: LXLT74 | E59: 12900000
A60: 2025-12-24 09:19:54 | B60: FORD | C60: TERRITORY | D60: RRWP38 | E60: 12800000
A61: 2025-12-24 09:22:59 | B61: HAVAL | C61: NEW JOLION | D61: TFRF61 | E61: 12300000
A62: 2025-12-24 09:25:20 | B62: PEUGEOT | C62: NUEVO 308 | D62: TJSJ77 | E62: 17900000
A63: 2025-12-24 09:27:08 | B63: BRILLIANCE | C63: X30 | D63: RJRF51 | E63: 5270000
A64: 2025-12-24 09:27:40 | B64: CITROEN | C64: C5 AIRCROSS | D64: LVWV64 | E64: 13500000
A65: 2025-12-24 10:12:16 | B65: JMC | C65: GRAND AVENUE | D65: TRTB48 | E65: 21500000
A66: 2025-12-24 10:22:37 | B66: KIA | C66: RIO 4 | D66: TBZP32 | E66: 12300000
A67: 2025-12-26 06:48:21 | B67: CHEVROLET | C67: NEW COLORADO | D67: SJRV42 | E67: 23200000
A68: 2025-12-26 06:50:30 | B68: PEUGEOT | C68: NEW RIFTER | D68: VBBC94 | E68: 20600000
A69: 2025-12-26 06:55:24 | B69: DFSK | C69: 580 | D69: SJJH94 | E69: 10000000
A70: 2025-12-26 07:00:49 | B70: PEUGEOT | C70: NUEVO 5008 | D70: SRWC14 | E70: 24900000
A71: 2025-12-26 07:01:38 | B71: PEUGEOT | C71: LANDTREK | D71: SLJL53 | E71: 18400000
A72: 2025-12-26 07:02:27 | B72: FIAT | C72: ARGO | D72: RXCG22 | E72: 8800000
A73: 2025-12-26 07:04:49 | B73: FORD | C73: F-150 NEW | D73: TJDB78 | E73: 49800000
A74: 2025-12-26 07:06:33 | B74: PEUGEOT | C74: NUEVO 3008 | D74: RSJF58 | E74: 20700000
A75: 2025-12-26 07:07:21 | B75: HAVAL | C75: H6 GT | D75: THRJ85 | E75: 19400000
A76: 2025-12-26 07:09:45 | B76: OMODA | C76: C5 | D76: TSSG86 | E76: 12800000
A77: 2025-12-26 07:11:10 | B77: PEUGEOT | C77: LANDTREK | D77: SLWF83 | E77: 17700000
A78: 2025-12-26 07:12:57 | B78: NISSAN | C78: VERSA | D78: RBJH77 | E78: 9800000
A79: 2025-12-26 07:14:22 | B79: JAC | C79: JS2 | D79: TJDF16 | E79: 9000000
A80: 2025-12-26 07:15:06 | B80: RAM | C80: NEW 1500 | D80: SCZP26 | E80: 34300000
A81: 2025-12-26 07:16:50 | B81: CHANGAN | C81: CX70 | D81: PYXJ35 | E81: 9500000
... A93: 2025-12-26 08:00:19 | B93: FORD | C93: F-150 | D93: PKTZ57 | E93: 29800000
A94: 2025-12-26 08:00:55 | B94: PEUGEOT | C94: 3008 | D94: TDYK32 | E94: 17100000
A95: 2025-12-26 08:03:31 | B95: FORD | C95: TERRITORY | D95: SSBR38 | E95: 13100000
A96: 2025-12-26 08:03:39 | B96: PEUGEOT | C96: NUEVO 2008 | D96: SVGL43 | E96: 18800000
A97: 2025-12-26 08:23:14 | B97: KIA | C97: NIRO | D97: TFGR11 | E97: 30400000
A98: 2025-12-26 08:27:01 | B98: SSANGYONG | C98: NEW KORANDO | D98: PKBJ31 | E98: 12100000
A99: 2025-12-26 08:28:00 | B99: PEUGEOT | C99: NUEVO 3008 | D99: SPSZ45 | E99: 19200000
A100: 2025-12-26 08:35:14 | B100: HYUNDAI | C100: ALL NEW SANTA FE | D100: TTVD23 | E100: 32100000
A101: 2025-12-26 08:37:13 | B101: PEUGEOT | C101: NUEVO 5008 | D101: SDGD26 | E101: 22000000
A102: 2025-12-26 08:42:21 | B102: FORD | C102: RANGER | D102: SWTR81 | E102: 18700000
A103: 2025-12-26 08:48:10 | B103: CHEVROLET | C103: ONIX | D103: SPSY59 | E103: 9900000
A104: 2025-12-26 08:49:38 | B104: FORD | C104: NUEVA RANGER | D104: TJSK30 | E104: 36200000
A105: 2025-12-26 08:50:52 | B105: SUZUKI | C105: NUEVO SWIFT | D105: SZHT24 | E105: 9800000
A106: 2025-12-26 08:54:20 | B106: JMC | C106: VIGUS | D106: SKSZ63 | E106: 11500000
... A111: 2025-12-26 09:19:15 | B111: OPEL | C111: NEW GRANDLAND | D111: TFGL44 | E111: 17400000
A112: 2025-12-26 09:21:40 | B112: DFSK | C112: 560 | D112: SSTS80 | E112: 8900000
A113: 2025-12-26 09:24:32 | B113: NISSAN | C113: QASHQAI | D113: SXTX58 | E113: 17300000
A114: 2025-12-26 09:27:22 | B114: NISSAN | C114: QASHQAI | D114: SFLX53 | E114: 17400000
A115: 2025-12-26 09:31:39 | B115: JEEP | C115: COMPASS | D115: TSYZ42 | E115: 24400000
A116: 2025-12-26 09:33:59 | B116: FORD | C116: NUEVA RANGER | D116: TSSB95 | E116: 49500000
A117: 2025-12-26 09:44:17 | B117: NISSAN | C117: QASHQAI | D117: TFGP60 | E117: 22700000
A118: 2025-12-26 09:52:13 | B118: NISSAN | C118: NUEVA X-TRAIL | D118: SSTS34 | E118: 27600000
A119: 2025-12-26 09:53:03 | B119: FORD | C119: TERRITORY | D119: RPSZ19 | E119: 12400000
A120: 2025-12-26 10:03:24 | B120: TOYOTA | C120: C-HR | D120: PXVL80 | E120: 19000000
...

Sheet INFORME VENTAS
A1: Marca | B1: Modelo | C1: Versión | D1: Año | E1: Modelo-version-año | F1: Placa Patente | G1: Suma de Unidad Venta | H1: Suma de Unidad Costo
G2: 0 | H2: 0
A3: AUDI | B3: A3 | C3: A3 HB 1.4 AUT | D3: 2019 | E3: =CONCATENATE(B3,C3,D3) -> A3A3 HB 1.4 AUT2019 | F3: KZRK80 | G3: 14582000 | H3: 15000000
A4: AUDI | B4: A3 | C4: A3 SEDAN 35 TFSI 1.4 AUT | D4: 2022 | E4: =CONCATENATE(B4,C4,D4) -> A3A3 SEDAN 35 TFSI 1.4 AUT2022 | F4: RTLW29 | G4: 22990000 | H4: 23800000
A5: AUDI | B5: Q2 | C5: Q2 35 TFSI 1.4 AUT | D5: 2023 | E5: =CONCATENATE(B5,C5,D5) -> Q2Q2 35 TFSI 1.4 AUT2023 | F5: SPZD69 | G5: 26190000 | H5: 22500000
A6: AUDI | B6: Q3 | C6: Q3 35 TFSI 1.4 AUT | D6: 2023 | E6: =CONCATENATE(B6,C6,D6) -> Q3Q3 35 TFSI 1.4 AUT2023 | F6: SRZH16 | G6: 25990000 | H6: 23200000
A7: AUDI | B7: Q3 | C7: Q3 35 TFSI SPORTBACK 1.4 AUT | D7: 2023 | E7: =CONCATENATE(B7,C7,D7) -> Q3Q3 35 TFSI SPORTBACK 1.4 AUT2023 | F7: SLYZ27 | G7: 33990000 | H7: 29000000
A8: AUDI | B8: Q5 | C8: Q5 TDI 2.0 | D8: 2012 | E8: =CONCATENATE(B8,C8,D8) -> Q5Q5 TDI 2.02012 | F8: DTLC56 | G8: 11000000 | H8: 15000000
A9: AUDI | B9: Q5 | C9: Q5 TFSI 4X4 2.0 AUT | D9: 2020 | E9: =CONCATENATE(B9,C9,D9) -> Q5Q5 TFSI 4X4 2.0 AUT2020 | F9: LPXH29 | G9: 25390000 | H9: 31300000
A10: AUDI | B10: Q5 | C10: Q5 TFSI 4X4 2.0 AUT | D10: 2020 | E10: =CONCATENATE(B10,C10,D10) -> Q5Q5 TFSI 4X4 2.0 AUT2020 | F10: PFRP23 | G10: 23490000 | H10: 32000000
A11: AUDI | B11: Q7 | C11: Q7 TDI 4X4 3.0 AUT | D11: 2019 | E11: =CONCATENATE(B11,C11,D11) -> Q7Q7 TDI 4X4 3.0 AUT2019 | F11: KWYD58 | G11: 33490000 | H11: 29000000
A12: BAIC | B12: BAIC | C12: X35 1.5 | D12: 2019 | E12: =CONCATENATE(B12,C12,D12) -> BAICX35 1.52019 | F12: LGXV34 | G12: 7990000 | H12: 8800000
A13: BAIC | B13: BAIC | C13: X35 1.5 | D13: 2023 | E13: =CONCATENATE(B13,C13,D13) -> BAICX35 1.52023 | F13: SBLF15 | G13: 7890000 | H13: 6500000
A14: BAIC | B14: BAIC | C14: X55 1.5T | D14: 2023 | E14: =CONCATENATE(B14,C14,D14) -> BAICX55 1.5T2023 | F14: SSRS44 | G14: 8690000 | H14: 6800000
... A326: CITROEN | B326: C4 | C326: C4 1.2 AT | D326: 2025 | E326: =CONCATENATE(B326,C326,D326) -> C4C4 1.2 AT2025 | F326: VBHL43 | G326: 18990000 | H326: 16500000
A327: CITROEN | B327: C4 | C327: C4 1.5 AUT | D327: 2025 | E327: =CONCATENATE(B327,C327,D327) -> C4C4 1.5 AUT2025 | G327: 17990000 | H327: 0
A328: CITROEN | B328: C4 | C328: C4 1.5 AUT | D328: 2025 | E328: =CONCATENATE(B328,C328,D328) -> C4C4 1.5 AUT2025 | F328: TXZB72 | G328: 17990000 | H328: 14500000
A329: CITROEN | B329: C4 | C329: C4 1.6 | D329: 2010 | E329: =CONCATENATE(B329,C329,D329) -> C4C4 1.62010 | F329: CJZV22 | G329: 2000000 | H329: 3600000
A330: CITROEN | B330: C4 | C330: C4 CACTUS HDI 1.6 | D330: 2016 | E330: =CONCATENATE(B330,C330,D330) -> C4C4 CACTUS HDI 1.62016 | F330: HRWS66 | G330: 9690000 | H330: 8000000
A331: CITROEN | B331: C4 | C331: C4 HDI 1.6 | D331: 2016 | E331: =CONCATENATE(B331,C331,D331) -> C4C4 HDI 1.62016 | F331: HJSY32 | G331: 8490000 | H331: 7000000
A332: CITROEN | B332: C5 | C332: C5 AIRCROSS 1.5 AUT | D332: 2019 | E332: =CONCATENATE(B332,C332,D332) -> C5C5 AIRCROSS 1.5 AUT2019 | G332: 16490000 | H332: 0
A333: CITROEN | B333: C5 | C333: C5 AIRCROSS 1.5 AUT | D333: 2019 | E333: =CONCATENATE(B333,C333,D333) -> C5C5 AIRCROSS 1.5 AUT2019 | F333: LFXV54 | G333: 27980000 | H333: 29800000
A334: CITROEN | B334: C5 | C334: C5 AIRCROSS 1.5 AUT | D334: 2020 | E334: =CONCATENATE(B334,C334,D334) -> C5C5 AIRCROSS 1.5 AUT2020 | F334: LVWV64 | G334: 14190000 | H334: 12000000
A335: CITROEN | B335: C5 | C335: C5 AIRCROSS BHDI 1.5 AUT | D335: 2020 | E335: =CONCATENATE(B335,C335,D335) -> C5C5 AIRCROSS BHDI 1.5 AUT2020 | F335: LVWY70 | G335: 21990000 | H335: 21330300
A336: CITROEN | B336: C5 | C336: C5 AIRCROSS BLUEHDI 1.5 AUT | D336: 2022 | E336: =CONCATENATE(B336,C336,D336) -> C5C5 AIRCROSS BLUEHDI 1.5 AUT2022 | F336: PCFG80 | G336: 18090000 | H336: 15500000
A337: CITROEN | B337: C5 | C337: C5 AIRCROSS CVA8 STT 1.5 AUT | D337: 2024 | E337: =CONCATENATE(B337,C337,D337) -> C5C5 AIRCROSS CVA8 STT 1.5 AUT2024 | F337: TCTS12 | G337: 19150000 | H337: 16750000
A338: CITROEN | B338: C-ELYSEE | C338: C ELYSEE 1.2 | D338: 2018 | E338: =CONCATENATE(B338,C338,D338) -> C-ELYSEEC ELYSEE 1.22018 | F338: KGLK41 | G338: 6100000 | H338: 4900000
A339: CITROEN | B339: C-ELYSEE | C339: C ELYSEE 1.6 | D339: 2017 | E339: =CONCATENATE(B339,C339,D339) -> C-ELYSEEC ELYSEE 1.62017 | F339: JGCC12 | G339: 5590000 | H339: 5000000
A340: CITROEN | B340: SPACETOURER | C340: BUSINEES HDI 2.0 | D340: 2022 | E340: =CONCATENATE(B340,C340,D340) -> SPACETOURERBUSINEES HDI 2.02022 | F340: PCFG40 | G340: 20390000 | H340: 17500000
A341: DFLM | B341: JOYEAR | C341: JOYEAR SX5 1.6 | D341: 2021 | E341: =CONCATENATE(B341,C341,D341) -> JOYEARJOYEAR SX5 1.62021 | F341: RFHP74 | G341: 7746004 | H341: 6500000
A342: DFM | B342: AX4 | C342: AX4 LUXURY 1.6 AUT | D342: 2021 | E342: =CONCATENATE(B342,C342,D342) -> AX4AX4 LUXURY 1.6 AUT2021 | F342: PSPC17 | G342: 7990000 | H342: 5700000
A343: DFM | B343: JOYEAR | C343: JOYEAR SX5 1.6 | D343: 2022 | E343: =CONCATENATE(B343,C343,D343) -> JOYEARJOYEAR SX5 1.62022 | F343: RXSL88 | G343: 7850000 | H343: 6500000
A344: DFM | B344: T5L | C344: T5L LUX 1.8 | D344: 2025 | E344: =CONCATENATE(B344,C344,D344) -> T5LT5L LUX 1.82025 | F344: TSRG98 | G344: 11990000 | H344: 10700000
... A380: DFSK | B380: CARGO | C380: CARGO VAN C35 1.5 | D380: 2022 | E380: =CONCATENATE(B380,C380,D380) -> CARGOCARGO VAN C35 1.52022 | F380: SCGS46 | G380: 10265960 | H380: 12000000
A381: DFSK | B381: DFSK | C381: CARGO BOX XL 1.3 | D381: 2014 | E381: =CONCATENATE(B381,C381,D381) -> DFSKCARGO BOX XL 1.32014 | G381: 3990000 | H381: 0
A382: DFSK | B382: DFSK | C382: CARGO BOX XL 1.3 | D382: 2014 | E382: =CONCATENATE(B382,C382,D382) -> DFSKCARGO BOX XL 1.32014 | F382: GBDZ39 | G382: 3990000 | H382: 4331719
A383: DFSK | B383: PICK UP D1 | C383: D1 COMFORT 2.3 | D383: 2024 | E383: =CONCATENATE(B383,C383,D383) -> PICK UP D1D1 COMFORT 2.32024 | F383: TCHY13 | G383: 13990000 | H383: 14500000
A384: DFSK | B384: PICK UP D1 | C384: D1 LUXURY 4X4 2.3 | D384: 2024 | E384: =CONCATENATE(B384,C384,D384) -> PICK UP D1D1 LUXURY 4X4 2.32024 | F384: TLRR98 | G384: 16490000 | H384: 13750000
A385: DFSK | B385: TRUCK | C385: TRUCK CS C21 1.3 | D385: 2026 | E385: =CONCATENATE(B385,C385,D385) -> TRUCKTRUCK CS C21 1.32026 | F385: VJTT72 | G385: 7690000 | H385: 6500000
A386: DFSK | B386: TRUCK | C386: TRUCK DC 1.0 | D386: 2025 | E386: =CONCATENATE(B386,C386,D386) -> TRUCKTRUCK DC 1.02025 | F386: VCRP11 | G386: 6990000 | H386: 0
A387: DFSK | B387: TRUCK | C387: TRUCK DC 1.3 | D387: 2024 | E387: =CONCATENATE(B387,C387,D387) -> TRUCKTRUCK DC 1.32024 | F387: TFCC55 | G387: 6810000 | H387: 5500000
A388: DFSK | B388: TRUCK | C388: TRUCK SERIE C DCAB 1.5 | D388: 2023 | E388: =CONCATENATE(B388,C388,D388) -> TRUCKTRUCK SERIE C DCAB 1.52023 | F388: SHLV24 | G388: 6490000 | H388: 5000000
A389: DODGE | B389: DODGE | C389: NEW RAM1500 SLT SPORT 4X4 5.7 AUT | D389: 2016 | E389: =CONCATENATE(B389,C389,D389) -> DODGENEW RAM1500 SLT SPORT 4X4 5.7 AUT2016 | F389: HYSL74 | G389: 17000000 | H389: 20400000
A390: DODGE | B390: DODGE | C390: RAM1500 LARAMIE 4X4 5.7 | D390: 2017 | E390: =CONCATENATE(B390,C390,D390) -> DODGERAM1500 LARAMIE 4X4 5.72017 | F390: JLXP52 | G390: 26490000 | H390: 24700000
A391: DODGE | B391: DURANGO | C391: NEW DURANGO CITADEL AWD 5.7 | D391: 2011 | E391: =CONCATENATE(B391,C391,D391) -> DURANGONEW DURANGO CITADEL AWD 5.72011 | F391: DBXP41 | G391: 4750000 | H391: 11000000
A392: DODGE | B392: JOURNEY | C392: JOURNEY 2.4 AUT | D392: 2016 | E392: =CONCATENATE(B392,C392,D392) -> JOURNEYJOURNEY 2.4 AUT2016 | F392: HLBT63 | G392: 11090000 | H392: 10000000
A393: DODGE | B393: RAM | C393: RAM1500 LARAMIE 4X4 5.7 | D393: 2018 | E393: =CONCATENATE(B393,C393,D393) -> RAMRAM1500 LARAMIE 4X4 5.72018 | F393: JXBR60 | G393: 29290000 | H393: 26000000
... A407: FIAT | B407: PULSE | C407: PULSE HB MT 1.3 | D407: 2025 | E407: =CONCATENATE(B407,C407,D407) -> PULSEPULSE HB MT 1.32025 | F407: VBRX43 | G407: 12590000 | H407: 10800000
A408: FIAT | B408: PULSE | C408: PULSE IMPETUS TF200 1.0 AUT | D408: 2022 | E408: =CONCATENATE(B408,C408,D408) -> PULSEPULSE IMPETUS TF200 1.0 AUT2022 | G408: 13490000 | H408: 0
A409: FIAT | B409: PULSE | C409: PULSE IMPETUS TF200 1.0 AUT | D409: 2022 | E409: =CONCATENATE(B409,C409,D409) -> PULSEPULSE IMPETUS TF200 1.0 AUT2022 | F409: RYDR17 | G409: 12990000 | H409: 19900000
A410: FIAT | B410: QUBO | C410: QUBO DYNAMIC 1.4 | D410: 2020 | E410: =CONCATENATE(B410,C410,D410) -> QUBOQUBO DYNAMIC 1.42020 | F410: PFRP57 | G410: 8490000 | H410: 8000000
A411: FIAT | B411: UNO WAY | C411: UNO WAY 1.4 | D411: 2016 | E411: =CONCATENATE(B411,C411,D411) -> UNO WAYUNO WAY 1.42016 | F411: HXRF54 | G411: 4990000 | H411: 3800000
A412: FIAT | B412: UNO WAY | C412: UNO WAY 1.4 | D412: 2017 | E412: =CONCATENATE(B412,C412,D412) -> UNO WAYUNO WAY 1.42017 | F412: JBJC25 | G412: 5990000 | H412: 5100000
A413: FIAT | B413: UNO WAY | C413: UNO WAY EVO 1.3 | D413: 2018 | E413: =CONCATENATE(B413,C413,D413) -> UNO WAYUNO WAY EVO 1.32018 | F413: KJYF93 | G413: 6790000 | H413: 5500000
A414: FIAT | B414: UNO WAY | C414: UNO WAY EVO 1.4 | D414: 2017 | E414: =CONCATENATE(B414,C414,D414) -> UNO WAYUNO WAY EVO 1.42017 | F414: JGBX93 | G414: 7090000 | H414: 5000000
A415: FIAT | B415: UNO WAY | C415: UNO WAY EVO 1.4 | D415: 2020 | E415: =CONCATENATE(B415,C415,D415) -> UNO WAYUNO WAY EVO 1.42020 | F415: LVXF83 | G415: 5990000 | H415: 4850000
A416: FIAT | B416: UNO WAY | C416: UNO WAY EVO FL 1.3 | D416: 2018 | E416: =CONCATENATE(B416,C416,D416) -> UNO WAYUNO WAY EVO FL 1.32018 | F416: KGLL79 | G416: 4990000 | H416: 4000000
A417: FORD | B417: BRONCO | C417: BRONCO SPORT 4X4 1.5 AUT | D417: 2023 | E417: =CONCATENATE(B417,C417,D417) -> BRONCOBRONCO SPORT 4X4 1.5 AUT2023 | F417: SYXT32 | G417: 20990000 | H417: 18300000
A418: FORD | B418: BRONCO | C418: BRONCO SPORT 4X4 1.5 AUT | D418: 2023 | E418: =CONCATENATE(B418,C418,D418) -> BRONCOBRONCO SPORT 4X4 1.5 AUT2023 | F418: SYXT50 | G418: 21690000 | H418: 18500000
A419: FORD | B419: BRONCO | C419: BRONCO SPORT 4X4 1.5 AUT | D419: 2024 | E419: =CONCATENATE(B419,C419,D419) -> BRONCOBRONCO SPORT 4X4 1.5 AUT2024 | F419: SYPZ14 | G419: 23990000 | H419: 21000000
A420: FORD | B420: BRONCO | C420: BRONCO SPORT WILDTRAK 4X4 2.0 AUT | D420: 2022 | E420: =CONCATENATE(B420,C420,D420) -> BRONCOBRONCO SPORT WILDTRAK 4X4 2.0 AUT2022 | F420: RTJJ48 | G420: 31790000 | H420: 28000000
... A443: FORD | B443: ECOSPORT | C443: ECOSPORT 2.0 AUT | D443: 2019 | E443: =CONCATENATE(B443,C443,D443) -> ECOSPORTECOSPORT 2.0 AUT2019 | F443: KWVP39 | G443: 11990000 | H443: 13000000
A444: FORD | B444: ECOSPORT | C444: ECOSPORT FREESTYLE 1.5 | D444: 2018 | E444: =CONCATENATE(B444,C444,D444) -> ECOSPORTECOSPORT FREESTYLE 1.52018 | G444: 7890000 | H444: 0
A445: FORD | B445: ECOSPORT | C445: ECOSPORT FREESTYLE 1.5 | D445: 2018 | E445: =CONCATENATE(B445,C445,D445) -> ECOSPORTECOSPORT FREESTYLE 1.52018 | F445: KGPD80 | G445: 6950000 | H445: 5800000
A446: FORD | B446: ECOSPORT | C446: ECOSPORT FREESTYLE 1.5 | D446: 2019 | E446: =CONCATENATE(B446,C446,D446) -> ECOSPORTECOSPORT FREESTYLE 1.52019 | F446: LBVT23 | G446: 8490000 | H446: 6000000
A447: FORD | B447: ECOSPORT | C447: ECOSPORT FREESTYLE 1.5 | D447: 2019 | E447: =CONCATENATE(B447,C447,D447) -> ECOSPORTECOSPORT FREESTYLE 1.52019 | F447: LHCL79 | G447: 9290000 | H447: 7983193
A448: FORD | B448: ECOSPORT | C448: ECOSPORT FREESTYLE 1.5 | D448: 2020 | E448: =CONCATENATE(B448,C448,D448) -> ECOSPORTECOSPORT FREESTYLE 1.52020 | F448: LVXD95 | G448: 10790000 | H448: 8900000
A449: FORD | B449: ECOSPORT | C449: ECOSPORT FREESTYLE 1.5 | D449: 2020 | E449: =CONCATENATE(B449,C449,D449) -> ECOSPORTECOSPORT FREESTYLE 1.52020 | F449: PFRR32 | G449: 9990000 | H449: 10500000
A450: FORD | B450: ECOSPORT | C450: ECOSPORT S 1.5 | D450: 2019 | E450: =CONCATENATE(B450,C450,D450) -> ECOSPORTECOSPORT S 1.52019 | F450: RGHD32 | G450: 11290000 | H450: 9500000
A451: FORD | B451: ECOSPORT | C451: ECOSPORT S 1.5 | D451: 2020 | E451: =CONCATENATE(B451,C451,D451) -> ECOSPORTECOSPORT S 1.52020 | F451: LYPC86 | G451: 8490000 | H451: 7074790
A452: FORD | B452: ECOSPORT | C452: ECOSPORT S 1.5 | D452: 2021 | E452: =CONCATENATE(B452,C452,D452) -> ECOSPORTECOSPORT S 1.52021 | F452: PFRZ91 | G452: 7990000 | H452: 6000000
A453: FORD | B453: ECOSPORT | C453: ECOSPORT S 1.5 | D453: 2021 | E453: =CONCATENATE(B453,C453,D453) -> ECOSPORTECOSPORT S 1.52021 | F453: PKJP78 | G453: 10790000 | H453: 8800000
A454: FORD | B454: ECOSPORT | C454: ECOSPORT TITANIUM 1.5 | D454: 2018 | E454: =CONCATENATE(B454,C454,D454) -> ECOSPORTECOSPORT TITANIUM 1.52018 | F454: KDTL69 | G454: 8990000 | H454: 7000000
A455: FORD | B455: ECOSPORT | C455: ECOSPORT TITANIUM 1.5 | D455: 2019 | E455: =CONCATENATE(B455,C455,D455) -> ECOSPORTECOSPORT TITANIUM 1.52019 | F455: KTCZ97 | G455: 10490000 | H455: 8483193
A456: FORD | B456: ECOSPORT | C456: ECOSPORT TITANIUM 1.5 | D456: 2019 | E456: =CONCATENATE(B456,C456,D456) -> ECOSPORTECOSPORT TITANIUM 1.52019 | F456: LBGV62 | G456: 8390000 | H456: 7300000
... A477: FORD | B477: EDGE | C477: EDGE SEL 2.0 AUT | D477: 2019 | E477: =CONCATENATE(B477,C477,D477) -> EDGEEDGE SEL 2.0 AUT2019 | F477: KTCZ34 | G477: 16990000 | H477: 16000000
A478: FORD | B478: EDGE | C478: EDGE SEL 4X4 2.0 AUT | D478: 2020 | E478: =CONCATENATE(B478,C478,D478) -> EDGEEDGE SEL 4X4 2.0 AUT2020 | G478: 20990000 | H478: 0
A479: FORD | B479: EDGE | C479: EDGE SEL 4X4 3.5 AUT | D479: 2019 | E479: =CONCATENATE(B479,C479,D479) -> EDGEEDGE SEL 4X4 3.5 AUT2019 | F479: LYPD12 | G479: 15990000 | H479: 15000000
A480: FORD | B480: ESCAPE | C480: ESCAPE 2.0 AUT | D480: 2018 | E480: =CONCATENATE(B480,C480,D480) -> ESCAPEESCAPE 2.0 AUT2018 | F480: JZGK45 | G480: 10290000 | H480: 8200000
A481: FORD | B481: ESCAPE | C481: ESCAPE 2.0 AUT | D481: 2019 | E481: =CONCATENATE(B481,C481,D481) -> ESCAPEESCAPE 2.0 AUT2019 | F481: LBVV62 | G481: 14690000 | H481: 13000000
A482: FORD | B482: ESCAPE | C482: ESCAPE 2.5 AT | D482: 2020 | E482: =CONCATENATE(B482,C482,D482) -> ESCAPEESCAPE 2.5 AT2020 | F482: LKZY27 | G482: 12575800 | H482: 12100000
A483: FORD | B483: ESCAPE | C483: ESCAPE 2.5 AUT | D483: 2017 | E483: =CONCATENATE(B483,C483,D483) -> ESCAPEESCAPE 2.5 AUT2017 | F483: JDKT68 | G483: 8189030 | H483: 8000000
A484: FORD | B484: ESCAPE | C484: ESCAPE 2.5 AUT | D484: 2020 | E484: =CONCATENATE(B484,C484,D484) -> ESCAPEESCAPE 2.5 AUT2020 | F484: LTZP19 | G484: 12416174 | H484: 11000000
A485: FORD | B485: ESCAPE | C485: ESCAPE 4X4 2.0 | D485: 2020 | E485: =CONCATENATE(B485,C485,D485) -> ESCAPEESCAPE 4X4 2.02020 | F485: LTZH55 | G485: 13690000 | H485: 10500000
A486: FORD | B486: ESCAPE | C486: ESCAPE 4X4 2.0 AUT | D486: 2018 | E486: =CONCATENATE(B486,C486,D486) -> ESCAPEESCAPE 4X4 2.0 AUT2018 | F486: JZGL35 | G486: 11590000 | H486: 9200000
A487: FORD | B487: ESCAPE | C487: ESCAPE 4X4 2.0 AUT | D487: 2018 | E487: =CONCATENATE(B487,C487,D487) -> ESCAPEESCAPE 4X4 2.0 AUT2018 | F487: KRWJ90 | G487: 9590000 | H487: 7700000
A488: FORD | B488: ESCAPE | C488: ESCAPE 4X4 2.0 AUT | D488: 2019 | E488: =CONCATENATE(B488,C488,D488) -> ESCAPEESCAPE 4X4 2.0 AUT2019 | F488: LHPY35 | G488: 13990000 | H488: 11500000
A489: FORD | B489: ESCAPE | C489: ESCAPE 4X4 2.0L AUT | D489: 2021 | E489: =CONCATENATE(B489,C489,D489) -> ESCAPEESCAPE 4X4 2.0L AUT2021 | F489: PRVR51 | G489: 16990000 | H489: 13000000
A490: FORD | B490: ESCAPE | C490: ESCAPE AWD 2.0 AUT | D490: 2023 | E490: =CONCATENATE(B490,C490,D490) -> ESCAPEESCAPE AWD 2.0 AUT2023 | F490: TRJC24 | G490: 20990000 | H490: 23870000
... A492: FORD | B492: ESCAPE | C492: ESCAPE FHEV 2.5 AUT | D492: 2023 | E492: =CONCATENATE(B492,C492,D492) -> ESCAPEESCAPE FHEV 2.5 AUT2023 | F492: SFLZ50 | G492: 21782120 | H492: 19000000
A493: FORD | B493: ESCAPE | C493: ESCAPE FHEV 2.5 AUT | D493: 2024 | E493: =CONCATENATE(B493,C493,D493) -> ESCAPEESCAPE FHEV 2.5 AUT2024 | G493: 26490000 | H493: 0
A494: FORD | B494: ESCAPE | C494: ESCAPE FHEV 2.5 AUT | D494: 2024 | E494: =CONCATENATE(B494,C494,D494) -> ESCAPEESCAPE FHEV 2.5 AUT2024 | F494: TKVB34 | G494: 26510000 | H494: 24000000
A495: FORD | B495: ESCAPE | C495: ESCAPE FHEV 2.5 AUT | D495: 2024 | E495: =CONCATENATE(B495,C495,D495) -> ESCAPEESCAPE FHEV 2.5 AUT2024 | F495: TPTZ45 | G495: 26990000 | H495: 24000000
A496: FORD | B496: ESCAPE | C496: ESCAPE TITANIUM 4X4 2.0 AUT | D496: 2020 | E496: =CONCATENATE(B496,C496,D496) -> ESCAPEESCAPE TITANIUM 4X4 2.0 AUT2020 | F496: LSYF35 | G496: 17990000 | H496: 14500000
A497: FORD | B497: EXPEDITION | C497: EXPEDITION LIMITED 4X4 3.5 AUT | D497: 2022 | E497: =CONCATENATE(B497,C497,D497) -> EXPEDITIONEXPEDITION LIMITED 4X4 3.5 AUT2022 | F497: RGTR45 | G497: 41990000 | H497: 38000000
A498: FORD | B498: EXPEDITION | C498: EXPEDITION LTD 4X4 3.5 AUT | D498: 2018 | E498: =CONCATENATE(B498,C498,D498) -> EXPEDITIONEXPEDITION LTD 4X4 3.5 AUT2018 | F498: KRPW91 | G498: 21990000 | H498: 19500000
A499: FORD | B499: EXPEDITION | C499: EXPEDITION LTD 4X4 3.5 AUT | D499: 2020 | E499: =CONCATENATE(B499,C499,D499) -> EXPEDITIONEXPEDITION LTD 4X4 3.5 AUT2020 | F499: PFSB87 | G499: 35990000 | H499: 31000000
A500: FORD | B500: EXPEDITION | C500: EXPEDITION XLT 3.5 AUT | D500: 2017 | E500: =CONCATENATE(B500,C500,D500) -> EXPEDITIONEXPEDITION XLT 3.5 AUT2017 | F500: JHSD53 | G500: 18000000 | H500: 15500000
A501: FORD | B501: EXPEDITION | C501: EXPEDITION XLT 3.5 AUT | D501: 2017 | E501: =CONCATENATE(B501,C501,D501) -> EXPEDITIONEXPEDITION XLT 3.5 AUT2017 | F501: JPZR22 | G501: 18990000 | H501: 16000000
A502: FORD | B502: EXPLORER | C502: EXPLORER 2.3 | D502: 2018 | E502: =CONCATENATE(B502,C502,D502) -> EXPLOREREXPLORER 2.32018 | F502: JXWF79 | G502: 13990000 | H502: 11500000
...

Sheet Hoja1
A1: Empresa | B1: IMPORTADORA TRENTO LTDA
A3: Marca | B3: Modelo | C3: Año | D3: Días Stock | E3: Placa Patente | F3: Estado Dealer
A4: BYD | B4: SHARK DMO | C4: 2025 | D4: 126 | E4: TGVF52 | F4: DISPONIBLE
A5: BYD | B5: SONG PLUS DM-i | C5: 2024 | D5: 214 | E5: TJDC55 | F5: DISPONIBLE
A6: CHANGAN | B6: CHANGAN | C6: 2022 | D6: 70 | E6: RXCG78 | F6: DISPONIBLE
A7: CHERY | B7: ARRIZO 5 | C7: 2019 | D7: 63 | E7: KZKL71 | F7: EN TALLER
A8: CHERY | B8: TIGGO 3 | C8: 2021 | D8: 292 | E8: RBZD91 | F8: EN RESCILIACION
A9: CHERY | B9: TIGGO 3 PRO | C9: 2026 | D9: 102 | E9: VKCY97 | F9: DISPONIBLE
A10: CHERY | B10: TIGGO 7 PRO | C10: 2022 | D10: 187 | E10: RVRD47 | F10: EN TALLER
A11: CHEVROLET | B11: CAPTIVA | C11: 2017 | D11: 348 | E11: JHSK67 | F11: EN TALLER
A12: CHEVROLET | B12: SILVERADO | C12: 2023 | D12: 291 | E12: SJDW14 | F12: DISPONIBLE
A13: CHEVROLET | B13: TAHOE | C13: 2020 | D13: 131 | E13: PDBT76 | F13: DISPONIBLE
A14: CITROEN | B14: C3 | C14: 2019 | D14: 98 | E14: LPXJ44 | F14: EN TALLER
A15: CITROEN | B15: C5 | C15: 2020 | D15: 588 | E15: LVWV64 | F15: EN TALLER
... A80: SUBARU | B80: FORESTER | C80: 2024 | D80: 75 | E80: TPCS18 | F80: DISPONIBLE
A81: Total general

Sheet BBDD
A1: Empresa | B1: Sucursal | C1: Folio Venta | D1: Venta | E1: Estado Venta | F1: Fecha Venta | G1: Tipo Documento (Folio) | H1: Vendedor | I1: Fecha Ingreso | J1: Fecha Facturación | K1: Numero VIN | L1: Marca | M1: Modelo | N1: Versión | O1: Código Versión | P1: Año | Q1: Kilometraje | R1: Código Interno | S1: Placa Patente | T1: Condición Vehículo | U1: Color Exterior | V1: Color Interior | W1: Precio Venta Total | X1: Estado AutoPro | Y1: Días Stock | Z1: Estado Dealer | AA1: Bodega | AB1: Equipamiento | AC1: Numero Motor | AD1: Numero Chasis | AE1: Proveedor | AF1: Fecha Disponibilidad | AG1: Factura Compra | AH1: Vencimiento Documento | AI1: Fecha Compra | AJ1: Fecha Vencto. Revisión Técnica | AK1: N° Propietarios | AL1: Folio Retoma | AM1: Fecha Retoma | AN1: Días Reservado | AO1: Precio Compra Neto | AP1: Gasto | AQ1: Accesorios | AR1: Total Costo | AS1: Precio Lista | AT1: Margen | AU1: Margen %
A2: AUTOMOTRIZ BALMACEDA LTDA. | B2: LOCAL USADOS | C2: 0 | D2: 0 | I2: 14-08-2025 17:36:07 | K2: VR3USHNSKSJ517115 | L2: PEUGEOT | M2: Nuevo 2008 | N2: 2008 ALLURE 130 1.2 | O2: N2008USA | P2: 2025 | Q2: 1510 | R2: BPESTWU000008 | S2: TXYV73 | T2: USADO | U2: GRIS ARTENSE | V2: POR DEFINIR | W2: 16990000 | X2: Disponible | Y2: 397 | Z2: DEVOLUCION NUEVOS DISPONIBLE | AA2: LOCAL USADOS VEHICULOS | AC2: 10TMA60199560 | AD2: VR3USHNSKSJ517115 | AE2: JULIO CESAR GUTIERREZ VARGAS | AF2: 14-08-2025 0:00:00 | AG2: 1 | AH2: 14-08-2025 0:00:00 | AI2: 14-08-2025 17:34:19 | AK2: 0 | AL2: 0 | AN2: 0 | AO2: 20390000 | AP2: 0 | AQ2: 0 | AR2: 20390000 | AS2: 16990000 | AT2: -3400000 | AU2: -2001
A3: AUTOMOTRIZ BALMACEDA LTDA. | B3: LOCAL PEUGEOT | C3: 0 | D3: 0 | I3: 06-11-2025 16:51:55 | K3: 9V8FF4HY1SA819290 | L3: PEUGEOT | M3: Landtrek | N3: LANDTREK BLUEHDI 4X4 2.2 AUT | O3: LANDUSA | P3: 2025 | Q3: 0 | R3: BPECMTU000007 | S3: VJBV25 | T3: USADO | U3: BLANCO BANQUISE | V3: POR DEFINIR | W3: 21990000 | X3: Disponible | Y3: 313 | Z3: EN TALLER | AA3: BODEGA LOCAL PEUGEOT | AC3: 10VRAC4012986 | AD3: 9V8FF4HY1SA819290 | AE3: ECO ARQUING LTDA | AF3: 06-11-2025 0:00:00 | AG3: 1 | AH3: 06-11-2025 0:00:00 | AI3: 06-11-2025 16:50:16 | AK3: 0 | AL3: 0 | AN3: 0 | AO3: 29381100 | AP3: 0 | AQ3: 0 | AR3: 29381100 | AS3: 21990000 | AT3: -7391100 | AU3: -3361
A4: AUTOMOTRIZ BALMACEDA LTDA. | B4: LOCAL PEUGEOT | C4: 0 | D4: 0 | I4: 28-05-2026 12:41:52 | K4: VR3KAHPY0VS001093 | L4: PEUGEOT | M4: NUEVO 3008 | N4: 3008 P64 GT Hybrid 136hp AT | O4: 1PPDSYTJH7NXA0B0167 | P4: 2026 | Q4: 0 | R4: BPESTWN002855 | S4: VZLY15 | T4: SEMINUEVO | U4: BLANCO OKENITA | V4: POR DEFINIR | W4: 37290000 | X4: Disponible | Y4: 110 | Z4: TEST CAR | AA4: BODEGA LOCAL PEUGEOT | AC4: 10XR050087229 | AD4: VR3KAHPY0VS001093 | AE4: FORUM DISTRIBUIDORA SA | AF4: 28-05-2026 0:00:00 | AG4: 0 | AK4: 0 | AL4: 0 | AN4: 0 | AO4: 28515882 | AP4: 1030553 | AQ4: 0 | AR4: 29546435 | AS4: 31336134 | AT4: 1789699 | AU4: 571
A5: AUTOMOTRIZ BALMACEDA LTDA. | B5: LOCAL PEUGEOT | C5: 0 | D5: 0 | I5: 12-09-2025 15:00:44 | K5: VR3EBYHZ9TJ514671 | L5: PEUGEOT | M5: Rifter | N5: RIFTER MCA ALLURE Diesel 130hp AT | O5: 1PK9CLTMK1JRA070059 | P5: 2026 | Q5: 0 | R5: BPESTWN002704 | S5: VKCY37 | T5: SEMINUEVO | U5: GRIS ARTENSE | V5: POR DEFINIR | W5: 26390000 | X5: Disponible | Y5: 368 | Z5: DEMO/INTERNO | AA5: BODEGA LOCAL PEUGEOT | AC5: 10Q4EP0347273 | AD5: VR3EBYHZ9TJ514671 | AE5: FORUM DISTRIBUIDORA SA | AF5: 12-09-2025 0:00:00 | AG5: 912478 | AH5: 25-09-2025 0:00:00 | AI5: 05-10-2025 21:25:13 | AK5: 0 | AL5: 0 | AN5: 0 | AO5: 18211764 | AP5: 826449 | AQ5: 0 | AR5: 19038213 | AS5: 22176471 | AT5: 3138258 | AU5: 1415
A6: AUTOMOTRIZ BALMACEDA LTDA. | B6: LOCAL PEUGEOT | C6: 0 | D6: 0 | I6: 03-12-2025 15:23:05 | K6: VF3YDT6FXTMB55780 | L6: PEUGEOT | M6: Boxer | N6: BOXER 2.2 | O6: BOXUSA1 | P6: 2026 | Q6: 2700 | R6: BPEFRGU000005 | S6: TGVK67 | T6: USADO | U6: BLANCO HIELO | V6: POR DEFINIR | W6: 31990000 | X6: Disponible | Y6: 286 | Z6: EN TALLER | AA6: BODEGA LOCAL PEUGEOT | AC6: 463571691903538 | AD6: VF3YDT6FXTMB55780 | AE6: DAVID REINALDO RAMIREZ PEÑA Y LILLO VENTA, MANTENCION Y RECARGA DE EXTINTORES E.I.R.L | AF6: 03-12-2025 0:00:00 | AG6: 1 | AH6: 03-12-2025 0:00:00 | AI6: 03-12-2025 15:22:45 | AK6: 0 | AL6: 0 | AN6: 0 | AO6: 32237100 | AP6: 0 | AQ6: 0 | AR6: 32237100 | AS6: 31990000 | AT6: -247100 | AU6: -77
A7: AUTOMOTRIZ BALMACEDA LTDA. | B7: BODEGA PDI | C7: 0 | D7: 0 | I7: 08-05-2026 12:47:17 | K7: VR3EDYHT4VJ003832 | L7: PEUGEOT | M7: NUEVA PARTNER | N7: PARTNER MCA L2 Diesel 100hp MT | O7: 2PK95CNMNKJRA070069 | P7: 2026 | Q7: 0 | R7: BPEFRGN001371 | S7: VYCP86 | T7: SEMINUEVO | U7: BLANCO HIELO | V7: POR DEFINIR | W7: 24264100 | X7: Disponible | Y7: 130 | Z7: TEST CAR | AA7: BODEGA PDI | AC7: 10Q4EU0696242 | AD7: VR3EDYHT4VJ003832 | AE7: FORUM DISTRIBUIDORA SA | AF7: 08-05-2026 0:00:00 | AG7: 0 | AK7: 0 | AL7: 0 | AN7: 0 | AO7: 18351000 | AP7: 0 | AQ7: 0 | AR7: 18351000 | AS7: 20390000 | AT7: 2039000 | AU7: 10
A8: AUTOMOTRIZ BALMACEDA LTDA. | B8: MEGACENTRO OVALLE | C8: 0 | D8: 0 | I8: 21-02-2024 15:15:59 | K8: 9V8FF4HY1RA800754 | L8: PEUGEOT | M8: Landtrek | N8: Landtrek Active BlueHDi 180 4x4 AT | O8: 2PKPEKHMQNN088 | P8: 2024 | Q8: 27913 | R8: BPECMTN000252 | S8: TJDB33 | T8: SEMINUEVO | U8: BLANCO BANQUISE | V8: POR DEFINIR | W8: 20990000 | X8: Disponible | Y8: 389 | Z8: DEMO/INTERNO | AA8: MEGACENTRO OVALLE VEHICULOS | AC8: 10VRAC4002482 | AD8: 9V8FF4HY1RA800754 | AE8: FORUM DISTRIBUIDORA SA | AF8: 22-08-2025 0:00:00 | AG8: 781565 | AH8: 19-03-2024 0:00:00 | AI8: 20-03-2024 14:57:19 | AK8: 0 | AL8: 0 | AN8: 0 | AO8: 26670800 | AP8: 991590 | AQ8: 0 | AR8: 27662390 | AS8: 20990000 | AT8: -6672390 | AU8: -3179
A9: AUTOMOTRIZ BALMACEDA LTDA. | B9: LOCAL USADOS | C9: 0 | D9: 0 | I9: 12-09-2025 16:02:19 | K9: VXKUSHNS5TW000787 | L9: OPEL | M9: NEW MOKKA | N9: Mokka GS Gasolina 130HP AT | O9: 1GQOSYHI21JRA033109 | P9: 2026 | Q9: 2705 | R9: BOPSTWN000228 | S9: VKCY38 | T9: SEMINUEVO | U9: VERDE LAGUNA | V9: POR DEFINIR | W9: 24890000 | X9: Disponible | Y9: 162 | Z9: DEMO/INTERNO | AA9: LOCAL USADOS VEHICULOS | AC9: 10XVBB2431060 | AD9: VXKUSHNS5TW000787 | AE9: FORUM DISTRIBUIDORA SA | AF9: 06-04-2026 0:00:00 | AG9: 912475 | AH9: 25-09-2025 0:00:00 | AI9: 05-10-2025 21:20:03 | AK9: 0 | AL9: 0 | AN9: 0 | AO9: 16665547 | AP9: 535096 | AQ9: 0 | AR9: 17200643 | AS9: 20915966 | AT9: 3715323 | AU9: 1776
A10: AUTOMOTRIZ BALMACEDA LTDA. | B10: LOCAL USADOS COPIAPO | C10: 0 | D10: 0 | I10: 07-01-2025 15:56:46 | K10: VR3FDAHDLN3007730 | L10: PEUGEOT | M10: Landtrek | N10: LANDTREK 4X4 1.9 | O10: LANUSA1 | P10: 2022 | Q10: 0 | R10: BPECMTU000002 | S10: RVYJ17 | T10: USADO | U10: GRIS GRAFITO | V10: POR DEFINIR | W10: 37355481 | X10: Disponible | Y10: 616 | Z10: EN TALLER | AA10: BODEGA VEHICULOS | AC10: A5D22001368 | AD10: VR3FDAHDLN3007730 | AE10: FERNANDO GABRIEL LEIVA PANGUE | AF10: 07-01-2025 0:00:00 | AG10: 1 | AH10: 07-01-2025 0:00:00 | AI10: 07-01-2025 15:55:41 | AK10: 0 | AL10: 0 | AN10: 0 | AO10: 37355481 | AP10: 894355 | AQ10: 0 | AR10: 38249836 | AS10: 37355481 | AT10: -894355 | AU10: -239
A11: AUTOMOTRIZ BALMACEDA LTDA. | B11: MEGACENTRO OVALLE | C11: 0 | D11: 0 | I11: 30-10-2023 16:00:03 | K11: VR3UDYHZSRJ524567 | L11: PEUGEOT | M11: Nuevo 2008 | N11: 2008 MCA Allure BlueHDi 130 EAT8 | O11: 1PP1SYPMK1JRA0 | P11: 2024 | Q11: 45647 | R11: BPESTWN002279 | S11: TJCZ90 | T11: SEMINUEVO | U11: BLANCO OKENITE | V11: POR DEFINIR | W11: 17590000 | X11: Disponible | Y11: 1051 | Z11: EN TALLER | AA11: MEGACENTRO OVALLE VEHICULOS | AC11: 10Q3DP1802788 | AD11: VR3UDYHZSRJ524567 | AE11: FORUM DISTRIBUIDORA SA | AF11: 30-10-2023 0:00:00 | AG11: 781568 | AH11: 19-03-2024 0:00:00 | AI11: 20-03-2024 15:01:46 | AK11: 0 | AL11: 0 | AN11: 0 | AO11: 21175461 | AP11: 1288456 | AQ11: 0 | AR11: 22463917 | AS11: 17590000 | AT11: -4873917 | AU11: -2771
A12: AUTOMOTRIZ BALMACEDA LTDA. | B12: BODEGA PDI | C12: 0 | D12: 0 | I12: 12-09-2025 15:22:18 | K12: VXKUPHNKXT4000863 | L12: OPEL | M12: NEW CORSA | N12: Corsa MCA Edition Gasolina 100HP AT | O12: 1GJOA5HL71J0A0F0018 | P12: 2026 | Q12: 0 | R12: BOPAUTN000108 | S12: VKCY43 | T12: SEMINUEVO | U12: GRIS GSE | V12: POR DEFINIR | W12: 18690000 | X12: Disponible | Y12: 368 | Z12: DEMO/INTERNO | AA12: BODEGA PDI | AC12: 10XVBB2453272 | AD12: VXKUPHNKXT4000863 | AE12: FORUM DISTRIBUIDORA SA | AF12: 12-09-2025 0:00:00 | AG12: 912470 | AH12: 25-09-2025 0:00:00 | AI12: 05-10-2025 21:09:55 | AK12: 0 | AL12: 0 | AN12: 0 | AO12: 13236975 | AP12: 460637 | AQ12: 0 | AR12: 13697612 | AS12: 15705882 | AT12: 2008270 | AU12: 1279
A13: AUTOMOTRIZ BALMACEDA LTDA. | B13: MEGACENTRO OVALLE | C13: 0 | D13: 0 | I13: 27-12-2025 22:18:45 | K13: VR3KAHPY3TS012523 | L13: PEUGEOT | M13: NUEVO 3008 | N13: 3008 P64 GT Hybrid 136hp AT | O13: 1PPDSYTJH7NXA0B0167 | P13: 2026 | Q13: 0 | R13: BPESTWN002763 | S13: VVYY78 | T13: SEMINUEVO | U13: GRIS ARTENSE | V13: POR DEFINIR | W13: 37290000 | X13: Disponible | Y13: 262 | Z13: USO GERENCIA | AA13: MEGACENTRO OVALLE VEHICULOS | AC13: 10XR050002280 | AD13: VR3KAHPY3TS012523 | AE13: FORUM DISTRIBUIDORA SA | AF13: 27-12-2025 0:00:00 | AG13: 0 | AK13: 0 | AL13: 0 | AN13: 0 | AO13: 28983865 | AP13: 1338304 | AQ13: 0 | AR13: 30322169 | AS13: 31336134 | AT13: 1013965 | AU13: 324
A14: AUTOMOTRIZ BALMACEDA LTDA. | B14: LOCAL PEUGEOT | C14: 0 | D14: 0 | I14: 12-09-2025 14:24:14 | K14: VR3USHNS6SJ525435 | L14: PEUGEOT | M14: Nuevo 2008 | N14: 2008 MCA Style Gasolina 130hp MT | O14: 1PP1SYHM6KJR2PG0000 | P14: 2026 | Q14: 0 | R14: BPESTWN002701 | S14: VKCY47 | T14: SEMINUEVO | U14: BLANCO OKENITE | V14: POR DEFINIR | W14: 21090000 | X14: Disponible | Y14: 368 | Z14: DEMO/INTERNO | AA14: BODEGA LOCAL PEUGEOT | AC14: 10TMA60220138 | AD14: VR3USHNS6SJ525435 | AE14: FORUM DISTRIBUIDORA SA | AF14: 12-09-2025 0:00:00 | AG14: 912464 | AH14: 25-09-2025 0:00:00 | AI14: 05-10-2025 20:51:32 | AK14: 0 | AL14: 0 | AN14: 0 | AO14: 14312605 | AP14: 409055 | AQ14: 0 | AR14: 14721660 | AS14: 17722689 | AT14: 3001029 | AU14: 1693
A15: AUTOMOTRIZ BALMACEDA LTDA. | B15: LOCAL USADOS | C15: 0 | D15: 0 | I15: 07-07-2023 13:26:15 | K15: VR3FDAHDLP3008724 | L15: PEUGEOT | M15: Landtrek | N15: LANDTREK 4X4 1.9 | O15: LANUSA1 | P15: 2022 | Q15: 1980 | R15: BPECMTU000001 | S15: RSYF47 | T15: USADO | U15: GRIS GRAFITO | V15: POR DEFINIR | W15: 19490000 | X15: Disponible | Y15: 1166 | Z15: DISPONIBLE | AA15: LOCAL USADOS VEHICULOS | AC15: A5D22001392 | AD15: VR3FDAHDLP3008724 | AE15: CONSTRUCTORA BRAP SPA | AF15: 07-07-2023 0:00:00 | AG15: 1 | AH15: 07-07-2023 0:00:00 | AI15: 07-07-2023 13:25:46 | AK15: 0 | AL15: 0 | AN15: 0 | AO15: 21000000 | AP15: 13250 | AQ15: 0 | AR15: 21013250 | AS15: 19490000 | AT15: -1523250 | AU15: -782
A16: CALLEGARI E HIJOS LTDA | B16: FORD BALMACEDA | C16: 0 | D16: 0 | I16: 09-10-2025 15:07:31 | K16: 8AFBR01K6SJ443936 | L16: FORD | M16: RANGER | N16: RANGER LTD 4X4 3.0 AUT | O16: RANDEVTDXB62 | P16: 2025 | Q16: 0 | R16: CFOCMTU000014 | S16: TDXB62 | T16: SEMINUEVO | U16: BLANCO | W16: 0 | X16: Disponible | Y16: 341 | Z16: EN PREPARACION | AA16: BODEGA FORD BALMACEDA VEHICULO | AC16: BF2X SJ443936 | AD16: 8AFBR01K6SJ443936 | AE16: BANCO DE CHILE | AF16: 09-10-2025 0:00:00 | AG16: 45641330 | AH16: 25-11-2025 0:00:00 | AI16: 11-12-2025 20:22:57 | AK16: 0 | AL16: 0 | AN16: 0 | AO16: 39290000 | AP16: 0 | AQ16: 0 | AR16: 39290000 | AS16: 0 | AT16: -39290000 | AU16: -3929000000
A17: CALLEGARI E HIJOS LTDA | B17: LOCAL USADOS | C17: 0 | D17: 0 | I17: 01-10-2025 12:34:07 | K17: KNAB3512A RT199134 | L17: KIA MOTORS | M17: MORNING | N17: MORNING MPI 1.2 | O17: MPI1 | P17: 2025 | Q17: 0 | R17: CKIAUTU000005 | S17: VBWV23 | T17: USADO | U17: VERDE BOSQUE | V17: POR DEFINIR | W17: 11490000 | X17: Disponible | Y17: 349 | Z17: EN TALLER | AA17: LOCAL USADOS VEHICULOS | AC17: G4LAPP262114 | AD17: KNAB3512A RT199134 | AE17: BENJAMIN MOISES SOTO ALFARO | AF17: 01-10-2025 0:00:00 | AG17: 1 | AH17: 01-10-2025 0:00:00 | AI17: 01-10-2025 12:33:42 | AK17: 0 | AL17: 0 | AN17: 12 | AO17: 12473300 | AP17: 0 | AQ17: 0 | AR17: 12473300 | AS17: 11490000 | AT17: -983300 | AU17: -856
A18: CALLEGARI E HIJOS LTDA | B18: LOCAL USADOS | C18: 0 | D18: 0 | I18: 26-09-2023 16:20:52 | K18: 9V8FF4HY1PA800411 | L18: PEUGEOT | M18: LANDTREK | N18: Landtrek Active BlueHdi 180 4x4 AT | O18: 2PKPEKHMQNN088 | P18: 2024 | Q18: 50982 | R18: CPECMTN000018 | S18: TBCP54 | T18: SEMINUEVO | U18: NEGRO PERLA NERA | V18: POR DEFINIR | W18: 20990000 | X18: Disponible | Y18: 174 | Z18: DEMO/INTERNO | AA18: LOCAL USADOS VEHICULOS | AC18: VRAC4001479 | AD18: 9V8FF4HY1PA800411 | AE18: AUTOMOTRIZ BALMACEDA LTDA | AF18: 25-03-2026 0:00:00 | AG18: 55045 | AH18: 26-10-2023 0:00:00 | AI18: 26-09-2023 16:20:37 | AK18: 0 | AL18: 0 | AN18: 0 | AO18: 29014497 | AP18: 3058563 | AQ18: 0 | AR18: 32073060 | AS18: 20990000 | AT18: -11083060 | AU18: -528
A19: CALLEGARI E HIJOS LTDA | B19: LOCAL USADOS | C19: 0 | D19: 0 | I19: 24-03-2025 10:27:56 | K19: VR3KAHPY1SS006024 | L19: PEUGEOT | M19: NUEVO 3008 | N19: New 3008 PREMIERE MHEV 136 eDCT6 | O19: TCPE26 | P19: 2025 | Q19: 23967 | R19: CPESTWN000076 | S19: VBBD31 | T19: SEMINUEVO | U19: NEGRO PERLA NERA | V19: POR DEFINIR | W19: 24290000 | X19: Disponible | Y19: 162 | Z19: DEMO/INTERNO | AA19: LOCAL USADOS VEHICULOS | AC19: 10ZA040047007 | AD19: VR3KAHPY1SS006024 | AE19: AUTOMOTRIZ BALMACEDA LTDA | AF19: 06-04-2026 0:00:00 | AG19: 66117 | AH19: 19-04-2025 0:00:00 | AI19: 24-03-2025 10:27:42 | AK19: 0 | AL19: 0 | AN19: 0 | AO19: 25546891 | AP19: 1916780 | AQ19: 0 | AR19: 27463671 | AS19: 24290000 | AT19: -3173671 | AU19: -1307
A20: CALLEGARI E HIJOS LTDA | B20: BODEGA PDI | C20: 0 | D20: 0 | I20: 04-01-2019 18:31:16 | K20: JF1GT7LL5KG071115 | L20: SUBARU | M20: XV | N20: NEW XV 2.0I AWD CVT DYNAMIC | O20: XV 5695 | P20: 2019 | Q20: 6400 | R20: CSUSTWN000408 | S20: LBGX66 | T20: SEMINUEVO | U20: BLANCO CRISTAL PERLADO | V20: POR DEFINIR | W20: 15900000 | X20: Disponible | Y20: 1411 | Z20: NO DISPONIBLE | AA20: BODEGA PDI | AC20: CE04013 | AD20: JF1GT7LL5KG071115 | AE20: FORUM DISTRIBUIDORA S.A | AF20: 04-11-2022 0:00:00 | AG20: 347702 | AH20: 11-01-2019 0:00:00 | AI20: 22-01-2019 10:34:11 | AK20: 0 | AL20: 0 | AN20: 0 | AO20: 12497480 | AP20: 3135424 | AQ20: 0 | AR20: 15632904 | AS20: 15900000 | AT20: 267096 | AU20: 168
A21: CALLEGARI E HIJOS LTDA | B21: BODEGA PDI | C21: 0 | D21: 0 | I21: 24-03-2025 10:46:04 | K21: VR3EDYHT7TN500055 | L21: PEUGEOT | M21: NUEVA PARTNER | N21: Partner MCA L1 BlueHdi 100 | O21: TCPE7 | P21: 2026 | Q21: 0 | R21: CPEFRGN000018 | S21: VBBD56 | T21: SEMINUEVO | U21: BLANCO BLANC ICY | V21: POR DEFINIR | W21: 22717100 | X21: Disponible | Y21: 544 | Z21: DEMO/INTERNO | AA21: BODEGA PDI | AC21: 10Q4EU0479175 | AD21: VR3EDYHT7TN500055 | AE21: AUTOMOTRIZ BALMACEDA LTDA | AF21: 20-03-2025 0:00:00 | AG21: 66129 | AH21: 19-04-2025 0:00:00 | AI21: 24-03-2025 10:45:51 | AK21: 0 | AL21: 0 | AN21: 0 | AO21: 17413917 | AP21: 1073628 | AQ21: 0 | AR21: 18487545 | AS21: 19090000 | AT21: 602455 | AU21: 316
A22: CALLEGARI E HIJOS LTDA | B22: LOCAL USADOS COPIAPO | C22: 0 | D22: 0 | I22: 03-02-2025 11:10:46 | K22: VR3UPHMHDS5001280 | L22: PEUGEOT | M22: NUEVO 208 | N22: Nuevo 208 MCA Active Pack Puretech 75 MT5 | O22: TCPE8 | P22: 2025 | Q22: 0 | R22: CPEAUTN000115 | S22: TYWT29 | T22: SEMINUEVO | U22: GRIS ARTENSE | V22: POR DEFINIR | W22: 16690000 | X22: Disponible | Y22: 144 | Z22: DEMO/INTERNO | AA22: BODEGA LOS CARRERA COPIAPO | AC22: 10XKDU0264699 | AD22: VR3UPHMHDS5001280 | AE22: AUTOMOTRIZ BALMACEDA LTDA | AF22: 24-04-2026 0:00:00 | AG22: 65154 | AH22: 02-03-2025 0:00:00 | AI22: 03-02-2025 11:10:31 | AK22: 0 | AL22: 0 | AN22: 0 | AO22: 12945210 | AP22: 923669 | AQ22: 0 | AR22: 13868879 | AS22: 14025210 | AT22: 156331 | AU22: 111
A23: CALLEGARI E HIJOS LTDA | B23: MEGACENTRO OVALLE | C23: 0 | D23: 0 | I23: 24-03-2025 10:03:39 | K23: VR3KAHPY1SS006126 | L23: PEUGEOT | M23: NUEVO 3008 | N23: New 3008 PREMIERE MHEV 136 eDCT6 | O23: TCPE26 | P23: 2026 | Q23: 0 | R23: CPESTWN000071 | S23: VBBD42 | T23: SEMINUEVO | U23: BLANCO OKENITE | V23: POR DEFINIR | W23: 32990000 | X23: Disponible | Y23: 544 | Z23: DEMO/INTERNO | AA23: MEGACENTRO OVALLE VEHICULOS | AC23: 10ZA040054673 | AD23: VR3KAHPY1SS006126 | AE23: AUTOMOTRIZ BALMACEDA LTDA | AF23: 20-03-2025 0:00:00 | AG23: 66110 | AH23: 19-04-2025 0:00:00 | AI23: 24-03-2025 10:03:23 | AK23: 0 | AL23: 0 | AN23: 0 | AO23: 25546891 | AP23: 1916780 | AQ23: 0 | AR23: 27463671 | AS23: 27722689 | AT23: 259018 | AU23: 93
A24: CALLEGARI E HIJOS LTDA | B24: LOCAL USADOS | C24: 0 | D24: 0 | I24: 28-02-2026 16:54:41 | K24: 8AFBR01C4SJ412077 | L24: FORD | M24: RANGER | N24: RANGER XLT 4X4 2.0 AUT | O24: RANDEV24 | P24: 2025 | Q24: 66000 | R24: CFOCMTU000019 | S24: TDWY79 | T24: USADO | U24: NEGRO | V24: POR DEFINIR | W24: 32990000 | X24: Disponible | Y24: 199 | Z24: EN TALLER | AA24: LOCAL USADOS VEHICULOS | AC24: YN2X SJ412077 | AD24: 8AFBR01C4SJ412077 | AE24: TERRA ELQUI SPA | AF24: 28-02-2026 0:00:00 | AG24: 1 | AH24: 28-02-2026 0:00:00 | AI24: 28-02-2026 16:53:37 | AK24: 0 | AL24: 0 | AN24: 0 | AO24: 25000000 | AP24: 0 | AQ24: 0 | AR24: 25000000 | AS24: 32990000 | AT24: 7990000 | AU24: 2422
A25: CALLEGARI E HIJOS LTDA | B25: LOCAL USADOS | C25: 0 | D25: 0 | I25: 16-09-2025 21:38:11 | K25: 3KPFF51ABSE120765 | L25: KIA MOTORS | M25: K3 CROSS | N25: K3 CROSS EX 1.6L 6AT | O25: KIA 2368 | P25: 2026 | Q25: 3756 | R25: CKISTWN011896 | S25: VKCY35 | T25: SEMINUEVO | U25: PLATEADO SUAVE | V25: POR DEFINIR | W25: 19990000 | X25: Disponible | Y25: 180 | Z25: DEMO/INTERNO | AA25: LOCAL USADOS VEHICULOS | AC25: G4FGSE037043 | AD25: 3KPFF51ABSE120765 | AE25: FORUM DISTRIBUIDORA S.A | AF25: 19-03-2026 0:00:00 | AG25: 912269 | AH25: 25-09-2025 0:00:00 | AI25: 06-10-2025 11:32:06 | AK25: 0 | AL25: 0 | AN25: 0 | AO25: 14110588 | AP25: 731651 | AQ25: 0 | AR25: 14842239 | AS25: 16798319 | AT25: 1956080 | AU25: 1164
A26: CALLEGARI E HIJOS LTDA | B26: FORD BALMACEDA | C26: 0 | D26: 0 | I26: 21-04-2026 12:40:27 | K26: 8AFBR01K1SJ019046 | L26: FORD | M26: RANGER | N26: RANGER LTD 4X4 3.0 AUT | O26: RANDEVTDXB62 | P26: 2026 | Q26: 2366 | R26: CFOCMTU000021 | S26: VSWV91 | T26: SEMINUEVO | U26: GRIS MERCURIO | V26: POR DEFINIR | W26: 42900000 | X26: Disponible | Y26: 147 | Z26: DEVOLUCION NUEVOS NO DISPONIBLE | AA26: BODEGA FORD BALMACEDA VEHICULO | AC26: BF2XSJ019046 | AD26: 8AFBR01K1SJ019046 | AE26: MASTER REDES IT SPA | AF26: 21-04-2026 0:00:00 | AG26: 202 | AH26: 15-04-2026 0:00:00 | AI26: 21-04-2026 12:37:52 | AK26: 0 | AL26: 0 | AN26: 0 | AO26: 39737899 | AP26: 0 | AQ26: 0 | AR26: 39737899 | AS26: 42900000 | AT26: 3162101 | AU26: 737
A27: CALLEGARI E HIJOS LTDA | B27: MEGACENTRO OVALLE | C27: 0 | D27: 0 | I27: 23-09-2024 13:25:20 | K27: VR3EDYHT2SJ514486 | L27: PEUGEOT | M27: NUEVA PARTNER | N27: Partner MCA L1 BlueHdi 100 | O27: TCPE7 | P27: 2025 | Q27: 0 | R27: CPEFRGN000016 | S27: TSGB37 | T27: SEMINUEVO | U27: BLANCO HIELO | V27: POR DEFINIR | W27: 22717100 | X27: Disponible | Y27: 728 | Z27: DEMO/INTERNO | AA27: MEGACENTRO OVALLE VEHICULOS | AC27: 10Q4EU0366595 | AD27: VR3EDYHT2SJ514486 | AE27: AUTOMOTRIZ BALMACEDA LTDA | AF27: 17-09-2024 0:00:00 | AG27: 62373 | AH27: 17-10-2024 0:00:00 | AI27: 23-09-2024 13:25:03 | AK27: 0 | AL27: 0 | AN27: 0 | AO27: 17322917 | AP27: 440794 | AQ27: 0 | AR27: 17763711 | AS27: 19090000 | AT27: 1326289 | AU27: 695
A28: CALLEGARI E HIJOS LTDA | B28: LOCAL USADOS | C28: 0 | D28: 0 | I28: 24-03-2025 10:08:03 | K28: VR3KAHPY1SS005755 | L28: PEUGEOT | M28: NUEVO 3008 | N28: New 3008 PREMIERE MHEV 136 eDCT6 | O28: TCPE26 | P28: 2025 | Q28: 8160 | R28: CPESTWN000072 | S28: VBBD50 | T28: SEMINUEVO | U28: GRIS ARTENSE | V28: POR DEFINIR | W28: 32990000 | X28: Disponible | Y28: 162 | Z28: DEMO/INTERNO | AA28: LOCAL USADOS VEHICULOS | AC28: 10ZA040040304 | AD28: VR3KAHPY1SS005755 | AE28: AUTOMOTRIZ BALMACEDA LTDA | AF28: 06-04-2026 0:00:00 | AG28: 66111 | AH28: 19-04-2025 0:00:00 | AI28: 24-03-2025 10:07:47 | AK28: 0 | AL28: 0 | AN28: 0 | AO28: 25546891 | AP28: 2425655 | AQ28: 0 | AR28: 27972546 | AS28: 27722689 | AT28: -249857 | AU28: -9
... A42: CALLEGARI E HIJOS LTDA | B42: LOCAL USADOS | C42: 0 | D42: 0 | I42: 23-09-2024 10:44:44 | K42: VF3M45GBURS003230 | L42: PEUGEOT | M42: NUEVO 3008 | N42: 3008 GT HYBRID4 300 eEAT8 | O42: TCPE1 | P42: 2025 | Q42: 7735 | R42: CPESTWN000039 | S42: TSGB43 | T42: SEMINUEVO | U42: BLANCO NACARADO | V42: POR DEFINIR | W42: 30590000 | X42: Disponible | Y42: 533 | Z42: DEMO/INTERNO | AA42: LOCAL USADOS VEHICULOS | AC42: 10FKBJ3063820 | AD42: VF3M45GBURS003230 | AE42: AUTOMOTRIZ BALMACEDA LTDA | AF42: 31-03-2025 0:00:00 | AG42: 62327 | AH42: 16-10-2024 0:00:00 | AI42: 23-09-2024 10:44:27 | AK42: 0 | AL42: 0 | AN42: 0 | AO42: 38661008 | AP42: 876679 | AQ42: 0 | AR42: 39537687 | AS42: 30590000 | AT42: -8947687 | AU42: -2925
A43: CALLEGARI E HIJOS LTDA | B43: MEGACENTRO COPIAPO | C43: 0 | D43: 0 | I43: 03-01-2017 1:36:33 | K43: KNCSJX76AG7995915 | L43: KIA MOTORS | M43: FRONTIER | N43: FRONTIER C/C 2.5 6MT | O43: 17--1336 | P43: 2016 | Q43: 0 | R43: CKICMTN001890 | S43: HTCD28 | T43: SEMINUEVO | U43: BLANCO INVIERNO | V43: NO DEFINIDO | W43: 15590000 | X43: Disponible | Y43: 3911 | Z43: VEHICULO USO DE SERVICIO | AA43: MEGACENTRO COPIAPO VEHICULOS | AC43: D4CBF790346 | AD43: KNCSJX76AG7995915 | AE43: FORUM DISTRIBUIDORA S.A | AF43: 31-12-2015 0:00:00 | AG43: 81310 | AH43: 31-12-2015 0:00:00 | AI43: 31-12-2015 0:00:00 | AJ43: 31-12-2015 0:00:00 | AK43: 0 | AL43: 0 | AN43: 0 | AO43: 13050001 | AP43: 2576087 | AQ43: 0 | AR43: 15626088 | AS43: 13100840 | AT43: -2525248 | AU43: -1928
A44: CALLEGARI E HIJOS LTDA | B44: LOCAL USADOS | C44: 0 | D44: 0 | I44: 26-02-2026 9:25:15 | K44: 8AFBR01C4 SJ466852 | L44: FORD | M44: RANGER | N44: RANGER XLT 4X4 2.0 | O44: FORANXLT4X420MT | P44: 2025 | Q44: 28620 | R44: CFOCMTU000018 | S44: VHGF48 | T44: USADO | U44: ROJO BARI | W44: 32990000 | X44: Disponible | Y44: 201 | Z44: DEVOLUCION NUEVOS DISPONIBLE | AA44: LOCAL USADOS VEHICULOS | AC44: YN2X SJ466852 | AD44: 8AFBR01C4 SJ466852 | AE44: NATALIA MARGARITA BUSTOS MUÑOZ | AF44: 26-02-2026 0:00:00 | AG44: 1 | AH44: 26-02-2026 0:00:00 | AI44: 26-02-2026 9:24:51 | AK44: 0 | AL44: 0 | AN44: 0 | AO44: 37000000 | AP44: 0 | AQ44: 0 | AR44: 37000000 | AS44: 32990000 | AT44: -4010000 | AU44: -1216
A45: CALLEGARI E HIJOS LTDA | B45: Local Premium | C45: 0 | D45: 0 | I45: 11-12-2025 21:17:36 | K45: 8AFBR00E2RJ365404 | L45: FORD | M45: RANGER | N45: RANGER XLS 2.0 | O45: FORANXLS20MT | P45: 2024 | Q45: 37000 | R45: CFOCMTU000016 | S45: TJDC25 | T45: USADO | U45: GRIS PLATA | V45: POR DEFINIR | W45: 24990000 | X45: Disponible | Y45: 298 | Z45: DEVOLUCION NUEVOS DISPONIBLE | AA45: LOCAL PREMIUM | AC45: P02XRJ365404 | AD45: 8AFBR00E2RJ365404 | AE45: SERVICIO DE INGENIERIA MANTENIMIENTO Y CONSTRUCCION SPA | AF45: 21-11-2025 0:00:00 | AG45: 119 | AH45: 21-11-2025 0:00:00 | AI45: 11-12-2025 21:15:04 | AK45: 0 | AL45: 0 | AN45: 0 | AO45: 23490000 | AP45: 0 | AQ45: 0 | AR45: 23490000 | AS45: 24990000 | AT45: 1500000 | AU45: 6
A46: CALLEGARI E HIJOS LTDA | B46: LOCAL CAMIONES COPIAPO | C46: 0 | D46: 0 | I46: 28-06-2024 8:46:29 | K46: MMBJJLC10RH006958 | L46: MITSUBISHI | M46: L-200 EURO 6B | N46: L200 KATANA XRT | O46: CMLC1TJJDQDL | P46: 2024 | Q46: 0 | R46: CMICMTN005188 | S46: TPJD34 | T46: SEMINUEVO | U46: PLATEADO | V46: POR DEFINIR | W46: 38068100 | X46: Disponible | Y46: 809 | Z46: TEST CAR | AA46: BODEGA CAMIONES COPIAPO | AC46: 4N16UAH7777 | AD46: MMBJJLC10RH006958 | AE46: BANSA SANTANDER S A | AF46: 28-06-2024 0:00:00 | AG46: 309007 | AH46: 03-07-2024 0:00:00 | AI46: 03-07-2024 16:32:51 | AK46: 0 | AL46: 0 | AN46: 0 | AO46: 28820700 | AP46: 922481 | AQ46: 0 | AR46: 29743181 | AS46: 31990000 | AT46: 2246819 | AU46: 702
A47: CALLEGARI E HIJOS LTDA | B47: LOCAL CAMIONES | C47: 0 | D47: 0 | I47: 30-06-2022 10:01:47 | K47: VF3YD3MFBP2U94054 | L47: PEUGEOT | M47: BOXER | N47: Boxer Furgón L2H2 BlueHdi 160 | O47: boxer | P47: 2022 | Q47: 0 | R47: CPEFRGN000004 | S47: RZSJ13 | T47: SEMINUEVO | U47: BLANCO HIELO | V47: POR DEFINIR | W47: 0 | X47: Disponible | Y47: 1538 | Z47: VEHICULO USO DE SERVICIO | AA47: LOCAL CAMIONES VEHICULOS | AC47: 10DY2Z4100754 | AD47: VF3YD3MFBP2U94054 | AE47: AUTOMOTRIZ BALMACEDA LTDA | AF47: 30-06-2022 0:00:00 | AG47: 0 | AH47: 15-03-2024 15:20:00 | AI47: 15-03-2024 15:20:00 | AK47: 0 | AL47: 0 | AN47: 0 | AO47: 0 | AP47: 3479924 | AQ47: 0 | AR47: 3479924 | AS47: 0 | AT47: -3479924 | AU47: -347992400
A48: CALLEGARI E HIJOS LTDA | B48: BODEGA PDI | C48: 0 | D48: 0 | I48: 05-08-2026 16:43:53 | K48: LVUGTBHD9TD153122 | L48: OMODA | M48: C5 | N48: C5 1.5T HEV DHT LUXURY | O48: T7150DB | P48: 2026 | Q48: 0 | R48: COMOSTWN000587 | S48: VXJX72 | T48: SEMINUEVO | U48: BLANCO TECHO NEGRO | V48: POR DEFINIR | W48: 21490000 | X48: Disponible | Y48: 41 | Z48: TEST CAR | AA48: BODEGA PDI | AC48: SQRH4J15BZTC65662 | AD48: LVUGTBHD9TD153122 | AE48: SOCIEDAD HERMANAS CALLEGARI LTDA | AF48: 05-08-2026 0:00:00 | AG48: 245236 | AH48: 09-07-2026 0:00:00 | AI48: 05-08-2026 16:43:39 | AK48: 0 | AL48: 0 | AN48: 0 | AO48: 16698151 | AP48: 0 | AQ48: 0 | AR48: 16698151 | AS48: 18058824 | AT48: 1360673 | AU48: 753
A49: CALLEGARI E HIJOS LTDA | B49: BODEGA PDI | C49: 0 | D49: 0 | I49: 23-09-2025 12:46:31 | K49: VR3FBYHZ3SY502526 | L49: PEUGEOT | M49: NUEVO 308 | N49: 308 Allure Diesel 130hp AT | O49: TCPE45 | P49: 2026 | Q49: 0 | R49: CPEAUTN000123 | S49: VGWS84 | T49: SEMINUEVO | U49: GRIS ARTENSE | V49: POR DEFINIR | W49: 27690000 | X49: Disponible | Y49: 357 | Z49: DEMO/INTERNO | AA49: BODEGA PDI | AC49: 10Q3EJ2013110 | AD49: VR3FBYHZ3SY502526 | AE49: AUTOMOTRIZ BALMACEDA LTDA | AF49: 23-09-2025 0:00:00 | AG49: 69782 | AH49: 23-10-2025 0:00:00 | AI49: 23-09-2025 12:44:57 | AK49: 0 | AL49: 0 | AN49: 0 | AO49: 21449412 | AP49: 1072084 | AQ49: 0 | AR49: 22521496 | AS49: 23268908 | AT49: 747412 | AU49: 321
A50: CALLEGARI E HIJOS LTDA | B50: BODEGA PDI | C50: 0 | D50: 0 | I50: 24-03-2025 10:18:58 | K50: VR3KAHPY2SS009627 | L50: PEUGEOT | M50: NUEVO 3008 | N50: New 3008 Allure MHEV 136 eDCT6 | O50: TCPE29 | P50: 2026 | Q50: 0 | R50: CPESTWN000075 | S50: VBBD27 | T50: SEMINUEVO | U50: AZUL OBSESSION | V50: POR DEFINIR | W50: 31990000 | X50: Disponible | Y50: 544 | Z50: DEMO/INTERNO | AA50: BODEGA PDI | AC50: 10ZA040094875 | AD50: VR3KAHPY2SS009627 | AE50: AUTOMOTRIZ BALMACEDA LTDA | AF50: 20-03-2025 0:00:00 | AG50: 66115 | AH50: 19-04-2025 0:00:00 | AI50: 24-03-2025 10:18:45 | AK50: 0 | AL50: 0 | AN50: 0 | AO50: 24773782 | AP50: 1877401 | AQ50: 0 | AR50: 26651183 | AS50: 26882353 | AT50: 231170 | AU50: 86
A51: CALLEGARI E HIJOS LTDA | B51: MEGACENTRO COPIAPO | C51: 0 | D51: 0 | I51: 24-02-2026 16:40:04 | K51: LJD0AA29AR0251362 | L51: KIA | M51: SOLUTO | N51: SOLUTO MPI 1.4 | O51: TDYG27 | P51: 2024 | Q51: 0 | R51: CKIAUTU000006 | S51: TDYG27 | T51: USADO | U51: PLATEADO TITANIO | V51: POR DEFINIR | W51: 11082000 | X51: Disponible | Y51: 203 | Z51: EN TALLER | AA51: MEGACENTRO COPIAPO VEHICULOS | AC51: G4LCP1045504 | AD51: LJD0AA29AR0251362 | AE51: RODRIGO ALEJANDRO MARTINEZ DROGUETT | AF51: 24-02-2026 0:00:00 | AG51: 1 | AH51: 24-02-2026 0:00:00 | AI51: 24-02-2026 16:38:04 | AK51: 0 | AL51: 0 | AN51: 0 | AO51: 11082000 | AP51: 0 | AQ51: 0 | AR51: 11082000 | AS51: 11082000 | AT51: 0 | AU51: 0
A52: CALLEGARI E HIJOS LTDA | B52: LOCAL USADOS | C52: 0 | D52: 0 | I52: 03-03-2025 12:04:16 | K52: W0VEDYHTXSN500914 | L52: OPEL | M52: COMBO | N52: COMBO MCA 1.5 TD | O52: TCOP5 | P52: 2025 | Q52: 40200 | R52: COPFRGN000005 | S52: TZHX27 | T52: SEMINUEVO | U52: BLANCO HIELO | V52: POR DEFINIR | W52: 16290000 | X52: Disponible | Y52: 174 | Z52: DEMO/INTERNO | AA52: LOCAL USADOS VEHICULOS | AC52: 10Q4EU0410660 | AD52: W0VEDYHTXSN500914 | AE52: AUTOMOTRIZ BALMACEDA LTDA | AF52: 25-03-2026 0:00:00 | AG52: 65756 | AH52: 30-03-2025 0:00:00 | AI52: 03-03-2025 12:04:01 | AK52: 0 | AL52: 0 | AN52: 0 | AO52: 17140917 | AP52: 641547 | AQ52: 0 | AR52: 17782464 | AS52: 16290000 | AT52: -1492464 | AU52: -916
A53: CALLEGARI E HIJOS LTDA | B53: LOCAL GILDEMEISTER COPIAPO | C53: 0 | D53: 0 | I53: 27-10-2025 9:42:22 | K53: LJ12EKS32S4705578 | L53: JAC | M53: JS | N53: JS4 1.5T CVT ADVANCE | O53: JS415TCVT-ADV | P53: 2026 | Q53: 6800 | R53: CJASTWN000003 | S53: VJTV59 | T53: SEMINUEVO | U53: GRIS | V53: POR DEFINIR | W53: 17690000 | X53: Disponible | Y53: 326 | Z53: EN PREPARACION | AA53: LOCAL GILDEMEISTER CPP AUTOS | AC53: R3378662 | AD53: LJ12EKS32S4705578 | AE53: SOCIEDAD HERMANAS CALLEGARI LTDA | AF53: 24-10-2025 0:00:00 | AG53: 235401 | AH53: 24-10-2025 0:00:00 | AI53: 27-10-2025 9:42:00 | AK53: 0 | AL53: 0 | AN53: 0 | AO53: 13802352 | AP53: 610282 | AQ53: 0 | AR53: 14412634 | AS53: 14865546 | AT53: 452912 | AU53: 305
A54: CALLEGARI E HIJOS LTDA | B54: LOCAL USADOS | C54: 0 | D54: 0 | I54: 22-09-2025 10:30:43 | K54: KNARH81EDS5340494 | L54: KIA MOTORS | M54: SORENTO | N54: SORENTO EX 3.5L GSL 8AT AWD FULL | O54: KIA 2360 | P54: 2026 | Q54: 3478 | R54: CKISTWN011901 | S54: VKCY69 | T54: SEMINUEVO | U54: GRIS ESTELAR | V54: POR DEFINIR | W54: 46990000 | X54: Disponible | Y54: 180 | Z54: DEMO/INTERNO | AA54: LOCAL USADOS VEHICULOS | AC54: G6DURA572414 | AD54: KNARH81EDS5340494 | AE54: FORUM DISTRIBUIDORA S.A | AF54: 19-03-2026 0:00:00 | AG54: 912265 | AH54: 25-09-2025 0:00:00 | AI54: 06-10-2025 11:30:04 | AK54: 0 | AL54: 0 | AN54: 0 | AO54: 33169412 | AP54: 2080269 | AQ54: 0 | AR54: 35249681 | AS54: 39487395 | AT54: 4237714 | AU54: 1073
A55: CALLEGARI E HIJOS LTDA | B55: MEGACENTRO LA SERENA | C55: 0 | D55: 0 | I55: 20-12-2022 11:10:56 | K55: LVZBN25B5NC055182 | L55: DFSK | M55: TRUCK | N55: TRUCK CS C31 1.5 I | O55: DFSK4815 | P55: 2023 | Q55: 0 | R55: CDFCMTN000223 | S55: SJVT21 | T55: SEMINUEVO | U55: BLANCO | V55: POR DEFINIR | W55: 11055100 | X55: Disponible | Y55: 1365 | Z55: VEHICULO USO DE SERVICIO | AA55: MEGACENTRO LA SERENA VEHICULOS | AC55: DK15-06-22314483 | AD55: LVZBN25B5NC055182 | AE55: SOCIEDAD HERMANAS CALLEGARI LTDA | AF55: 20-12-2022 0:00:00 | AG55: 0 | AH55: 28-06-2024 9:26:00 | AI55: 28-06-2024 9:26:00 | AK55: 0 | AL55: 0 | AN55: 0 | AO55: 0 | AP55: 1443780 | AQ55: 0 | AR55: 1443780 | AS55: 9290000 | AT55: 7846220 | AU55: 8446
A56: CALLEGARI E HIJOS LTDA | B56: HNAS. CALLEGARI COPIAPO 2 | C56: 0 | D56: 0 | I56: 26-02-2020 16:55:36 | K56: JMBXTGA2WKU002604 | L56: MITSUBISHI | M56: ASX | N56: ASK 2.0 AUT | O56: AMI7 | P56: 2020 | Q56: 0 | R56: CMISTWU000001 | S56: JZJS90 | T56: USADO | U56: BLANCO | V56: POR DEFINIR | W56: 12990000 | X56: Disponible | Y56: 2393 | Z56: SINIESTRADO | AA56: Bodega Vehiculo Local SK2 Copiapo | AC56: 4B11 AN5102 | AD56: JMBXTGA2WKU002604 | AE56: ANNA MACARENA PIAZZOLI WITTWER | AF56: 26-02-2020 0:00:00 | AG56: 1 | AH56: 26-02-2020 0:00:00 | AI56: 26-02-2020 16:54:38 | AK56: 0 | AL56: 0 | AN56: 0 | AO56: 12990000 | AP56: 0 | AQ56: 0 | AR56: 12990000 | AS56: 12990000 | AT56: 0 | AU56: 0
... A68: CALLEGARI E HIJOS LTDA | B68: MEGACENTRO OVALLE | C68: 0 | D68: 0 | I68: 30-04-2025 17:08:29 | K68: VR3KAHPY9SS021323 | L68: PEUGEOT | M68: NUEVO 5008 | N68: New 5008 Gt MHEV 136 eDCT6 | O68: TCPE34 | P68: 2026 | Q68: 0 | R68: CPESTWN000082 | S68: VCRK22 | T68: SEMINUEVO | U68: BLANCO OKENITE | V68: POR DEFINIR | W68: 39690000 | X68: Disponible | Y68: 503 | Z68: DEMO/INTERNO | AA68: MEGACENTRO OVALLE VEHICULOS | AC68: 10XR000045986 | AD68: VR3KAHPY9SS021323 | AE68: AUTOMOTRIZ BALMACEDA LTDA | AF68: 30-04-2025 0:00:00 | AG68: 67014 | AH68: 30-05-2025 0:00:00 | AI68: 30-04-2025 17:08:15 | AK68: 0 | AL68: 0 | AN68: 0 | AO68: 26724370 | AP68: 1167961 | AQ68: 0 | AR68: 27892331 | AS68: 33352941 | AT68: 5460610 | AU68: 1637
A69: CALLEGARI E HIJOS LTDA | B69: MEGACENTRO LA SERENA | C69: 0 | D69: 0 | I69: 01-07-2019 10:41:50 | K69: LVZKN2197KCA01948 | L69: DFSK | M69: CARGO | N69: CARGO BOX CS C21 AC | O69: DFSK4680 | P69: 2019 | Q69: 0 | R69: CDFCMTN000067 | S69: LLBT66 | T69: SEMINUEVO | U69: BLANCO | V69: POR DEFINIR | W69: 8556100 | X69: Disponible | Y69: 2643 | Z69: VEHICULO USO DE SERVICIO | AA69: MEGACENTRO LA SERENA VEHICULOS | AC69: DK12-05-18560333 | AD69: LVZKN2197KCA01948 | AE69: FORUM DISTRIBUIDORA S.A | AF69: 21-06-2019 0:00:00 | AG69: 0 | AK69: 0 | AL69: 0 | AN69: 0 | AO69: 0 | AP69: 2315480 | AQ69: 0 | AR69: 2315480 | AS69: 7190000 | AT69: 4874520 | AU69: 678
A70: CALLEGARI E HIJOS LTDA | B70: MEGACENTRO OVALLE | C70: 0 | D70: 0 | I70: 24-03-2025 10:11:14 | K70: VR3USHNSKSJ511783 | L70: PEUGEOT | M70: NUEVO 2008 | N70: 2008 MCA Allure Puretech 130 | O70: TCPE9 | P70: 2026 | Q70: 0 | R70: CPESTWN000073 | S70: VBBD35 | T70: SEMINUEVO | U70: BLANCO OKENITE | V70: POR DEFINIR | W70: 23090000 | X70: Disponible | Y70: 544 | Z70: DEMO/INTERNO | AA70: MEGACENTRO OVALLE VEHICULOS | AC70: 10TMA60193087 | AD70: VR3USHNSKSJ511783 | AE70: AUTOMOTRIZ BALMACEDA LTDA | AF70: 20-03-2025 0:00:00 | AG70: 66112 | AH70: 19-04-2025 0:00:00 | AI70: 24-03-2025 10:11:00 | AK70: 0 | AL70: 0 | AN70: 0 | AO70: 17893109 | AP70: 1109845 | AQ70: 0 | AR70: 19002954 | AS70: 19403361 | AT70: 400407 | AU70: 206
A71: CALLEGARI E HIJOS LTDA | B71: HNAS. CALLEGARI COPIAPO 2 | C71: 0 | D71: 0 | I71: 26-06-2019 12:06:29 | K71: LVZKN2193KCA01946 | L71: DFSK | M71: CARGO | N71: CARGO BOX CS C21 AC | O71: DFSK4680 | P71: 2019 | Q71: 0 | R71: CDFCMTN000066 | S71: LLBK39 | T71: SEMINUEVO | U71: BLANCO | V71: POR DEFINIR | W71: 8556100 | X71: Disponible | Y71: 2643 | Z71: VEHICULO USO DE SERVICIO | AA71: Bodega Vehiculo Local SK2 Copiapo | AC71: DK12-05-18560293 | AD71: LVZKN2193KCA01946 | AE71: FORUM DISTRIBUIDORA S.A | AF71: 21-06-2019 0:00:00 | AG71: 0 | AK71: 0 | AL71: 0 | AN71: 0 | AO71: 0 | AP71: 2502458 | AQ71: 0 | AR71: 2502458 | AS71: 7190000 | AT71: 4687542 | AU71: 652
A72: CALLEGARI E HIJOS LTDA | B72: MEGACENTRO LA SERENA | C72: 0 | D72: 0 | I72: 10-07-2026 19:02:55 | K72: 8AFBR01E9SJ499007 | L72: FORD | M72: RANGER | N72: Ranger Dsl XLS 4x4 2.0L | O72: AEE5 | P72: 2026 | Q72: 0 | R72: CFOCMTN008056 | S72: VJTR16 | T72: SEMINUEVO | U72: BLANCO | V72: POR DEFINIR | W72: 39638900 | X72: Disponible | Y72: 67 | Z72: DEVOLUCION NUEVOS NO DISPONIBLE | AA72: MEGACENTRO LA SERENA VEHICULOS | AC72: P02XSJ499007 | AD72: 8AFBR01E9SJ499007 | AE72: COMERCIAL CORDOVA Y COMPAÑIA LIMITADA | AF72: 10-07-2026 0:00:00 | AG72: 34 | AH72: 10-07-2026 0:00:00 | AI72: 10-07-2026 19:02:42 | AK72: 0 | AL72: 0 | AN72: 0 | AO72: 27190000 | AP72: 0 | AQ72: 0 | AR72: 27190000 | AS72: 33310000 | AT72: 6120000 | AU72: 1837
A73: CALLEGARI E HIJOS LTDA | B73: MEGACENTRO LA SERENA | C73: 0 | D73: 0 | I73: 13-07-2026 17:13:10 | K73: 3KPFD41ABRE059627 | L73: KIA MOTORS | M73: K3 SEDAN | N73: K3 EX 1.6L 6AT FULL | O73: 2467 | P73: 2025 | Q73: 0 | R73: CKIAUTN014864 | S73: VJTV56 | T73: USADO | U73: BLANCO INVIERNO | V73: POR DEFINIR | W73: 22490000 | X73: Disponible | Y73: 64 | Z73: DEVOLUCION NUEVOS NO DISPONIBLE | AA73: MEGACENTRO LA SERENA VEHICULOS | AC73: G4FGRE043262 | AD73: 3KPFD41ABRE059627 | AE73: CALLEGARI E HIJOS LTDA | AF73: 13-07-2026 0:00:00 | AG73: 0 | AK73: 0 | AL73: 0 | AN73: 0 | AO73: 20614000 | AP73: 0 | AQ73: 0 | AR73: 20614000 | AS73: 18899160 | AT73: -1714840 | AU73: -907
A74: CALLEGARI E HIJOS LTDA | B74: BODEGA PDI | C74: 0 | D74: 0 | I74: 03-02-2025 12:15:12 | K74: VR3KAHPY1SS005762 | L74: PEUGEOT | M74: NUEVO 3008 | N74: New 3008 PREMIERE MHEV 136 eDCT6 | O74: TCPE26 | P74: 2026 | Q74: 0 | R74: CPESTWN000064 | S74: TYWT28 | T74: SEMINUEVO | U74: GRIS ARTENSE | V74: POR DEFINIR | W74: 32990000 | X74: Disponible | Y74: 592 | Z74: DEMO/INTERNO | AA74: BODEGA PDI | AC74: 10ZA040039215 | AD74: VR3KAHPY1SS005762 | AE74: AUTOMOTRIZ BALMACEDA LTDA | AF74: 31-01-2025 0:00:00 | AG74: 65156 | AH74: 02-03-2025 0:00:00 | AI74: 03-02-2025 12:14:57 | AK74: 0 | AL74: 0 | AN74: 0 | AO74: 25392269 | AP74: 1615238 | AQ74: 0 | AR74: 27007507 | AS74: 27722689 | AT74: 715182 | AU74: 258
A75: CALLEGARI E HIJOS LTDA | B75: Local Premium | C75: 0 | D75: 0 | I75: 30-06-2026 16:43:10 | K75: 8AFBR00E6RJ371870 | L75: FORD | M75: RANGER | N75: Ranger Dsl XLS 4x2 2.0L MT | O75: ACE4 | P75: 2024 | Q75: 33641 | R75: CFOCMTN008050 | S75: TJDC59 | T75: SEMINUEVO | U75: GRIS PLATA | V75: POR DEFINIR | W75: 24990000 | X75: Disponible | Y75: 77 | Z75: DEVOLUCION NUEVOS DISPONIBLE | AA75: LOCAL PREMIUM | AC75: P02XRJ371870 | AD75: 8AFBR00E6RJ371870 | AE75: SERVICIO DE INGENIERIA MANTENIMIENTO Y CONSTRUCCION SPA | AF75: 30-06-2026 0:00:00 | AG75: 129 | AH75: 01-04-2026 0:00:00 | AI75: 30-06-2026 16:42:41 | AK75: 0 | AL75: 0 | AN75: 0 | AO75: 23490000 | AP75: 0 | AQ75: 0 | AR75: 23490000 | AS75: 24990000 | AT75: 1500000 | AU75: 6
A76: CALLEGARI E HIJOS LTDA | B76: LOCAL USADOS | C76: 0 | D76: 0 | I76: 01-03-2024 10:01:09 | K76: VR3USHNSSRJ521355 | L76: PEUGEOT | M76: NUEVO 2008 | N76: 2008 MCA Allure Puretech 130 EAT8 | O76: 1PP1SYPM61JRA0 | P76: 2024 | Q76: 23200 | R76: CPESTWN000030 | S76: THRL53 | T76: SEMINUEVO | U76: NEGRO PERLA NERA | V76: POR DEFINIR | W76: 25390000 | X76: Disponible | Y76: 929 | Z76: TEST CAR | AA76: LOCAL USADOS VEHICULOS | AC76: 10XVBB2116969 | AD76: VR3USHNSSRJ521355 | AE76: AUTOMOTRIZ BALMACEDA LTDA | AF76: 29-02-2024 0:00:00 | AG76: 58197 | AH76: 30-03-2024 0:00:00 | AI76: 01-03-2024 10:00:55 | AK76: 0 | AL76: 0 | AN76: 0 | AO76: 19683866 | AP76: 1805871 | AQ76: 0 | AR76: 21489737 | AS76: 21336134 | AT76: -153603 | AU76: -72
A77: CALLEGARI E HIJOS LTDA | B77: MEGACENTRO LA SERENA | C77: 0 | D77: 0 | I77: 18-12-2025 16:00:51 | K77: LJXCU2BB0THF42074 | L77: FORD | M77: TERRITORY | N77: Territory Titanium 1.5 FHEV | O77: TT12 | P77: 2026 | Q77: 0 | R77: CFOSTWN006573 | S77: VRHS21 | T77: SEMINUEVO | U77: BLANCO PERLADO | V77: POR DEFINIR | W77: 32590000 | X77: Disponible | Y77: 271 | Z77: TEST CAR | AA77: MEGACENTRO LA SERENA VEHICULOS | AC77: S8G085741 | AD77: LJXCU2BB0THF42074 | AE77: FORUM DISTRIBUIDORA S.A | AF77: 18-12-2025 0:00:00 | AG77: 938997 | AH77: 26-12-2025 0:00:00 | AI77: 26-12-2025 12:36:09 | AK77: 0 | AL77: 0 | AN77: 0 | AO77: 24100168 | AP77: 703323 | AQ77: 0 | AR77: 24803491 | AS77: 27386555 | AT77: 2583064 | AU77: 943
A78: CALLEGARI E HIJOS LTDA | B78: FORD BALMACEDA | C78: 0 | D78: 0 | I78: 02-10-2025 16:16:27 | K78: 8AFBR01C4RJ356801 | L78: FORD | M78: RANGER | N78: RANGER XLT 4X4 2.0 AUT | O78: RANDEV24 | P78: 2024 | Q78: 0 | R78: CFOCMTU000013 | S78: TBJF15 | T78: USADO | U78: ROJO BARI | V78: POR DEFINIR | W78: 39151000 | X78: Disponible | Y78: 348 | Z78: EN TALLER | AA78: BODEGA FORD BALMACEDA VEHICULO | AC78: YN2X RJ356801 | AD78: 8AFBR01C4RJ356801 | AE78: ROBERTO SANTA CRUZ ALBASINI | AF78: 02-10-2025 0:00:00 | AG78: 977 | AH78: 25-11-2025 0:00:00 | AI78: 11-12-2025 20:57:11 | AK78: 0 | AL78: 0 | AN78: 0 | AO78: 32900000 | AP78: 0 | AQ78: 0 | AR78: 32900000 | AS78: 39151000 | AT78: 6251000 | AU78: 1597
A79: CALLEGARI E HIJOS LTDA | B79: LOCAL USADOS COPIAPO | C79: 0 | D79: 0 | I79: 23-09-2024 11:08:50 | K79: VF3M45GFURS009935 | L79: PEUGEOT | M79: NUEVO 3008 | N79: 3008 GT Black Pack Puretech 180 EAT8 | O79: TCPE6 | P79: 2025 | Q79: 9609 | R79: CPESTWN000044 | S79: TSGB48 | T79: SEMINUEVO | U79: BLANCO NACARADO | V79: POR DEFINIR | W79: 25990000 | X79: Disponible | Y79: 538 | Z79: DEMO/INTERNO | AA79: BODEGA LOS CARRERA COPIAPO | AC79: 10FKBL3135598 | AD79: VF3M45GFURS009935 | AE79: AUTOMOTRIZ BALMACEDA LTDA | AF79: 26-03-2025 0:00:00 | AG79: 62332 | AH79: 16-10-2024 0:00:00 | AI79: 23-09-2024 11:08:32 | AK79: 0 | AL79: 0 | AN79: 0 | AO79: 25856134 | AP79: 1237071 | AQ79: 0 | AR79: 27093205 | AS79: 25990000 | AT79: -1103205 | AU79: -424
A80: CALLEGARI E HIJOS LTDA | B80: LOCAL USADOS | C80: 0 | D80: 0 | I80: 31-01-2026 11:25:19 | K80: LNBMCULK4TD263671 | L80: BAIC | M80: BJ30 | N80: BJ30 LV5 AWD HEV | O80: B-B30H | P80: 2026 | Q80: 2500 | R80: CBAICSTWN000003 | S80: VSWT54 | T80: SEMINUEVO | U80: VERDE | V80: POR DEFINIR | W80: 24900000 | X80: Disponible | Y80: 228 | Z80: EN PREPARACION | AA80: LOCAL USADOS VEHICULOS | AC80: A156T2H*XH04S903893* | AD80: LNBMCULK4TD263671 | AE80: SOCIEDAD HERMANAS CALLEGARI LTDA | AF80: 30-01-2026 0:00:00 | AG80: 240020 | AH80: 30-01-2026 0:00:00 | AI80: 31-01-2026 11:25:04 | AK80: 0 | AL80: 0 | AN80: 0 | AO80: 21210924 | AP80: 976055 | AQ80: 0 | AR80: 22186979 | AS80: 24900000 | AT80: 2713021 | AU80: 109
A81: CALLEGARI E HIJOS LTDA | B81: MEGACENTRO LA SERENA | C81: 0 | D81: 0 | I81: 24-02-2017 18:20:22 | K81: S/V.............. | L81: KIA MOTORS | M81: SOUL | N81: SOUL LX 1.6 MEC A/C DAB ABS 4X2 | O81: SOUL LX 1.6 MEC A/C DAB A | P81: 2009 | Q81: 0 | R81: CKIAUTU000002 | S81: BZBL60 | T81: USADO | U81: BLANCO CLARO | V81: POR DEFINIR | W81: 8990000 | X81: Disponible | Y81: 3490 | Z81: NO DISPONIBLE | AA81: MEGACENTRO LA SERENA VEHICULOS | AC81: G4FC9H422017 | AD81: S/V.............. | AE81: KIA CHILE S A | AF81: 24-02-2017 0:00:00 | AG81: 142281 | AH81: 15-04-2009 0:00:00 | AI81: 24-02-2017 18:19:42 | AK81: 0 | AL81: 0 | AN81: 0 | AO81: 7295200 | AP81: 0 | AQ81: 0 | AR81: 7295200 | AS81: 8990000 | AT81: 1694800 | AU81: 1885
A82: CALLEGARI E HIJOS LTDA | B82: MEGACENTRO OVALLE | C82: 0 | D82: 0 | I82: 03-02-2025 11:00:56 | K82: VR3USHPY5SJ521831 | L82: PEUGEOT | M82: NUEVO 2008 | N82: New 2008 MCA Allure MHEV 136 EDCT6 | O82: TCPE21 | P82: 2026 | Q82: 0 | R82: CPESTWN000058 | S82: TYWT12 | T82: SEMINUEVO | U82: BLANCO OKENITE | V82: POR DEFINIR | W82: 27190000 | X82: Disponible | Y82: 592 | Z82: DEMO/INTERNO | AA82: MEGACENTRO OVALLE VEHICULOS | AC82: 10Z1AM0043649 | AD82: VR3USHPY5SJ521831 | AE82: AUTOMOTRIZ BALMACEDA LTDA | AF82: 31-01-2025 0:00:00 | AG82: 65157 | AH82: 02-03-2025 0:00:00 | AI82: 03-02-2025 11:00:23 | AK82: 0 | AL82: 0 | AN82: 0 | AO82: 21062857 | AP82: 876709 | AQ82: 0 | AR82: 21939566 | AS82: 22848739 | AT82: 909173 | AU82: 398
A83: CALLEGARI E HIJOS LTDA | B83: FORD BALMACEDA | C83: 0 | D83: 0 | I83: 08-05-2019 12:07:51 | K83: LVZKN2178JCA00241 | L83: DFSK | M83: CARGO | N83: CARGO BOX CS XL 1.3 DA EV | O83: DFSK4565 | P83: 2019 | Q83: 0 | R83: CDFCMTN000063 | S83: LDVR15 | T83: SEMINUEVO | U83: BLANCO | V83: POR DEFINIR | W83: 6890100 | X83: Disponible | Y83: 2749 | Z83: VEHICULO USO DE SERVICIO | AA83: BODEGA FORD BALMACEDA VEHICULO | AC83: BG13-2017121678 | AD83: LVZKN2178JCA00241 | AE83: IMPORTADORA TRENTO LTDA | AF83: 07-03-2019 0:00:00 | AG83: 0 | AH83: 28-11-2024 11:48:00 | AI83: 28-11-2024 11:48:00 | AK83: 0 | AL83: 0 | AN83: 0 | AO83: 0 | AP83: 2624366 | AQ83: 0 | AR83: 2624366 | AS83: 5790000 | AT83: 3165634 | AU83: 5467
A84: CALLEGARI E HIJOS LTDA | B84: LOCAL FCO. DE AGUIRRE | C84: 0 | D84: 0 | I84: 27-02-2017 9:19:21 | K84: JMYSNCY4A8U000861 | L84: MITSUBISHI | M84: LANCER | N84: LANCER 2.0 MT R/GT | O84: LANCER 2.0 MT R/GT | P84: 2008 | Q84: 0 | R84: CMIAUTU000001 | S84: BSHP51 | T84: SEMINUEVO | U84: PLATEADO | V84: POR DEFINIR | W84: 0 | X84: Disponible | Y84: 3487 | Z84: USO GERENCIA | AA84: bodega vehiculos | AC84: 4B11 BP1780 | AD84: JMYSNCY4A8U000861 | AE84: MMC CHILE SPA | AF84: 27-02-2017 0:00:00 | AG84: 0 | AK84: 0 | AL84: 0 | AN84: 0 | AO84: 0 | AP84: 1558253 | AQ84: 0 | AR84: 1558253 | AS84: 0 | AT84: -1558253 | AU84: -155825300
A85: CALLEGARI E HIJOS LTDA | B85: MEGACENTRO LA SERENA | C85: 0 | D85: 0 | I85: 25-06-2019 12:09:39 | K85: LVZKN2191KCA01945 | L85: DFSK | M85: CARGO | N85: CARGO BOX CS C21 AC | O85: DFSK4680 | P85: 2019 | Q85: 0 | R85: CDFCMTN000065 | S85: LLBK37 | T85: SEMINUEVO | U85: BLANCO | V85: POR DEFINIR | W85: 8556100 | X85: Disponible | Y85: 2643 | Z85: VEHICULO USO DE SERVICIO | AA85: MEGACENTRO LA SERENA VEHICULOS | AC85: DK12-05-18560291 | AD85: LVZKN2191KCA01945 | AE85: FORUM DISTRIBUIDORA S.A | AF85: 21-06-2019 0:00:00 | AG85: 0 | AH85: 02-06-2023 11:47:00 | AI85: 02-06-2023 11:47:00 | AK85: 0 | AL85: 0 | AN85: 0 | AO85: 0 | AP85: 2454691 | AQ85: 0 | AR85: 2454691 | AS85: 7190000 | AT85: 4735309 | AU85: 6586
A86: IMPORTADORA TRENTO LTDA | B86: LOCAL PREMIUM CAR SALES | C86: 0 | D86: 0 | I86: 06-04-2026 13:31:44 | K86: VF3M45GYWPS011277 | L86: PEUGEOT | M86: 3008 | N86: 3008 THP 165HP 1.6 AUT | O86: PE3008AT | P86: 2023 | Q86: 63000 | R86: TPESTWU000452 | S86: SWBW23 | T86: USADO | U86: BLANCO NACARADO | V86: POR DEFINIR | W86: 15490000 | X86: Disponible | Y86: 162 | Z86: DISPONIBLE | AA86: PREMIUM CAR SALES | AB86: AE,CC,EE,AAC,ABS,LL,VC,AISO,AAUTO,CRE,MAV,ACD,SR,U | AC86: 10FJCX3008191 | AD86: VF3M45GYWPS011277 | AE86: MARIO ANDRES TABILO ABARCA | AF86: 06-04-2026 0:00:00 | AG86: 1 | AH86: 06-04-2026 0:00:00 | AI86: 06-04-2026 13:30:57 | AJ86: 30-06-2027 0:00:00 | AK86: 1 | AL86: 0 | AN86: 0 | AO86: 14000000 | AP86: 339240 | AQ86: 0 | AR86: 14339240 | AS86: 15490000 | AT86: 1150760 | AU86: 743
A87: IMPORTADORA TRENTO LTDA | B87: LOCAL PREMIUM CAR SALES | C87: 0 | D87: 0 | I87: 16-05-2024 13:37:55 | K87: 2FMPK4J93PBA47752 | L87: FORD | M87: EDGE | N87: EDGE AWD 2.0 CVT | O87: FED001 | P87: 2024 | Q87: 5000 | R87: TFOSTWU001301 | S87: TFFD89 | T87: USADO | U87: BLANCO METALICO | V87: POR DEFINIR | W87: 27990000 | X87: Disponible | Y87: 852 | Z87: DISPONIBLE | AA87: PREMIUM CAR SALES | AB87: AE,CC,EE,AAC,ABS,LL,TC,VC,ESP,SS,AISO,ACP,AAUTO,AE | AC87: PBA47752 | AD87: 2FMPK4J93PBA47752 | AE87: LORETO ROXANA REBOLLEDO RISSETTI | AF87: 16-05-2024 0:00:00 | AG87: 1 | AH87: 28-02-2026 15:33:00 | AI87: 28-02-2026 15:33:00 | AK87: 0 | AL87: 0 | AN87: 0 | AO87: 33990000 | AP87: 709880 | AQ87: 0 | AR87: 34699880 | AS87: 27990000 | AT87: -6709880 | AU87: -2397
A88: IMPORTADORA TRENTO LTDA | B88: LOCAL PREMIUM CAR SALES | C88: 0 | D88: 0 | I88: 01-09-2026 16:37:35 | K88: @@.//++./.+@+/..+ | L88: CITROEN | M88: C3 | N88: C3 PURETECH 4X2 1.2 | O88: CIC3PT12 | P88: 2024 | Q88: 38242 | R88: TCIAUTU000138 | S88: TRJG95 | T88: USADO | U88: GRIS ARTENSE NEGRO | V88: POR DEFINIR | W88: 7990000 | X88: Disponible | Y88: 14 | Z88: EN PREPARACION | AA88: PREMIUM CAR SALES | AC88: 10VQAC0018924 | AD88: 935CCHMEERB515443 | AE88: GUSTAVO ADOLFO INOSTROZA MELLA | AF88: 01-09-2026 0:00:00 | AG88: 1 | AH88: 01-09-2026 0:00:00 | AI88: 01-09-2026 16:37:06 | AK88: 3 | AL88: 0 | AN88: 0 | AO88: 6600000 | AP88: 228240 | AQ88: 0 | AR88: 6828240 | AS88: 7990000 | AT88: 1161760 | AU88: 1454
A89: IMPORTADORA TRENTO LTDA | B89: LOCAL PREMIUM CAR SALES | C89: 0 | D89: 0 | I89: 01-09-2026 16:43:19 | K89: LVVDB21B2RD108221 | L89: OMODA | M89: C5 | N89: C5 1.5 AUT | O89: OMC515AT | P89: 2024 | Q89: 29645 | R89: TOMOSTWU000017 | S89: TPTY64 | T89: USADO | U89: GRIS ACERADO TECHO NEGRO | V89: POR DEFINIR | W89: 12390000 | X89: Disponible | Y89: 14 | Z89: DISPONIBLE | AA89: PREMIUM CAR SALES | AC89: SQRE4T15CCHRB01885 | AD89: LVVDB21B2RD108221 | AE89: VICTOR MATIAS SALAS RIVERA | AF89: 01-09-2026 0:00:00 | AG89: 1 | AH89: 01-09-2026 0:00:00 | AI89: 01-09-2026 16:42:18 | AK89: 1 | AL89: 0 | AN89: 0 | AO89: 11000000 | AP89: 294240 | AQ89: 0 | AR89: 11294240 | AS89: 12390000 | AT89: 1095760 | AU89: 884
A90: IMPORTADORA TRENTO LTDA | B90: LOCAL SALAMANCA | C90: 0 | D90: 0 | I90: 30-04-2026 15:19:16 | K90: LVVDB21B4 SC023313 | L90: CHERY | M90: TIGGO 3 PRO | N90: TIGGO 3 PRO GLS 1.5 AUT | O90: CHTIG3PRGLS15AT | P90: 2026 | Q90: 22255 | R90: TCYSTWU000352 | S90: VKCY97 | T90: USADO | U90: GRIS PLATA | V90: POR DEFINIR | W90: 11690000 | X90: Disponible | Y90: 138 | Z90: DISPONIBLE | AA90: BODEGA VEHICULOS | AC90: SQRE4G15CBDRL00035 | AD90: LVVDB21B4 SC023313 | AE90: RUTH ESTER OSSANDON NARBONA | AF90: 30-04-2026 0:00:00 | AG90: 1 | AH90: 30-04-2026 0:00:00 | AI90: 30-04-2026 15:17:56 | AK90: 1 | AL90: 0 | AN90: 0 | AO90: 10000000 | AP90: 279240 | AQ90: 0 | AR90: 10279240 | AS90: 11690000 | AT90: 1410760 | AU90: 1207
A91: IMPORTADORA TRENTO LTDA | B91: MEGACENTRO OVALLE | C91: 0 | D91: 0 | I91: 21-08-2026 11:15:12 | K91: VR3USHNSK NJ511632 | L91: PEUGEOT | M91: 2008 | N91: 2008 PURETECH 130 1.2 | O91: 2PU8 | P91: 2021 | Q91: 20803 | R91: TPESTWU000474 | S91: RCBL14 | T91: USADO | U91: ROJO ELIXIR | V91: POR DEFINIR | W91: 11290000 | X91: Disponible | Y91: 25 | Z91: EN PREPARACION | AA91: BODEGA OVALLEveih | AC91: 10Z1AC0089106 | AD91: VR3USHNSK NJ511632 | AE91: SAMUEL GUILLERMO GUZMAN BRIONES | AF91: 21-08-2026 0:00:00 | AG91: 1 | AH91: 21-08-2026 0:00:00 | AI91: 21-08-2026 11:11:08 | AK91: 1 | AL91: 0 | AN91: 0 | AO91: 9300000 | AP91: 268740 | AQ91: 0 | AR91: 9568740 | AS91: 11290000 | AT91: 1721260 | AU91: 1525
A92: IMPORTADORA TRENTO LTDA | B92: LOCAL USADOS COPIAPO | C92: 0 | D92: 0 | I92: 03-07-2026 10:13:37 | K92: /////+++*./++*... | L92: MAZDA | M92: NEW CX 5 | N92: NEW CX 5 R 2.0 AT | O92: MANECX520AT | P92: 2022 | Q92: 80925 | R92: TMASTWU000107 | S92: RKZT70 | T92: USADO | U92: PLATEADO PLATA METALIZADO | V92: POR DEFINIR | W92: 16990000 | X92: Disponible | Y92: 74 | Z92: DISPONIBLE | AA92: BODEGA LOS CARRERA COPIAPO | AB92: AE,CC,EE,AAC,ABS,LL,VC,AISO,AAUTO,CRE,MAV,ACD,SR,U | AC92: PE 21654797 | AD92: JM7KF2W76N0693317 | AE92: ANABEL JOSÉ LOPETEGUI GONZALEZ | AF92: 03-07-2026 0:00:00 | AG92: 1 | AH92: 03-08-2026 16:37:00 | AI92: 03-08-2026 16:37:00 | AK92: 1 | AL92: 0 | AN92: 0 | AO92: 14000000 | AP92: 339240 | AQ92: 0 | AR92: 14339240 | AS92: 16990000 | AT92: 2650760 | AU92: 156
A93: IMPORTADORA TRENTO LTDA | B93: LOCAL USADOS COPIAPO | C93: 0 | D93: 0 | I93: 13-11-2025 16:08:09 | K93: VF3MCYHZU PS006748 | L93: PEUGEOT | M93: 5008 | N93: 5008 BLUEHDI 130 1.5 AUT | O93: 5008BH130 | P93: 2023 | Q93: 66999 | R93: TPESTWU000433 | S93: SFLW13 | T93: USADO | U93: BLANCO NACARADO | V93: POR DEFINIR | W93: 20990000 | X93: Disponible | Y93: 306 | Z93: DISPONIBLE | AA93: BODEGA LOS CARRERA COPIAPO | AB93: AE,CC,EE,AAC,ABS,LL,VC,AISO,AAUTO,CRE,MAV,ACD,SR,U | AC93: 10Q4EP0125437 | AD93: VF3MCYHZU PS006748 | AE93: YOANA ELENA ROJAS HENRIQUEZ | AF93: 13-11-2025 0:00:00 | AG93: 1 | AH93: 04-06-2026 10:00:00 | AI93: 04-06-2026 10:00:00 | AJ93: 30-06-2027 0:00:00 | AK93: 1 | AL93: 0 | AN93: 0 | AO93: 19800000 | AP93: 423030 | AQ93: 0 | AR93: 20223030 | AS93: 20990000 | AT93: 766970 | AU93: 365
A94: IMPORTADORA TRENTO LTDA | B94: LOCAL PREMIUM CAR SALES | C94: 0 | D94: 0 | I94: 01-09-2026 16:15:06 | K94: LVVDB21B4 SD032393 | L94: OMODA | M94: C5 | N94: C5 1.5 AUT | O94: OMC515AT | P94: 2025 | Q94: 1600 | R94: TOMOSTWU000016 | S94: TSZB33 | T94: USADO | U94: AZUL INDIGO | V94: POR DEFINIR | W94: 11390000 | X94: Disponible | Y94: 14 | Z94: CON PRENDA | AA94: PREMIUM CAR SALES | AC94: SQRE4T15CCHRH00682 | AD94: LVVDB21B4 SD032393 | AE94: CAMILA ALEJANDRA EGUILUZ ALDUNATE | AF94: 01-09-2026 0:00:00 | AG94: 1 | AH94: 01-09-2026 0:00:00 | AI94: 01-09-2026 16:14:38 | AK94: 1 | AL94: 0 | AN94: 0 | AO94: 9800000 | AP94: 276240 | AQ94: 0 | AR94: 10076240 | AS94: 11390000 | AT94: 1313760 | AU94: 1153
A95: IMPORTADORA TRENTO LTDA | B95: MEGACENTRO OVALLE | C95: 0 | D95: 0 | I95: 01-09-2026 17:25:22 | K95: LVVDB11B8SC008954 | L95: CHERY | M95: TIGGO 3 PRO | N95: TIGGO 3 PRO GLX 1.5 | O95: CHT3PROUSA | P95: 2025 | Q95: 15440 | R95: TCYSTWU000368 | S95: TTVX42 | T95: USADO | U95: ROJO METALIZADO | V95: POR DEFINIR | W95: 10490000 | X95: Disponible | Y95: 14 | Z95: EN PREPARACION | AA95: BODEGA OVALLEveih | AC95: SQRE4G15CBCRH00051 | AD95: LVVDB11B8SC008954 | AE95: ANGELICA MAGDALENA RODRIGUEZ JOFRE | AF95: 01-09-2026 0:00:00 | AG95: 1 | AH95: 01-09-2026 0:00:00 | AI95: 01-09-2026 17:24:50 | AK95: 1 | AL95: 0 | AN95: 0 | AO95: 8400000 | AP95: 255240 | AQ95: 0 | AR95: 8655240 | AS95: 10490000 | AT95: 1834760 | AU95: 1749
A96: IMPORTADORA TRENTO LTDA | B96: LOCAL PREMIUM CAR SALES | C96: 0 | D96: 0 | I96: 31-07-2026 15:12:03 | K96: VF3M45GFU PS005512 | L96: PEUGEOT | M96: 5008 | N96: 5008 PURETECH 180 EAT8 1.6 AUT | O96: PE5008PT16AT | P96: 2022 | Q96: 44332 | R96: TPESTWU000469 | S96: SDGD26 | T96: USADO | U96: BLANCO NACARADO | V96: POR DEFINIR | W96: 18990000 | X96: Disponible | Y96: 46 | Z96: EN PREPARACION | AA96: PREMIUM CAR SALES | AB96: AE,CC,EE,AAC,ABS,LL,AISO,AAUTO,CRE,MAV,ACD,SR,DLL, | AC96: 10FKBL2934118 | AD96: VF3M45GFU PS005512 | AE96: DAVID ANDRES SEPULVEDA VARGAS | AF96: 31-07-2026 0:00:00 | AG96: 1 | AH96: 31-07-2026 0:00:00 | AI96: 31-07-2026 15:11:39 | AK96: 3 | AL96: 0 | AN96: 0 | AO96: 15900000 | AP96: 367740 | AQ96: 0 | AR96: 16267740 | AS96: 18990000 | AT96: 2722260 | AU96: 1434
A97: IMPORTADORA TRENTO LTDA | B97: MEGACENTRO OVALLE | C97: 0 | D97: 0 | I97: 04-02-2026 12:44:44 | K97: 3N1AB7AE8LY202955 | L97: NISSAN | M97: SENTRA | N97: SENTRA 1.8 AT | O97: NISEN18AT | P97: 2020 | Q97: 96000 | R97: TNIAUTU000649 | S97: PDBJ62 | T97: USADO | U97: BLANCO PERLA | V97: POR DEFINIR | W97: 9490000 | X97: Disponible | Y97: 223 | Z97: DISPONIBLE | AA97: BODEGA OVALLEveih | AB97: AE,CC,EE,NB,ABS,LL,4AB,AC,AISO,AAUTO,ACD,DLL | AC97: MRA8720448J | AD97: 3N1AB7AE8LY202955 | AE97: RUPERTO ALEJANDRO GALLEGOS GUTIERREZ | AF97: 04-02-2026 0:00:00 | AG97: 1 | AH97: 09-07-2026 17:20:00 | AI97: 09-07-2026 17:20:00 | AJ97: 31-05-2026 0:00:00 | AK97: 4 | AL97: 0 | AN97: 0 | AO97: 8500000 | AP97: 253530 | AQ97: 0 | AR97: 8753530 | AS97: 9490000 | AT97: 736470 | AU97: 776
A98: IMPORTADORA TRENTO LTDA | B98: LOCAL PREMIUM CAR SALES | C98: 0 | D98: 0 | I98: 27-06-2026 12:46:52 | K98: 3FTTW8E31PRA29529 | L98: FORD | M98: MAVERICK | N98: MAVERICK LARIAT 2.5 AUT | O98: FOMALA25ATFHEV | P98: 2025 | Q98: 31490 | R98: TFOCMTU001164 | S98: SYRD37 | T98: USADO | U98: PLATEADO METALICO | V98: POR DEFINIR | W98: 25990000 | X98: Disponible | Y98: 80 | Z98: DISPONIBLE | AA98: PREMIUM CAR SALES | AB98: AE,CC,EE,AAC,ABS,LL,ESP,AISO,AAUTO,CRE,MAV,ACD,SR, | AC98: PRA29529 | AD98: 3FTTW8E31PRA29529 | AE98: RVR LIMITADA | AF98: 27-06-2026 0:00:00 | AG98: 1 | AH98: 27-06-2026 0:00:00 | AI98: 27-06-2026 12:46:07 | AK98: 1 | AL98: 0 | AN98: 0 | AO98: 22500000 | AP98: 466740 | AQ98: 0 | AR98: 22966740 | AS98: 25990000 | AT98: 3023260 | AU98: 1163
A99: IMPORTADORA TRENTO LTDA | B99: LOCAL PREMIUM CAR SALES | C99: 0 | D99: 0 | I99: 01-09-2026 16:55:12 | K99: /..//+*+///++*... | L99: CITROEN | M99: C3 | N99: C3 1.5 | O99: CIC315MTHDI | P99: 2021 | Q99: 57477 | R99: TCISTWU000011 | S99: PFRW44 | T99: USADO | U99: GRIS ARTENSE BLANCO | V99: POR DEFINIR | W99: 9590000 | X99: Disponible | Y99: 14 | Z99: EN PREPARACION | AA99: PREMIUM CAR SALES | AB99: AE,CC,EE,ABS,AC,CRE,MAV,ACD,UD,DLL | AC99: 10Q4DF0006109 | AD99: VF7SXYHTUNT500202 | AE99: RODRIGO ANDRES SAINZ LOPEZ | AF99: 01-09-2026 0:00:00 | AG99: 1 | AH99: 01-09-2026 0:00:00 | AI99: 01-09-2026 16:53:40 | AK99: 1 | AL99: 0 | AN99: 0 | AO99: 7600000 | AP99: 243240 | AQ99: 0 | AR99: 7843240 | AS99: 9590000 | AT99: 1746760 | AU99: 1821
A100: IMPORTADORA TRENTO LTDA | B100: LOCAL PREMIUM CAR SALES | C100: 0 | D100: 0 | I100: 01-09-2026 18:15:01 | K100: KNANC814BP6226370 | L100: KIA MOTORS | M100: CARNIVAL | N100: CARNIVAL EX GSL 3.5 AUT | O100: KICARNIEXGSL35AT | P100: 2023 | Q100: 57917 | R100: TKISTWU001349 | S100: SLRL79 | T100: USADO | U100: PLATEADO SUAVE | V100: POR DEFINIR | W100: 23490000 | X100: Disponible | Y100: 14 | Z100: EN TALLER EXTERNO | AA100: PREMIUM CAR SALES | AB100: AE,CC,EE,ABS,LL,4AB,AC,AISO,AAUTO,MAV,ACD,SR,DLL | AC100: G6DUNA855831 | AD100: KNANC814BP6226370 | AE100: HECTOR RODRIGO CARRASCO HUERTA | AF100: 01-09-2026 0:00:00 | AG100: 1 | AH100: 01-09-2026 0:00:00 | AI100: 01-09-2026 18:14:31 | AK100: 1 | AL100: 0 | AN100: 0 | AO100: 19000000 | AP100: 414240 | AQ100: 0 | AR100: 19414240 | AS100: 23490000 | AT100: 4075760 | AU100: 1735
A101: IMPORTADORA TRENTO LTDA | B101: LOCAL PREMIUM CAR SALES | C101: 0 | D101: 0 | I101: 18-02-2026 9:30:32 | K101: 1FMCU0BZ6 NUB02251 | L101: FORD | M101: ESCAPE | N101: ESCAPE FHEV 2.5 AUT | O101: FOESFEHV20AT | P101: 2023 | Q101: 80000 | R101: TFOSTWU001399 | S101: SKSZ29 | T101: USADO | U101: GRIS | V101: POR DEFINIR | W101: 16990000 | X101: Disponible | Y101: 209 | Z101: DISPONIBLE | AA101: PREMIUM CAR SALES | AB101: AE,CC,EE,AAC,ABS,LL,VC,ESP,SS,AISO,ACP,AAUTO,CRE,M | AC101: NUB02251 | AD101: 1FMCU0BZ6 NUB02251 | AE101: KARLA NIKOL FLORES CASTILLO | AF101: 18-02-2026 0:00:00 | AG101: 1 | AH101: 18-02-2026 0:00:00 | AI101: 18-02-2026 9:30:04 | AK101: 0 | AL101: 0 | AN101: 0 | AO101: 15400000 | AP101: 357030 | AQ101: 0 | AR101: 15757030 | AS101: 16990000 | AT101: 1232970 | AU101: 726
A102: IMPORTADORA TRENTO LTDA | B102: LOCAL PREMIUM CAR SALES | C102: 0 | D102: 0 | I102: 22-06-2026 11:30:26 | K102: 1FMUK8DH3 SGA72696 | L102: FORD | M102: EXPLORER | N102: EXPLORER ACTIVE 4X4 2.3 AUT | O102: EAC4X4 | P102: 2025 | Q102: 43000 | R102: TFOSTWU001414 | S102: VBBB67 | T102: USADO | U102: AZUL VAPORIZADO | V102: POR DEFINIR | W102: 36990000 | X102: Disponible | Y102: 85 | Z102: DISPONIBLE | AA102: PREMIUM CAR SALES | AB102: AE,CC,EE,AAC,ABS,LL,VC,AISO,AAUTO,CRE,MAV,ACD,SR,U | AC102: SGA72696 | AD102: 1FMUK8DH3 SGA72696 | AE102: LA AVICOLA LIMITADA | AF102: 22-06-2026 0:00:00 | AG102: 1 | AH102: 22-06-2026 0:00:00 | AI102: 22-06-2026 11:30:05 | AK102: 1 | AL102: 0 | AN102: 0 | AO102: 30000000 | AP102: 579240 | AQ102: 0 | AR102: 30579240 | AS102: 36990000 | AT102: 6410760 | AU102: 1733
A103: IMPORTADORA TRENTO LTDA | B103: LOCAL USADOS | C103: 0 | D103: 0 | I103: 28-02-2026 11:42:29 | K103: 1FM5K8FH7KGA98168 | L103: FORD | M103: EXPLORER | N103: EXPLORER LTD 4X4 2.3 AUT | O103: EXPUS1 | P103: 2020 | Q103: 84600 | R103: TFOSTWU001401 | S103: LSZV62 | T103: USADO | U103: BLANCO METAL | V103: POR DEFINIR | W103: 22990000 | X103: Disponible | Y103: 199 | Z103: EN TALLER | AA103: BODEGA VEHICULOS | AC103: KGA98168 | AD103: 1FM5K8FH7KGA98168 | AE103: CLAUDIO VALENZUELA CELIS | AF103: 28-02-2026 0:00:00 | AG103: 1 | AH103: 28-02-2026 0:00:00 | AI103: 28-02-2026 11:42:08 | AK103: 0 | AL103: 0 | AN103: 0 | AO103: 17000000 | AP103: 381030 | AQ103: 0 | AR103: 17381030 | AS103: 22990000 | AT103: 5608970 | AU103: 244
A104: IMPORTADORA TRENTO LTDA | B104: MEGACENTRO OVALLE | C104: 0 | D104: 0 | I104: 27-05-2026 17:54:58 | K104: JF1SK7LL5RG259442 | L104: SUBARU | M104: FORESTER | N104: FORESTER 4X4 2.0 AT | O104: SF99 | P104: 2024 | Q104: 76000 | R104: TSUSTWU000399 | S104: TPCS18 | T104: USADO | U104: PLATEADO HIELO CLARO | V104: POR DEFINIR | W104: 20490000 | X104: Disponible | Y104: 111 | Z104: DISPONIBLE | AA104: BODEGA OVALLEveih | AB104: AE,CC,EE,NB,AAC,ABS,LL,VC,AISO,AAUTO,CRE,MAV,ACD,S | AC104: YX96759 | AD104: JF1SK7LL5RG259442 | AE104: EDUARDO ENRIQUE ANTIQUERA ANTIQUERA | AF104: 27-05-2026 0:00:00 | AG104: 1 | AH104: 27-05-2026 0:00:00 | AI104: 27-05-2026 17:50:26 | AK104: 1 | AL104: 0 | AN104: 0 | AO104: 19000000 | AP104: 414240 | AQ104: 0 | AR104: 19414240 | AS104: 20490000 | AT104: 1075760 | AU104: 525
A105: IMPORTADORA TRENTO LTDA | B105: LOCAL USADOS COPIAPO | C105: 0 | D105: 0 | I105: 28-01-2026 17:28:07 | K105: 1FMCU0BZ6NUB03562 | L105: FORD | M105: ESCAPE | N105: ESCAPE FHEV 2.5 AUT | O105: FOESFEHV20AT | P105: 2023 | Q105: 45000 | R105: TFOSTWU001396 | S105: SBLD74 | T105: USADO | U105: BLANCO METALICO | V105: POR DEFINIR | W105: 18990000 | X105: Disponible | Y105: 230 | Z105: DISPONIBLE | AA105: BODEGA LOS CARRERA COPIAPO | AB105: AE,CC,EE,AAC,ABS,LL,AISO,AAUTO,CRE,MAV,ACD,SR,UD,D | AC105: NUB03562 | AD105: 1FMCU0BZ6NUB03562 | AE105: SOCIEDAD COMERCIAL HERMANOS GODOY ARAYA SPA | AF105: 28-01-2026 0:00:00 | AG105: 1 | AH105: 28-01-2026 0:00:00 | AI105: 28-01-2026 17:22:31 | AK105: 1 | AL105: 0 | AN105: 0 | AO105: 17500000 | AP105: 388530 | AQ105: 0 | AR105: 17888530 | AS105: 18990000 | AT105: 1101470 | AU105: 58
A106: IMPORTADORA TRENTO LTDA | B106: LOCAL PREMIUM CAR SALES | C106: 0 | D106: 0 | I106: 31-07-2026 15:45:20 | K106: 3VW7B6AU8GM038142 | L106: VOLKSWAGEN | M106: GOLF | N106: GOLF HB 1.4 AUT | O106: VOGOLFHB14AT | P106: 2016 | Q106: 80000 | R106: TVOAUTU000227 | S106: HTSJ81 | T106: USADO | U106: GRIS PLATINO | V106: POR DEFINIR | W106: 8990000 | X106: Disponible | Y106: 46 | Z106: NO DISPONIBLE | AA106: PREMIUM CAR SALES | AB106: AE,CC,EE,ABS,LL,4AB,AC,AISO,AAUTO,MAV,ACD,DLL | AC106: CZD 221032 | AD106: 3VW7B6AU8GM038142 | AE106: AGUSTIN ALBERTO SOLARI ALVAREZ | AF106: 31-07-2026 0:00:00 | AG106: 1 | AH106: 31-07-2026 0:00:00 | AI106: 31-07-2026 15:37:31 | AK106: 2 | AL106: 0 | AN106: 0 | AO106: 6600000 | AP106: 228240 | AQ106: 0 | AR106: 6828240 | AS106: 8990000 | AT106: 2161760 | AU106: 2405
A107: IMPORTADORA TRENTO LTDA | B107: LOCAL PREMIUM CAR SALES | C107: 0 | D107: 0 | I107: 01-09-2026 16:09:53 | K107: LJD3BA1DAR0022486 | L107: KIA MOTORS | M107: SONET | N107: SONET EX 4X2 MT 1.5 | O107: KISONEX15MT | P107: 2025 | Q107: 45341 | R107: TKISTWU001346 | S107: TSZB88 | T107: USADO | U107: ROJO ESCARLATA | V107: POR DEFINIR | W107: 13490000 | X107: Disponible | Y107: 14 | Z107: DISPONIBLE | AA107: PREMIUM CAR SALES | AC107: G4FLR1120351 | AD107: LJD3BA1DAR0022486 | AE107: JUAN LUIS VILLALOBOS ORTIZ | AF107: 01-09-2026 0:00:00 | AG107: 1 | AH107: 01-09-2026 0:00:00 | AI107: 01-09-2026 16:09:22 | AK107: 1 | AL107: 0 | AN107: 0 | AO107: 10500000 | AP107: 286740 | AQ107: 0 | AR107: 10786740 | AS107: 13490000 | AT107: 2703260 | AU107: 2004
A108: IMPORTADORA TRENTO LTDA | B108: LOCAL USADOS | C108: 0 | D108: 0 | I108: 05-02-2026 13:04:12 | K108: VF3M45GFUPS010582 | L108: PEUGEOT | M108: 5008 | N108: 5008 PURETECH 180 EAT8 1.6 AUT | O108: PE5008PT16AT | P108: 2023 | Q108: 76000 | R108: TPESTWU000446 | S108: SJKL16 | T108: USADO | U108: GRIS ARTENSE | V108: POR DEFINIR | W108: 17990000 | X108: Disponible | Y108: 222 | Z108: DISPONIBLE | AA108: BODEGA VEHICULOS | AB108: AE,CC,EE,AAC,ABS,LL,VC,AISO,AAUTO,CRE,MAV,ACD,SR,U | AC108: 10FKBL3003916 | AD108: VF3M45GFUPS010582 | AE108: JOHNNY SEBASTIAN DIAZ ZAMORANO | AF108: 05-02-2026 0:00:00 | AG108: 1 | AH108: 05-02-2026 0:00:00 | AI108: 05-02-2026 13:00:32 | AJ108: 30-09-2027 0:00:00 | AK108: 1 | AL108: 0 | AN108: 0 | AO108: 16500000 | AP108: 373530 | AQ108: 0 | AR108: 16873530 | AS108: 17990000 | AT108: 1116470 | AU108: 621
A109: IMPORTADORA TRENTO LTDA | B109: LOCAL PREMIUM CAR SALES | C109: 0 | D109: 0 | I109: 27-08-2026 11:28:53 | K109: KPT40A1XSRP095912 | L109: SSANGYONG | M109: NEW REXTON | N109: NEW REXTON LX 4X4 2.0 AUT | O109: SSNREXLX4X42.0AT | P109: 2023 | Q109: 31306 | R109: TSYSTWU000345 | S109: SXBS86 | T109: USADO | U109: GRIS GRAFITO | V109: POR DEFINIR | W109: 18990000 | X109: Disponible | Y109: 19 | Z109: CON PRENDA | AA109: PREMIUM CAR SALES | AC109: 17495012502467 | AD109: KPT40A1XSRP095912 | AE109: AMAGMALU SPA | AF109: 27-08-2026 0:00:00 | AG109: 1 | AH109: 27-08-2026 0:00:00 | AI109: 27-08-2026 11:24:54 | AK109: 1 | AL109: 0 | AN109: 0 | AO109: 15800000 | AP109: 366240 | AQ109: 0 | AR109: 16166240 | AS109: 18990000 | AT109: 2823760 | AU109: 1487
A110: IMPORTADORA TRENTO LTDA | B110: LOCAL USADOS COPIAPO | C110: 0 | D110: 0 | I110: 06-04-2026 14:59:49 | K110: 9V8FF4HY1 RA800320 | L110: PEUGEOT | M110: LANDTREK | N110: LANDTREK BLUEHDI 4X4 2.2 AUT | O110: PELNDDHI4X422AT | P110: 2024 | Q110: 29570 | R110: TPECMTU000018 | S110: TFGP78 | T110: USADO | U110: GRIS ALUMINIUM | V110: POR DEFINIR | W110: 17990000 | X110: Disponible | Y110: 162 | Z110: DISPONIBLE | AA110: BODEGA LOS CARRERA COPIAPO | AB110: AE,CC,EE,NB,AAC,ABS,LL,VC,AISO,AAUTO,CRE,ACD,SR,UD | AC110: 10VRAC4001968 | AD110: 9V8FF4HY1 RA800320 | AE110: RODRIGO ALEJANDRO FUENTES ARAYA | AF110: 06-04-2026 0:00:00 | AG110: 1 | AH110: 06-04-2026 0:00:00 | AI110: 06-04-2026 14:59:18 | AK110: 1 | AL110: 0 | AN110: 0 | AO110: 16000000 | AP110: 369240 | AQ110: 0 | AR110: 16369240 | AS110: 17990000 | AT110: 1620760 | AU110: 901
A111: IMPORTADORA TRENTO LTDA | B111: MEGACENTRO OVALLE | C111: 0 | D111: 0 | I111: 27-08-2026 16:15:36 | K111: LVTDB11B6 TD091482 | L111: CHERY | M111: TIGGO 8 | N111: TIGGO 8 LTD 1.5 | O111: CHTGGO815 | P111: 2026 | Q111: 1504 | R111: TCYSTWU000365 | S111: VVYY26 | T111: USADO | U111: GRIS GRAFITO OSCURO | V111: POR DEFINIR | W111: 11990000 | X111: Disponible | Y111: 19 | Z111: EN PREPARACION | AA111: BODEGA OVALLEveih | AC111: SQRE4T15CFFTA00029 | AD111: LVTDB11B6 TD091482 | AE111: SERGIO FERMIN GALLEGUILLOS MALDONADO | AF111: 27-08-2026 0:00:00 | AG111: 1 | AH111: 27-08-2026 0:00:00 | AI111: 27-08-2026 16:09:39 | AK111: 1 | AL111: 0 | AN111: 0 | AO111: 10300000 | AP111: 283740 | AQ111: 0 | AR111: 10583740 | AS111: 11990000 | AT111: 1406260 | AU111: 1173
A112: IMPORTADORA TRENTO LTDA | B112: MEGACENTRO OVALLE | C112: 0 | D112: 0 | I112: 03-07-2026 10:07:46 | K112: .////+*+///++*... | L112: FORD | M112: TERRITORY | N112: TERRITORY TITANIUM 4X2 1.5 AUT | O112: FOTETI15AT | P112: 2024 | Q112: 42000 | R112: TFOSTWU001417 | S112: TPWR77 | T112: USADO | U112: BLANCO METALICO | V112: POR DEFINIR | W112: 15990000 | X112: Disponible | Y112: 74 | Z112: EN PREPARACION | AA112: BODEGA OVALLEveih | AB112: AE,CC,EE,AAC,ABS,LL,VC,AISO,AAUTO,CRE,MAV,ACD,SR,U | AC112: R1G000717 | AD112: LJXCU2BBXRTF55890 | AE112: SEBASTIAN CERPA | AF112: 03-07-2026 0:00:00 | AG112: 1 | AH112: 03-07-2026 0:00:00 | AI112: 03-07-2026 10:07:23 | AK112: 1 | AL112: 0 | AN112: 0 | AO112: 12600000 | AP112: 318240 | AQ112: 0 | AR112: 12918240 | AS112: 15990000 | AT112: 3071760 | AU112: 1921
A113: IMPORTADORA TRENTO LTDA | B113: LOCAL PREMIUM CAR SALES | C113: 0 | D113: 0 | I113: 22-07-2026 16:29:47 | K113: KMHSU81CAJU819741 | L113: HYUNDAI | M113: HYUNDAI | N113: SANTA FE GLS 2.4 | O113: 20--THYSTF001 | P113: 2018 | Q113: 68000 | R113: THYSTWU000555 | S113: JXTB68 | T113: USADO | U113: BLANCO | V113: POR DEFINIR | W113: 11990000 | X113: Disponible | Y113: 55 | Z113: NO DISPONIBLE | AA113: PREMIUM CAR SALES | AB113: AE,CC,EE,ABS,LL,4AB,AC,AISO,AAUTO,CRE,MAV,ACD,SR,D | AC113: G4KEHA985578 | AD113: KMHSU81CAJU819741 | AE113: PAULINA ANDREA OÑATE ORTUVIA | AF113: 22-07-2026 0:00:00 | AG113: 1 | AH113: 12-08-2026 15:58:00 | AI113: 12-08-2026 15:58:00 | AK113: 3 | AL113: 0 | AN113: 0 | AO113: 9200000 | AP113: 267240 | AQ113: 0 | AR113: 9467240 | AS113: 11990000 | AT113: 2522760 | AU113: 2104
A114: IMPORTADORA TRENTO LTDA | B114: LOCAL PREMIUM CAR SALES | C114: 0 | D114: 0 | I114: 30-04-2024 14:05:18 | K114: */+--....../*.... | L114: VOLKSWAGEN | M114: AMAROK | N114: AMAROK DCAB TDI DOHC 4X4 2.0 AUT | O114: VWA44 | P114: 2023 | Q114: 15600 | R114: TVOCMTU000037 | S114: SRHZ99 | T114: USADO | U114: GRIS INDIO METALIZADO | V114: POR DEFINIR | W114: 33190000 | X114: Disponible | Y114: 868 | Z114: NO DISPONIBLE | AA114: PREMIUM CAR SALES | AB114: AE,CC,EE,NB,AAC,ABS,LL,TC,VC,ESP,SS,AISO,AAUTO,CRE | AC114: CSH 255654 | AD114: WV1ZZZ2HZPA010091 | AE114: INMOBILIA ROJAS ALVAREZ LTDA | AF114: 30-04-2024 0:00:00 | AG114: 1 | AH114: 12-05-2025 17:38:00 | AI114: 12-05-2025 17:38:00 | AK114: 0 | AL114: 0 | AN114: 0 | AO114: 28500000 | AP114: 1097663 | AQ114: 0 | AR114: 29597663 | AS114: 33190000 | AT114: 3592337 | AU114: 1082
A115: IMPORTADORA TRENTO LTDA | B115: LOCAL USADOS COPIAPO | C115: 0 | D115: 0 | I115: 28-11-2025 12:40:34 | K115: SJNTAAJ12 PA121164 | L115: NISSAN | M115: QASHQAI | N115: QASHQAI TURBO 1.3 | O115: ASTR77 | P115: 2023 | Q115: 45000 | R115: TNISTWU000600 | S115: SFLX53 | T115: USADO | U115: BLANCO PERLA | V115: POR DEFINIR | W115: 16490000 | X115: Disponible | Y115: 291 | Z115: DISPONIBLE | AA115: BODEGA LOS CARRERA COPIAPO | AB115: AE,CC,EE,ABS,LL,VC,AC,AISO,AAUTO,CRE,MAV,ACD,SR,UD | AC115: HR13460529A | AD115: SJNTAAJ12 PA121164 | AE115: PATRICIA JESUS PAYACAN PALACIOS | AF115: 28-11-2025 0:00:00 | AG115: 1 | AH115: 04-06-2026 9:56:00 | AI115: 04-06-2026 9:56:00 | AJ115: 30-06-2026 0:00:00 | AK115: 1 | AL115: 0 | AN115: 0 | AO115: 15400000 | AP115: 566967 | AQ115: 0 | AR115: 15966967 | AS115: 16490000 | AT115: 523033 | AU115: 317
A116: IMPORTADORA TRENTO LTDA | B116: LOCAL PREMIUM CAR SALES | C116: 0 | D116: 0 | I116: 31-07-2026 18:20:39 | K116: SJNTAAJ12SA464098 | L116: NISSAN | M116: QASHQAI | N116: QASHQAI TURBO 1.3 | O116: ASTR77 | P116: 2024 | Q116: 26279 | R116: TNISTWU000618 | S116: TRBD16 | T116: USADO | U116: PLATEADO SATIN | V116: POR DEFINIR | W116: 19290000 | X116: Disponible | Y116: 46 | Z116: CON PRENDA | AA116: PREMIUM CAR SALES | AB116: AE,CC,EE,AAC,ABS,LL,VC,4AB,AISO,AAUTO,CRE,MAV,ACD, | AC116: HR13693149A | AD116: SJNTAAJ12SA464098 | AE116: PABLO JOSE ROBERTO GORMAZ AVILA | AF116: 31-07-2026 0:00:00 | AG116: 1 | AH116: 31-07-2026 0:00:00 | AI116: 31-07-2026 18:13:15 | AK116: 1 | AL116: 0 | AN116: 0 | AO116: 17000000 | AP116: 0 | AQ116: 0 | AR116: 17000000 | AS116: 19290000 | AT116: 2290000 | AU116: 1187
A117: IMPORTADORA TRENTO LTDA | B117: LOCAL PREMIUM CAR SALES | C117: 0 | D117: 0 | I117: 28-08-2026 18:17:56 | K117: JF1SK7LL5KG017905 | L117: SUBARU | M117: FORESTER | N117: FORESTER CVT 4X4 2.0 AUT | O117: FCV1 | P117: 2020 | Q117: 47000 | R117: TSUSTWU000405 | S117: PJDF47 | T117: USADO | U117: BLANCO CRISTAL PERLADO | V117: POR DEFINIR | W117: 17990000 | X117: Disponible | Y117: 18 | Z117: EN PREPARACION | AA117: PREMIUM CAR SALES | AC117: YG09464 | AD117: JF1SK7LL5KG017905 | AE117: PAULINA NICOL CHOCANO VERGARA | AF117: 28-08-2026 0:00:00 | AG117: 1 | AH117: 28-08-2026 0:00:00 | AI117: 28-08-2026 18:17:31 | AK117: 2 | AL117: 0 | AN117: 0 | AO117: 15700000 | AP117: 364740 | AQ117: 0 | AR117: 16064740 | AS117: 17990000 | AT117: 1925260 | AU117: 107
A118: IMPORTADORA TRENTO LTDA | B118: LOCAL USADOS COPIAPO | C118: 0 | D118: 0 | I118: 02-09-2026 17:54:42 | K118: VR3KAHPY5 TS001135 | L118: PEUGEOT | M118: 5008 | N118: 5008 MHEV 1.2 AUT | O118: PEU508MHEV12AT | P118: 2026 | Q118: 11659 | R118: TPESTWU000479 | S118: VKGH56 | T118: USADO | U118: GRIS TITANE | V118: POR DEFINIR | W118: 26990000 | X118: Disponible | Y118: 13 | Z118: EN PREPARACION | AA118: BODEGA LOS CARRERA COPIAPO | AC118: 10ZA040115180 | AD118: VR3KAHPY5 TS001135 | AE118: ESTEBAN ARTURO EXEQUIEL MOLINA SAN JUAN | AF118: 02-09-2026 0:00:00 | AG118: 1 | AH118: 02-09-2026 0:00:00 | AI118: 02-09-2026 17:51:33 | AK118: 1 | AL118: 0 | AN118: 0 | AO118: 23200000 | AP118: 0 | AQ118: 0 | AR118: 23200000 | AS118: 26990000 | AT118: 3790000 | AU118: 1404
A119: IMPORTADORA TRENTO LTDA | B119: LOCAL USADOS COPIAPO | C119: 0 | D119: 0 | I119: 06-02-2026 23:32:37 | K119: 98859125B TKS03533 | L119: RAM | M119: RAM 1500 | N119: RAMPAGE DS LARAMIE 4X4 2.0 AUT | O119: RARAMCSLA4X420AT | P119: 2025 | Q119: 16869 | R119: TRACMTU000050 | S119: VFSF65 | T119: USADO | U119: PLATEADO PLATA BILLET | V119: POR DEFINIR | W119: 30990000 | X119: Disponible | Y119: 221 | Z119: DISPONIBLE | AA119: BODEGA LOS CARRERA COPIAPO | AB119: AE,CC,EE,AAC,ABS,LL,VC,AC,AISO,AAUTO,CRE,MAV,ACD,S | AC119: 463495081880130 | AD119: 98859125B TKS03533 | AE119: BERNARDO MAURICIO CORTES AVALOS | AF119: 06-02-2026 0:00:00 | AG119: 60226 | AH119: 06-02-2026 0:00:00 | AI119: 06-02-2026 23:31:06 | AK119: 0 | AL119: 0 | AN119: 0 | AO119: 29000000 | AP119: 561030 | AQ119: 0 | AR119: 29561030 | AS119: 30990000 | AT119: 1428970 | AU119: 461
A120: IMPORTADORA TRENTO LTDA | B120: LOCAL USADOS COPIAPO | C120: 0 | D120: 0 | I120: 30-03-2026 13:25:15 | K120: VF3MCYHZUNL000473 | L120: PEUGEOT | M120: 5008 | N120: 5008 BLUEHDI 130 1.5 AUT | O120: 5008BH130 | P120: 2021 | Q120: 77000 | R120: TPESTWU000450 | S120: PZTS12 | T120: USADO | U120: GRIS PLATINIUM | V120: POR DEFINIR | W120: 15490000 | X120: Disponible | Y120: 169 | Z120: DISPONIBLE | AA120: BODEGA LOS CARRERA COPIAPO | AB120: AE,CC,EE,AAC,ABS,LL,VC,AISO,AAUTO,CRE,MAV,ACD,SR,U | AC120: 10Q3EJ1170226 | AD120: VF3MCYHZUNL000473 | AE120: JESSICA ALEJANDRA MELLA TAPIA | AF120: 30-03-2026 0:00:00 | AG120: 1 | AH120: 30-03-2026 0:00:00 | AI120: 30-03-2026 13:24:46 | AK120: 1 | AL120: 0 | AN120: 0 | AO120: 14600000 | AP120: 348240 | AQ120: 0 | AR120: 14948240 | AS120: 15490000 | AT120: 541760 | AU120: 35
A121: IMPORTADORA TRENTO LTDA | B121: LOCAL PREMIUM CAR SALES | C121: 0 | D121: 0 | I121: 30-07-2026 19:21:11 | K121: 1FTFW1E53MFD11881 | L121: FORD | M121: F-150 | N121: F150 LARIAT LUXURY 4X4 5.0L AUT | O121: F150AUT | P121: 2022 | Q121: 72706 | R121: TFOCMTU001168 | S121: RXRV75 | T121: USADO | U121: NEGRO UNIVERSO | V121: POR DEFINIR | W121: 35990000 | X121: Disponible | Y121: 47 | Z121: DISPONIBLE | AA121: PREMIUM CAR SALES | AB121: AE,CC,EE,AAC,ABS,LL,VC,AISO,AAUTO,CRE,MAV,ACD,SR,D | AC121: MFD11881 | AD121: 1FTFW1E53MFD11881 | AE121: FELIPE ANDRES CARVAJAL MOLINA | AF121: 30-07-2026 0:00:00 | AG121: 1 | AH121: 30-07-2026 0:00:00 | AI121: 30-07-2026 19:20:51 | AK121: 3 | AL121: 0 | AN121: 0 | AO121: 29200000 | AP121: 567240 | AQ121: 0 | AR121: 29767240 | AS121: 35990000 | AT121: 6222760 | AU121: 1729
A122: IMPORTADORA TRENTO LTDA | B122: LOCAL PREMIUM CAR SALES | C122: 0 | D122: 0 | I122: 01-09-2026 15:31:58 | K122: LSCBBZ2G3TG802268 | L122: CHANGAN | M122: HUNTER | N122: HUNTER 4X4 2.0 | O122: CHAHUN4X420 | P122: 2026 | Q122: 5250 | R122: TCGCMTU000006 | S122: VRHK60 | T122: USADO | U122: GRIS | V122: POR DEFINIR | W122: 17990000 | X122: Disponible | Y122: 14 | Z122: DISPONIBLE | AA122: PREMIUM CAR SALES | AC122: GW4D20M25171040038 | AD122: LSCBBZ2G3TG802268 | AE122: CLAUDIO ALFONSO ASTORGA PIZARRO | AF122: 01-09-2026 0:00:00 | AG122: 1 | AH122: 01-09-2026 0:00:00 | AI122: 01-09-2026 15:29:54 | AK122: 3 | AL122: 0 | AN122: 0 | AO122: 15000000 | AP122: 354240 | AQ122: 0 | AR122: 15354240 | AS122: 17990000 | AT122: 2635760 | AU122: 1465
A123: IMPORTADORA TRENTO LTDA | B123: LOCAL SALAMANCA | C123: 0 | D123: 0 | I123: 02-10-2025 17:10:39 | K123: 9V8FF4HY1RA800991 | L123: PEUGEOT | M123: LANDTREK | N123: LANDTREK BLUEHDI 4X4 2.2 AUT | O123: PELANHDI4X422AT | P123: 2025 | Q123: 5800 | R123: TPECMTU000016 | S123: TSSB38 | T123: USADO | U123: GRIS ALUMINIUM | V123: POR DEFINIR | W123: 20990000 | X123: Disponible | Y123: 348 | Z123: DISPONIBLE | AA123: BODEGA VEHICULOS | AB123: AE,CC,EE,AAC,ABS,LL,VC,AISO,AAUTO,CRE,MAV,ACD,SR,U | AC123: 10VRAC4002861 | AD123: 9V8FF4HY1RA800991 | AE123: JONATHAN JAVIER LARA BARRAZA | AF123: 02-10-2025 0:00:00 | AG123: 1 | AH123: 02-10-2025 0:00:00 | AI123: 02-10-2025 17:09:54 | AK123: 1 | AL123: 0 | AN123: 0 | AO123: 27929100 | AP123: 918614 | AQ123: 0 | AR123: 28847714 | AS123: 20990000 | AT123: -7857714 | AU123: -3744
A124: IMPORTADORA TRENTO LTDA | B124: LOCAL PREMIUM CAR SALES | C124: 0 | D124: 0 | I124: 21-08-2026 11:05:21 | K124: LEFEDDE13RTP05097 | L124: JMC | M124: VIGUS | N124: VIGUS 4X4 2.0 | O124: JMVIG4X420MT | P124: 2025 | Q124: 71526 | R124: TJMCMTU000018 | S124: TSSG29 | T124: USADO | U124: BLANCO | V124: POR DEFINIR | W124: 13990000 | X124: Disponible | Y124: 25 | Z124: EN PREPARACION | AA124: PREMIUM CAR SALES | AC124: PCP80797 | AD124: LEFEDDE13RTP05097 | AE124: CAM OBRAS DE INGENIERIA Y TRANSPORTES SPA | AF124: 21-08-2026 0:00:00 | AG124: 1 | AH124: 21-08-2026 0:00:00 | AI124: 21-08-2026 10:58:54 | AK124: 1 | AL124: 0 | AN124: 0 | AO124: 11500000 | AP124: 301740 | AQ124: 0 | AR124: 11801740 | AS124: 13990000 | AT124: 2188260 | AU124: 1564
...
